Workbook
Name OLE_LINK1: 'CUADRO 2-EJECUCION DE GASTOS'!#REF!

Sheet CUADRO 1-EJECUCION DE INGRESOS
H1: =+NOW() -> 43581.475 | I1: =+NOW() -> 43581.475
A3: ADMINISTRADORA DE LOS RECURSOS DEL SISTEMA GENERAL DE SEGURIDAD SOCIAL EN SALUD
A4: PRESUPUESTO DE INGRESOS 2019
A5: UNIDAD DE RECURSOS ADMINISTRADOS - URA
A6: CUADRO No. 1
A9: CÓDIGO RUBRO | B9: CONCEPTO DEL RUBRO | C9: AFORO INICIAL | D9: MODIFICACIÓN PRESUPUESTAL | E9: AFORO DEFINITIVO | F9: Ingresos Acumulados Desde 01/01/2019 hasta 28/02/2019 | G9: Ingresos Desde 01/03/2019 hasta 31/03/2019 | H9: Ingresos Acumulados Desde 01/01/2019 hasta 31/03/2019 | I9: EJECUCIÓN ACUMULADA (%)
A10: URA
A11: 0-0-0-0 | B11: DISPONIBILIDAD INICIAL | C11: 422831681000 | D11: =+VLOOKUP(A11,ingresos!$A$1:$F$90,3,FALSE) -> 0 | E11: =+VLOOKUP(A11,ingresos!$A$1:$F$90,4,FALSE) -> 422831681000 | F11: 422831681000 | G11: =+VLOOKUP(A11,ingresos!$A$1:$E$100,5,FALSE) -> 0 | H11: =+G11+F11 -> 422831681000 | I11: =IFERROR(H11/E11*100,0) -> 100
A12: 1-0-0-0 | B12: INGRESOS CORRIENTES | C12: 52054407755223 | D12: =+D13+D27 -> 0 | E12: =+E13+E27 -> 52054407755223 | F12: 8.3161597e+12 | G12: =+G13+G27 -> 4.1211559e+12 | H12: =+G12+F12 -> 1.2437316e+13 | I12: =IFERROR(H12/E12*100,0) -> 23.892915
A13: 1-2-0-0 | B13: Aportes e Impuestos | C13: 19781797637181 | D13: =+D14 -> 0 | E13: =+E14+E26 -> 19781797637181 | F13: 2.958478e+12 | G13: =+G14+G26 -> 1.5255619e+12 | H13: =+G13+F13 -> 4.4840399e+12 | I13: =IFERROR(H13/E13*100,0) -> 22.667505
A14: 1-2-1-0 | B14: Aportes de la Nación | C14: 19781797637181 | D14: =+D15+D18+D19+D20+D21+D24+D25 -> 0 | E14: =+E15+E18+E19+E20+E21+E25+E24+E26 -> 19781797637181 | F14: 2.958478e+12 | G14: =+G15+G18+G19+G20+G21+G25+G24+G26 -> 1.5255619e+12 | H14: =+G14+F14 -> 4.4840399e+12 | I14: =IFERROR(H14/E14*100,0) -> 22.667505
A15: 1-2-1-1 | B15: Aportes de la Nación para el Aseguramiento en Salud | C15: 17803782346000 | D15: =+D16+D17 -> 0 | E15: =+E16+E17 -> 17803782346000 | F15: 2483963724334 | G15: =+SUM(G16:G17) -> 1241981862167 | H15: =+G15+F15 -> 3725945586501 | I15: =IFERROR(H15/E15*100,0) -> 20.927832
A16: 1-2-1-1-01 | B16: Aportes de la Nación para el Aseguramiento en Salud Cierre | C16: 13686804885516 | D16: =+VLOOKUP(A16,ingresos!$A$1:$F$90,3,FALSE) -> 0 | E16: =+VLOOKUP(A16,ingresos!$A$1:$F$90,4,FALSE) -> 13686804885516 | F16: 1.9095677e+12 | G16: =+VLOOKUP(A16,ingresos!$A$1:$E$100,5,FALSE) -> 954783825621 | H16: =+G16+F16 -> 2.8643515e+12 | I16: =IFERROR(H16/E16*100,0) -> 20.927832
A17: 1-2-1-1-02 | B17: Imporenta | C17: 4116977460484 | D17: =+VLOOKUP(A17,ingresos!$A$1:$F$90,3,FALSE) -> 0 | E17: =+VLOOKUP(A17,ingresos!$A$1:$F$90,4,FALSE) -> 4116977460484 | F17: 5.7439607e+11 | G17: =+VLOOKUP(A17,ingresos!$A$1:$E$100,5,FALSE) -> 287198036546 | H17: =+G17+F17 -> 8.6159411e+11 | I17: =IFERROR(H17/E17*100,0) -> 20.927832
A18: 1-2-1-2 | B18: Compensación Regalías para el Régimen Subsidiado | C18: 226673765000 | D18: =+VLOOKUP(A18,ingresos!$A$1:$F$90,3,FALSE) -> 0 | E18: =+VLOOKUP(A18,ingresos!$A$1:$F$90,4,FALSE) -> 226673765000 | F18: 113336882500 | G18: =+VLOOKUP(A18,ingresos!$A$1:$E$100,5,FALSE) -> 113336882500 | H18: =+G18+F18 -> 226673765000 | I18: =IFERROR(H18/E18*100,0) -> 100
A19: 1-2-1-3 | B19: Impuesto sobre la renta para la equidad CREE | C19: 0 | D19: =+VLOOKUP(A19,ingresos!$A$1:$F$90,3,FALSE) -> 0 | E19: =+VLOOKUP(A19,ingresos!$A$1:$F$90,4,FALSE) -> 0 | F19: 0 | G19: =+VLOOKUP(A19,ingresos!$A$1:$E$100,5,FALSE) -> 0 | H19: =+G19+F19 -> 0 | I19: =IFERROR(H19/E19*100,0) -> 0
A20: 1-2-1-4 | B20: SGP FONSAET | C20: 95551523562 | D20: =+VLOOKUP(A20,ingresos!$A$1:$F$90,3,FALSE) -> 0 | E20: =+VLOOKUP(A20,ingresos!$A$1:$F$90,4,FALSE) -> 95551523562 | F20: 0 | G20: =+VLOOKUP(A20,ingresos!$A$1:$E$100,5,FALSE) -> 0 | H20: =+G20+F20 -> 0 | I20: =IFERROR(H20/E20*100,0) -> 0
A21: 1-2-1-5 | B21: PRIMA FONSAT Y CONTRIBUCION SOAT | C21: 1640527441000 | D21: =+D22+D23 -> 0 | E21: =+E22+E23 -> 1640527441000 | F21: 3.4250956e+11 | G21: =+SUM(G22:G23) -> 1.6024653e+11 | H21: =+G21+F21 -> 5.0275609e+11 | I21: =IFERROR(H21/E21*100,0) -> 30.646003
A22: 1-2-1-5-01 | B22: % Prima (FONSAT) Decreto Ley 1335 de 2009 | C22: 363281118360 | D22: =+VLOOKUP(A22,ingresos!$A$1:$F$90,3,FALSE) -> 0 | E22: =+VLOOKUP(A22,ingresos!$A$1:$F$90,4,FALSE) -> 363281118360 | F22: 7.770565e+10 | G22: =+VLOOKUP(A22,ingresos!$A$1:$E$100,5,FALSE) -> 5.707715e+10 | H22: =+G22+F22 -> 1.347828e+11 | I22: =IFERROR(H22/E22*100,0) -> 37.101515
A23: 1-2-1-5-02 | B23: Contribución Seguro Obligatorio de Accidentes de Tránsito - SOAT- Decreto Ley 1335 de 2009 | C23: 1277246322640 | D23: =+VLOOKUP(A23,ingresos!$A$1:$F$90,3,FALSE) -> 0 | E23: =+VLOOKUP(A23,ingresos!$A$1:$F$90,4,FALSE) -> 1277246322640 | F23: 264803908400 | G23: =+VLOOKUP(A23,ingresos!$A$1:$E$100,5,FALSE) -> 1.0316938e+11 | H23: =+G23+F23 -> 3.6797329e+11 | I23: =IFERROR(H23/E23*100,0) -> 28.809892
A24: 1-2-1-7 | B24: Impuesto social a las municiones y explosivos | C24: 6410791000 | D24: =+VLOOKUP(A24,ingresos!$A$1:$F$90,3,FALSE) -> 0 | E24: =+VLOOKUP(A24,ingresos!$A$1:$F$90,4,FALSE) -> 6410791000 | F24: 17688023264 | G24: =+VLOOKUP(A24,ingresos!$A$1:$E$100,5,FALSE) -> 9314667807 | H24: =+G24+F24 -> 27002691071 | I24: =IFERROR(H24/E24*100,0) -> 421.20685
A25: 1-2-1-8 | B25: Impuesto social a las armas | C25: 8851770619 | D25: =+VLOOKUP(A25,ingresos!$A$1:$F$90,3,FALSE) -> 0 | E25: =+VLOOKUP(A25,ingresos!$A$1:$F$90,4,FALSE) -> 8851770619 | F25: 979828837 | G25: =+VLOOKUP(A25,ingresos!$A$1:$E$100,5,FALSE) -> 681954075 | H25: =+G25+F25 -> 1661782912 | I25: =IFERROR(H25/E25*100,0) -> 18.773452
A26: 1-2-9-0 | B26: Otros aportes e impuestos de la nación | C26: 0 | D26: =+VLOOKUP(A26,ingresos!$A$1:$F$90,3,FALSE) -> 0 | E26: =+VLOOKUP(A26,ingresos!$A$1:$F$90,4,FALSE) -> 0 | F26: 0 | G26: =+VLOOKUP(A26,ingresos!$A$1:$E$100,5,FALSE) -> 0 | H26: =+G26+F26 -> 0 | I26: =IFERROR(H26/E26*100,0) -> 0
A27: 1-3-0-0 | B27: Otros Ingresos Corrientes | C27: 32272610118042 | D27: =+D28 -> 0 | E27: =+E28+E56 -> 32272610118042 | F27: 5.3576817e+12 | G27: =+G28+G56 -> 2.595594e+12 | H27: =+G27+F27 -> 7.9532757e+12 | I27: =IFERROR(H27/E27*100,0) -> 24.644042
A28: 1-3-5-0 | B28: Ingresos Sistema General de Seguridad Social en Salud | C28: 22105255788877 | D28: =+D29+D32+D35+D40+D50+D53 -> 0 | E28: =+E29+E32+E35+E40+E50+E53 -> 22105255788877 | F28: 3.6706222e+12 | G28: =+G29+G32+G35+G40+G50+G53 -> 1.7958387e+12 | H28: =+G28+F28 -> 5.4664609e+12 | I28: =IFERROR(H28/E28*100,0) -> 24.729236
A29: 1-3-5-1 | B29: Cotizaciones al SGSSS | C29: 20346328129563 | D29: =+SUM(D30:D31) -> 0 | E29: =+SUM(E30:E31) -> 20346328129563 | F29: 3285700130298 | G29: =+SUM(G30:G31) -> 1621342026439 | H29: =+G29+F29 -> 4907042156737 | I29: =IFERROR(H29/E29*100,0) -> 24.117581
A30: 1-3-5-1-01 | B30: Régimen Contributivo CSF | C30: 6807438619821 | D30: =+VLOOKUP(A30,ingresos!$A$1:$F$90,3,FALSE) -> 0 | E30: =+VLOOKUP(A30,ingresos!$A$1:$F$90,4,FALSE) -> 6807438619821 | F30: 1202615909013 | G30: =+VLOOKUP(A30,ingresos!$A$1:$E$100,5,FALSE) -> 491482450650 | H30: =+G30+F30 -> 1694098359663 | I30: =IFERROR(H30/E30*100,0) -> 24.885988
A31: 1-3-5-1-02 | B31: Régimen Contributivo SSF | C31: 13538889509742 | D31: =+VLOOKUP(A31,ingresos!$A$1:$F$90,3,FALSE) -> 0 | E31: =+VLOOKUP(A31,ingresos!$A$1:$F$90,4,FALSE) -> 13538889509742 | F31: 2083084221285 | G31: =+VLOOKUP(A31,ingresos!$A$1:$E$100,5,FALSE) -> 1129859575789 | H31: =+G31+F31 -> 3212943797074 | I31: =IFERROR(H31/E31*100,0) -> 23.731221
A32: 1-3-5-2 | B32: Aporte Solidaridad de Regímenes de Excepcion y Especiales | C32: 1000356775894 | D32: =+SUM(D33:D34) -> 0 | E32: =+SUM(E33:E34) -> 1000356775894 | F32: 1.3400928e+11 | G32: =+SUM(G33:G34) -> 7.5525452e+10 | H32: =+G32+F32 -> 2.0953473e+11 | I32: =IFERROR(H32/E32*100,0) -> 20.946
A33: 1-3-5-2-01 | B33: Cotizaciones afiliados REX con ingresos adicionales | C33: 594961177882 | D33: =+VLOOKUP(A33,ingresos!$A$1:$F$90,3,FALSE) -> 0 | E33: =+VLOOKUP(A33,ingresos!$A$1:$F$90,4,FALSE) -> 594961177882 | F33: 82936264813 | G33: =+VLOOKUP(A33,ingresos!$A$1:$E$100,5,FALSE) -> 44315066621 | H33: =+G33+F33 -> 127251331434 | I33: =IFERROR(H33/E33*100,0) -> 21.388174
A34: 1-3-5-2-02 | B34: Aporte Solidario entidades REX | C34: 405395598012 | D34: =+VLOOKUP(A34,ingresos!$A$1:$F$90,3,FALSE) -> 0 | E34: =+VLOOKUP(A34,ingresos!$A$1:$F$90,4,FALSE) -> 405395598012 | F34: 5.1073012e+10 | G34: =+VLOOKUP(A34,ingresos!$A$1:$E$100,5,FALSE) -> 3.1210386e+10 | H34: =+G34+F34 -> 8.2283398e+10 | I34: =IFERROR(H34/E34*100,0) -> 20.297063
A35: 1-3-5-3 | B35: Aportes Cajas de Compensación Familiar | C35: 499207099674 | D35: =+SUM(D36:D39) -> 0 | E35: =+SUM(E36:E39) -> 499207099674 | F35: 9.3428124e+10 | G35: =+SUM(G36:G39) -> 4.3063898e+10 | H35: =+G35+F35 -> 1.3649202e+11 | I35: =IFERROR(H35/E35*100,0) -> 27.341763
A36: 1-3-5-3-01 | B36: Aportes CCF Artículo 217 Ley 100 de 1993 CSF | C36: 466578060617 | D36: =+VLOOKUP(A36,ingresos!$A$1:$F$90,3,FALSE) -> 0 | E36: =+VLOOKUP(A36,ingresos!$A$1:$F$90,4,FALSE) -> 466578060617 | F36: 8.5265426e+10 | G36: =+VLOOKUP(A36,ingresos!$A$1:$E$100,5,FALSE) -> 3.9735725e+10 | H36: =+G36+F36 -> 1.2500115e+11 | I36: =IFERROR(H36/E36*100,0) -> 26.791048
A37: 1-3-5-3-02 | B37: Aportes CCF Artículo 217 Ley 100 de 1993 SSF | C37: 28877831435 | D37: =+VLOOKUP(A37,ingresos!$A$1:$F$90,3,FALSE) -> 0 | E37: =+VLOOKUP(A37,ingresos!$A$1:$F$90,4,FALSE) -> 28877831435 | F37: 6162595138 | G37: =+VLOOKUP(A37,ingresos!$A$1:$E$100,5,FALSE) -> 2958034371 | H37: =+G37+F37 -> 9120629509 | I37: =IFERROR(H37/E37*100,0) -> 31.583499
A38: 1-3-5-3-03 | B38: Aportes CCF Balance | C38: 3751207622 | D38: =+VLOOKUP(A38,ingresos!$A$1:$F$90,3,FALSE) -> 0 | E38: =+VLOOKUP(A38,ingresos!$A$1:$F$90,4,FALSE) -> 3751207622 | F38: 2000102769 | G38: =+VLOOKUP(A38,ingresos!$A$1:$E$100,5,FALSE) -> 0 | H38: =+G38+F38 -> 2000102769 | I38: =IFERROR(H38/E38*100,0) -> 53.318903
A39: 1-3-5-3-04 | B39: Otros Aportes CCF | C39: 0 | D39: =+VLOOKUP(A39,ingresos!$A$1:$F$90,3,FALSE) -> 0 | E39: =+VLOOKUP(A39,ingresos!$A$1:$F$90,4,FALSE) -> 0 | F39: 0 | G39: =+VLOOKUP(A39,ingresos!$A$1:$E$100,5,FALSE) -> 370138433 | H39: =+G39+F39 -> 370138433 | I39: =IFERROR(H39/E39*100,0) -> 0
A40: 1-3-5-5 | B40: Reintegros / Recuperaciones | C40: 0 | D40: =+SUM(D41:D49) -> 0 | E40: =+SUM(E41:E49) -> 0 | F40: 1.2360676e+11 | G40: =+SUM(G41:G49) -> 3.7775885e+10 | H40: =+G40+F40 -> 1.6138265e+11 | I40: =IFERROR(H40/E40*100,0) -> 0
A41: 1-3-5-5-01 | B41: UPC Régimen Contributivo Vigencias anteriores | C41: 0 | D41: =+VLOOKUP(A41,ingresos!$A$1:$F$90,3,FALSE) -> 0 | E41: =+VLOOKUP(A41,ingresos!$A$1:$F$90,4,FALSE) -> 0 | F41: 7.4635413e+09 | G41: =+VLOOKUP(A41,ingresos!$A$1:$E$100,5,FALSE) -> 1.0871628e+08 | H41: =+G41+F41 -> 7.5722576e+09 | I41: =IFERROR(H41/E41*100,0) -> 0
A42: 1-3-5-5-02 | B42: P&P Vigencias anteriores | C42: 0 | D42: =+VLOOKUP(A42,ingresos!$A$1:$F$90,3,FALSE) -> 0 | E42: =+VLOOKUP(A42,ingresos!$A$1:$F$90,4,FALSE) -> 0 | F42: 0 | G42: =+VLOOKUP(A42,ingresos!$A$1:$E$100,5,FALSE) -> 0 | H42: =+G42+F42 -> 0 | I42: =IFERROR(H42/E42*100,0) -> 0
A43: 1-3-5-5-03 | B43: Licencias de Maternidad y Paternidad Vigencias anteriores | C43: 0 | D43: =+VLOOKUP(A43,ingresos!$A$1:$F$90,3,FALSE) -> 0 | E43: =+VLOOKUP(A43,ingresos!$A$1:$F$90,4,FALSE) -> 0 | F43: 0 | G43: =+VLOOKUP(A43,ingresos!$A$1:$E$100,5,FALSE) -> 0 | H43: =+G43+F43 -> 0 | I43: =IFERROR(H43/E43*100,0) -> 0
A44: 1-3-5-5-04 | B44: UPC Régimen Subsidiado Vigencias anteriores | C44: 0 | D44: =+VLOOKUP(A44,ingresos!$A$1:$F$90,3,FALSE) -> 0 | E44: =+VLOOKUP(A44,ingresos!$A$1:$F$90,4,FALSE) -> 0 | F44: 9.6903395e+10 | G44: =+VLOOKUP(A44,ingresos!$A$1:$E$100,5,FALSE) -> 3.7157296e+10 | H44: =+G44+F44 -> 1.3406069e+11 | I44: =IFERROR(H44/E44*100,0) -> 0
A45: 1-3-5-5-05 | B45: Recobros Vigencias anteriores | C45: 0 | D45: =+VLOOKUP(A45,ingresos!$A$1:$F$90,3,FALSE) -> 0 | E45: =+VLOOKUP(A45,ingresos!$A$1:$F$90,4,FALSE) -> 0 | F45: 3.3217163e+09 | G45: =+VLOOKUP(A45,ingresos!$A$1:$E$100,5,FALSE) -> 2.7461587e+08 | H45: =+G45+F45 -> 3.5963322e+09 | I45: =IFERROR(H45/E45*100,0) -> 0
A46: 1-3-5-5-06 | B46: Reclamaciones Vigencias anteriores | C46: 0 | D46: =+VLOOKUP(A46,ingresos!$A$1:$F$90,3,FALSE) -> 0 | E46: =+VLOOKUP(A46,ingresos!$A$1:$F$90,4,FALSE) -> 0 | F46: 10750119 | G46: =+VLOOKUP(A46,ingresos!$A$1:$E$100,5,FALSE) -> 79226149 | H46: =+G46+F46 -> 89976268 | I46: =IFERROR(H46/E46*100,0) -> 0
A47: 1-3-5-5-07 | B47: Procesos de Repetición | C47: 0 | D47: =+VLOOKUP(A47,ingresos!$A$1:$F$90,3,FALSE) -> 0 | E47: =+VLOOKUP(A47,ingresos!$A$1:$F$90,4,FALSE) -> 0 | F47: 57413044 | G47: =+VLOOKUP(A47,ingresos!$A$1:$E$100,5,FALSE) -> 31151811 | H47: =+G47+F47 -> 88564855 | I47: =IFERROR(H47/E47*100,0) -> 0
A48: 1-3-5-5-08 | B48: Reintegro por contratos vigencias anteriores | C48: 0 | D48: =+VLOOKUP(A48,ingresos!$A$1:$F$90,3,FALSE) -> 0 | E48: =+VLOOKUP(A48,ingresos!$A$1:$F$90,4,FALSE) -> 0 | F48: 78226360 | G48: =+VLOOKUP(A48,ingresos!$A$1:$E$100,5,FALSE) -> 124879176 | H48: =+G48+F48 -> 203105536 | I48: =IFERROR(H48/E48*100,0) -> 0
A49: 1-3-5-5-09 | B49: Otros reintegros / recuperaciones | C49: 0 | D49: =+VLOOKUP(A49,ingresos!$A$1:$F$90,3,FALSE) -> 0 | E49: =+VLOOKUP(A49,ingresos!$A$1:$F$90,4,FALSE) -> 0 | F49: 1.5771718e+10 | G49: =+VLOOKUP(A49,ingresos!$A$1:$E$100,5,FALSE) -> 0 | H49: =+G49+F49 -> 1.5771718e+10 | I49: =IFERROR(H49/E49*100,0) -> 0
A50: 1-3-5-6 | B50: Multas | C50: 0 | D50: =+SUM(D51:D52) -> 0 | E50: =+SUM(E51:E52) -> 0 | F50: 0 | G50: =+SUM(G51:G52) -> 0 | H50: =+G50+F50 -> 0 | I50: =IFERROR(H50/E50*100,0) -> 0
A51: 1-3-5-6-01 | B51: Multas Antitabaco | C51: 0 | D51: =+VLOOKUP(A51,ingresos!$A$1:$F$90,3,FALSE) -> 0 | E51: =+VLOOKUP(A51,ingresos!$A$1:$F$90,4,FALSE) -> 0 | F51: 0 | G51: =+VLOOKUP(A51,ingresos!$A$1:$E$100,5,FALSE) -> 0 | H51: =+G51+F51 -> 0 | I51: =IFERROR(H51/E51*100,0) -> 0
A52: 1-3-5-6-02 | B52: Otras Multas | C52: 0 | D52: =+VLOOKUP(A52,ingresos!$A$1:$F$90,3,FALSE) -> 0 | E52: =+VLOOKUP(A52,ingresos!$A$1:$F$90,4,FALSE) -> 0 | F52: 0 | G52: =+VLOOKUP(A52,ingresos!$A$1:$E$100,5,FALSE) -> 0 | H52: =+G52+F52 -> 0 | I52: =IFERROR(H52/E52*100,0) -> 0
A53: 1-3-5-7 | B53: Otros ingresos Diversos | C53: 259363783746 | D53: =+SUM(D54:D55) -> 0 | E53: =+SUM(E54:E55) -> 259363783746 | F53: 3.3877896e+10 | G53: =+SUM(G54:G55) -> 1.8131441e+10 | H53: =+G53+F53 -> 5.2009337e+10 | I53: =IFERROR(H53/E53*100,0) -> 20.05266
A54: 1-3-5-7-01 | B54: Aportes adicionales en Salud | C54: 259363783746 | D54: =+VLOOKUP(A54,ingresos!$A$1:$F$90,3,FALSE) -> 0 | E54: =+VLOOKUP(A54,ingresos!$A$1:$F$90,4,FALSE) -> 259363783746 | F54: 31693250904 | G54: =+VLOOKUP(A54,ingresos!$A$1:$E$100,5,FALSE) -> 18270673590 | H54: =+G54+F54 -> 49963924494 | I54: =IFERROR(H54/E54*100,0) -> 19.264033
A55: 1-3-5-7-02 | B55: Otros ingresos Diversos | C55: 0 | D55: =+VLOOKUP(A55,ingresos!$A$1:$F$90,3,FALSE) -> 0 | E55: =+VLOOKUP(A55,ingresos!$A$1:$F$90,4,FALSE) -> 0 | F55: 2.1846449e+09 | G55: =+VLOOKUP(A55,ingresos!$A$1:$E$100,5,FALSE) -> -1.3923232e+08 | H55: =+G55+F55 -> 2.0454126e+09 | I55: =IFERROR(H55/E55*100,0) -> 0
A56: 1-3-6-0 | B56: Recursos ET Aseguramiento en Salud | C56: 10167354329165 | D56: =+D57+D58+D59+D62+D65 -> 0 | E56: =+E57+E58+E59+E62+E65 -> 10167354329165 | F56: 1.6870595e+12 | G56: =+G57+G58+G59+G62+G65 -> 7.9975531e+11 | H56: =+G56+F56 -> 2.4868148e+12 | I56: =IFERROR(H56/E56*100,0) -> 24.458819
A57: 1-3-6-1 | B57: Sistema General de Participaciones Régimen Subsidiado | C57: 8428995552661 | D57: =+VLOOKUP(A57,ingresos!$A$1:$F$90,3,FALSE) -> 0 | E57: =+VLOOKUP(A57,ingresos!$A$1:$F$90,4,FALSE) -> 8428995552661 | F57: 1242094599263 | G57: =+VLOOKUP(A57,ingresos!$A$1:$E$100,5,FALSE) -> 648690095349 | H57: =+G57+F57 -> 1890784694612 | I57: =IFERROR(H57/E57*100,0) -> 22.43191
A58: 1-3-6-2 | B58: Recursos Provenientes de COLJUEGOS para R.S. | C58: 376773007880 | D58: =+VLOOKUP(A58,ingresos!$A$1:$F$90,3,FALSE) -> 0 | E58: =+VLOOKUP(A58,ingresos!$A$1:$F$90,4,FALSE) -> 376773007880 | F58: 100418030390 | G58: =+VLOOKUP(A58,ingresos!$A$1:$E$100,5,FALSE) -> 22865410067 | H58: =+G58+F58 -> 123283440457 | I58: =IFERROR(H58/E58*100,0) -> 32.720879
A59: 1-3-6-7 | B59: Recursos Fonpet | C59: 200000000000 | D59: =+SUM(D60:D61) -> 0 | E59: =+SUM(E60:E61) -> 200000000000 | F59: 0 | G59: =+SUM(G60:G61) -> 0 | H59: =+G59+F59 -> 0 | I59: =IFERROR(H59/E59*100,0) -> 0
A60: 1-3-6-7-01 | B60: Recursos LOTTO en Línea-FONPET | C60: 0 | D60: =+VLOOKUP(A60,ingresos!$A$1:$F$90,3,FALSE) -> 0 | E60: =+VLOOKUP(A60,ingresos!$A$1:$F$90,4,FALSE) -> 0 | F60: 0 | G60: =+VLOOKUP(A60,ingresos!$A$1:$E$100,5,FALSE) -> 0 | H60: =+G60+F60 -> 0 | I60: =IFERROR(H60/E60*100,0) -> 0
A61: 1-3-6-7-02 | B61: Otros recursos FONPET diferentes a LOTTO en Línea | C61: 200000000000 | D61: =+VLOOKUP(A61,ingresos!$A$1:$F$90,3,FALSE) -> 0 | E61: =+VLOOKUP(A61,ingresos!$A$1:$F$90,4,FALSE) -> 200000000000 | F61: 0 | G61: =+VLOOKUP(A61,ingresos!$A$1:$E$100,5,FALSE) -> 0 | H61: =+G61+F61 -> 0 | I61: =IFERROR(H61/E61*100,0) -> 0
A62: 1-3-6-8 | B62: Otros Recursos de las Entidades Territoriales para Aseguramiento | C62: 1124585768624 | D62: =+SUM(D63:D64) -> 0 | E62: =+SUM(E63:E64) -> 1124585768624 | F62: 3.3549867e+11 | G62: =+SUM(G63:G64) -> 1.281998e+11 | H62: =+G62+F62 -> 4.6369848e+11 | I62: =IFERROR(H62/E62*100,0) -> 41.232825
A63: 1-3-6-8-01 | B63: Otros recursos Departamentales y Distritales para Aseguramiento | C63: 1042745130904 | D63: =+VLOOKUP(A63,ingresos!$A$1:$F$90,3,FALSE) -> 0 | E63: =+VLOOKUP(A63,ingresos!$A$1:$F$90,4,FALSE) -> 1042745130904 | F63: 3.241288e+11 | G63: =+VLOOKUP(A63,ingresos!$A$1:$E$100,5,FALSE) -> 1.2233546e+11 | H63: =+G63+F63 -> 4.4646427e+11 | I63: =IFERROR(H63/E63*100,0) -> 42.816241
A64: 1-3-6-8-02 | B64: Otros Recursos Municipales para Aseguramiento | C64: 81840637720 | D64: =+VLOOKUP(A64,ingresos!$A$1:$F$90,3,FALSE) -> 0 | E64: =+VLOOKUP(A64,ingresos!$A$1:$F$90,4,FALSE) -> 81840637720 | F64: 1.136987e+10 | G64: =+VLOOKUP(A64,ingresos!$A$1:$E$100,5,FALSE) -> 5.8643423e+09 | H64: =+G64+F64 -> 1.7234212e+10 | I64: =IFERROR(H64/E64*100,0) -> 21.058257
A65: 1-3-6-9 | B65: Recursos USPEC | C65: 37000000000 | D65: =+VLOOKUP(A65,ingresos!$A$1:$F$90,3,FALSE) -> 0 | E65: =+VLOOKUP(A65,ingresos!$A$1:$F$90,4,FALSE) -> 37000000000 | F65: 9.0481925e+09 | G65: =+VLOOKUP(A65,ingresos!$A$1:$E$100,5,FALSE) -> 0 | H65: =+G65+F65 -> 9.0481925e+09 | I65: =IFERROR(H65/E65*100,0) -> 24.454574
A66: 2-0-0-0 | B66: RECURSOS DE CAPITAL | C66: 159585154000 | D66: =+D67+D71+D87+D95 -> 0 | E66: =+E67+E71+E87+E95 -> 159585154000 | F66: 1.0493212e+11 | G66: =+G67+G71+G87+G95 -> 3.1972668e+10 | H66: =+G66+F66 -> 1.3690478e+11 | I66: =IFERROR(H66/E66*100,0) -> 85.78792
A67: 2-1-0-0 | B67: Recuperación de Cartera | C67: 80000000000 | D67: =+SUM(D68:D70) -> 0 | E67: =+SUM(E68:E70) -> 80000000000 | F67: 2.9748987e+10 | G67: =+SUM(G68:G70) -> 1.4000695e+10 | H67: =+G67+F67 -> 4.3749682e+10 | I67: =IFERROR(H67/E67*100,0) -> 54.687102
A68: 2-1-0-0-01 | B68: Restitución operación Fosyga RS Ley 1608 de 2013 | C68: 0 | D68: =+VLOOKUP(A68,ingresos!$A$1:$F$90,3,FALSE) -> 0 | E68: =+VLOOKUP(A68,ingresos!$A$1:$F$90,4,FALSE) -> 0 | F68: 3102390008 | G68: =+VLOOKUP(A68,ingresos!$A$1:$E$100,5,FALSE) -> 677396130 | H68: =+G68+F68 -> 3779786138 | I68: =IFERROR(H68/E68*100,0) -> 0
A69: 2-1-0-0-02 | B69: Amortización Operaciones de Compra de Cartera | C69: 80000000000 | D69: =+VLOOKUP(A69,ingresos!$A$1:$F$90,3,FALSE) -> 0 | E69: =+VLOOKUP(A69,ingresos!$A$1:$F$90,4,FALSE) -> 80000000000 | F69: 2.6646597e+10 | G69: =+VLOOKUP(A69,ingresos!$A$1:$E$100,5,FALSE) -> 1.3323299e+10 | H69: =+G69+F69 -> 3.9969896e+10 | I69: =IFERROR(H69/E69*100,0) -> 49.962369
A70: 2-1-0-0-03 | B70: Recuperación Operaciones de Fortalecimiento Financiero y Patrimonial a entidades del sector salud | C70: 0 | D70: =+VLOOKUP(A70,ingresos!$A$1:$F$90,3,FALSE) -> 0 | E70: =+VLOOKUP(A70,ingresos!$A$1:$F$90,4,FALSE) -> 0 | F70: 0 | G70: =+VLOOKUP(A70,ingresos!$A$1:$E$100,5,FALSE) -> 0 | H70: =+G70+F70 -> 0 | I70: =IFERROR(H70/E70*100,0) -> 0
A71: 2-4-0-0 | B71: Rendimientos Financieros e Intereses | C71: 24675676069 | D71: =+SUM(D72:D86) -> 0 | E71: =+SUM(E72:E86) -> 24675676069 | F71: 7.2373582e+10 | G71: =+SUM(G72:G86) -> 1.2121406e+10 | H71: =+G71+F71 -> 8.4494988e+10 | I71: =IFERROR(H71/E71*100,0) -> 342.42218
A72: 2-4-0-0-01 | B72: Rendimientos cuentas de recaudo EPS -CSF- | C72: 0 | D72: =+VLOOKUP(A72,ingresos!$A$1:$F$90,3,FALSE) -> 0 | E72: =+VLOOKUP(A72,ingresos!$A$1:$F$90,4,FALSE) -> 0 | F72: 700769064 | G72: =+VLOOKUP(A72,ingresos!$A$1:$E$100,5,FALSE) -> -15845609 | H72: =+G72+F72 -> 684923455 | I72: =IFERROR(H72/E72*100,0) -> 0
A73: 2-4-0-0-02 | B73: Rendimientos cuentas de recaudo EPS -SSF- | C73: 7615081557 | D73: =+VLOOKUP(A73,ingresos!$A$1:$F$90,3,FALSE) -> 0 | E73: =+VLOOKUP(A73,ingresos!$A$1:$F$90,4,FALSE) -> 7615081557 | F73: 1552635328 | G73: =+VLOOKUP(A73,ingresos!$A$1:$E$100,5,FALSE) -> 0 | H73: =+G73+F73 -> 1552635328 | I73: =IFERROR(H73/E73*100,0) -> 20.388952
A74: 2-4-0-0-03 | B74: Rendimientos cuentas de Ahorros ADRES URA | C74: 7060594512 | D74: =+VLOOKUP(A74,ingresos!$A$1:$F$90,3,FALSE) -> 0 | E74: =+VLOOKUP(A74,ingresos!$A$1:$F$90,4,FALSE) -> 7060594512 | F74: 1.0291687e+10 | G74: =+VLOOKUP(A74,ingresos!$A$1:$E$100,5,FALSE) -> 5.5876614e+09 | H74: =+G74+F74 -> 1.5879348e+10 | I74: =IFERROR(H74/E74*100,0) -> 224.90101
A75: 2-4-0-0-04 | B75: Rendimientos cuentas de Corrientes ADRES URA | C75: 0 | D75: =+VLOOKUP(A75,ingresos!$A$1:$F$90,3,FALSE) -> 0 | E75: =+VLOOKUP(A75,ingresos!$A$1:$F$90,4,FALSE) -> 0 | F75: 0 | G75: =+VLOOKUP(A75,ingresos!$A$1:$E$100,5,FALSE) -> 0 | H75: =+G75+F75 -> 0 | I75: =IFERROR(H75/E75*100,0) -> 0
A76: 2-4-0-0-06 | B76: Rendimientos sobre títulos del portafolio de Inversiones | C76: 0 | D76: =+VLOOKUP(A76,ingresos!$A$1:$F$90,3,FALSE) -> 0 | E76: =+VLOOKUP(A76,ingresos!$A$1:$F$90,4,FALSE) -> 0 | F76: 0 | G76: =+VLOOKUP(A76,ingresos!$A$1:$E$100,5,FALSE) -> 0 | H76: =+G76+F76 -> 0 | I76: =IFERROR(H76/E76*100,0) -> 0
A77: 2-4-0-0-07 | B77: Rendimientos sobre recursos entregados en administración | C77: 0 | D77: =+VLOOKUP(A77,ingresos!$A$1:$F$90,3,FALSE) -> 0 | E77: =+VLOOKUP(A77,ingresos!$A$1:$F$90,4,FALSE) -> 0 | F77: 2.0821718e+09 | G77: =+VLOOKUP(A77,ingresos!$A$1:$E$100,5,FALSE) -> 1.2318381e+09 | H77: =+G77+F77 -> 3.3140099e+09 | I77: =IFERROR(H77/E77*100,0) -> 0
A78: 2-4-0-0-08 | B78: Otros rendimientos financieros | C78: 0 | D78: =+VLOOKUP(A78,ingresos!$A$1:$F$90,3,FALSE) -> 0 | E78: =+VLOOKUP(A78,ingresos!$A$1:$F$90,4,FALSE) -> 0 | F78: 93770095 | G78: =+VLOOKUP(A78,ingresos!$A$1:$E$100,5,FALSE) -> 9.6537746e+08 | H78: =+G78+F78 -> 1.0591476e+09 | I78: =IFERROR(H78/E78*100,0) -> 0
A79: 2-4-0-0-09 | B79: Intereses Operaciones Compra de Cartera | C79: 0 | D79: =+VLOOKUP(A79,ingresos!$A$1:$F$90,3,FALSE) -> 0 | E79: =+VLOOKUP(A79,ingresos!$A$1:$F$90,4,FALSE) -> 0 | F79: 4.6413508e+08 | G79: =+VLOOKUP(A79,ingresos!$A$1:$E$100,5,FALSE) -> 1.9780108e+08 | H79: =+G79+F79 -> 6.6193616e+08 | I79: =IFERROR(H79/E79*100,0) -> 0
A80: 2-4-0-0-10 | B80: Intereses sobre restituciones | C80: 0 | D80: =+VLOOKUP(A80,ingresos!$A$1:$F$90,3,FALSE) -> 0 | E80: =+VLOOKUP(A80,ingresos!$A$1:$F$90,4,FALSE) -> 0 | F80: 20648701 | G80: =+VLOOKUP(A80,ingresos!$A$1:$E$100,5,FALSE) -> 40489104 | H80: =+G80+F80 -> 61137805 | I80: =IFERROR(H80/E80*100,0) -> 0
A81: 2-4-0-0-11 | B81: Intereses de mora sobre compra de cartera | C81: 0 | D81: =+VLOOKUP(A81,ingresos!$A$1:$F$90,3,FALSE) -> 0 | E81: =+VLOOKUP(A81,ingresos!$A$1:$F$90,4,FALSE) -> 0 | F81: 0 | G81: =+VLOOKUP(A81,ingresos!$A$1:$E$100,5,FALSE) -> 0 | H81: =+G81+F81 -> 0 | I81: =IFERROR(H81/E81*100,0) -> 0
A82: 2-4-0-0-12 | B82: Intereses de mora sobre restituciones | C82: 0 | D82: =+VLOOKUP(A82,ingresos!$A$1:$F$90,3,FALSE) -> 0 | E82: =+VLOOKUP(A82,ingresos!$A$1:$F$90,4,FALSE) -> 0 | F82: 4.1934568e+10 | G82: =+VLOOKUP(A82,ingresos!$A$1:$E$100,5,FALSE) -> 4.2640477e+09 | H82: =+G82+F82 -> 4.6198615e+10 | I82: =IFERROR(H82/E82*100,0) -> 0
A83: 2-4-0-0-13 | B83: Intereses de mora cotizaciones R.C. | C83: 10000000000 | D83: =+VLOOKUP(A83,ingresos!$A$1:$F$90,3,FALSE) -> 0 | E83: =+VLOOKUP(A83,ingresos!$A$1:$F$90,4,FALSE) -> 10000000000 | F83: 15232898721 | G83: =+VLOOKUP(A83,ingresos!$A$1:$E$100,5,FALSE) -> -150114856 | H83: =+G83+F83 -> 15082783865 | I83: =IFERROR(H83/E83*100,0) -> 150.82784
... A86: 2-4-0-0-16 | B86: Otros Intereses | C86: 0 | D86: =+VLOOKUP(A86,ingresos!$A$1:$F$90,3,FALSE) -> 0 | E86: =+VLOOKUP(A86,ingresos!$A$1:$F$90,4,FALSE) -> 0 | F86: 30650 | G86: =+VLOOKUP(A86,ingresos!$A$1:$E$100,5,FALSE) -> 0 | H86: =+G86+F86 -> 30650 | I86: =IFERROR(H86/E86*100,0) -> 0
A87: 2-5-0-0 | B87: Recusos con destinación específica | C87: 54909477931 | D87: =+SUM(D88:D94) -> 0 | E87: =+SUM(E88:E94) -> 54909477931 | F87: 2805132620 | G87: =+SUM(G88:G94) -> 5.84783e+09 | H87: =+G87+F87 -> 8.6529626e+09 | I87: =IFERROR(H87/E87*100,0) -> 15.758596
A88: 2-5-0-0-01 | B88: Excedentes -Servicios prestados a la población pobre y los servicios No POS entidades territoriales. (Num, 2 art. 3 Ley 1608 de 2013) | C88: 0 | D88: =+VLOOKUP(A88,ingresos!$A$1:$F$90,3,FALSE) -> 0 | E88: =+VLOOKUP(A88,ingresos!$A$1:$F$90,4,FALSE) -> 0 | F88: 0 | G88: =+VLOOKUP(A88,ingresos!$A$1:$E$100,5,FALSE) -> 0 | H88: =+G88+F88 -> 0 | I88: =IFERROR(H88/E88*100,0) -> 0
A89: 2-5-0-0-02 | B89: Recursos SGP Propósito General Libre Inversión | C89: 13909477931 | D89: =+VLOOKUP(A89,ingresos!$A$1:$F$90,3,FALSE) -> 0 | E89: =+VLOOKUP(A89,ingresos!$A$1:$F$90,4,FALSE) -> 13909477931 | F89: 321806276 | G89: =+VLOOKUP(A89,ingresos!$A$1:$E$100,5,FALSE) -> 795558858 | H89: =+G89+F89 -> 1117365134 | I89: =IFERROR(H89/E89*100,0) -> 8.0331206
A90: 2-5-0-0-03 | B90: Excedentes recursos FAEP para el reconocimiento de deuda por contratos del Régimen Subsidiado realizados hasta marzo 31 de 2011. | C90: 0 | D90: =+VLOOKUP(A90,ingresos!$A$1:$F$90,3,FALSE) -> 0 | E90: =+VLOOKUP(A90,ingresos!$A$1:$F$90,4,FALSE) -> 0 | F90: 0 | G90: =+VLOOKUP(A90,ingresos!$A$1:$E$100,5,FALSE) -> 0 | H90: =+G90+F90 -> 0 | I90: =IFERROR(H90/E90*100,0) -> 0
A91: 2-5-0-0-04 | B91: Excedentes recursos de LOTTO en línea -FONPET para reconocimiento de deuda por contratos del Régimen Subsidiado realizados hasta marzo 31 de 2011 | C91: 2000000000 | D91: =+VLOOKUP(A91,ingresos!$A$1:$F$90,3,FALSE) -> 0 | E91: =+VLOOKUP(A91,ingresos!$A$1:$F$90,4,FALSE) -> 2000000000 | F91: 0 | G91: =+VLOOKUP(A91,ingresos!$A$1:$E$100,5,FALSE) -> 0 | H91: =+G91+F91 -> 0 | I91: =IFERROR(H91/E91*100,0) -> 0
A92: 2-5-0-0-05 | B92: Excedentes de Aportes Patronales / Resolución 2360 de 2016 | C92: 0 | D92: =+VLOOKUP(A92,ingresos!$A$1:$F$90,3,FALSE) -> 0 | E92: =+VLOOKUP(A92,ingresos!$A$1:$F$90,4,FALSE) -> 0 | F92: 41772215 | G92: =+VLOOKUP(A92,ingresos!$A$1:$E$100,5,FALSE) -> 1158659.2 | H92: =+G92+F92 -> 42930874 | I92: =IFERROR(H92/E92*100,0) -> 0
A93: 2-5-0-0-06 | B93: Regalías – artículo 5 Ley 1797 de 2016 | C93: 3000000000 | D93: =+VLOOKUP(A93,ingresos!$A$1:$F$90,3,FALSE) -> 0 | E93: =+VLOOKUP(A93,ingresos!$A$1:$F$90,4,FALSE) -> 3000000000 | F93: 0 | G93: =+VLOOKUP(A93,ingresos!$A$1:$E$100,5,FALSE) -> 0 | H93: =+G93+F93 -> 0 | I93: =IFERROR(H93/E93*100,0) -> 0
A94: 2-5-0-0-07 | B94: Recursos CCF / FOSFEC - Ley 1929 de 2018 | C94: 36000000000 | D94: =+VLOOKUP(A94,ingresos!$A$1:$F$90,3,FALSE) -> 0 | E94: =+VLOOKUP(A94,ingresos!$A$1:$F$90,4,FALSE) -> 36000000000 | F94: 2441554129 | G94: =+VLOOKUP(A94,ingresos!$A$1:$E$100,5,FALSE) -> 5.0511124e+09 | H94: =+G94+F94 -> 7.4926666e+09 | I94: =IFERROR(H94/E94*100,0) -> 20.812963
A95: 2-9-0-0 | B95: Otros Recursos de Capital | C95: 0 | D95: =+SUM(D96:D97) -> 0 | E95: =+SUM(E96:E97) -> 0 | F95: 4414618 | G95: =+SUM(G96:G97) -> 2737805 | H95: =+G95+F95 -> 7152423 | I95: =IFERROR(H95/E95*100,0) -> 0
A96: 2-9-0-0-01 | B96: Liquidación patrimonios autónomos Sector Salud | C96: 0 | D96: =+VLOOKUP(A96,ingresos!$A$1:$F$90,3,FALSE) -> 0 | E96: =+VLOOKUP(A96,ingresos!$A$1:$F$90,4,FALSE) -> 0 | F96: 0 | G96: =+VLOOKUP(A96,ingresos!$A$1:$E$100,5,FALSE) -> 0 | H96: =+G96+F96 -> 0 | I96: =IFERROR(H96/E96*100,0) -> 0
A97: 2-9-0-0-02 | B97: Otros Recursos de Capital no contemplados en los anteriores | C97: 0 | D97: =+VLOOKUP(A97,ingresos!$A$1:$F$90,3,FALSE) -> 0 | E97: =+VLOOKUP(A97,ingresos!$A$1:$F$90,4,FALSE) -> 0 | F97: 4414618 | G97: =+VLOOKUP(A97,ingresos!$A$1:$E$100,5,FALSE) -> 2737805 | H97: =+G97+F97 -> 7152423 | I97: =IFERROR(H97/E97*100,0) -> 0
B99: TOTAL | C99: =+C66+C12+C11 -> 52636824590223 | D99: =+D66+D12+D11 -> 0 | E99: =+E66+E12+E11 -> 52636824590223 | F99: =+F66+F12+F11 -> 8.8439235e+12 | G99: =+G66+G12+G11 -> 4.1531286e+12 | H99: =+G99+F99 -> 1.2997052e+13 | I99: =IFERROR(H99/E99*100,0) -> 24.691938
C100: 52636824590223 | D100: 0 | E100: 52636824590223 | F100: 8.8439235e+12 | G100: 4.1531286e+12 | H100: 1.2997052e+13 | I100: 24.69
C101: =+C100-C99 -> 0 | D101: =+D100-D99 -> 0 | E101: =+E100-E99 -> 0 | F101: =+F100-F99 -> 0 | G101: =+G100-G99 -> 0 | H101: =+H100-H99 -> -0.03125 | I101: =+I100-I99 -> -0.001937961
F102: dif. Por el excel | H102: dif. Por el excel
E104: =+E99/1000000 -> 52636825
E107: =+E31+E37+E73 -> 13575382422734 | H107: =+H31+H37+H73 -> 3223617061911
E108: =+E107/1000000 -> 13575382

Sheet CUADRO 2-EJECUCION DE GASTOS
M1: =+TODAY() -> 43581 | N1: =+NOW() -> 43581.475
A3: ADMINISTRADORA DE LOS RECURSOS DEL SISTEMA GENERAL DE SEGURIDAD SOCIAL EN SALUD
A4: PRESUPUESTO DE GASTOS 2019
A5: UNIDAD DE RECURSOS ADMINISTRADOS - URA
A6: CUADRO No. 2
A9: CÓDIGO RUBRO | B9: CONCEPTO DEL RUBRO | C9: APROPIACIÓN DEFINITIVA | D9: EJECUCION PRESUPUESTAL ACUMULADA DESDE 01/01/2019 HASTA 28/02/2019 | G9: EJECUCION PRESUPUESTAL DESDE 01/03/2019 HASTA 31/03/2019 | J9: EJECUCION PRESUPUESTAL ACUMULADA DESDE 01/01/2019 HASTA 31/03/2019 | M9: %
D10: T. CDP | E10: T. RP | F10: T. PAGOS-OP | G10: CDP | H10: RP | I10: PAGOS-OP | J10: T. CDP | K10: T. RP | L10: T. PAGOS-OP | M10: RP | N10: OP
B11: URA
A12: A-3-0-0-0 | B12: TRANSFERENCIAS | C12: =+C13+C18+C24 -> 52382816715223 | D12: 8.1885623e+12 | E12: 7.9637997e+12 | F12: 7.9637997e+12 | G12: =+G13+G18+G24 -> 4.2065312e+12 | H12: =+H13+H18+H24 -> 4.0422416e+12 | I12: =+I13+I18+I24 -> 4.0422416e+12 | J12: =+G12+D12 -> 1.2395093e+13 | K12: =+H12+E12 -> 1.2006041e+13 | L12: =+I12+F12 -> 1.2006041e+13 | M12: =+IFERROR(K12*100/C12,0) -> 22.919809 | N12: =+IFERROR(L12*100/C12,0) -> 22.919809
A13: A-3-2-0-0 | B13: TRANSFERENCIAS AL SECTOR PUBLICO | C13: =+C14+C16 -> 231725030430 | D13: 228185519661 | E13: 2.0285041e+10 | F13: 2.0285041e+10 | G13: =+G14+G16 -> 0 | H13: =+H14+H16 -> 9.1046497e+09 | I13: =+I14+I16 -> 9.1046497e+09 | J13: =+G13+D13 -> 228185519661 | K13: =+H13+E13 -> 2.9389691e+10 | L13: =+I13+F13 -> 2.9389691e+10 | M13: =+IFERROR(K13*100/C13,0) -> 12.683002 | N13: =+IFERROR(L13*100/C13,0) -> 12.683002
A14: A-3-2-1-0 | B14: Transferencias Entidades de Administración Pública Central | C14: =+C15 -> 86345030430 | D14: 82805519661 | E14: 1.380092e+10 | F14: 1.380092e+10 | G14: =+G15 -> 0 | H14: =+H15 -> 6.8799777e+09 | I14: =+I15 -> 6.8799777e+09 | J14: =+J15 -> 82805519661 | K14: =+K15 -> 2.0680898e+10 | L14: =+L15 -> 2.0680898e+10 | M14: =+IFERROR(K14*100/C14,0) -> 23.951463 | N14: =+IFERROR(L14*100/C14,0) -> 23.951463
A15: A-3-2-1-01 | B15: Contribución IVC Superintendencia Nacional de Salud | C15: =+VLOOKUP(A15,gasto!$A$4:$F$68,3,FALSE) -> 86345030430 | D15: 82805519661 | E15: 1.380092e+10 | F15: 1.380092e+10 | G15: =+VLOOKUP(A15,gasto!$A$4:$F$68,4,FALSE) -> 0 | H15: =+VLOOKUP(A15,gasto!$A$4:$F$68,5,FALSE) -> 6.8799777e+09 | I15: =+VLOOKUP(A15,gasto!$A$4:$F$68,6,FALSE) -> 6.8799777e+09 | J15: =+G15+D15 -> 82805519661 | K15: =+H15+E15 -> 2.0680898e+10 | L15: =+I15+F15 -> 2.0680898e+10 | M15: =+IFERROR(K15*100/C15,0) -> 23.951463 | N15: =+IFERROR(L15*100/C15,0) -> 23.951463
A16: A-3-2-2-0 | B16: Empresas Públicas Nacionales no financieras -ADRES | C16: =+C17 -> 145380000000 | D16: 145380000000 | E16: 6.484121e+09 | F16: 6.484121e+09 | G16: =+G17 -> 0 | H16: =+H17 -> 2.224672e+09 | I16: =+I17 -> 2.224672e+09 | J16: =+J17 -> 145380000000 | K16: =+K17 -> 8.7087929e+09 | L16: =+L17 -> 8.7087929e+09 | M16: =+IFERROR(K16*100/C16,0) -> 5.9903652 | N16: =+IFERROR(L16*100/C16,0) -> 5.9903652
A17: A-3-2-2-0-01 | B17: Aportes hasta del 0,5% recursos CSF para el desarrollo objeto ADRES | C17: =+VLOOKUP(A17,gasto!$A$4:$F$68,3,FALSE) -> 145380000000 | D17: 145380000000 | E17: 6.484121e+09 | F17: 6.484121e+09 | G17: =+VLOOKUP(A17,gasto!$A$4:$F$68,4,FALSE) -> 0 | H17: =+VLOOKUP(A17,gasto!$A$4:$F$68,5,FALSE) -> 2.224672e+09 | I17: =+VLOOKUP(A17,gasto!$A$4:$F$68,6,FALSE) -> 2.224672e+09 | J17: =+G17+D17 -> 145380000000 | K17: =+H17+E17 -> 8.7087929e+09 | L17: =+I17+F17 -> 8.7087929e+09 | M17: =+IFERROR(K17*100/C17,0) -> 5.9903652 | N17: =+IFERROR(L17*100/C17,0) -> 5.9903652
A18: A-3-6-0-0 | B18: OTRAS TRANSFERENCIAS | C18: =+C19+C22 -> 180000000000 | D18: 1656232 | E18: 1656232 | F18: 1656232 | G18: =+G19+G22 -> 31449750 | H18: =+H19+H22 -> 31449750 | I18: =+I19+I22 -> 31449750 | J18: =+G18+D18 -> 33105982 | K18: =+H18+E18 -> 33105982 | L18: =+I18+F18 -> 33105982 | M18: =+IFERROR(K18*100/C18,0) -> 0.018392212 | N18: =+IFERROR(L18*100/C18,0) -> 0.018392212
A19: A-3-6-1-0 | B19: Sentencias y Conciliaciones URA | C19: =+SUM(C20:C21) -> 20000000000 | D19: 1656232 | E19: 1656232 | F19: 1656232 | G19: =+SUM(G20:G21) -> 31449750 | H19: =+SUM(H20:H21) -> 31449750 | I19: =+SUM(I20:I21) -> 31449750 | J19: =+SUM(J20:J21) -> 33105982 | K19: =+SUM(K20:K21) -> 33105982 | L19: =+SUM(L20:L21) -> 33105982 | M19: =+IFERROR(K19*100/C19,0) -> 0.16552991 | N19: =+IFERROR(L19*100/C19,0) -> 0.16552991
A20: A-3-6-1-1 | B20: Sentencias URA | C20: =+VLOOKUP(A20,gasto!$A$4:$F$68,3,FALSE) -> 20000000000 | D20: 1656232 | E20: 1656232 | F20: 1656232 | G20: =+VLOOKUP(A20,gasto!$A$4:$F$68,4,FALSE) -> 31449750 | H20: =+VLOOKUP(A20,gasto!$A$4:$F$68,5,FALSE) -> 31449750 | I20: =+VLOOKUP(A20,gasto!$A$4:$F$68,6,FALSE) -> 31449750 | J20: =+G20+D20 -> 33105982 | K20: =+H20+E20 -> 33105982 | L20: =+I20+F20 -> 33105982 | M20: =+IFERROR(K20*100/C20,0) -> 0.16552991 | N20: =+IFERROR(L20*100/C20,0) -> 0.16552991
A21: A-3-6-1-2 | B21: Conciliaciones URA | C21: =+VLOOKUP(A21,gasto!$A$4:$F$68,3,FALSE) -> 0 | D21: 0 | E21: 0 | F21: 0 | G21: =+VLOOKUP(A21,gasto!$A$4:$F$68,4,FALSE) -> 0 | H21: =+VLOOKUP(A21,gasto!$A$4:$F$68,5,FALSE) -> 0 | I21: =+VLOOKUP(A21,gasto!$A$4:$F$68,6,FALSE) -> 0 | J21: =+G21+D21 -> 0 | K21: =+H21+E21 -> 0 | L21: =+I21+F21 -> 0 | M21: =+IFERROR(K21*100/C21,0) -> 0 | N21: =+IFERROR(L21*100/C21,0) -> 0
A22: A-3-6-3-0 | B22: Destinatarios de otras transferencias Corrientes - Compensación Chance | C22: =+C23 -> 160000000000 | D22: 0 | E22: 0 | F22: 0 | G22: =+G23 -> 0 | H22: =+H23 -> 0 | I22: =+I23 -> 0 | J22: =+J23 -> 0 | K22: =+K23 -> 0 | L22: =+L23 -> 0 | M22: =+IFERROR(K22*100/C22,0) -> 0 | N22: =+IFERROR(L22*100/C22,0) -> 0
A23: A-3-6-3-0-01 | B23: Otras transferencias - Compensación del Chance Decreto 2550/12 | C23: =+VLOOKUP(A23,gasto!$A$4:$F$68,3,FALSE) -> 160000000000 | D23: 0 | E23: 0 | F23: 0 | G23: =+VLOOKUP(A23,gasto!$A$4:$F$68,4,FALSE) -> 0 | H23: =+VLOOKUP(A23,gasto!$A$4:$F$68,5,FALSE) -> 0 | I23: =+VLOOKUP(A23,gasto!$A$4:$F$68,6,FALSE) -> 0 | J23: =+G23+D23 -> 0 | K23: =+H23+E23 -> 0 | L23: =+I23+F23 -> 0 | M23: =+IFERROR(K23*100/C23,0) -> 0 | N23: =+IFERROR(L23*100/C23,0) -> 0
A24: A-3-9-0-0 | B24: ADMINISTRACIÓN DE RECURSOS DEL SGSSS | C24: =+C25+C30+C33+C36+C37+C38+C42+C45+C52+C56+C66+C77+C79+C81 -> 51971091684793 | D24: 7.9603752e+12 | E24: 7.943513e+12 | F24: 7.943513e+12 | G24: =+G25+G30+G33+G36+G37+G38+G42+G45+G52+G56+G66+G77+G79+G81 -> 4.2064997e+12 | H24: =+H25+H30+H33+H36+H37+H38+H42+H45+H52+H56+H66+H77+H79+H81 -> 4.0331055e+12 | I24: =+I25+I30+I33+I36+I37+I38+I42+I45+I52+I56+I66+I77+I79+I81 -> 4.0331055e+12 | J24: =+G24+D24 -> 1.2166875e+13 | K24: =+H24+E24 -> 1.1976619e+13 | L24: =+I24+F24 -> 1.1976619e+13 | M24: =+IFERROR(K24*100/C24,0) -> 23.04477 | N24: =+IFERROR(L24*100/C24,0) -> 23.04477
A25: A-3-9-1-0 | B25: UPC Régimen Contributivo | C25: =+SUM(C26:C29) -> 23057892632980 | D25: 3586588732801 | E25: 3586588732801 | F25: 3586588732801 | G25: =+SUM(G26:G29) -> 1834230895932 | H25: =+SUM(H26:H29) -> 1824562647330 | I25: =+SUM(I26:I29) -> 1824562647330 | J25: =+SUM(J26:J29) -> 5420819628733 | K25: =+SUM(K26:K29) -> 5411151380131 | L25: =+SUM(L26:L29) -> 5411151380131 | M25: =+IFERROR(K25*100/C25,0) -> 23.467675 | N25: =+IFERROR(L25*100/C25,0) -> 23.467675
A26: A-3-9-1-0-01 | B26: UPC Régimen Contributivo SSF | C26: =+VLOOKUP(A26,gasto!$A$4:$F$68,3,FALSE) -> 12399109660289 | D26: 1917636082993 | E26: 1917636082993 | F26: 1917636082993 | G26: =+VLOOKUP(A26,gasto!$A$4:$F$68,4,FALSE) -> 1041100938124 | H26: =+VLOOKUP(A26,gasto!$A$4:$F$68,5,FALSE) -> 1041100938124 | I26: =+VLOOKUP(A26,gasto!$A$4:$F$68,6,FALSE) -> 1041100938124 | J26: =+G26+D26 -> 2958737021117 | K26: =+H26+E26 -> 2958737021117 | L26: =+I26+F26 -> 2958737021117 | M26: =+IFERROR(K26*100/C26,0) -> 23.862496 | N26: =+IFERROR(L26*100/C26,0) -> 23.862496
A27: A-3-9-1-0-02 | B27: UPC Régimen Contributivo CSF | C27: =+VLOOKUP(A27,gasto!$A$4:$F$68,3,FALSE) -> 10647939289644 | D27: 1668110496494 | E27: 1668110496494 | F27: 1668110496494 | G27: =+VLOOKUP(A27,gasto!$A$4:$F$68,4,FALSE) -> 783128428075 | H27: =+VLOOKUP(A27,gasto!$A$4:$F$68,5,FALSE) -> 783128428075 | I27: =+VLOOKUP(A27,gasto!$A$4:$F$68,6,FALSE) -> 783128428075 | J27: =+G27+D27 -> 2451238924569 | K27: =+H27+E27 -> 2451238924569 | L27: =+I27+F27 -> 2451238924569 | M27: =+IFERROR(K27*100/C27,0) -> 23.020782 | N27: =+IFERROR(L27*100/C27,0) -> 23.020782
A28: A-3-9-1-0-03 | B28: Devolución aportes y cotizaciones no conciliadas vigencia anterior | C28: =+VLOOKUP(A28,gasto!$A$4:$F$68,3,FALSE) -> 10223147816 | D28: 842153314 | E28: 842153314 | F28: 842153314 | G28: =+VLOOKUP(A28,gasto!$A$4:$F$68,4,FALSE) -> 9380994502 | H28: =+VLOOKUP(A28,gasto!$A$4:$F$68,5,FALSE) -> 333281131 | I28: =+VLOOKUP(A28,gasto!$A$4:$F$68,6,FALSE) -> 333281131 | J28: =+G28+D28 -> 10223147816 | K28: =+H28+E28 -> 1175434445 | L28: =+I28+F28 -> 1175434445 | M28: =+IFERROR(K28*100/C28,0) -> 11.497774 | N28: =+IFERROR(L28*100/C28,0) -> 11.497774
A29: A-3-9-1-0-04 | B29: Rendimientos Financieros de los Saldos no Compensados de los Aportes Patronales según Art. 12 Decreto 1636 de 2016 | C29: =+VLOOKUP(A29,gasto!$A$4:$F$68,3,FALSE) -> 620535231 | D29: 0 | E29: 0 | F29: 0 | G29: =+VLOOKUP(A29,gasto!$A$4:$F$68,4,FALSE) -> 620535231 | H29: =+VLOOKUP(A29,gasto!$A$4:$F$68,5,FALSE) -> 0 | I29: =+VLOOKUP(A29,gasto!$A$4:$F$68,6,FALSE) -> 0 | J29: =+G29+D29 -> 620535231 | K29: =+H29+E29 -> 0 | L29: =+I29+F29 -> 0 | M29: =+IFERROR(K29*100/C29,0) -> 0 | N29: =+IFERROR(L29*100/C29,0) -> 0
A30: A-3-9-2-0 | B30: Per capita Programas de Promoción y Prevención R.C | C30: =+SUM(C31:C32) -> 646778600953 | D30: 81551392440 | E30: 81551392440 | F30: 81551392440 | G30: =+SUM(G31:G32) -> 41358142449 | H30: =+SUM(H31:H32) -> 41358142449 | I30: =+SUM(I31:I32) -> 41358142449 | J30: =+SUM(J31:J32) -> 122909534889 | K30: =+SUM(K31:K32) -> 122909534889 | L30: =+SUM(L31:L32) -> 122909534889 | M30: =+IFERROR(K30*100/C30,0) -> 19.00334 | N30: =+IFERROR(L30*100/C30,0) -> 19.00334
A31: A-3-9-2-0-01 | B31: Per capita Programas de Promoción y Prevención R.C SSF | C31: =+VLOOKUP(A31,gasto!$A$4:$F$68,3,FALSE) -> 510526042986 | D31: 64718393615 | E31: 64718393615 | F31: 64718393615 | G31: =+VLOOKUP(A31,gasto!$A$4:$F$68,4,FALSE) -> 34508054189 | H31: =+VLOOKUP(A31,gasto!$A$4:$F$68,5,FALSE) -> 34508054189 | I31: =+VLOOKUP(A31,gasto!$A$4:$F$68,6,FALSE) -> 34508054189 | J31: =+G31+D31 -> 99226447804 | K31: =+H31+E31 -> 99226447804 | L31: =+I31+F31 -> 99226447804 | M31: =+IFERROR(K31*100/C31,0) -> 19.436119 | N31: =+IFERROR(L31*100/C31,0) -> 19.436119
A32: A-3-9-2-0-02 | B32: Per capita Programas de Promoción y Prevención R.C CSF | C32: =+VLOOKUP(A32,gasto!$A$4:$F$68,3,FALSE) -> 136252557967 | D32: 16832998825 | E32: 16832998825 | F32: 16832998825 | G32: =+VLOOKUP(A32,gasto!$A$4:$F$68,4,FALSE) -> 6850088260 | H32: =+VLOOKUP(A32,gasto!$A$4:$F$68,5,FALSE) -> 6850088260 | I32: =+VLOOKUP(A32,gasto!$A$4:$F$68,6,FALSE) -> 6850088260 | J32: =+G32+D32 -> 23683087085 | K32: =+H32+E32 -> 23683087085 | L32: =+I32+F32 -> 23683087085 | M32: =+IFERROR(K32*100/C32,0) -> 17.381756 | N32: =+IFERROR(L32*100/C32,0) -> 17.381756
A33: A-3-9-3-0 | B33: Incapacidades | C33: =+SUM(C34:C35) -> 814461941941 | D33: 131878529536 | E33: 131878529536 | F33: 131878529536 | G33: =+SUM(G34:G35) -> 65846859451 | H33: =+SUM(H34:H35) -> 65846859451 | I33: =+SUM(I34:I35) -> 65846859451 | J33: =+SUM(J34:J35) -> 197725388987 | K33: =+SUM(K34:K35) -> 197725388987 | L33: =+SUM(L34:L35) -> 197725388987 | M33: =+IFERROR(K33*100/C33,0) -> 24.276811 | N33: =+IFERROR(L33*100/C33,0) -> 24.276811
A34: A-3-9-3-0-01 | B34: Incapacidades SSF | C34: =+VLOOKUP(A34,gasto!$A$4:$F$68,3,FALSE) -> 629253806467 | D34: 100729744677 | E34: 100729744677 | F34: 100729744677 | G34: =+VLOOKUP(A34,gasto!$A$4:$F$68,4,FALSE) -> 54250583476 | H34: =+VLOOKUP(A34,gasto!$A$4:$F$68,5,FALSE) -> 54250583476 | I34: =+VLOOKUP(A34,gasto!$A$4:$F$68,6,FALSE) -> 54250583476 | J34: =+G34+D34 -> 154980328153 | K34: =+H34+E34 -> 154980328153 | L34: =+I34+F34 -> 154980328153 | M34: =+IFERROR(K34*100/C34,0) -> 24.629224 | N34: =+IFERROR(L34*100/C34,0) -> 24.629224
A35: A-3-9-3-0-02 | B35: Incapacidades CSF | C35: =+VLOOKUP(A35,gasto!$A$4:$F$68,3,FALSE) -> 185208135474 | D35: 31148784859 | E35: 31148784859 | F35: 31148784859 | G35: =+VLOOKUP(A35,gasto!$A$4:$F$68,4,FALSE) -> 11596275975 | H35: =+VLOOKUP(A35,gasto!$A$4:$F$68,5,FALSE) -> 11596275975 | I35: =+VLOOKUP(A35,gasto!$A$4:$F$68,6,FALSE) -> 11596275975 | J35: =+G35+D35 -> 42745060834 | K35: =+H35+E35 -> 42745060834 | L35: =+I35+F35 -> 42745060834 | M35: =+IFERROR(K35*100/C35,0) -> 23.079473 | N35: =+IFERROR(L35*100/C35,0) -> 23.079473
A36: A-3-9-4-0 | B36: Licencias de Maternidad y Paternidad | C36: =+VLOOKUP(A36,gasto!$A$4:$F$68,3,FALSE) -> 838554045453 | D36: 132874717317 | E36: 132874717317 | F36: 132874717317 | G36: =+VLOOKUP(A36,gasto!$A$4:$F$68,4,FALSE) -> 62858550503 | H36: =+VLOOKUP(A36,gasto!$A$4:$F$68,5,FALSE) -> 62858550503 | I36: =+VLOOKUP(A36,gasto!$A$4:$F$68,6,FALSE) -> 62858550503 | J36: =+G36+D36 -> 195733267820 | K36: =+H36+E36 -> 195733267820 | L36: =+I36+F36 -> 195733267820 | M36: =+IFERROR(K36*100/C36,0) -> 23.341759 | N36: =+IFERROR(L36*100/C36,0) -> 23.341759
A37: A-3-9-5-0 | B37: Prestaciones Económicas Regímenes Especial y de Excepción | C37: =+VLOOKUP(A37,gasto!$A$4:$F$68,3,FALSE) -> 4102227236 | D37: 4102227236 | E37: 573098002 | F37: 573098002 | G37: =+VLOOKUP(A37,gasto!$A$4:$F$68,4,FALSE) -> 0 | H37: =+VLOOKUP(A37,gasto!$A$4:$F$68,5,FALSE) -> 512934097 | I37: =+VLOOKUP(A37,gasto!$A$4:$F$68,6,FALSE) -> 512934097 | J37: =+G37+D37 -> 4102227236 | K37: =+H37+E37 -> 1086032099 | L37: =+I37+F37 -> 1086032099 | M37: =+IFERROR(K37*100/C37,0) -> 26.474206 | N37: =+IFERROR(L37*100/C37,0) -> 26.474206
A38: A-3-9-6-0 | B38: UPC Régimen Subsidiado | C38: =+SUM(C39:C41) -> 21586257607421 | D38: 3.5329488e+12 | E38: 3.5329488e+12 | F38: 3.5329488e+12 | G38: =+SUM(G39:G41) -> 1.8140245e+12 | H38: =+SUM(H39:H41) -> 1.7770245e+12 | I38: =+SUM(I39:I41) -> 1.7770245e+12 | J38: =+SUM(J39:J41) -> 5.3469733e+12 | K38: =+SUM(K39:K41) -> 5.3099733e+12 | L38: =+SUM(L39:L41) -> 5.3099733e+12 | M38: =+IFERROR(K38*100/C38,0) -> 24.59886 | N38: =+IFERROR(L38*100/C38,0) -> 24.59886
A39: A-3-9-6-0-01 | B39: UPC´S R.S. Cajas de Compensación Familiar SSF | C39: =+VLOOKUP(A39,gasto!$A$4:$F$68,3,FALSE) -> 28877831435 | D39: 6162595138 | E39: 6162595138 | F39: 6162595138 | G39: =+VLOOKUP(A39,gasto!$A$4:$F$68,4,FALSE) -> 2958034371 | H39: =+VLOOKUP(A39,gasto!$A$4:$F$68,5,FALSE) -> 2958034371 | I39: =+VLOOKUP(A39,gasto!$A$4:$F$68,6,FALSE) -> 2958034371 | J39: =+G39+D39 -> 9120629509 | K39: =+H39+E39 -> 9120629509 | L39: =+I39+F39 -> 9120629509 | M39: =+IFERROR(K39*100/C39,0) -> 31.583499 | N39: =+IFERROR(L39*100/C39,0) -> 31.583499
A40: A-3-9-6-0-02 | B40: UPC´S R.S. CSF | C40: =+VLOOKUP(A40,gasto!$A$4:$F$68,3,FALSE) -> 21520379775986 | D40: 3.5267863e+12 | E40: 3.5267863e+12 | F40: 3.5267863e+12 | G40: =+VLOOKUP(A40,gasto!$A$4:$F$68,4,FALSE) -> 1.7740665e+12 | H40: =+VLOOKUP(A40,gasto!$A$4:$F$68,5,FALSE) -> 1.7740665e+12 | I40: =+VLOOKUP(A40,gasto!$A$4:$F$68,6,FALSE) -> 1.7740665e+12 | J40: =+G40+D40 -> 5.3008527e+12 | K40: =+H40+E40 -> 5.3008527e+12 | L40: =+I40+F40 -> 5.3008527e+12 | M40: =+IFERROR(K40*100/C40,0) -> 24.631781 | N40: =+IFERROR(L40*100/C40,0) -> 24.631781
A41: A-3-9-6-0-03 | B41: UPC´S R.S. USPEC | C41: =+VLOOKUP(A41,gasto!$A$4:$F$68,3,FALSE) -> 37000000000 | D41: 0 | E41: 0 | F41: 0 | G41: =+VLOOKUP(A41,gasto!$A$4:$F$68,4,FALSE) -> 37000000000 | H41: =+VLOOKUP(A41,gasto!$A$4:$F$68,5,FALSE) -> 0 | I41: =+VLOOKUP(A41,gasto!$A$4:$F$68,6,FALSE) -> 0 | J41: =+G41+D41 -> 37000000000 | K41: =+H41+E41 -> 0 | L41: =+I41+F41 -> 0 | M41: =+IFERROR(K41*100/C41,0) -> 0 | N41: =+IFERROR(L41*100/C41,0) -> 0
A42: A-3-9-7-0 | B42: Prestaciones Excepcionales - Recobros | C42: =+SUM(C43:C44) -> 4083854535766 | D42: 4.7481956e+11 | E42: 4.7481956e+11 | F42: 4.7481956e+11 | G42: =+SUM(G43:G44) -> 2.5808004e+11 | H42: =+SUM(H43:H44) -> 2.5808004e+11 | I42: =+SUM(I43:I44) -> 2.5808004e+11 | J42: =+SUM(J43:J44) -> 7.3289961e+11 | K42: =+SUM(K43:K44) -> 7.3289961e+11 | L42: =+SUM(L43:L44) -> 7.3289961e+11 | M42: =+IFERROR(K42*100/C42,0) -> 17.946271 | N42: =+IFERROR(L42*100/C42,0) -> 17.946271
A43: A-3-9-7-0-01 | B43: Recobros - Reembolsos Régimen Contributivo | C43: =+VLOOKUP(A43,gasto!$A$4:$F$68,3,FALSE) -> 4072663890220 | D43: 4.7446392e+11 | E43: 4.7446392e+11 | F43: 4.7446392e+11 | G43: =+VLOOKUP(A43,gasto!$A$4:$F$68,4,FALSE) -> 2.5801471e+11 | H43: =+VLOOKUP(A43,gasto!$A$4:$F$68,5,FALSE) -> 2.5801471e+11 | I43: =+VLOOKUP(A43,gasto!$A$4:$F$68,6,FALSE) -> 2.5801471e+11 | J43: =+G43+D43 -> 7.3247863e+11 | K43: =+H43+E43 -> 7.3247863e+11 | L43: =+I43+F43 -> 7.3247863e+11 | M43: =+IFERROR(K43*100/C43,0) -> 17.985246 | N43: =+IFERROR(L43*100/C43,0) -> 17.985246
A44: A-3-9-7-0-02 | B44: Recobros - Reembolsos Régimen Subsidiado - Tutelas | C44: =+VLOOKUP(A44,gasto!$A$4:$F$68,3,FALSE) -> 11190645546 | D44: 3.5564701e+08 | E44: 3.5564701e+08 | F44: 3.5564701e+08 | G44: =+VLOOKUP(A44,gasto!$A$4:$F$68,4,FALSE) -> 65328665 | H44: =+VLOOKUP(A44,gasto!$A$4:$F$68,5,FALSE) -> 65328665 | I44: =+VLOOKUP(A44,gasto!$A$4:$F$68,6,FALSE) -> 65328665 | J44: =+G44+D44 -> 4.2097568e+08 | K44: =+H44+E44 -> 4.2097568e+08 | L44: =+I44+F44 -> 4.2097568e+08 | M44: =+IFERROR(K44*100/C44,0) -> 3.7618534 | N44: =+IFERROR(L44*100/C44,0) -> 3.7618534
A45: A-3-9-8-0 | B45: Atención en Salud, Transporte Primario, Indemnizaciones y Auxilio Funerario Víctimas | C45: =+SUM(C46:C51) -> 260989164610 | D45: 222768589 | E45: 222768589 | F45: 222768589 | G45: =+SUM(G46:G51) -> 1.5686938e+09 | H45: =+SUM(H46:H51) -> 1.5686938e+09 | I45: =+SUM(I46:I51) -> 1.5686938e+09 | J45: =+SUM(J46:J51) -> 1.7914624e+09 | K45: =+SUM(K46:K51) -> 1.7914624e+09 | L45: =+SUM(L46:L51) -> 1.7914624e+09 | M45: =+IFERROR(K45*100/C45,0) -> 0.68641257 | N45: =+IFERROR(L45*100/C45,0) -> 0.68641257
A46: A-3-9-8-0-01 | B46: Eventos territoristas | C46: =+VLOOKUP(A46,gasto!$A$4:$F$68,3,FALSE) -> 272244074 | D46: 0 | E46: 0 | F46: 0 | G46: =+VLOOKUP(A46,gasto!$A$4:$F$68,4,FALSE) -> 3537000 | H46: =+VLOOKUP(A46,gasto!$A$4:$F$68,5,FALSE) -> 3537000 | I46: =+VLOOKUP(A46,gasto!$A$4:$F$68,6,FALSE) -> 3537000 | J46: =+G46+D46 -> 3537000 | K46: =+H46+E46 -> 3537000 | L46: =+I46+F46 -> 3537000 | M46: =+IFERROR(K46*100/C46,0) -> 1.2992018 | N46: =+IFERROR(L46*100/C46,0) -> 1.2992018
A47: A-3-9-8-0-02 | B47: Eventos Catastróficos | C47: =+VLOOKUP(A47,gasto!$A$4:$F$68,3,FALSE) -> 2733436752 | D47: 0 | E47: 0 | F47: 0 | G47: =+VLOOKUP(A47,gasto!$A$4:$F$68,4,FALSE) -> 19531050 | H47: =+VLOOKUP(A47,gasto!$A$4:$F$68,5,FALSE) -> 19531050 | I47: =+VLOOKUP(A47,gasto!$A$4:$F$68,6,FALSE) -> 19531050 | J47: =+G47+D47 -> 19531050 | K47: =+H47+E47 -> 19531050 | L47: =+I47+F47 -> 19531050 | M47: =+IFERROR(K47*100/C47,0) -> 0.71452357 | N47: =+IFERROR(L47*100/C47,0) -> 0.71452357
A48: A-3-9-8-0-03 | B48: Accidentes de Transito | C48: =+VLOOKUP(A48,gasto!$A$4:$F$68,3,FALSE) -> 227724483784 | D48: 0 | E48: 0 | F48: 0 | G48: =+VLOOKUP(A48,gasto!$A$4:$F$68,4,FALSE) -> 1.5456258e+09 | H48: =+VLOOKUP(A48,gasto!$A$4:$F$68,5,FALSE) -> 1.5456258e+09 | I48: =+VLOOKUP(A48,gasto!$A$4:$F$68,6,FALSE) -> 1.5456258e+09 | J48: =+G48+D48 -> 1.5456258e+09 | K48: =+H48+E48 -> 1.5456258e+09 | L48: =+I48+F48 -> 1.5456258e+09 | M48: =+IFERROR(K48*100/C48,0) -> 0.67872622 | N48: =+IFERROR(L48*100/C48,0) -> 0.67872622
A49: A-3-9-8-0-04 | B49: Apoyo Reclamaciones Reserva especial | C49: =+VLOOKUP(A49,gasto!$A$4:$F$68,3,FALSE) -> 250000000 | D49: 0 | E49: 0 | F49: 0 | G49: =+VLOOKUP(A49,gasto!$A$4:$F$68,4,FALSE) -> 0 | H49: =+VLOOKUP(A49,gasto!$A$4:$F$68,5,FALSE) -> 0 | I49: =+VLOOKUP(A49,gasto!$A$4:$F$68,6,FALSE) -> 0 | J49: =+G49+D49 -> 0 | K49: =+H49+E49 -> 0 | L49: =+I49+F49 -> 0 | M49: =+IFERROR(K49*100/C49,0) -> 0 | N49: =+IFERROR(L49*100/C49,0) -> 0
A50: A-3-9-8-0-05 | B50: Oficina de Gestión Territorial, Emergencias y Desastres-Atención de urgencias nacionales y extranjeros — zonas fronterizas. Art 57 Ley 1815 de 2016 | C50: =+VLOOKUP(A50,gasto!$A$4:$F$68,3,FALSE) -> 30000000000 | D50: 222768589 | E50: 222768589 | F50: 222768589 | G50: =+VLOOKUP(A50,gasto!$A$4:$F$68,4,FALSE) -> 0 | H50: =+VLOOKUP(A50,gasto!$A$4:$F$68,5,FALSE) -> 0 | I50: =+VLOOKUP(A50,gasto!$A$4:$F$68,6,FALSE) -> 0 | J50: =+G50+D50 -> 222768589 | K50: =+H50+E50 -> 222768589 | L50: =+I50+F50 -> 222768589 | M50: =+IFERROR(K50*100/C50,0) -> 0.74256196 | N50: =+IFERROR(L50*100/C50,0) -> 0.74256196
A51: A-3-9-8-0-06 | B51: Apoyo Reclamaciones Victimas Poblaciòn desplazada | C51: =+VLOOKUP(A51,gasto!$A$4:$F$68,3,FALSE) -> 9000000 | D51: 0 | E51: 0 | F51: 0 | G51: =+VLOOKUP(A51,gasto!$A$4:$F$68,4,FALSE) -> 0 | H51: =+VLOOKUP(A51,gasto!$A$4:$F$68,5,FALSE) -> 0 | I51: =+VLOOKUP(A51,gasto!$A$4:$F$68,6,FALSE) -> 0 | J51: =+G51+D51 -> 0 | K51: =+H51+E51 -> 0 | L51: =+I51+F51 -> 0 | M51: =+IFERROR(K51*100/C51,0) -> 0 | N51: =+IFERROR(L51*100/C51,0) -> 0
A52: A-3-9-9-0 | B52: Fortalecimiento Red Nacional de Urgencias, Emergencia Sanitaria y eventos Catastróficos | C52: =+SUM(C53:C55) -> 3988276390 | D52: 0 | E52: 0 | F52: 0 | G52: =+SUM(G53:G55) -> 0 | H52: =+SUM(H53:H55) -> 0 | I52: =+SUM(I53:I55) -> 0 | J52: =+SUM(J53:J55) -> 0 | K52: =+SUM(K53:K55) -> 0 | L52: =+SUM(L53:L55) -> 0 | M52: =+IFERROR(K52*100/C52,0) -> 0 | N52: =+IFERROR(L52*100/C52,0) -> 0
A53: A-3-9-9-0-01 | B53: Oficina de Gestión Territorial, Emergencias y Desastres-Fortalecimiento Red Nacional de Urgencias | C53: =+VLOOKUP(A53,gasto!$A$4:$F$68,3,FALSE) -> 3988276390 | D53: 0 | E53: 0 | F53: 0 | G53: =+VLOOKUP(A53,gasto!$A$4:$F$68,4,FALSE) -> 0 | H53: =+VLOOKUP(A53,gasto!$A$4:$F$68,5,FALSE) -> 0 | I53: =+VLOOKUP(A53,gasto!$A$4:$F$68,6,FALSE) -> 0 | J53: =+G53+D53 -> 0 | K53: =+H53+E53 -> 0 | L53: =+I53+F53 -> 0 | M53: =+IFERROR(K53*100/C53,0) -> 0 | N53: =+IFERROR(L53*100/C53,0) -> 0
A54: A-3-9-9-0-02 | B54: Emergencia Sanitaria | C54: =+VLOOKUP(A54,gasto!$A$4:$F$68,3,FALSE) -> 0 | D54: 0 | E54: 0 | F54: 0 | G54: =+VLOOKUP(A54,gasto!$A$4:$F$68,4,FALSE) -> 0 | H54: =+VLOOKUP(A54,gasto!$A$4:$F$68,5,FALSE) -> 0 | I54: =+VLOOKUP(A54,gasto!$A$4:$F$68,6,FALSE) -> 0 | J54: =+G54+D54 -> 0 | K54: =+H54+E54 -> 0 | L54: =+I54+F54 -> 0 | M54: =+IFERROR(K54*100/C54,0) -> 0 | N54: =+IFERROR(L54*100/C54,0) -> 0
A55: A-3-9-9-0-03 | B55: Eventos Catastróficos | C55: =+VLOOKUP(A55,gasto!$A$4:$F$68,3,FALSE) -> 0 | D55: 0 | E55: 0 | F55: 0 | G55: =+VLOOKUP(A55,gasto!$A$4:$F$68,4,FALSE) -> 0 | H55: =+VLOOKUP(A55,gasto!$A$4:$F$68,5,FALSE) -> 0 | I55: =+VLOOKUP(A55,gasto!$A$4:$F$68,6,FALSE) -> 0 | J55: =+G55+D55 -> 0 | K55: =+H55+E55 -> 0 | L55: =+I55+F55 -> 0 | M55: =+IFERROR(K55*100/C55,0) -> 0 | N55: =+IFERROR(L55*100/C55,0) -> 0
A56: A-3-9-10-0 | B56: Otros Programas de Salud Promoción y prevención | C56: =+SUM(C57:C65) -> 104120791000 | D56: 13835751052 | E56: 502751052 | F56: 502751052 | G56: =+SUM(G57:G65) -> 1727696652 | H56: =+SUM(H57:H65) -> 0 | I56: =+SUM(I57:I65) -> 0 | J56: =+SUM(J57:J65) -> 15563447704 | K56: =+SUM(K57:K65) -> 502751052 | L56: =+SUM(L57:L65) -> 502751052 | M56: =+IFERROR(K56*100/C56,0) -> 0.48285366 | N56: =+IFERROR(L56*100/C56,0) -> 0.48285366
A57: A-3-9-10-0-01 | B57: Dirección de Promoción y Prevención - Programas de Salud de P y P - VACUNAS | C57: =+VLOOKUP(A57,gasto!$A$4:$F$68,3,FALSE) -> 56595754535 | D57: 0 | E57: 0 | F57: 0 | G57: =+VLOOKUP(A57,gasto!$A$4:$F$68,4,FALSE) -> 0 | H57: =+VLOOKUP(A57,gasto!$A$4:$F$68,5,FALSE) -> 0 | I57: =+VLOOKUP(A57,gasto!$A$4:$F$68,6,FALSE) -> 0 | J57: =+G57+D57 -> 0 | K57: =+H57+E57 -> 0 | L57: =+I57+F57 -> 0 | M57: =+IFERROR(K57*100/C57,0) -> 0 | N57: =+IFERROR(L57*100/C57,0) -> 0
A58: A-3-9-10-0-02 | B58: Oficina de Promoción Social - programa de Atención Psicosocial y Salud Integral a Víctimas del Conflicto Armado Programa PAPSIVI | C58: =+VLOOKUP(A58,gasto!$A$4:$F$68,3,FALSE) -> 18000000000 | D58: 13835751052 | E58: 502751052 | F58: 502751052 | G58: =+VLOOKUP(A58,gasto!$A$4:$F$68,4,FALSE) -> 0 | H58: =+VLOOKUP(A58,gasto!$A$4:$F$68,5,FALSE) -> 0 | I58: =+VLOOKUP(A58,gasto!$A$4:$F$68,6,FALSE) -> 0 | J58: =+G58+D58 -> 13835751052 | K58: =+H58+E58 -> 502751052 | L58: =+I58+F58 -> 502751052 | M58: =+IFERROR(K58*100/C58,0) -> 2.7930614 | N58: =+IFERROR(L58*100/C58,0) -> 2.7930614
A59: A-3-9-10-0-03 | B59: Programa mujeres víctimas de la violencia | C59: =+VLOOKUP(A59,gasto!$A$4:$F$68,3,FALSE) -> 0 | D59: 0 | E59: 0 | F59: 0 | G59: =+VLOOKUP(A59,gasto!$A$4:$F$68,4,FALSE) -> 0 | H59: =+VLOOKUP(A59,gasto!$A$4:$F$68,5,FALSE) -> 0 | I59: =+VLOOKUP(A59,gasto!$A$4:$F$68,6,FALSE) -> 0 | J59: =+G59+D59 -> 0 | K59: =+H59+E59 -> 0 | L59: =+I59+F59 -> 0 | M59: =+IFERROR(K59*100/C59,0) -> 0 | N59: =+IFERROR(L59*100/C59,0) -> 0
A60: A-3-9-10-0-04 | B60: Otros Programas de Salud diferentes a los anteriores | C60: =+VLOOKUP(A60,gasto!$A$4:$F$68,3,FALSE) -> 0 | D60: 0 | E60: 0 | F60: 0 | G60: =+VLOOKUP(A60,gasto!$A$4:$F$68,4,FALSE) -> 0 | H60: =+VLOOKUP(A60,gasto!$A$4:$F$68,5,FALSE) -> 0 | I60: =+VLOOKUP(A60,gasto!$A$4:$F$68,6,FALSE) -> 0 | J60: =+G60+D60 -> 0 | K60: =+H60+E60 -> 0 | L60: =+I60+F60 -> 0 | M60: =+IFERROR(K60*100/C60,0) -> 0 | N60: =+IFERROR(L60*100/C60,0) -> 0
A61: A-3-9-10-0-05 | B61: Campañas de Prevencion de la Violencia y Promoción de la Convivencia Pacifica a Nivel Nacional o Territorial | C61: =+VLOOKUP(A61,gasto!$A$4:$F$68,3,FALSE) -> 409233681 | D61: 0 | E61: 0 | F61: 0 | G61: =+VLOOKUP(A61,gasto!$A$4:$F$68,4,FALSE) -> 0 | H61: =+VLOOKUP(A61,gasto!$A$4:$F$68,5,FALSE) -> 0 | I61: =+VLOOKUP(A61,gasto!$A$4:$F$68,6,FALSE) -> 0 | J61: =+G61+D61 -> 0 | K61: =+H61+E61 -> 0 | L61: =+I61+F61 -> 0 | M61: =+IFERROR(K61*100/C61,0) -> 0 | N61: =+IFERROR(L61*100/C61,0) -> 0
A62: A-3-9-10-0-06 | B62: Prevención y Sanción de Formas de Violencia y discriminación Contra las Mujeres | C62: =+VLOOKUP(A62,gasto!$A$4:$F$68,3,FALSE) -> 6001557319 | D62: 0 | E62: 0 | F62: 0 | G62: =+VLOOKUP(A62,gasto!$A$4:$F$68,4,FALSE) -> 1727696652 | H62: =+VLOOKUP(A62,gasto!$A$4:$F$68,5,FALSE) -> 0 | I62: =+VLOOKUP(A62,gasto!$A$4:$F$68,6,FALSE) -> 0 | J62: =+G62+D62 -> 1727696652 | K62: =+H62+E62 -> 0 | L62: =+I62+F62 -> 0 | M62: =+IFERROR(K62*100/C62,0) -> 0 | N62: =+IFERROR(L62*100/C62,0) -> 0
A63: A-3-9-10-0-07 | B63: Atención Usuario Protesis PIP Resolución 0258 de 2012 | C63: =+VLOOKUP(A63,gasto!$A$4:$F$68,3,FALSE) -> 160000000 | D63: 0 | E63: 0 | F63: 0 | G63: =+VLOOKUP(A63,gasto!$A$4:$F$68,4,FALSE) -> 0 | H63: =+VLOOKUP(A63,gasto!$A$4:$F$68,5,FALSE) -> 0 | I63: =+VLOOKUP(A63,gasto!$A$4:$F$68,6,FALSE) -> 0 | J63: =+G63+D63 -> 0 | K63: =+H63+E63 -> 0 | L63: =+I63+F63 -> 0 | M63: =+IFERROR(K63*100/C63,0) -> 0 | N63: =+IFERROR(L63*100/C63,0) -> 0
A64: A-3-9-10-0-08 | B64: Déficit Cajas de Compensación Familiar - Balance | C64: =+VLOOKUP(A64,gasto!$A$4:$F$68,3,FALSE) -> 2000000000 | D64: 0 | E64: 0 | F64: 0 | G64: =+VLOOKUP(A64,gasto!$A$4:$F$68,4,FALSE) -> 0 | H64: =+VLOOKUP(A64,gasto!$A$4:$F$68,5,FALSE) -> 0 | I64: =+VLOOKUP(A64,gasto!$A$4:$F$68,6,FALSE) -> 0 | J64: =+G64+D64 -> 0 | K64: =+H64+E64 -> 0 | L64: =+I64+F64 -> 0 | M64: =+IFERROR(K64*100/C64,0) -> 0 | N64: =+IFERROR(L64*100/C64,0) -> 0
A65: A-3-9-10-0-09 | B65: Certificado de Discapacidad, Suministro de Fórmula Terapéutica | C65: =+VLOOKUP(A65,gasto!$A$4:$F$68,3,FALSE) -> 20954245465 | D65: 0 | E65: 0 | F65: 0 | G65: =+VLOOKUP(A65,gasto!$A$4:$F$68,4,FALSE) -> 0 | H65: =+VLOOKUP(A65,gasto!$A$4:$F$68,5,FALSE) -> 0 | I65: =+VLOOKUP(A65,gasto!$A$4:$F$68,6,FALSE) -> 0 | J65: =+G65+D65 -> 0 | K65: =+H65+E65 -> 0 | L65: =+I65+F65 -> 0 | M65: =+IFERROR(K65*100/C65,0) -> 0 | N65: =+IFERROR(L65*100/C65,0) -> 0
A66: A-3-9-11-0 | B66: Recursos con destinación específica | C66: =+SUM(C67:C76) -> 366925255924 | D66: 0 | E66: 0 | F66: 0 | G66: =+SUM(G67:G76) -> 126804327603 | H66: =+SUM(H67:H76) -> 1293105057 | I66: =+SUM(I67:I76) -> 1293105057 | J66: =+SUM(J67:J76) -> 126804327603 | K66: =+SUM(K67:K76) -> 1293105057 | L66: =+SUM(L67:L76) -> 1293105057 | M66: =+IFERROR(K66*100/C66,0) -> 0.35241648 | N66: =+IFERROR(L66*100/C66,0) -> 0.35241648
A67: A-3-9-11-0-01 | B67: Pago a IPS de servicios prestados a la población pobre no asegurada y servicios no incluidos en el Plan de beneficios Pago a IPS de servicios prestados a la población, exceden(Art. 3 Ley 1608 de 2013) | C67: =+VLOOKUP(A67,gasto!$A$4:$F$68,3,FALSE) -> 5801668388 | D67: 0 | E67: 0 | F67: 0 | G67: =+VLOOKUP(A67,gasto!$A$4:$F$68,4,FALSE) -> 0 | H67: =+VLOOKUP(A67,gasto!$A$4:$F$68,5,FALSE) -> 0 | I67: =+VLOOKUP(A67,gasto!$A$4:$F$68,6,FALSE) -> 0 | J67: =+G67+D67 -> 0 | K67: =+H67+E67 -> 0 | L67: =+I67+F67 -> 0 | M67: =+IFERROR(K67*100/C67,0) -> 0 | N67: =+IFERROR(L67*100/C67,0) -> 0
A68: A-3-9-11-0-02 | B68: Reconocimiento de deuda por contratos del Régimen Subsidiado realizados hasta marzo 31 de 2011- Recursos LOTTO en Línea – FONPET | C68: =+VLOOKUP(A68,gasto!$A$4:$F$68,3,FALSE) -> 5000000000 | D68: 0 | E68: 0 | F68: 0 | G68: =+VLOOKUP(A68,gasto!$A$4:$F$68,4,FALSE) -> 0 | H68: =+VLOOKUP(A68,gasto!$A$4:$F$68,5,FALSE) -> 0 | I68: =+VLOOKUP(A68,gasto!$A$4:$F$68,6,FALSE) -> 0 | J68: =+G68+D68 -> 0 | K68: =+H68+E68 -> 0 | L68: =+I68+F68 -> 0 | M68: =+IFERROR(K68*100/C68,0) -> 0 | N68: =+IFERROR(L68*100/C68,0) -> 0
A69: A-3-9-11-0-03 | B69: Reconocimiento de deuda por contratos del Régimen Subsidiado realizados hasta marzo 31 de 2011- Recursos FAEP | C69: =+VLOOKUP(A69,gasto!$A$4:$F$68,3,FALSE) -> 800000000 | D69: 0 | E69: 0 | F69: 0 | G69: =+VLOOKUP(A69,gasto!$A$4:$F$68,4,FALSE) -> 0 | H69: =+VLOOKUP(A69,gasto!$A$4:$F$68,5,FALSE) -> 0 | I69: =+VLOOKUP(A69,gasto!$A$4:$F$68,6,FALSE) -> 0 | J69: =+G69+D69 -> 0 | K69: =+H69+E69 -> 0 | L69: =+I69+F69 -> 0 | M69: =+IFERROR(K69*100/C69,0) -> 0 | N69: =+IFERROR(L69*100/C69,0) -> 0
A70: A-3-9-11-0-04 | B70: Pago de deudas Régimen Subsidiado – Artículo 275 de la Ley 1450 de 2011 - SGP Libre Inversión | C70: =+VLOOKUP(A70,gasto!$A$4:$F$68,3,FALSE) -> 20000000000 | D70: 0 | E70: 0 | F70: 0 | G70: =+VLOOKUP(A70,gasto!$A$4:$F$68,4,FALSE) -> 0 | H70: =+VLOOKUP(A70,gasto!$A$4:$F$68,5,FALSE) -> 0 | I70: =+VLOOKUP(A70,gasto!$A$4:$F$68,6,FALSE) -> 0 | J70: =+G70+D70 -> 0 | K70: =+H70+E70 -> 0 | L70: =+I70+F70 -> 0 | M70: =+IFERROR(K70*100/C70,0) -> 0 | N70: =+IFERROR(L70*100/C70,0) -> 0
A71: A-3-9-11-0-05 | B71: Excedentes de Aportes Patronales / Resolución 2360 de 2016 | C71: =+VLOOKUP(A71,gasto!$A$4:$F$68,3,FALSE) -> 49454127709 | D71: 0 | E71: 0 | F71: 0 | G71: =+VLOOKUP(A71,gasto!$A$4:$F$68,4,FALSE) -> 0 | H71: =+VLOOKUP(A71,gasto!$A$4:$F$68,5,FALSE) -> 0 | I71: =+VLOOKUP(A71,gasto!$A$4:$F$68,6,FALSE) -> 0 | J71: =+G71+D71 -> 0 | K71: =+H71+E71 -> 0 | L71: =+I71+F71 -> 0 | M71: =+IFERROR(K71*100/C71,0) -> 0 | N71: =+IFERROR(L71*100/C71,0) -> 0
A72: A-3-9-11-0-06 | B72: Regalías – Art. 5 Ley 1797 de 2016 | C72: =+VLOOKUP(A72,gasto!$A$4:$F$68,3,FALSE) -> 3000000000 | D72: 0 | E72: 0 | F72: 0 | G72: =+VLOOKUP(A72,gasto!$A$4:$F$68,4,FALSE) -> 0 | H72: =+VLOOKUP(A72,gasto!$A$4:$F$68,5,FALSE) -> 0 | I72: =+VLOOKUP(A72,gasto!$A$4:$F$68,6,FALSE) -> 0 | J72: =+G72+D72 -> 0 | K72: =+H72+E72 -> 0 | L72: =+I72+F72 -> 0 | M72: =+IFERROR(K72*100/C72,0) -> 0 | N72: =+IFERROR(L72*100/C72,0) -> 0
A73: A-3-9-11-0-07 | B73: Otros Recursos con Destinación Especifica | C73: =+VLOOKUP(A73,gasto!$A$4:$F$68,3,FALSE) -> 55000000000 | D73: 0 | E73: 0 | F73: 0 | G73: =+VLOOKUP(A73,gasto!$A$4:$F$68,4,FALSE) -> 10502751052 | H73: =+VLOOKUP(A73,gasto!$A$4:$F$68,5,FALSE) -> 0 | I73: =+VLOOKUP(A73,gasto!$A$4:$F$68,6,FALSE) -> 0 | J73: =+G73+D73 -> 10502751052 | K73: =+H73+E73 -> 0 | L73: =+I73+F73 -> 0 | M73: =+IFERROR(K73*100/C73,0) -> 0 | N73: =+IFERROR(L73*100/C73,0) -> 0
A74: A-3-9-11-0-08 | B74: Recursos CCF / FOSFEC - Ley 1929 de 2018 | C74: =+VLOOKUP(A74,gasto!$A$4:$F$68,3,FALSE) -> 36000000000 | D74: 0 | E74: 0 | F74: 0 | G74: =+VLOOKUP(A74,gasto!$A$4:$F$68,4,FALSE) -> 0 | H74: =+VLOOKUP(A74,gasto!$A$4:$F$68,5,FALSE) -> 0 | I74: =+VLOOKUP(A74,gasto!$A$4:$F$68,6,FALSE) -> 0 | J74: =+G74+D74 -> 0 | K74: =+H74+E74 -> 0 | L74: =+I74+F74 -> 0 | M74: =+IFERROR(K74*100/C74,0) -> 0 | N74: =+IFERROR(L74*100/C74,0) -> 0
A75: A-3-9-11-0-09 | B75: Saneamiento aportes patronales SGP | C75: =+VLOOKUP(A75,gasto!$A$4:$F$68,3,FALSE) -> 76869459827 | D75: 0 | E75: 0 | F75: 0 | G75: =+VLOOKUP(A75,gasto!$A$4:$F$68,4,FALSE) -> 1301576551 | H75: =+VLOOKUP(A75,gasto!$A$4:$F$68,5,FALSE) -> 1293105057 | I75: =+VLOOKUP(A75,gasto!$A$4:$F$68,6,FALSE) -> 1293105057 | J75: =+G75+D75 -> 1301576551 | K75: =+H75+E75 -> 1293105057 | L75: =+I75+F75 -> 1293105057 | M75: =+IFERROR(K75*100/C75,0) -> 1.6822091 | N75: =+IFERROR(L75*100/C75,0) -> 1.6822091
A76: A-3-9-11-0-10 | B76: Devolución recursos Entidades Territoriales | C76: =+VLOOKUP(A76,gasto!$A$4:$F$68,3,FALSE) -> 115000000000 | D76: 0 | E76: 0 | F76: 0 | G76: =+VLOOKUP(A76,gasto!$A$4:$F$68,4,FALSE) -> 115000000000 | H76: =+VLOOKUP(A76,gasto!$A$4:$F$68,5,FALSE) -> 0 | I76: =+VLOOKUP(A76,gasto!$A$4:$F$68,6,FALSE) -> 0 | J76: =+G76+D76 -> 115000000000 | K76: =+H76+E76 -> 0 | L76: =+I76+F76 -> 0 | M76: =+IFERROR(K76*100/C76,0) -> 0 | N76: =+IFERROR(L76*100/C76,0) -> 0
A77: A-3-9-12-0 | B77: Pago Obligaciones ESE´S con Recursos FONSAET | C77: =+C78 -> 95551523562 | D77: 0 | E77: 0 | F77: 0 | G77: =+G78 -> 0 | H77: =+H78 -> 0 | I77: =+I78 -> 0 | J77: =+J78 -> 0 | K77: =+K78 -> 0 | L77: =+L78 -> 0 | M77: =+IFERROR(K77*100/C77,0) -> 0 | N77: =+IFERROR(L77*100/C77,0) -> 0
A78: A-3-9-12-0-01 | B78: Pago Obligaciones EPS FONSAET | C78: =+VLOOKUP(A78,gasto!$A$4:$F$68,3,FALSE) -> 95551523562 | D78: 0 | E78: 0 | F78: 0 | G78: =+VLOOKUP(A78,gasto!$A$4:$F$68,4,FALSE) -> 0 | H78: =+VLOOKUP(A78,gasto!$A$4:$F$68,5,FALSE) -> 0 | I78: =+VLOOKUP(A78,gasto!$A$4:$F$68,6,FALSE) -> 0 | J78: =+G78+D78 -> 0 | K78: =+H78+E78 -> 0 | L78: =+I78+F78 -> 0 | M78: =+IFERROR(K78*100/C78,0) -> 0 | N78: =+IFERROR(L78*100/C78,0) -> 0
A79: A-3-9-13-0 | B79: Reconocimiento Rendimientos Financieros cuentas de recaudo EPS SSF | C79: =+C80 -> 7615081557 | D79: 1552635328 | E79: 1552635328 | F79: 1552635328 | G79: =+G80 -> 0 | H79: =+H80 -> 0 | I79: =+I80 -> 0 | J79: =+J80 -> 1552635328 | K79: =+K80 -> 1552635328 | L79: =+L80 -> 1552635328 | M79: =+IFERROR(K79*100/C79,0) -> 20.388952 | N79: =+IFERROR(L79*100/C79,0) -> 20.388952
A80: A-3-9-13-0-01 | B80: Rendimientos Financieros EPS SSF | C80: =+VLOOKUP(A80,gasto!$A$4:$F$68,3,FALSE) -> 7615081557 | D80: 1552635328 | E80: 1552635328 | F80: 1552635328 | G80: =+VLOOKUP(A80,gasto!$A$4:$F$68,4,FALSE) -> 0 | H80: =+VLOOKUP(A80,gasto!$A$4:$F$68,5,FALSE) -> 0 | I80: =+VLOOKUP(A80,gasto!$A$4:$F$68,6,FALSE) -> 0 | J80: =+G80+D80 -> 1552635328 | K80: =+H80+E80 -> 1552635328 | L80: =+I80+F80 -> 1552635328 | M80: =+IFERROR(K80*100/C80,0) -> 20.388952 | N80: =+IFERROR(L80*100/C80,0) -> 20.388952
A81: A-3-9-14-0 | B81: Apoyo Financiero y Fortalecimiento Patrimonial a las Entidades del Sector Salud | C81: =+SUM(C82:C84) -> 100000000000 | D81: 0 | E81: 0 | F81: 0 | G81: =+SUM(G82:G84) -> 0 | H81: =+SUM(H82:H84) -> 0 | I81: =+SUM(I82:I84) -> 0 | J81: =+SUM(J82:J84) -> 0 | K81: =+SUM(K82:K84) -> 0 | L81: =+SUM(L82:L84) -> 0 | M81: =+IFERROR(K81*100/C81,0) -> 0 | N81: =+IFERROR(L81*100/C81,0) -> 0
A82: A-3-9-14-0-01 | B82: Operaciones de Compra de Cartera | C82: =+VLOOKUP(A82,gasto!$A$4:$F$100,3,FALSE) -> 60000000000 | D82: 0 | E82: 0 | F82: 0 | G82: =+VLOOKUP(A82,gasto!$A$4:$F$100,4,FALSE) -> 0 | H82: =+VLOOKUP(A82,gasto!$A$4:$F$100,5,FALSE) -> 0 | I82: =+VLOOKUP(A82,gasto!$A$4:$F$100,6,FALSE) -> 0 | J82: =+G82+D82 -> 0 | K82: =+H82+E82 -> 0 | L82: =+I82+F82 -> 0 | M82: =+IFERROR(K82*100/C82,0) -> 0 | N82: =+IFERROR(L82*100/C82,0) -> 0
A83: A-3-9-14-0-02 | B83: Operaciones de Fortalecimiento Patrimonial Tasa Compensada | C83: =+VLOOKUP(A83,gasto!$A$4:$F$100,3,FALSE) -> 40000000000 | D83: 0 | E83: 0 | F83: 0 | G83: =+VLOOKUP(A83,gasto!$A$4:$F$100,4,FALSE) -> 0 | H83: =+VLOOKUP(A83,gasto!$A$4:$F$100,5,FALSE) -> 0 | I83: =+VLOOKUP(A83,gasto!$A$4:$F$100,6,FALSE) -> 0 | J83: =+G83+D83 -> 0 | K83: =+H83+E83 -> 0 | L83: =+I83+F83 -> 0 | M83: =+IFERROR(K83*100/C83,0) -> 0 | N83: =+IFERROR(L83*100/C83,0) -> 0
A84: A-3-9-14-0-03 | B84: Operaciones de Fortalecimiento Patrimonial - Bocas | C84: =+VLOOKUP(A84,gasto!$A$4:$F$100,3,FALSE) -> 0 | D84: 0 | E84: 0 | F84: 0 | G84: =+VLOOKUP(A84,gasto!$A$4:$F$100,4,FALSE) -> 0 | H84: =+VLOOKUP(A84,gasto!$A$4:$F$100,5,FALSE) -> 0 | I84: =+VLOOKUP(A84,gasto!$A$4:$F$100,6,FALSE) -> 0 | J84: =+G84+D84 -> 0 | K84: =+H84+E84 -> 0 | L84: =+I84+F84 -> 0 | M84: =+IFERROR(K84*100/C84,0) -> 0 | N84: =+IFERROR(L84*100/C84,0) -> 0
A85: A-9-9-9-9 | B85: Disponibilidad Final | C85: =+VLOOKUP(A85,gasto!$A$4:$F$100,3,FALSE) -> 254007875000 | D85: 0 | E85: 0 | F85: 0 | G85: =+VLOOKUP(A85,gasto!$A:$K,4,FALSE) -> 0 | H85: =+VLOOKUP(A85,gasto!$A:$K,4,FALSE) -> 0 | I85: =+VLOOKUP(A85,gasto!$A:$K,4,FALSE) -> 0 | J85: =+G85+D85 -> 0 | K85: =+H85+E85 -> 0 | L85: =+I85+F85 -> 0 | M85: =+IFERROR(K85*100/C85,0) -> 0 | N85: =+IFERROR(L85*100/C85,0) -> 0
A87: TOTAL | B87: TOTAL | C87: =+C85+C12 -> 52636824590223 | D87: =+D85+D12 -> 8.1885623e+12 | E87: =+E85+E12 -> 7.9637997e+12 | F87: =+F85+F12 -> 7.9637997e+12 | G87: =+G85+G12 -> 4.2065312e+12 | H87: =+H85+H12 -> 4.0422416e+12 | I87: =+I85+I12 -> 4.0422416e+12 | J87: =+J85+J12 -> 1.2395093e+13 | ... L87: =+L85+L12 -> 1.2006041e+13 | M87: =+IFERROR(K87*100/C87,0) -> 22.809205 | N87: =+IFERROR(L87*100/C87,0) -> 22.809205
C88: 52636824590223 | D88: 8.1885623e+12 | E88: 7.9637997e+12 | F88: 7.9637997e+12 | G88: 4.2065312e+12 | H88: 4.0422416e+12 | I88: 4.0422416e+12 | J88: 1.2395093e+13 | K88: 1.2006041e+13 | L88: 1.2006041e+13 | M88: 22.81 | N88: 22.81
C89: =+C88-C87 -> 0 | D89: =+D88-D87 -> 0 | E89: =+E88-E87 -> 0 | F89: =+F88-F87 -> 0 | G89: =+G88-G87 -> 0 | H89: =+H88-H87 -> 0 | I89: =+I88-I87 -> 0 | J89: =+J88-J87 -> -0.08984375 | ... N89: =+N88-N87 -> 0.00079485636
C90: =+C88/1000000 -> 52636825 | D90: =+D88/1000000 -> 8188562.3 | E90: =+E88/1000000 -> 7963799.7 | F90: =+F88/1000000 -> 7963799.7 | G90: =+G88/1000000 -> 4206531.2 | H90: =+H88/1000000 -> 4042241.6 | I90: =+I88/1000000 -> 4042241.6 | J90: =+J88/1000000 -> 12395093 | ... L90: =+L88/1000000 -> 12006041
C91: dif. Por excel | D91: dif. Por excel

Sheet ingresos
A1: RUBRO | B1: inicial | C1: MODIFICACIONES | D1: AFORO DEFINITIVO | E1: INGRESO MES | F1: % | G1: acum
A2: 0-0-0-0 | B2: 422831681000 | C2: 0 | D2: 422831681000 | E2: 0 | G2: 422831681000 | H2: =+VLOOKUP(A2,'CUADRO 1-EJECUCION DE INGRESOS'!$A$11:$I$97,8,FALSE) -> 422831681000 | I2: =+H2-G2 -> 0
A3: 1-2-1-1 | B3: 17803782346000 | C3: 0 | D3: 17803782346000 | E3: 1241981862167 | G3: 3725945586501 | H3: =+VLOOKUP(A3,'CUADRO 1-EJECUCION DE INGRESOS'!$A$11:$I$97,8,FALSE) -> 3725945586501 | I3: =+H3-G3 -> 0
A4: 1-2-1-1-01 | B4: 13686804885516 | C4: 0 | D4: 13686804885516 | E4: 954783825621 | G4: 2.8643515e+12 | H4: =+VLOOKUP(A4,'CUADRO 1-EJECUCION DE INGRESOS'!$A$11:$I$97,8,FALSE) -> 2.8643515e+12 | I4: =+H4-G4 -> 0
A5: 1-2-1-1-02 | B5: 4116977460484 | C5: 0 | D5: 4116977460484 | E5: 287198036546 | G5: 8.6159411e+11 | H5: =+VLOOKUP(A5,'CUADRO 1-EJECUCION DE INGRESOS'!$A$11:$I$97,8,FALSE) -> 8.6159411e+11 | I5: =+H5-G5 -> 0
A6: 1-2-1-2 | B6: 226673765000 | C6: 0 | D6: 226673765000 | E6: 113336882500 | G6: 226673765000 | H6: =+VLOOKUP(A6,'CUADRO 1-EJECUCION DE INGRESOS'!$A$11:$I$97,8,FALSE) -> 226673765000 | I6: =+H6-G6 -> 0
A7: 1-2-1-3 | B7: 0 | C7: 0 | D7: 0 | E7: 0 | G7: 0 | H7: =+VLOOKUP(A7,'CUADRO 1-EJECUCION DE INGRESOS'!$A$11:$I$97,8,FALSE) -> 0 | I7: =+H7-G7 -> 0
A8: 1-2-1-4 | B8: 95551523562 | C8: 0 | D8: 95551523562 | E8: 0 | G8: 0 | H8: =+VLOOKUP(A8,'CUADRO 1-EJECUCION DE INGRESOS'!$A$11:$I$97,8,FALSE) -> 0 | I8: =+H8-G8 -> 0
A9: 1-2-1-5 | B9: 1640527441000 | C9: 0 | D9: 1640527441000 | E9: 1.6024653e+11 | G9: 5.0275609e+11 | H9: =+VLOOKUP(A9,'CUADRO 1-EJECUCION DE INGRESOS'!$A$11:$I$97,8,FALSE) -> 5.0275609e+11 | I9: =+H9-G9 -> 0
A10: 1-2-1-5-01 | B10: 363281118360 | C10: 0 | D10: 363281118360 | E10: 5.707715e+10 | G10: 1.347828e+11 | H10: =+VLOOKUP(A10,'CUADRO 1-EJECUCION DE INGRESOS'!$A$11:$I$97,8,FALSE) -> 1.347828e+11 | I10: =+H10-G10 -> 0
A11: 1-2-1-5-02 | B11: 1277246322640 | C11: 0 | D11: 1277246322640 | E11: 1.0316938e+11 | G11: 3.6797329e+11 | H11: =+VLOOKUP(A11,'CUADRO 1-EJECUCION DE INGRESOS'!$A$11:$I$97,8,FALSE) -> 3.6797329e+11 | I11: =+H11-G11 -> 0
A12: 1-2-1-7 | B12: 6410791000 | C12: 0 | D12: 6410791000 | E12: 9314667807 | G12: 27002691071 | H12: =+VLOOKUP(A12,'CUADRO 1-EJECUCION DE INGRESOS'!$A$11:$I$97,8,FALSE) -> 27002691071 | I12: =+H12-G12 -> 0
A13: 1-2-1-8 | B13: 8851770619 | C13: 0 | D13: 8851770619 | E13: 681954075 | G13: 1661782912 | H13: =+VLOOKUP(A13,'CUADRO 1-EJECUCION DE INGRESOS'!$A$11:$I$97,8,FALSE) -> 1661782912 | I13: =+H13-G13 -> 0
... A81: 2-9-0-0-01 | B81: 0 | C81: 0 | D81: 0 | E81: 0 | G81: 0 | H81: =+VLOOKUP(A81,'CUADRO 1-EJECUCION DE INGRESOS'!$A$11:$I$97,8,FALSE) -> 0 | I81: =+H81-G81 -> 0
A82: 2-9-0-0-02 | B82: 0 | D82: 0 | E82: 2737805 | G82: 7152423 | H82: =+VLOOKUP(A82,'CUADRO 1-EJECUCION DE INGRESOS'!$A$11:$I$97,8,FALSE) -> 7152423 | I82: =+H82-G82 -> 0

Sheet gasto
D1: República de Colombia | E1: EJECUCIÓN DE EGRESOS ACUMULADOS | F1: ADRES ADMINISTRADORA DE LOS RECURSOS DEL SGSSS
A2: CÓDIGO RUBRO | B2: CONCEPTO DEL RUBRO | C2: APROPIACIÓN DEFINITIVA | D2: CDP | E2: RP | F2: PAGOS-OGAG | G2: T. CDP | H2: T. RP | I2: T. PAGOS-OGAG | J2: RP | K2: PAGOS
A3: URA
A4: A-3-2-1-0 | B4: Transferencias Entidades de Administración Pública Central | C4: 86345030430 | D4: 0 | E4: 6.8799777e+09 | F4: 6.8799777e+09 | G4: 82805519661 | H4: 2.0680898e+10 | I4: 2.0680898e+10 | J4: 23.95 | K4: 23.95
A5: A-3-2-1-01 | B5: Contribución IVC Superintendencia Nacional de Salud | C5: 86345030430 | D5: 0 | E5: 6.8799777e+09 | F5: 6.8799777e+09 | G5: 82805519661 | H5: 2.0680898e+10 | I5: 2.0680898e+10 | J5: 23.95 | K5: 23.95
A6: A-3-2-2-0 | B6: Empresas Públicas Nacionales no financieras -ADRES | C6: 145380000000 | D6: 0 | E6: 2.224672e+09 | F6: 2.224672e+09 | G6: 145380000000 | H6: 8.7087929e+09 | I6: 8.7087929e+09 | J6: 5.99 | K6: 5.99
A7: A-3-2-2-0-01 | B7: Aportes hasta del 0,5% recursos CSF para el desarrollo objeto ADRES | C7: 145380000000 | D7: 0 | E7: 2.224672e+09 | F7: 2.224672e+09 | G7: 145380000000 | H7: 8.7087929e+09 | I7: 8.7087929e+09 | J7: 5.99 | K7: 5.99
A8: A-3-6-1-0 | B8: Sentencias y Conciliaciones URA | C8: 20000000000 | D8: 31449750 | E8: 31449750 | F8: 31449750 | G8: 33105982 | H8: 33105982 | I8: 33105982 | J8: 0.17 | K8: 0.17
A9: A-3-6-1-1 | B9: Sentencias URA | C9: 20000000000 | D9: 31449750 | E9: 31449750 | F9: 31449750 | G9: 33105982 | H9: 33105982 | I9: 33105982 | J9: 0.17 | K9: 0.17
A10: A-3-6-1-2 | B10: Conciliaciones URA | C10: 0 | D10: 0 | E10: 0 | F10: 0 | G10: 0 | H10: 0 | I10: 0 | J10: 0 | K10: 0
A11: A-3-6-3-0 | B11: Destinatarios de otras transferencias Corrientes - Compensación Chance | C11: 160000000000 | D11: 0 | E11: 0 | F11: 0 | G11: 0 | H11: 0 | I11: 0 | J11: 0 | K11: 0
A12: A-3-6-3-0-01 | B12: Otras transferencias - Compensación del Chance Decreto 2550/12 | C12: 160000000000 | D12: 0 | E12: 0 | F12: 0 | G12: 0 | H12: 0 | I12: 0 | J12: 0 | K12: 0
A13: A-3-9-1-0 | B13: UPC Régimen Contributivo | C13: 23057892632980 | D13: 1834230895932 | E13: 1824562647330 | F13: 1824562647330 | G13: 5420819628733 | H13: 5411151380131 | I13: 5411151380131 | J13: 23.47 | K13: 23.47
A14: A-3-9-1-0-01 | B14: UPC Régimen Contributivo SSF | C14: 12399109660289 | D14: 1041100938124 | E14: 1041100938124 | F14: 1041100938124 | G14: 2958737021117 | H14: 2958737021117 | I14: 2958737021117 | J14: 23.86 | K14: 23.86
A15: A-3-9-1-0-02 | B15: UPC Régimen Contributivo CSF | C15: 10647939289644 | D15: 783128428075 | E15: 783128428075 | F15: 783128428075 | G15: 2451238924569 | H15: 2451238924569 | I15: 2451238924569 | J15: 23.02 | K15: 23.02
... A73: A-9-9-9-9 | B73: Disponibilidad Final | C73: 254007875000 | D73: 0 | E73: 0 | F73: 0 | G73: 0 | H73: 0 | I73: 0 | J73: 0 | K73: 0
F84: =+'CUADRO 2-EJECUCION DE GASTOS'!I89+gasto!F21 -> 65846859451
