Workbook
Name OLE_LINK1: 'CUADRO 2-EJECUCION DE GASTOS'!#REF!

Sheet CUADRO 1-EJECUCION DE INGRESOS
H1: =+NOW() -> 43522.607 | I1: =+NOW() -> 43522.607
A3: ADMINISTRADORA DE LOS RECURSOS DEL SISTEMA GENERAL DE SEGURIDAD SOCIAL EN SALUD
A4: PRESUPUESTO DE INGRESOS 2019
A5: UNIDAD DE RECURSOS ADMINISTRADOS - URA
A6: CUADRO No. 1
A9: CÓDIGO RUBRO | B9: CONCEPTO DEL RUBRO | C9: AFORO INICIAL | D9: MODIFICACIÓN PRESUPUESTAL | E9: AFORO DEFINITIVO | F9: Ingresos Acumulados Desde 01/01/2019 hasta 01/01/2019 | G9: Ingresos Desde 01/01/2019 hasta 31/01/2019 | H9: Ingresos Acumulados Desde 01/01/2019 hasta 31/01/2019 | I9: EJECUCIÓN ACUMULADA (%)
A10: URA
A11: 0-0-0-0 | B11: DISPONIBILIDAD INICIAL | C11: =+VLOOKUP(A11,ingresos!$A$1:$B$81,2,) -> 422831681000 | D11: =+VLOOKUP(A11,ingresos!$A$1:$F$81,3,FALSE) -> 0 | E11: =+VLOOKUP(A11,ingresos!$A$1:$F$81,4,FALSE) -> 422831681000 | F11: 0 | G11: =+VLOOKUP(A11,ingresos!$A$1:$E$100,5,FALSE) -> 422831681000 | H11: =+G11+F11 -> 422831681000 | I11: =IFERROR(H11/E11*100,0) -> 100
A12: 1-0-0-0 | B12: INGRESOS CORRIENTES | C12: =+C13+C27 -> 52054407755223 | D12: =+D13+D27 -> 0 | E12: =+E13+E27 -> 52054407755223 | F12: 0 | G12: =+G13+G27 -> 4.2522704e+12 | H12: =+G12+F12 -> 4.2522704e+12 | I12: =IFERROR(H12/E12*100,0) -> 8.1688959
A13: 1-2-0-0 | B13: Aportes e Impuestos | C13: =+C14+C26 -> 19781797637181 | D13: =+D14 -> 0 | E13: =+E14+E26 -> 19781797637181 | F13: 0 | G13: =+G14+G26 -> 1.5037638e+12 | H13: =+G13+F13 -> 1.5037638e+12 | I13: =IFERROR(H13/E13*100,0) -> 7.6017552
A14: 1-2-1-0 | B14: Aportes de la Nación | C14: =+C15+C18+C19+C20+C21+C25+C24+C26 -> 19781797637181 | D14: =+D15+D18+D19+D20+D21+D24+D25 -> 0 | E14: =+E15+E18+E19+E20+E21+E25+E24+E26 -> 19781797637181 | F14: 0 | G14: =+G15+G18+G19+G20+G21+G25+G24+G26 -> 1.5037638e+12 | H14: =+G14+F14 -> 1.5037638e+12 | I14: =IFERROR(H14/E14*100,0) -> 7.6017552
A15: 1-2-1-1 | B15: Aportes de la Nación para el Aseguramiento en Salud | C15: =+SUM(C16:C17) -> 17803782346000 | D15: =+D16+D17 -> 0 | E15: =+E16+E17 -> 17803782346000 | F15: 0 | G15: =+SUM(G16:G17) -> 1241981862167 | H15: =+G15+F15 -> 1241981862167 | I15: =IFERROR(H15/E15*100,0) -> 6.9759439
A16: 1-2-1-1-01 | B16: Aportes de la Nación para el Aseguramiento en Salud Cierre | C16: =+VLOOKUP(A16,ingresos!$A$1:$B$81,2,) -> 13686804885516 | D16: =+VLOOKUP(A16,ingresos!$A$1:$F$81,3,FALSE) -> 0 | E16: =+VLOOKUP(A16,ingresos!$A$1:$F$81,4,FALSE) -> 13686804885516 | F16: 0 | G16: =+VLOOKUP(A16,ingresos!$A$1:$E$100,5,FALSE) -> 9.5478383e+11 | H16: =+G16+F16 -> 9.5478383e+11 | I16: =IFERROR(H16/E16*100,0) -> 6.9759439
A17: 1-2-1-1-02 | B17: Imporenta | C17: =+VLOOKUP(A17,ingresos!$A$1:$B$81,2,) -> 4116977460484 | D17: =+VLOOKUP(A17,ingresos!$A$1:$F$81,3,FALSE) -> 0 | E17: =+VLOOKUP(A17,ingresos!$A$1:$F$81,4,FALSE) -> 4116977460484 | F17: 0 | G17: =+VLOOKUP(A17,ingresos!$A$1:$E$100,5,FALSE) -> 2.8719804e+11 | H17: =+G17+F17 -> 2.8719804e+11 | I17: =IFERROR(H17/E17*100,0) -> 6.9759439
A18: 1-2-1-2 | B18: Compensación Regalías para el Régimen Subsidiado | C18: =+VLOOKUP(A18,ingresos!$A$1:$B$81,2,) -> 226673765000 | D18: =+VLOOKUP(A18,ingresos!$A$1:$F$81,3,FALSE) -> 0 | E18: =+VLOOKUP(A18,ingresos!$A$1:$F$81,4,FALSE) -> 226673765000 | F18: 0 | G18: =+VLOOKUP(A18,ingresos!$A$1:$E$100,5,FALSE) -> 0 | H18: =+G18+F18 -> 0 | I18: =IFERROR(H18/E18*100,0) -> 0
A19: 1-2-1-3 | B19: Impuesto sobre la renta para la equidad CREE | C19: =+VLOOKUP(A19,ingresos!$A$1:$B$81,2,) -> 0 | D19: =+VLOOKUP(A19,ingresos!$A$1:$F$81,3,FALSE) -> 0 | E19: =+VLOOKUP(A19,ingresos!$A$1:$F$81,4,FALSE) -> 0 | F19: 0 | G19: =+VLOOKUP(A19,ingresos!$A$1:$E$100,5,FALSE) -> 0 | H19: =+G19+F19 -> 0 | I19: =IFERROR(H19/E19*100,0) -> 0
A20: 1-2-1-4 | B20: SGP FONSAET | C20: =+VLOOKUP(A20,ingresos!$A$1:$B$81,2,) -> 95551523562 | D20: =+VLOOKUP(A20,ingresos!$A$1:$F$81,3,FALSE) -> 0 | E20: =+VLOOKUP(A20,ingresos!$A$1:$F$81,4,FALSE) -> 95551523562 | F20: 0 | G20: =+VLOOKUP(A20,ingresos!$A$1:$E$100,5,FALSE) -> 0 | H20: =+G20+F20 -> 0 | I20: =IFERROR(H20/E20*100,0) -> 0
A21: 1-2-1-5 | B21: PRIMA FONSAT Y CONTRIBUCION SOAT | C21: =+SUM(C22:C23) -> 1640527441000 | D21: =+D22+D23 -> 0 | E21: =+E22+E23 -> 1640527441000 | F21: 0 | G21: =+SUM(G22:G23) -> 2.455599e+11 | H21: =+G21+F21 -> 2.455599e+11 | I21: =IFERROR(H21/E21*100,0) -> 14.968351
A22: 1-2-1-5-01 | B22: % Prima (FONSAT) Decreto Ley 1335 de 2009 | C22: =+VLOOKUP(A22,ingresos!$A$1:$B$81,2,) -> 363281118360 | D22: =+VLOOKUP(A22,ingresos!$A$1:$F$81,3,FALSE) -> 0 | E22: =+VLOOKUP(A22,ingresos!$A$1:$F$81,4,FALSE) -> 363281118360 | F22: 0 | G22: =+VLOOKUP(A22,ingresos!$A$1:$E$100,5,FALSE) -> 7.770565e+10 | H22: =+G22+F22 -> 7.770565e+10 | I22: =IFERROR(H22/E22*100,0) -> 21.38995
A23: 1-2-1-5-02 | B23: Contribución Seguro Obligatorio de Accidentes de Tránsito - SOAT- Decreto Ley 1335 de 2009 | C23: =+VLOOKUP(A23,ingresos!$A$1:$B$81,2,) -> 1277246322640 | D23: =+VLOOKUP(A23,ingresos!$A$1:$F$81,3,FALSE) -> 0 | E23: =+VLOOKUP(A23,ingresos!$A$1:$F$81,4,FALSE) -> 1277246322640 | F23: 0 | G23: =+VLOOKUP(A23,ingresos!$A$1:$E$100,5,FALSE) -> 167854247950 | H23: =+G23+F23 -> 167854247950 | I23: =IFERROR(H23/E23*100,0) -> 13.141885
A24: 1-2-1-7 | B24: Impuesto social a las municiones y explosivos | C24: =+VLOOKUP(A24,ingresos!$A$1:$B$81,2,) -> 6410791000 | D24: =+VLOOKUP(A24,ingresos!$A$1:$F$81,3,FALSE) -> 0 | E24: =+VLOOKUP(A24,ingresos!$A$1:$F$81,4,FALSE) -> 6410791000 | F24: 0 | G24: =+VLOOKUP(A24,ingresos!$A$1:$E$100,5,FALSE) -> 15439498040 | H24: =+G24+F24 -> 15439498040 | I24: =IFERROR(H24/E24*100,0) -> 240.83608
A25: 1-2-1-8 | B25: Impuesto social a las armas | C25: =+VLOOKUP(A25,ingresos!$A$1:$B$81,2,) -> 8851770619 | D25: =+VLOOKUP(A25,ingresos!$A$1:$F$81,3,FALSE) -> 0 | E25: =+VLOOKUP(A25,ingresos!$A$1:$F$81,4,FALSE) -> 8851770619 | F25: 0 | G25: =+VLOOKUP(A25,ingresos!$A$1:$E$100,5,FALSE) -> 782571447 | H25: =+G25+F25 -> 782571447 | I25: =IFERROR(H25/E25*100,0) -> 8.8408464
A26: 1-2-9-0 | B26: Otros aportes e impuestos de la nación | C26: =+VLOOKUP(A26,ingresos!$A$1:$B$81,2,) -> 0 | D26: =+VLOOKUP(A26,ingresos!$A$1:$F$81,3,FALSE) -> 0 | E26: =+VLOOKUP(A26,ingresos!$A$1:$F$81,4,FALSE) -> 0 | F26: 0 | G26: =+VLOOKUP(A26,ingresos!$A$1:$E$100,5,FALSE) -> 0 | H26: =+G26+F26 -> 0 | I26: =IFERROR(H26/E26*100,0) -> 0
A27: 1-3-0-0 | B27: Otros Ingresos Corrientes | C27: =+C28+C56 -> 32272610118042 | D27: =+D28 -> 0 | E27: =+E28+E56 -> 32272610118042 | F27: 0 | G27: =+G28+G56 -> 2.7485066e+12 | H27: =+G27+F27 -> 2.7485066e+12 | I27: =IFERROR(H27/E27*100,0) -> 8.5165301
A28: 1-3-5-0 | B28: Ingresos Sistema General de Seguridad Social en Salud | C28: =+C29+C32+C35+C40+C50+C53 -> 22105255788877 | D28: =+D29+D32+D35+D40+D50+D53 -> 0 | E28: =+E29+E32+E35+E40+E50+E53 -> 22105255788877 | F28: 0 | G28: =+G29+G32+G35+G40+G50+G53 -> 1.918439e+12 | H28: =+G28+F28 -> 1.918439e+12 | I28: =IFERROR(H28/E28*100,0) -> 8.6786555
A29: 1-3-5-1 | B29: Cotizaciones al SGSSS | C29: =+SUM(C30:C31) -> 20346328129563 | D29: =+SUM(D30:D31) -> 0 | E29: =+SUM(E30:E31) -> 20346328129563 | F29: 0 | G29: =+SUM(G30:G31) -> 1706496864866 | H29: =+G29+F29 -> 1706496864866 | I29: =IFERROR(H29/E29*100,0) -> 8.3872473
A30: 1-3-5-1-01 | B30: Régimen Contributivo CSF | C30: =+VLOOKUP(A30,ingresos!$A$1:$B$81,2,) -> 6807438619821 | D30: =+VLOOKUP(A30,ingresos!$A$1:$F$81,3,FALSE) -> 0 | E30: =+VLOOKUP(A30,ingresos!$A$1:$F$81,4,FALSE) -> 6807438619821 | F30: 0 | G30: =+VLOOKUP(A30,ingresos!$A$1:$E$100,5,FALSE) -> 716197711248 | H30: =+G30+F30 -> 716197711248 | I30: =IFERROR(H30/E30*100,0) -> 10.52081
A31: 1-3-5-1-02 | B31: Régimen Contributivo SSF | C31: =+VLOOKUP(A31,ingresos!$A$1:$B$81,2,) -> 13538889509742 | D31: =+VLOOKUP(A31,ingresos!$A$1:$F$81,3,FALSE) -> 0 | E31: =+VLOOKUP(A31,ingresos!$A$1:$F$81,4,FALSE) -> 13538889509742 | F31: 0 | G31: =+VLOOKUP(A31,ingresos!$A$1:$E$100,5,FALSE) -> 990299153618 | H31: =+G31+F31 -> 990299153618 | I31: =IFERROR(H31/E31*100,0) -> 7.3144784
A32: 1-3-5-2 | B32: Aporte Solidaridad de Regímenes de Excepcion y Especiales | C32: =+SUM(C33:C34) -> 1000356775894 | D32: =+SUM(D33:D34) -> 0 | E32: =+SUM(E33:E34) -> 1000356775894 | F32: 0 | G32: =+SUM(G33:G34) -> 6.2818952e+10 | H32: =+G32+F32 -> 6.2818952e+10 | I32: =IFERROR(H32/E32*100,0) -> 6.2796548
A33: 1-3-5-2-01 | B33: Cotizaciones afiliados REX con ingresos adicionales | C33: =+VLOOKUP(A33,ingresos!$A$1:$B$81,2,) -> 594961177882 | D33: =+VLOOKUP(A33,ingresos!$A$1:$F$81,3,FALSE) -> 0 | E33: =+VLOOKUP(A33,ingresos!$A$1:$F$81,4,FALSE) -> 594961177882 | F33: 0 | G33: =+VLOOKUP(A33,ingresos!$A$1:$E$100,5,FALSE) -> 40622846969 | H33: =+G33+F33 -> 40622846969 | I33: =IFERROR(H33/E33*100,0) -> 6.8278147
A34: 1-3-5-2-02 | B34: Aporte Solidario entidades REX | C34: =+VLOOKUP(A34,ingresos!$A$1:$B$81,2,) -> 405395598012 | D34: =+VLOOKUP(A34,ingresos!$A$1:$F$81,3,FALSE) -> 0 | E34: =+VLOOKUP(A34,ingresos!$A$1:$F$81,4,FALSE) -> 405395598012 | F34: 0 | G34: =+VLOOKUP(A34,ingresos!$A$1:$E$100,5,FALSE) -> 2.2196105e+10 | H34: =+G34+F34 -> 2.2196105e+10 | I34: =IFERROR(H34/E34*100,0) -> 5.4751717
A35: 1-3-5-3 | B35: Aportes Cajas de Compensación Familiar | C35: =+SUM(C36:C39) -> 499207099674 | D35: =+SUM(D36:D39) -> 0 | E35: =+SUM(E36:E39) -> 499207099674 | F35: 0 | G35: =+SUM(G36:G39) -> 5.0320072e+10 | H35: =+G35+F35 -> 5.0320072e+10 | I35: =IFERROR(H35/E35*100,0) -> 10.079999
A36: 1-3-5-3-01 | B36: Aportes CCF Artículo 217 Ley 100 de 1993 CSF | C36: =+VLOOKUP(A36,ingresos!$A$1:$B$81,2,) -> 466578060617 | D36: =+VLOOKUP(A36,ingresos!$A$1:$F$81,3,FALSE) -> 0 | E36: =+VLOOKUP(A36,ingresos!$A$1:$F$81,4,FALSE) -> 466578060617 | F36: 0 | G36: =+VLOOKUP(A36,ingresos!$A$1:$E$100,5,FALSE) -> 4.660073e+10 | H36: =+G36+F36 -> 4.660073e+10 | I36: =IFERROR(H36/E36*100,0) -> 9.9877672
A37: 1-3-5-3-02 | B37: Aportes CCF Artículo 217 Ley 100 de 1993 SSF | C37: =+VLOOKUP(A37,ingresos!$A$1:$B$81,2,) -> 28877831435 | D37: =+VLOOKUP(A37,ingresos!$A$1:$F$81,3,FALSE) -> 0 | E37: =+VLOOKUP(A37,ingresos!$A$1:$F$81,4,FALSE) -> 28877831435 | F37: 0 | G37: =+VLOOKUP(A37,ingresos!$A$1:$E$100,5,FALSE) -> 3204560767 | H37: =+G37+F37 -> 3204560767 | I37: =IFERROR(H37/E37*100,0) -> 11.096958
A38: 1-3-5-3-03 | B38: Aportes CCF Balance | C38: =+VLOOKUP(A38,ingresos!$A$1:$B$81,2,) -> 3751207622 | D38: =+VLOOKUP(A38,ingresos!$A$1:$F$81,3,FALSE) -> 0 | E38: =+VLOOKUP(A38,ingresos!$A$1:$F$81,4,FALSE) -> 3751207622 | F38: 0 | G38: =+VLOOKUP(A38,ingresos!$A$1:$E$100,5,FALSE) -> 514780895 | H38: =+G38+F38 -> 514780895 | I38: =IFERROR(H38/E38*100,0) -> 13.723071
A39: 1-3-5-3-04 | B39: Otros Aportes CCF | C39: =+VLOOKUP(A39,ingresos!$A$1:$B$81,2,) -> 0 | D39: =+VLOOKUP(A39,ingresos!$A$1:$F$81,3,FALSE) -> 0 | E39: =+VLOOKUP(A39,ingresos!$A$1:$F$81,4,FALSE) -> 0 | F39: 0 | G39: =+VLOOKUP(A39,ingresos!$A$1:$E$100,5,FALSE) -> 0 | H39: =+G39+F39 -> 0 | I39: =IFERROR(H39/E39*100,0) -> 0
A40: 1-3-5-5 | B40: Reintegros / Recuperaciones | C40: =+SUM(C41:C49) -> 0 | D40: =+SUM(D41:D49) -> 0 | E40: =+SUM(E41:E49) -> 0 | F40: 0 | G40: =+SUM(G41:G49) -> 8.1696375e+10 | H40: =+G40+F40 -> 8.1696375e+10 | I40: =IFERROR(H40/E40*100,0) -> 0
A41: 1-3-5-5-01 | B41: UPC Régimen Contributivo Vigencias anteriores | C41: =+VLOOKUP(A41,ingresos!$A$1:$B$81,2,) -> 0 | D41: =+VLOOKUP(A41,ingresos!$A$1:$F$81,3,FALSE) -> 0 | E41: =+VLOOKUP(A41,ingresos!$A$1:$F$81,4,FALSE) -> 0 | F41: 0 | G41: =+VLOOKUP(A41,ingresos!$A$1:$E$100,5,FALSE) -> 7.3991137e+09 | H41: =+G41+F41 -> 7.3991137e+09 | I41: =IFERROR(H41/E41*100,0) -> 0
A42: 1-3-5-5-02 | B42: P&P Vigencias anteriores | C42: =+VLOOKUP(A42,ingresos!$A$1:$B$81,2,) -> 0 | D42: =+VLOOKUP(A42,ingresos!$A$1:$F$81,3,FALSE) -> 0 | E42: =+VLOOKUP(A42,ingresos!$A$1:$F$81,4,FALSE) -> 0 | F42: 0 | G42: =+VLOOKUP(A42,ingresos!$A$1:$E$100,5,FALSE) -> 0 | H42: =+G42+F42 -> 0 | I42: =IFERROR(H42/E42*100,0) -> 0
A43: 1-3-5-5-03 | B43: Licencias de Maternidad y Paternidad Vigencias anteriores | C43: =+VLOOKUP(A43,ingresos!$A$1:$B$81,2,) -> 0 | D43: =+VLOOKUP(A43,ingresos!$A$1:$F$81,3,FALSE) -> 0 | E43: =+VLOOKUP(A43,ingresos!$A$1:$F$81,4,FALSE) -> 0 | F43: 0 | G43: =+VLOOKUP(A43,ingresos!$A$1:$E$100,5,FALSE) -> 0 | H43: =+G43+F43 -> 0 | I43: =IFERROR(H43/E43*100,0) -> 0
A44: 1-3-5-5-04 | B44: UPC Régimen Subsidiado Vigencias anteriores | C44: =+VLOOKUP(A44,ingresos!$A$1:$B$81,2,) -> 0 | D44: =+VLOOKUP(A44,ingresos!$A$1:$F$81,3,FALSE) -> 0 | E44: =+VLOOKUP(A44,ingresos!$A$1:$F$81,4,FALSE) -> 0 | F44: 0 | G44: =+VLOOKUP(A44,ingresos!$A$1:$E$100,5,FALSE) -> 5.9962076e+10 | H44: =+G44+F44 -> 5.9962076e+10 | I44: =IFERROR(H44/E44*100,0) -> 0
A45: 1-3-5-5-05 | B45: Recobros Vigencias anteriores | C45: =+VLOOKUP(A45,ingresos!$A$1:$B$81,2,) -> 0 | D45: =+VLOOKUP(A45,ingresos!$A$1:$F$81,3,FALSE) -> 0 | E45: =+VLOOKUP(A45,ingresos!$A$1:$F$81,4,FALSE) -> 0 | F45: 0 | G45: =+VLOOKUP(A45,ingresos!$A$1:$E$100,5,FALSE) -> 2.9480673e+09 | H45: =+G45+F45 -> 2.9480673e+09 | I45: =IFERROR(H45/E45*100,0) -> 0
A46: 1-3-5-5-06 | B46: Reclamaciones Vigencias anteriores | C46: =+VLOOKUP(A46,ingresos!$A$1:$B$81,2,) -> 0 | D46: =+VLOOKUP(A46,ingresos!$A$1:$F$81,3,FALSE) -> 0 | E46: =+VLOOKUP(A46,ingresos!$A$1:$F$81,4,FALSE) -> 0 | F46: 0 | G46: =+VLOOKUP(A46,ingresos!$A$1:$E$100,5,FALSE) -> 179282.14 | H46: =+G46+F46 -> 179282.14 | I46: =IFERROR(H46/E46*100,0) -> 0
A47: 1-3-5-5-07 | B47: Procesos de Repetición | C47: =+VLOOKUP(A47,ingresos!$A$1:$B$81,2,) -> 0 | D47: =+VLOOKUP(A47,ingresos!$A$1:$F$81,3,FALSE) -> 0 | E47: =+VLOOKUP(A47,ingresos!$A$1:$F$81,4,FALSE) -> 0 | F47: 0 | G47: =+VLOOKUP(A47,ingresos!$A$1:$E$100,5,FALSE) -> 32724190 | H47: =+G47+F47 -> 32724190 | I47: =IFERROR(H47/E47*100,0) -> 0
A48: 1-3-5-5-08 | B48: Reintegro por contratos vigencias anteriores | C48: =+VLOOKUP(A48,ingresos!$A$1:$B$81,2,) -> 0 | D48: =+VLOOKUP(A48,ingresos!$A$1:$F$81,3,FALSE) -> 0 | E48: =+VLOOKUP(A48,ingresos!$A$1:$F$81,4,FALSE) -> 0 | F48: 0 | G48: =+VLOOKUP(A48,ingresos!$A$1:$E$100,5,FALSE) -> 0 | H48: =+G48+F48 -> 0 | I48: =IFERROR(H48/E48*100,0) -> 0
A49: 1-3-5-5-09 | B49: Otros reintegros / recuperaciones | C49: =+VLOOKUP(A49,ingresos!$A$1:$B$81,2,) -> 0 | D49: =+VLOOKUP(A49,ingresos!$A$1:$F$81,3,FALSE) -> 0 | E49: =+VLOOKUP(A49,ingresos!$A$1:$F$81,4,FALSE) -> 0 | F49: 0 | G49: =+VLOOKUP(A49,ingresos!$A$1:$E$100,5,FALSE) -> 1.1354214e+10 | H49: =+G49+F49 -> 1.1354214e+10 | I49: =IFERROR(H49/E49*100,0) -> 0
A50: 1-3-5-6 | B50: Multas | C50: =+SUM(C51:C52) -> 0 | D50: =+SUM(D51:D52) -> 0 | E50: =+SUM(E51:E52) -> 0 | F50: 0 | G50: =+SUM(G51:G52) -> 0 | H50: =+G50+F50 -> 0 | I50: =IFERROR(H50/E50*100,0) -> 0
A51: 1-3-5-6-01 | B51: Multas Antitabaco | C51: =+VLOOKUP(A51,ingresos!$A$1:$B$81,2,) -> 0 | D51: =+VLOOKUP(A51,ingresos!$A$1:$F$81,3,FALSE) -> 0 | E51: =+VLOOKUP(A51,ingresos!$A$1:$F$81,4,FALSE) -> 0 | F51: 0 | G51: =+VLOOKUP(A51,ingresos!$A$1:$E$100,5,FALSE) -> 0 | H51: =+G51+F51 -> 0 | I51: =IFERROR(H51/E51*100,0) -> 0
A52: 1-3-5-6-02 | B52: Otras Multas | C52: =+VLOOKUP(A52,ingresos!$A$1:$B$81,2,) -> 0 | D52: =+VLOOKUP(A52,ingresos!$A$1:$F$81,3,FALSE) -> 0 | E52: =+VLOOKUP(A52,ingresos!$A$1:$F$81,4,FALSE) -> 0 | F52: 0 | G52: =+VLOOKUP(A52,ingresos!$A$1:$E$100,5,FALSE) -> 0 | H52: =+G52+F52 -> 0 | I52: =IFERROR(H52/E52*100,0) -> 0
A53: 1-3-5-7 | B53: Otros ingresos Diversos | C53: =+SUM(C54:C55) -> 259363783746 | D53: =+SUM(D54:D55) -> 0 | E53: =+SUM(E54:E55) -> 259363783746 | F53: 0 | G53: =+SUM(G54:G55) -> 1.7106742e+10 | H53: =+G53+F53 -> 1.7106742e+10 | I53: =IFERROR(H53/E53*100,0) -> 6.5956556
A54: 1-3-5-7-01 | B54: Aportes adicionales en Salud | C54: =+VLOOKUP(A54,ingresos!$A$1:$B$81,2,) -> 259363783746 | D54: =+VLOOKUP(A54,ingresos!$A$1:$F$81,3,FALSE) -> 0 | E54: =+VLOOKUP(A54,ingresos!$A$1:$F$81,4,FALSE) -> 259363783746 | F54: 0 | G54: =+VLOOKUP(A54,ingresos!$A$1:$E$100,5,FALSE) -> 15085843664 | H54: =+G54+F54 -> 15085843664 | I54: =IFERROR(H54/E54*100,0) -> 5.8164804
A55: 1-3-5-7-02 | B55: Otros ingresos Diversos | C55: =+VLOOKUP(A55,ingresos!$A$1:$B$81,2,) -> 0 | D55: =+VLOOKUP(A55,ingresos!$A$1:$F$81,3,FALSE) -> 0 | E55: =+VLOOKUP(A55,ingresos!$A$1:$F$81,4,FALSE) -> 0 | F55: 0 | G55: =+VLOOKUP(A55,ingresos!$A$1:$E$100,5,FALSE) -> 2.0208983e+09 | H55: =+G55+F55 -> 2.0208983e+09 | I55: =IFERROR(H55/E55*100,0) -> 0
A56: 1-3-6-0 | B56: Recursos ET Aseguramiento en Salud | C56: =+C57+C58+C59+C62+C65 -> 10167354329165 | D56: =+D57+D58+D59+D62+D65 -> 0 | E56: =+E57+E58+E59+E62+E65 -> 10167354329165 | F56: =+F57+F58+F59+F62+F65 -> 0 | G56: =+G57+G58+G59+G62+G65 -> 8.3006756e+11 | H56: =+G56+F56 -> 8.3006756e+11 | I56: =IFERROR(H56/E56*100,0) -> 8.1640468
A57: 1-3-6-1 | B57: Sistema General de Participaciones Régimen Subsidiado | C57: =+VLOOKUP(A57,ingresos!$A$1:$B$81,2,) -> 8428995552661 | D57: =+VLOOKUP(A57,ingresos!$A$1:$F$81,3,FALSE) -> 0 | E57: =+VLOOKUP(A57,ingresos!$A$1:$F$81,4,FALSE) -> 8428995552661 | F57: 0 | G57: =+VLOOKUP(A57,ingresos!$A$1:$E$100,5,FALSE) -> 593404503914 | H57: =+G57+F57 -> 593404503914 | I57: =IFERROR(H57/E57*100,0) -> 7.0400382
A58: 1-3-6-2 | B58: Recursos Provenientes de COLJUEGOS para R.S. | C58: =+VLOOKUP(A58,ingresos!$A$1:$B$81,2,) -> 376773007880 | D58: =+VLOOKUP(A58,ingresos!$A$1:$F$81,3,FALSE) -> 0 | E58: =+VLOOKUP(A58,ingresos!$A$1:$F$81,4,FALSE) -> 376773007880 | F58: 0 | G58: =+VLOOKUP(A58,ingresos!$A$1:$E$100,5,FALSE) -> 76639292618 | H58: =+G58+F58 -> 76639292618 | I58: =IFERROR(H58/E58*100,0) -> 20.340972
A59: 1-3-6-7 | B59: Recursos Fonpet | C59: =+SUM(C60:C61) -> 200000000000 | D59: =+SUM(D60:D61) -> 0 | E59: =+SUM(E60:E61) -> 200000000000 | F59: 0 | G59: =+SUM(G60:G61) -> 0 | H59: =+G59+F59 -> 0 | I59: =IFERROR(H59/E59*100,0) -> 0
A60: 1-3-6-7-01 | B60: Recursos LOTTO en Línea-FONPET | C60: =+VLOOKUP(A60,ingresos!$A$1:$B$81,2,) -> 0 | D60: =+VLOOKUP(A60,ingresos!$A$1:$F$81,3,FALSE) -> 0 | E60: =+VLOOKUP(A60,ingresos!$A$1:$F$81,4,FALSE) -> 0 | F60: 0 | G60: =+VLOOKUP(A60,ingresos!$A$1:$E$100,5,FALSE) -> 0 | H60: =+G60+F60 -> 0 | I60: =IFERROR(H60/E60*100,0) -> 0
A61: 1-3-6-7-02 | B61: Otros recursos FONPET diferentes a LOTTO en Línea | C61: =+VLOOKUP(A61,ingresos!$A$1:$B$81,2,) -> 200000000000 | D61: =+VLOOKUP(A61,ingresos!$A$1:$F$81,3,FALSE) -> 0 | E61: =+VLOOKUP(A61,ingresos!$A$1:$F$81,4,FALSE) -> 200000000000 | F61: 0 | G61: =+VLOOKUP(A61,ingresos!$A$1:$E$100,5,FALSE) -> 0 | H61: =+G61+F61 -> 0 | I61: =IFERROR(H61/E61*100,0) -> 0
A62: 1-3-6-8 | B62: Otros Recursos de las Entidades Territoriales para Aseguramiento | C62: =+SUM(C63:C64) -> 1124585768624 | D62: =+SUM(D63:D64) -> 0 | E62: =+SUM(E63:E64) -> 1124585768624 | F62: 0 | G62: =+SUM(G63:G64) -> 1.5097557e+11 | H62: =+G62+F62 -> 1.5097557e+11 | I62: =IFERROR(H62/E62*100,0) -> 13.424994
A63: 1-3-6-8-01 | B63: Otros recursos Departamentales y Distritales para Aseguramiento | C63: =+VLOOKUP(A63,ingresos!$A$1:$B$81,2,) -> 1042745130904 | D63: =+VLOOKUP(A63,ingresos!$A$1:$F$81,3,FALSE) -> 0 | E63: =+VLOOKUP(A63,ingresos!$A$1:$F$81,4,FALSE) -> 1042745130904 | F63: 0 | G63: =+VLOOKUP(A63,ingresos!$A$1:$E$100,5,FALSE) -> 1.5009551e+11 | H63: =+G63+F63 -> 1.5009551e+11 | I63: =IFERROR(H63/E63*100,0) -> 14.394266
A64: 1-3-6-8-02 | B64: Otros Recursos Municipales para Aseguramiento | C64: =+VLOOKUP(A64,ingresos!$A$1:$B$81,2,) -> 81840637720 | D64: =+VLOOKUP(A64,ingresos!$A$1:$F$81,3,FALSE) -> 0 | E64: =+VLOOKUP(A64,ingresos!$A$1:$F$81,4,FALSE) -> 81840637720 | F64: 0 | G64: =+VLOOKUP(A64,ingresos!$A$1:$E$100,5,FALSE) -> 8.8006098e+08 | H64: =+G64+F64 -> 8.8006098e+08 | I64: =IFERROR(H64/E64*100,0) -> 1.0753349
A65: 1-3-6-9 | B65: Recursos USPEC | C65: =+VLOOKUP(A65,ingresos!$A$1:$B$81,2,) -> 37000000000 | D65: =+VLOOKUP(A65,ingresos!$A$1:$F$81,3,FALSE) -> 0 | E65: =+VLOOKUP(A65,ingresos!$A$1:$F$81,4,FALSE) -> 37000000000 | F65: 0 | G65: =+VLOOKUP(A65,ingresos!$A$1:$E$100,5,FALSE) -> 9.0481925e+09 | H65: =+G65+F65 -> 9.0481925e+09 | I65: =IFERROR(H65/E65*100,0) -> 24.454574
A66: 2-0-0-0 | B66: RECURSOS DE CAPITAL | C66: =+C67+C71+C87+C95 -> 159585154000 | D66: =+D67+D71+D87+D95 -> 0 | E66: =+E67+E71+E87+E95 -> 159585154000 | F66: 0 | G66: =+G67+G71+G87+G95 -> 63224543322 | H66: =+G66+F66 -> 63224543322 | I66: =IFERROR(H66/E66*100,0) -> 39.618061
A67: 2-1-0-0 | B67: Recuperación de Cartera | C67: =+SUM(C68:C70) -> 80000000000 | D67: =+SUM(D68:D70) -> 0 | E67: =+SUM(E68:E70) -> 80000000000 | F67: 0 | G67: =+SUM(G68:G70) -> 1.6425689e+10 | H67: =+G67+F67 -> 1.6425689e+10 | I67: =IFERROR(H67/E67*100,0) -> 20.532111
A68: 2-1-0-0-01 | B68: Restitución operación Fosyga RS Ley 1608 de 2013 | C68: =+VLOOKUP(A68,ingresos!$A$1:$B$81,2,) -> 0 | D68: =+VLOOKUP(A68,ingresos!$A$1:$F$81,3,FALSE) -> 0 | E68: =+VLOOKUP(A68,ingresos!$A$1:$F$81,4,FALSE) -> 0 | F68: 0 | G68: =+VLOOKUP(A68,ingresos!$A$1:$E$100,5,FALSE) -> 3102390008 | H68: =+G68+F68 -> 3102390008 | I68: =IFERROR(H68/E68*100,0) -> 0
A69: 2-1-0-0-02 | B69: Amortización Operaciones de Compra de Cartera | C69: =+VLOOKUP(A69,ingresos!$A$1:$B$81,2,) -> 80000000000 | D69: =+VLOOKUP(A69,ingresos!$A$1:$F$81,3,FALSE) -> 0 | E69: =+VLOOKUP(A69,ingresos!$A$1:$F$81,4,FALSE) -> 80000000000 | F69: 0 | G69: =+VLOOKUP(A69,ingresos!$A$1:$E$100,5,FALSE) -> 1.3323299e+10 | H69: =+G69+F69 -> 1.3323299e+10 | I69: =IFERROR(H69/E69*100,0) -> 16.654123
A70: 2-1-0-0-03 | B70: Recuperación Operaciones de Fortalecimiento Financiero y Patrimonial a entidades del sector salud | C70: =+VLOOKUP(A70,ingresos!$A$1:$B$81,2,) -> 0 | D70: =+VLOOKUP(A70,ingresos!$A$1:$F$81,3,FALSE) -> 0 | E70: =+VLOOKUP(A70,ingresos!$A$1:$F$81,4,FALSE) -> 0 | F70: 0 | G70: =+VLOOKUP(A70,ingresos!$A$1:$E$100,5,FALSE) -> 0 | H70: =+G70+F70 -> 0 | I70: =IFERROR(H70/E70*100,0) -> 0
A71: 2-4-0-0 | B71: Rendimientos Financieros e Intereses | C71: =+SUM(C72:C86) -> 24675676069 | D71: =+SUM(D72:D86) -> 0 | E71: =+SUM(E72:E86) -> 24675676069 | F71: =+SUM(F72:F86) -> 0 | G71: =+SUM(G72:G86) -> 4.5102427e+10 | H71: =+G71+F71 -> 4.5102427e+10 | I71: =IFERROR(H71/E71*100,0) -> 182.78092
A72: 2-4-0-0-01 | B72: Rendimientos cuentas de recaudo EPS -CSF- | C72: =+VLOOKUP(A72,ingresos!$A$1:$B$81,2,) -> 0 | D72: =+VLOOKUP(A72,ingresos!$A$1:$F$81,3,FALSE) -> 0 | E72: =+VLOOKUP(A72,ingresos!$A$1:$F$81,4,FALSE) -> 0 | F72: 0 | G72: =+VLOOKUP(A72,ingresos!$A$1:$E$100,5,FALSE) -> 178521745 | H72: =+G72+F72 -> 178521745 | I72: =IFERROR(H72/E72*100,0) -> 0
A73: 2-4-0-0-02 | B73: Rendimientos cuentas de recaudo EPS -SSF- | C73: =+VLOOKUP(A73,ingresos!$A$1:$B$81,2,) -> 7615081557 | D73: =+VLOOKUP(A73,ingresos!$A$1:$F$81,3,FALSE) -> 0 | E73: =+VLOOKUP(A73,ingresos!$A$1:$F$81,4,FALSE) -> 7615081557 | F73: 0 | G73: =+VLOOKUP(A73,ingresos!$A$1:$E$100,5,FALSE) -> 817079635 | H73: =+G73+F73 -> 817079635 | I73: =IFERROR(H73/E73*100,0) -> 10.729756
A74: 2-4-0-0-03 | B74: Rendimientos cuentas de Ahorros ADRES URA | C74: =+VLOOKUP(A74,ingresos!$A$1:$B$81,2,) -> 7060594512 | D74: =+VLOOKUP(A74,ingresos!$A$1:$F$81,3,FALSE) -> 0 | E74: =+VLOOKUP(A74,ingresos!$A$1:$F$81,4,FALSE) -> 7060594512 | F74: 0 | G74: =+VLOOKUP(A74,ingresos!$A$1:$E$100,5,FALSE) -> 5.8704756e+09 | H74: =+G74+F74 -> 5.8704756e+09 | I74: =IFERROR(H74/E74*100,0) -> 83.144211
A75: 2-4-0-0-04 | B75: Rendimientos cuentas de Corrientes ADRES URA | C75: =+VLOOKUP(A75,ingresos!$A$1:$B$81,2,) -> 0 | D75: =+VLOOKUP(A75,ingresos!$A$1:$F$81,3,FALSE) -> 0 | E75: =+VLOOKUP(A75,ingresos!$A$1:$F$81,4,FALSE) -> 0 | F75: 0 | G75: =+VLOOKUP(A75,ingresos!$A$1:$E$100,5,FALSE) -> 0 | H75: =+G75+F75 -> 0 | I75: =IFERROR(H75/E75*100,0) -> 0
A76: 2-4-0-0-06 | B76: Rendimientos sobre títulos del portafolio de Inversiones | C76: =+VLOOKUP(A76,ingresos!$A$1:$B$81,2,) -> 0 | D76: =+VLOOKUP(A76,ingresos!$A$1:$F$81,3,FALSE) -> 0 | E76: =+VLOOKUP(A76,ingresos!$A$1:$F$81,4,FALSE) -> 0 | F76: 0 | G76: =+VLOOKUP(A76,ingresos!$A$1:$E$100,5,FALSE) -> 0 | H76: =+G76+F76 -> 0 | I76: =IFERROR(H76/E76*100,0) -> 0
A77: 2-4-0-0-07 | B77: Rendimientos sobre recursos entregados en administración | C77: =+VLOOKUP(A77,ingresos!$A$1:$B$81,2,) -> 0 | D77: =+VLOOKUP(A77,ingresos!$A$1:$F$81,3,FALSE) -> 0 | E77: =+VLOOKUP(A77,ingresos!$A$1:$F$81,4,FALSE) -> 0 | F77: 0 | G77: =+VLOOKUP(A77,ingresos!$A$1:$E$100,5,FALSE) -> 1.1863602e+09 | H77: =+G77+F77 -> 1.1863602e+09 | I77: =IFERROR(H77/E77*100,0) -> 0
A78: 2-4-0-0-08 | B78: Otros rendimientos financieros | C78: =+VLOOKUP(A78,ingresos!$A$1:$B$81,2,) -> 0 | D78: =+VLOOKUP(A78,ingresos!$A$1:$F$81,3,FALSE) -> 0 | E78: =+VLOOKUP(A78,ingresos!$A$1:$F$81,4,FALSE) -> 0 | F78: 0 | G78: =+VLOOKUP(A78,ingresos!$A$1:$E$100,5,FALSE) -> 86531232 | H78: =+G78+F78 -> 86531232 | I78: =IFERROR(H78/E78*100,0) -> 0
A79: 2-4-0-0-09 | B79: Intereses Operaciones Compra de Cartera | C79: =+VLOOKUP(A79,ingresos!$A$1:$B$81,2,) -> 0 | D79: =+VLOOKUP(A79,ingresos!$A$1:$F$81,3,FALSE) -> 0 | E79: =+VLOOKUP(A79,ingresos!$A$1:$F$81,4,FALSE) -> 0 | F79: 0 | G79: =+VLOOKUP(A79,ingresos!$A$1:$E$100,5,FALSE) -> 2.9670161e+08 | H79: =+G79+F79 -> 2.9670161e+08 | I79: =IFERROR(H79/E79*100,0) -> 0
A80: 2-4-0-0-10 | B80: Intereses sobre restituciones | C80: =+VLOOKUP(A80,ingresos!$A$1:$B$81,2,) -> 0 | D80: =+VLOOKUP(A80,ingresos!$A$1:$F$81,3,FALSE) -> 0 | E80: =+VLOOKUP(A80,ingresos!$A$1:$F$81,4,FALSE) -> 0 | F80: 0 | G80: =+VLOOKUP(A80,ingresos!$A$1:$E$100,5,FALSE) -> 11104317 | H80: =+G80+F80 -> 11104317 | I80: =IFERROR(H80/E80*100,0) -> 0
A81: 2-4-0-0-11 | B81: Intereses de mora sobre compra de cartera | C81: =+VLOOKUP(A81,ingresos!$A$1:$B$81,2,) -> 0 | D81: =+VLOOKUP(A81,ingresos!$A$1:$F$81,3,FALSE) -> 0 | E81: =+VLOOKUP(A81,ingresos!$A$1:$F$81,4,FALSE) -> 0 | F81: 0 | G81: =+VLOOKUP(A81,ingresos!$A$1:$E$100,5,FALSE) -> 0 | H81: =+G81+F81 -> 0 | I81: =IFERROR(H81/E81*100,0) -> 0
A82: 2-4-0-0-12 | B82: Intereses de mora sobre restituciones | C82: =+VLOOKUP(A82,ingresos!$A$1:$B$81,2,) -> 0 | D82: =+VLOOKUP(A82,ingresos!$A$1:$F$81,3,FALSE) -> 0 | E82: =+VLOOKUP(A82,ingresos!$A$1:$F$81,4,FALSE) -> 0 | F82: 0 | G82: =+VLOOKUP(A82,ingresos!$A$1:$E$100,5,FALSE) -> 3.2094515e+10 | H82: =+G82+F82 -> 3.2094515e+10 | I82: =IFERROR(H82/E82*100,0) -> 0
A83: 2-4-0-0-13 | B83: Intereses de mora cotizaciones R.C. | C83: =+VLOOKUP(A83,ingresos!$A$1:$B$81,2,) -> 10000000000 | D83: =+VLOOKUP(A83,ingresos!$A$1:$F$81,3,FALSE) -> 0 | E83: =+VLOOKUP(A83,ingresos!$A$1:$F$81,4,FALSE) -> 10000000000 | F83: 0 | G83: =+VLOOKUP(A83,ingresos!$A$1:$E$100,5,FALSE) -> 4561034421 | H83: =+G83+F83 -> 4561034421 | I83: =IFERROR(H83/E83*100,0) -> 45.610344
... A86: 2-4-0-0-16 | B86: Otros Intereses | C86: =+VLOOKUP(A86,ingresos!$A$1:$B$81,2,) -> 0 | D86: =+VLOOKUP(A86,ingresos!$A$1:$F$81,3,FALSE) -> 0 | E86: =+VLOOKUP(A86,ingresos!$A$1:$F$81,4,FALSE) -> 0 | F86: 0 | G86: =+VLOOKUP(A86,ingresos!$A$1:$E$100,5,FALSE) -> 0 | H86: =+G86+F86 -> 0 | I86: =IFERROR(H86/E86*100,0) -> 0
A87: 2-5-0-0 | B87: Recusos con destinación específica | C87: =+SUM(C88:C94) -> 54909477931 | D87: =+SUM(D88:D94) -> 0 | E87: =+SUM(E88:E94) -> 54909477931 | F87: 0 | G87: =+SUM(G88:G94) -> 1693304104 | H87: =+G87+F87 -> 1693304104 | I87: =IFERROR(H87/E87*100,0) -> 3.0838102
A88: 2-5-0-0-01 | B88: Excedentes -Servicios prestados a la población pobre y los servicios No POS entidades territoriales. (Num, 2 art. 3 Ley 1608 de 2013) | C88: =+VLOOKUP(A88,ingresos!$A$1:$B$81,2,) -> 0 | D88: =+VLOOKUP(A88,ingresos!$A$1:$F$81,3,FALSE) -> 0 | E88: =+VLOOKUP(A88,ingresos!$A$1:$F$81,4,FALSE) -> 0 | F88: 0 | G88: =+VLOOKUP(A88,ingresos!$A$1:$E$100,5,FALSE) -> 0 | H88: =+G88+F88 -> 0 | I88: =IFERROR(H88/E88*100,0) -> 0
A89: 2-5-0-0-02 | B89: Recursos SGP Propósito General Libre Inversión | C89: =+VLOOKUP(A89,ingresos!$A$1:$B$81,2,) -> 13909477931 | D89: =+VLOOKUP(A89,ingresos!$A$1:$F$81,3,FALSE) -> 0 | E89: =+VLOOKUP(A89,ingresos!$A$1:$F$81,4,FALSE) -> 13909477931 | F89: 0 | G89: =+VLOOKUP(A89,ingresos!$A$1:$E$100,5,FALSE) -> 321806276 | H89: =+G89+F89 -> 321806276 | I89: =IFERROR(H89/E89*100,0) -> 2.3135755
A90: 2-5-0-0-03 | B90: Excedentes recursos FAEP para el reconocimiento de deuda por contratos del Régimen Subsidiado realizados hasta marzo 31 de 2011. | C90: =+VLOOKUP(A90,ingresos!$A$1:$B$81,2,) -> 0 | D90: =+VLOOKUP(A90,ingresos!$A$1:$F$81,3,FALSE) -> 0 | E90: =+VLOOKUP(A90,ingresos!$A$1:$F$81,4,FALSE) -> 0 | F90: 0 | G90: =+VLOOKUP(A90,ingresos!$A$1:$E$100,5,FALSE) -> 0 | H90: =+G90+F90 -> 0 | I90: =IFERROR(H90/E90*100,0) -> 0
A91: 2-5-0-0-04 | B91: Excedentes recursos de LOTTO en línea -FONPET para reconocimiento de deuda por contratos del Régimen Subsidiado realizados hasta marzo 31 de 2011 | C91: =+VLOOKUP(A91,ingresos!$A$1:$B$81,2,) -> 2000000000 | D91: =+VLOOKUP(A91,ingresos!$A$1:$F$81,3,FALSE) -> 0 | E91: =+VLOOKUP(A91,ingresos!$A$1:$F$81,4,FALSE) -> 2000000000 | F91: 0 | G91: =+VLOOKUP(A91,ingresos!$A$1:$E$100,5,FALSE) -> 0 | H91: =+G91+F91 -> 0 | I91: =IFERROR(H91/E91*100,0) -> 0
A92: 2-5-0-0-05 | B92: Excedentes de Aportes Patronales / Resolución 2360 de 2016 | C92: =+VLOOKUP(A92,ingresos!$A$1:$B$81,2,) -> 0 | D92: =+VLOOKUP(A92,ingresos!$A$1:$F$81,3,FALSE) -> 0 | E92: =+VLOOKUP(A92,ingresos!$A$1:$F$81,4,FALSE) -> 0 | F92: 0 | G92: =+VLOOKUP(A92,ingresos!$A$1:$E$100,5,FALSE) -> 41772215 | H92: =+G92+F92 -> 41772215 | I92: =IFERROR(H92/E92*100,0) -> 0
A93: 2-5-0-0-06 | B93: Regalías – artículo 5 Ley 1797 de 2016 | C93: =+VLOOKUP(A93,ingresos!$A$1:$B$81,2,) -> 3000000000 | D93: =+VLOOKUP(A93,ingresos!$A$1:$F$81,3,FALSE) -> 0 | E93: =+VLOOKUP(A93,ingresos!$A$1:$F$81,4,FALSE) -> 3000000000 | F93: 0 | G93: =+VLOOKUP(A93,ingresos!$A$1:$E$100,5,FALSE) -> 0 | H93: =+G93+F93 -> 0 | I93: =IFERROR(H93/E93*100,0) -> 0
A94: 2-5-0-0-07 | B94: Recursos CCF / FOSFEC - Ley 1929 de 2018 | C94: =+VLOOKUP(A94,ingresos!$A$1:$B$81,2,) -> 36000000000 | D94: =+VLOOKUP(A94,ingresos!$A$1:$F$81,3,FALSE) -> 0 | E94: =+VLOOKUP(A94,ingresos!$A$1:$F$81,4,FALSE) -> 36000000000 | F94: 0 | G94: =+VLOOKUP(A94,ingresos!$A$1:$E$100,5,FALSE) -> 1329725613 | H94: =+G94+F94 -> 1329725613 | I94: =IFERROR(H94/E94*100,0) -> 3.6936823
A95: 2-9-0-0 | B95: Otros Recursos de Capital | C95: =+SUM(C96:C97) -> 0 | D95: =+SUM(D96:D97) -> 0 | E95: =+SUM(E96:E97) -> 0 | F95: 0 | G95: =+SUM(G96:G97) -> 3123909 | H95: =+G95+F95 -> 3123909 | I95: =IFERROR(H95/E95*100,0) -> 0
A96: 2-9-0-0-01 | B96: Liquidación patrimonios autónomos Sector Salud | C96: =+VLOOKUP(A96,ingresos!$A$1:$B$81,2,) -> 0 | D96: =+VLOOKUP(A96,ingresos!$A$1:$F$81,3,FALSE) -> 0 | E96: =+VLOOKUP(A96,ingresos!$A$1:$F$81,4,FALSE) -> 0 | F96: 0 | G96: =+VLOOKUP(A96,ingresos!$A$1:$E$100,5,FALSE) -> 0 | H96: =+G96+F96 -> 0 | I96: =IFERROR(H96/E96*100,0) -> 0
A97: 2-9-0-0-02 | B97: Otros Recursos de Capital no contemplados en los anteriores | C97: =+VLOOKUP(A97,ingresos!$A$1:$B$81,2,) -> 0 | D97: =+VLOOKUP(A97,ingresos!$A$1:$F$81,3,FALSE) -> 0 | E97: =+VLOOKUP(A97,ingresos!$A$1:$F$81,4,FALSE) -> 0 | F97: 0 | G97: =+VLOOKUP(A97,ingresos!$A$1:$E$100,5,FALSE) -> 3123909 | H97: =+G97+F97 -> 3123909 | I97: =IFERROR(H97/E97*100,0) -> 0
B99: TOTAL | C99: =+C66+C12+C11 -> 52636824590223 | D99: =+D66+D12+D11 -> 0 | E99: =+E66+E12+E11 -> 52636824590223 | F99: =+F66+F12+F11 -> 0 | G99: =+G66+G12+G11 -> 4.7383266e+12 | H99: =+G99+F99 -> 4.7383266e+12 | I99: =IFERROR(H99/E99*100,0) -> 9.0019234
C101: 52636824590223 | D101: 0 | E101: 52636824590223 | F101: 0 | G101: 4.7383266e+12 | H101: 4.7383266e+12 | I101: 9
C102: =+C101-C99 -> 0 | D102: =+D101-D99 -> 0 | E102: =+E99-E101 -> 0 | F102: =+F101-F99 -> 0 | G102: =+G101-G99 -> 0 | H102: =+H101-H99 -> 0 | I102: =+I101-I99 -> -0.0019233837
F103: dif. Por el excel | H103: dif. Por el excel

Sheet CUADRO 2-EJECUCION DE GASTOS
M1: =+TODAY() -> 43522 | N1: =+NOW() -> 43522.607
A3: ADMINISTRADORA DE LOS RECURSOS DEL SISTEMA GENERAL DE SEGURIDAD SOCIAL EN SALUD
A4: PRESUPUESTO DE GASTOS 2019
A5: UNIDAD DE RECURSOS ADMINISTRADOS - URA
A6: CUADRO No. 2
A9: CÓDIGO RUBRO | B9: CONCEPTO DEL RUBRO | C9: APROPIACIÓN DEFINITIVA | D9: EJECUCION PRESUPUESTAL ACUMULADA DESDE 01/01/2019 HASTA 31/01/2019 | G9: EJECUCION PRESUPUESTAL DESDE 01/01/2019 HASTA 31/01/2019 | J9: EJECUCION PRESUPUESTAL ACUMULADA DESDE 01/01/2019 HASTA 31/01/2019 | M9: %
D10: T. CDP | E10: T. RP | F10: T. PAGOS-OP | G10: CDP | H10: RP | I10: PAGOS-OP | J10: T. CDP | K10: T. RP | L10: T. PAGOS-OP | M10: RP | N10: OP
B11: URA
A12: A-3-0-0-0 | B12: TRANSFERENCIAS | C12: =+C13+C18+C24 -> 52382816715223 | D12: 0 | E12: 0 | F12: 0 | G12: =+G13+G18+G24 -> 4.1486636e+12 | H12: =+H13+H18+H24 -> 3.9911398e+12 | I12: =+I13+I18+I24 -> 3.9911398e+12 | J12: =+G12+D12 -> 4.1486636e+12 | K12: =+H12+E12 -> 3.9911398e+12 | L12: =+I12+F12 -> 3.9911398e+12 | M12: =+IFERROR(K12*100/C12,0) -> 7.6191776 | N12: =+IFERROR(L12*100/C12,0) -> 7.6191776
A13: A-3-2-0-0 | B13: TRANSFERENCIAS AL SECTOR PUBLICO | C13: =+C14+C16 -> 231725030430 | D13: 0 | E13: 0 | F13: 0 | G13: =+G14+G16 -> 145380000000 | H13: =+H14+H16 -> 4.166544e+09 | I13: =+I14+I16 -> 4.166544e+09 | J13: =+G13+D13 -> 145380000000 | K13: =+H13+E13 -> 4.166544e+09 | L13: =+I13+F13 -> 4.166544e+09 | M13: =+IFERROR(K13*100/C13,0) -> 1.7980552 | N13: =+IFERROR(L13*100/C13,0) -> 1.7980552
A14: A-3-2-1-0 | B14: Transferencias Entidades de Administración Pública Central | C14: =+C15 -> 86345030430 | D14: =+D15 -> 0 | E14: =+E15 -> 0 | F14: =+F15 -> 0 | G14: =+G15 -> 0 | H14: =+H15 -> 0 | I14: =+I15 -> 0 | J14: =+J15 -> 0 | ... L14: =+L15 -> 0 | M14: =+IFERROR(K14*100/C14,0) -> 0 | N14: =+IFERROR(L14*100/C14,0) -> 0
A15: A-3-2-1-01 | B15: Contribución IVC Superintendencia Nacional de Salud | C15: =+VLOOKUP(A15,gasto!$A$4:$F$68,3,FALSE) -> 86345030430 | D15: 0 | E15: 0 | F15: 0 | G15: =+VLOOKUP(A15,gasto!$A$4:$F$68,4,FALSE) -> 0 | H15: =+VLOOKUP(A15,gasto!$A$4:$F$68,5,FALSE) -> 0 | I15: =+VLOOKUP(A15,gasto!$A$4:$F$68,6,FALSE) -> 0 | J15: =+G15+D15 -> 0 | K15: =+H15+E15 -> 0 | L15: =+I15+F15 -> 0 | M15: =+IFERROR(K15*100/C15,0) -> 0 | N15: =+IFERROR(L15*100/C15,0) -> 0
A16: A-3-2-2-0 | B16: Empresas Públicas Nacionales no financieras -ADRES | C16: =+C17 -> 145380000000 | D16: =+D17 -> 0 | E16: =+E17 -> 0 | F16: =+F17 -> 0 | G16: =+G17 -> 145380000000 | H16: =+H17 -> 4.166544e+09 | I16: =+I17 -> 4.166544e+09 | J16: =+J17 -> 145380000000 | ... L16: =+L17 -> 4.166544e+09 | M16: =+IFERROR(K16*100/C16,0) -> 2.8659678 | N16: =+IFERROR(L16*100/C16,0) -> 2.8659678
A17: A-3-2-2-0-01 | B17: Aportes hasta del 0,5% recursos CSF para el desarrollo objeto ADRES | C17: =+VLOOKUP(A17,gasto!$A$4:$F$68,3,FALSE) -> 145380000000 | D17: 0 | E17: 0 | F17: 0 | G17: =+VLOOKUP(A17,gasto!$A$4:$F$68,4,FALSE) -> 145380000000 | H17: =+VLOOKUP(A17,gasto!$A$4:$F$68,5,FALSE) -> 4.166544e+09 | I17: =+VLOOKUP(A17,gasto!$A$4:$F$68,6,FALSE) -> 4.166544e+09 | J17: =+G17+D17 -> 145380000000 | K17: =+H17+E17 -> 4.166544e+09 | L17: =+I17+F17 -> 4.166544e+09 | M17: =+IFERROR(K17*100/C17,0) -> 2.8659678 | N17: =+IFERROR(L17*100/C17,0) -> 2.8659678
A18: A-3-6-0-0 | B18: OTRAS TRANSFERENCIAS | C18: =+C19+C22 -> 180000000000 | D18: 0 | E18: 0 | F18: 0 | G18: =+G19+G22 -> 1656232 | H18: =+H19+H22 -> 0 | I18: =+I19+I22 -> 0 | J18: =+G18+D18 -> 1656232 | K18: =+H18+E18 -> 0 | L18: =+I18+F18 -> 0 | M18: =+IFERROR(K18*100/C18,0) -> 0 | N18: =+IFERROR(L18*100/C18,0) -> 0
A19: A-3-6-1-0 | B19: Sentencias y Conciliaciones URA | C19: =+SUM(C20:C21) -> 20000000000 | D19: =+SUM(D20:D21) -> 0 | E19: =+SUM(E20:E21) -> 0 | F19: =+SUM(F20:F21) -> 0 | G19: =+SUM(G20:G21) -> 1656232 | H19: =+SUM(H20:H21) -> 0 | I19: =+SUM(I20:I21) -> 0 | J19: =+SUM(J20:J21) -> 1656232 | ... L19: =+SUM(L20:L21) -> 0 | M19: =+IFERROR(K19*100/C19,0) -> 0 | N19: =+IFERROR(L19*100/C19,0) -> 0
A20: A-3-6-1-1 | B20: Sentencias URA | C20: =+VLOOKUP(A20,gasto!$A$4:$F$68,3,FALSE) -> 20000000000 | D20: 0 | E20: 0 | F20: 0 | G20: =+VLOOKUP(A20,gasto!$A$4:$F$68,4,FALSE) -> 1656232 | H20: =+VLOOKUP(A20,gasto!$A$4:$F$68,5,FALSE) -> 0 | I20: =+VLOOKUP(A20,gasto!$A$4:$F$68,6,FALSE) -> 0 | J20: =+G20+D20 -> 1656232 | K20: =+H20+E20 -> 0 | L20: =+I20+F20 -> 0 | M20: =+IFERROR(K20*100/C20,0) -> 0 | N20: =+IFERROR(L20*100/C20,0) -> 0
A21: A-3-6-1-2 | B21: Conciliaciones URA | C21: =+VLOOKUP(A21,gasto!$A$4:$F$68,3,FALSE) -> 0 | D21: 0 | E21: 0 | F21: 0 | G21: =+VLOOKUP(A21,gasto!$A$4:$F$68,4,FALSE) -> 0 | H21: =+VLOOKUP(A21,gasto!$A$4:$F$68,5,FALSE) -> 0 | I21: =+VLOOKUP(A21,gasto!$A$4:$F$68,6,FALSE) -> 0 | J21: =+G21+D21 -> 0 | K21: =+H21+E21 -> 0 | L21: =+I21+F21 -> 0 | M21: =+IFERROR(K21*100/C21,0) -> 0 | N21: =+IFERROR(L21*100/C21,0) -> 0
A22: A-3-6-3-0 | B22: Destinatarios de otras transferencias Corrientes - Compensación Chance | C22: =+C23 -> 160000000000 | D22: =+D23 -> 0 | E22: =+E23 -> 0 | F22: =+F23 -> 0 | G22: =+G23 -> 0 | H22: =+H23 -> 0 | I22: =+I23 -> 0 | J22: =+J23 -> 0 | ... L22: =+L23 -> 0 | M22: =+IFERROR(K22*100/C22,0) -> 0 | N22: =+IFERROR(L22*100/C22,0) -> 0
A23: A-3-6-3-0-01 | B23: Otras transferencias - Compensación del Chance Decreto 2550/12 | C23: =+VLOOKUP(A23,gasto!$A$4:$F$68,3,FALSE) -> 160000000000 | D23: 0 | E23: 0 | F23: 0 | G23: =+VLOOKUP(A23,gasto!$A$4:$F$68,4,FALSE) -> 0 | H23: =+VLOOKUP(A23,gasto!$A$4:$F$68,5,FALSE) -> 0 | I23: =+VLOOKUP(A23,gasto!$A$4:$F$68,6,FALSE) -> 0 | J23: =+G23+D23 -> 0 | K23: =+H23+E23 -> 0 | L23: =+I23+F23 -> 0 | M23: =+IFERROR(K23*100/C23,0) -> 0 | N23: =+IFERROR(L23*100/C23,0) -> 0
A24: A-3-9-0-0 | B24: ADMINISTRACIÓN DE RECURSOS DEL SGSSS | C24: =+C25+C30+C33+C36+C37+C38+C42+C45+C52+C56+C66+C77+C79+C81 -> 51971091684793 | D24: 0 | E24: 0 | F24: 0 | G24: =+G25+G30+G33+G36+G37+G38+G42+G45+G52+G56+G66+G77+G79+G81 -> 4.003282e+12 | H24: =+H25+H30+H33+H36+H37+H38+H42+H45+H52+H56+H66+H77+H79+H81 -> 3.9869733e+12 | I24: =+I25+I30+I33+I36+I37+I38+I42+I45+I52+I56+I66+I77+I79+I81 -> 3.9869733e+12 | J24: =+G24+D24 -> 4.003282e+12 | K24: =+H24+E24 -> 3.9869733e+12 | L24: =+I24+F24 -> 3.9869733e+12 | M24: =+IFERROR(K24*100/C24,0) -> 7.6715211 | N24: =+IFERROR(L24*100/C24,0) -> 7.6715211
A25: A-3-9-1-0 | B25: UPC Régimen Contributivo | C25: =+SUM(C26:C29) -> 23057892632980 | D25: =+SUM(D26:D29) -> 0 | E25: =+SUM(E26:E29) -> 0 | F25: =+SUM(F26:F29) -> 0 | G25: =+SUM(G26:G29) -> 1825601270168 | H25: =+SUM(H26:H29) -> 1825601270168 | I25: =+SUM(I26:I29) -> 1825601270168 | J25: =+SUM(J26:J29) -> 1825601270168 | ... L25: =+SUM(L26:L29) -> 1825601270168 | M25: =+IFERROR(K25*100/C25,0) -> 7.917468 | N25: =+IFERROR(L25*100/C25,0) -> 7.917468
A26: A-3-9-1-0-01 | B26: UPC Régimen Contributivo SSF | C26: =+VLOOKUP(A26,gasto!$A$4:$F$68,3,FALSE) -> 12399109660289 | D26: 0 | E26: 0 | F26: 0 | G26: =+VLOOKUP(A26,gasto!$A$4:$F$68,4,FALSE) -> 910942673794 | H26: =+VLOOKUP(A26,gasto!$A$4:$F$68,5,FALSE) -> 910942673794 | I26: =+VLOOKUP(A26,gasto!$A$4:$F$68,6,FALSE) -> 910942673794 | J26: =+G26+D26 -> 910942673794 | K26: =+H26+E26 -> 910942673794 | L26: =+I26+F26 -> 910942673794 | M26: =+IFERROR(K26*100/C26,0) -> 7.3468394 | N26: =+IFERROR(L26*100/C26,0) -> 7.3468394
A27: A-3-9-1-0-02 | B27: UPC Régimen Contributivo CSF | C27: =+VLOOKUP(A27,gasto!$A$4:$F$68,3,FALSE) -> 10647939289644 | D27: 0 | E27: 0 | F27: 0 | G27: =+VLOOKUP(A27,gasto!$A$4:$F$68,4,FALSE) -> 914297953268 | H27: =+VLOOKUP(A27,gasto!$A$4:$F$68,5,FALSE) -> 914297953268 | I27: =+VLOOKUP(A27,gasto!$A$4:$F$68,6,FALSE) -> 914297953268 | J27: =+G27+D27 -> 914297953268 | K27: =+H27+E27 -> 914297953268 | L27: =+I27+F27 -> 914297953268 | M27: =+IFERROR(K27*100/C27,0) -> 8.5866188 | N27: =+IFERROR(L27*100/C27,0) -> 8.5866188
A28: A-3-9-1-0-03 | B28: Devolución aportes y cotizaciones no conciliadas vigencia anterior | C28: =+VLOOKUP(A28,gasto!$A$4:$F$68,3,FALSE) -> 10223147816 | D28: 0 | E28: 0 | F28: 0 | G28: =+VLOOKUP(A28,gasto!$A$4:$F$68,4,FALSE) -> 360643106 | H28: =+VLOOKUP(A28,gasto!$A$4:$F$68,5,FALSE) -> 360643106 | I28: =+VLOOKUP(A28,gasto!$A$4:$F$68,6,FALSE) -> 360643106 | J28: =+G28+D28 -> 360643106 | K28: =+H28+E28 -> 360643106 | L28: =+I28+F28 -> 360643106 | M28: =+IFERROR(K28*100/C28,0) -> 3.527711 | N28: =+IFERROR(L28*100/C28,0) -> 3.527711
A29: A-3-9-1-0-04 | B29: Rendimientos Financieros de los Saldos no Compensados de los Aportes Patronales según Art. 12 Decreto 1636 de 2016 | C29: =+VLOOKUP(A29,gasto!$A$4:$F$68,3,FALSE) -> 620535231 | D29: 0 | E29: 0 | F29: 0 | G29: =+VLOOKUP(A29,gasto!$A$4:$F$68,4,FALSE) -> 0 | H29: =+VLOOKUP(A29,gasto!$A$4:$F$68,5,FALSE) -> 0 | I29: =+VLOOKUP(A29,gasto!$A$4:$F$68,6,FALSE) -> 0 | J29: =+G29+D29 -> 0 | K29: =+H29+E29 -> 0 | L29: =+I29+F29 -> 0 | M29: =+IFERROR(K29*100/C29,0) -> 0 | N29: =+IFERROR(L29*100/C29,0) -> 0
A30: A-3-9-2-0 | B30: Per capita Programas de Promoción y Prevención R.C | C30: =+SUM(C31:C32) -> 646778600953 | D30: =+SUM(D31:D32) -> 0 | E30: =+SUM(E31:E32) -> 0 | F30: =+SUM(F31:F32) -> 0 | G30: =+SUM(G31:G32) -> 41852875331 | H30: =+SUM(H31:H32) -> 41852875331 | I30: =+SUM(I31:I32) -> 41852875331 | J30: =+SUM(J31:J32) -> 41852875331 | ... L30: =+SUM(L31:L32) -> 41852875331 | M30: =+IFERROR(K30*100/C30,0) -> 6.470974 | N30: =+IFERROR(L30*100/C30,0) -> 6.470974
A31: A-3-9-2-0-01 | B31: Per capita Programas de Promoción y Prevención R.C SSF | C31: =+VLOOKUP(A31,gasto!$A$4:$F$68,3,FALSE) -> 510526042986 | D31: 0 | E31: 0 | F31: 0 | G31: =+VLOOKUP(A31,gasto!$A$4:$F$68,4,FALSE) -> 31541610651 | H31: =+VLOOKUP(A31,gasto!$A$4:$F$68,5,FALSE) -> 31541610651 | I31: =+VLOOKUP(A31,gasto!$A$4:$F$68,6,FALSE) -> 31541610651 | J31: =+G31+D31 -> 31541610651 | K31: =+H31+E31 -> 31541610651 | L31: =+I31+F31 -> 31541610651 | M31: =+IFERROR(K31*100/C31,0) -> 6.1782569 | N31: =+IFERROR(L31*100/C31,0) -> 6.1782569
A32: A-3-9-2-0-02 | B32: Per capita Programas de Promoción y Prevención R.C CSF | C32: =+VLOOKUP(A32,gasto!$A$4:$F$68,3,FALSE) -> 136252557967 | D32: 0 | E32: 0 | F32: 0 | G32: =+VLOOKUP(A32,gasto!$A$4:$F$68,4,FALSE) -> 10311264680 | H32: =+VLOOKUP(A32,gasto!$A$4:$F$68,5,FALSE) -> 10311264680 | I32: =+VLOOKUP(A32,gasto!$A$4:$F$68,6,FALSE) -> 10311264680 | J32: =+G32+D32 -> 10311264680 | K32: =+H32+E32 -> 10311264680 | L32: =+I32+F32 -> 10311264680 | M32: =+IFERROR(K32*100/C32,0) -> 7.5677586 | N32: =+IFERROR(L32*100/C32,0) -> 7.5677586
A33: A-3-9-3-0 | B33: Incapacidades | C33: =+SUM(C34:C35) -> 814461941941 | D33: =+SUM(D34:D35) -> 0 | E33: =+SUM(E34:E35) -> 0 | F33: =+SUM(F34:F35) -> 0 | G33: =+SUM(G34:G35) -> 67741191373 | H33: =+SUM(H34:H35) -> 67741191373 | I33: =+SUM(I34:I35) -> 67741191373 | J33: =+SUM(J34:J35) -> 67741191373 | ... L33: =+SUM(L34:L35) -> 67741191373 | M33: =+IFERROR(K33*100/C33,0) -> 8.3172936 | N33: =+IFERROR(L33*100/C33,0) -> 8.3172936
A34: A-3-9-3-0-01 | B34: Incapacidades SSF | C34: =+VLOOKUP(A34,gasto!$A$4:$F$68,3,FALSE) -> 629253806467 | D34: 0 | E34: 0 | F34: 0 | G34: =+VLOOKUP(A34,gasto!$A$4:$F$68,4,FALSE) -> 47814869173 | H34: =+VLOOKUP(A34,gasto!$A$4:$F$68,5,FALSE) -> 47814869173 | I34: =+VLOOKUP(A34,gasto!$A$4:$F$68,6,FALSE) -> 47814869173 | J34: =+G34+D34 -> 47814869173 | K34: =+H34+E34 -> 47814869173 | L34: =+I34+F34 -> 47814869173 | M34: =+IFERROR(K34*100/C34,0) -> 7.5986619 | N34: =+IFERROR(L34*100/C34,0) -> 7.5986619
A35: A-3-9-3-0-02 | B35: Incapacidades CSF | C35: =+VLOOKUP(A35,gasto!$A$4:$F$68,3,FALSE) -> 185208135474 | D35: 0 | E35: 0 | F35: 0 | G35: =+VLOOKUP(A35,gasto!$A$4:$F$68,4,FALSE) -> 19926322200 | H35: =+VLOOKUP(A35,gasto!$A$4:$F$68,5,FALSE) -> 19926322200 | I35: =+VLOOKUP(A35,gasto!$A$4:$F$68,6,FALSE) -> 19926322200 | J35: =+G35+D35 -> 19926322200 | K35: =+H35+E35 -> 19926322200 | L35: =+I35+F35 -> 19926322200 | M35: =+IFERROR(K35*100/C35,0) -> 10.758881 | N35: =+IFERROR(L35*100/C35,0) -> 10.758881
A36: A-3-9-4-0 | B36: Licencias de Maternidad y Paternidad | C36: =+VLOOKUP(A36,gasto!$A$4:$F$68,3,FALSE) -> 838554045453 | D36: 0 | E36: 0 | F36: 0 | G36: =+VLOOKUP(A36,gasto!$A$4:$F$68,4,FALSE) -> 67879430670 | H36: =+VLOOKUP(A36,gasto!$A$4:$F$68,5,FALSE) -> 67879430670 | I36: =+VLOOKUP(A36,gasto!$A$4:$F$68,6,FALSE) -> 67879430670 | J36: =+G36+D36 -> 67879430670 | K36: =+H36+E36 -> 67879430670 | L36: =+I36+F36 -> 67879430670 | M36: =+IFERROR(K36*100/C36,0) -> 8.0948188 | N36: =+IFERROR(L36*100/C36,0) -> 8.0948188
A37: A-3-9-5-0 | B37: Prestaciones Económicas Regímenes Especial y de Excepción | C37: =+VLOOKUP(A37,gasto!$A$4:$F$68,3,FALSE) -> 4102227236 | D37: 0 | E37: 0 | F37: 0 | G37: =+VLOOKUP(A37,gasto!$A$4:$F$68,4,FALSE) -> 3048911179 | H37: =+VLOOKUP(A37,gasto!$A$4:$F$68,5,FALSE) -> 73201075 | I37: =+VLOOKUP(A37,gasto!$A$4:$F$68,6,FALSE) -> 73201075 | J37: =+G37+D37 -> 3048911179 | K37: =+H37+E37 -> 73201075 | L37: =+I37+F37 -> 73201075 | M37: =+IFERROR(K37*100/C37,0) -> 1.7844227 | N37: =+IFERROR(L37*100/C37,0) -> 1.7844227
A38: A-3-9-6-0 | B38: UPC Régimen Subsidiado | C38: =+SUM(C39:C41) -> 21586257607421 | D38: =+SUM(D39:D41) -> 0 | E38: =+SUM(E39:E41) -> 0 | F38: =+SUM(F39:F41) -> 0 | G38: =+SUM(G39:G41) -> 1.7760712e+12 | H38: =+SUM(H39:H41) -> 1.7760712e+12 | I38: =+SUM(I39:I41) -> 1.7760712e+12 | J38: =+SUM(J39:J41) -> 1.7760712e+12 | ... L38: =+SUM(L39:L41) -> 1.7760712e+12 | M38: =+IFERROR(K38*100/C38,0) -> 8.2277866 | N38: =+IFERROR(L38*100/C38,0) -> 8.2277866
A39: A-3-9-6-0-01 | B39: UPC´S R.S. Cajas de Compensación Familiar SSF | C39: =+VLOOKUP(A39,gasto!$A$4:$F$68,3,FALSE) -> 28877831435 | D39: 0 | E39: 0 | F39: 0 | G39: =+VLOOKUP(A39,gasto!$A$4:$F$68,4,FALSE) -> 3204560767 | H39: =+VLOOKUP(A39,gasto!$A$4:$F$68,5,FALSE) -> 3204560767 | I39: =+VLOOKUP(A39,gasto!$A$4:$F$68,6,FALSE) -> 3204560767 | J39: =+G39+D39 -> 3204560767 | K39: =+H39+E39 -> 3204560767 | L39: =+I39+F39 -> 3204560767 | M39: =+IFERROR(K39*100/C39,0) -> 11.096958 | N39: =+IFERROR(L39*100/C39,0) -> 11.096958
A40: A-3-9-6-0-02 | B40: UPC´S R.S. CSF | C40: =+VLOOKUP(A40,gasto!$A$4:$F$68,3,FALSE) -> 21520379775986 | D40: 0 | E40: 0 | F40: 0 | G40: =+VLOOKUP(A40,gasto!$A$4:$F$68,4,FALSE) -> 1.7728666e+12 | H40: =+VLOOKUP(A40,gasto!$A$4:$F$68,5,FALSE) -> 1.7728666e+12 | I40: =+VLOOKUP(A40,gasto!$A$4:$F$68,6,FALSE) -> 1.7728666e+12 | J40: =+G40+D40 -> 1.7728666e+12 | K40: =+H40+E40 -> 1.7728666e+12 | L40: =+I40+F40 -> 1.7728666e+12 | M40: =+IFERROR(K40*100/C40,0) -> 8.2380825 | N40: =+IFERROR(L40*100/C40,0) -> 8.2380825
A41: A-3-9-6-0-03 | B41: UPC´S R.S. USPEC | C41: =+VLOOKUP(A41,gasto!$A$4:$F$68,3,FALSE) -> 37000000000 | D41: 0 | E41: 0 | F41: 0 | G41: =+VLOOKUP(A41,gasto!$A$4:$F$68,4,FALSE) -> 0 | H41: =+VLOOKUP(A41,gasto!$A$4:$F$68,5,FALSE) -> 0 | I41: =+VLOOKUP(A41,gasto!$A$4:$F$68,6,FALSE) -> 0 | J41: =+G41+D41 -> 0 | K41: =+H41+E41 -> 0 | L41: =+I41+F41 -> 0
A42: A-3-9-7-0 | B42: Prestaciones Excepcionales - Recobros | C42: =+SUM(C43:C44) -> 4083854535766 | D42: =+SUM(D43:D44) -> 0 | E42: =+SUM(E43:E44) -> 0 | F42: =+SUM(F43:F44) -> 0 | G42: =+SUM(G43:G44) -> 2.0671425e+11 | H42: =+SUM(H43:H44) -> 2.0671425e+11 | I42: =+SUM(I43:I44) -> 2.0671425e+11 | J42: =+SUM(J43:J44) -> 2.0671425e+11 | ... L42: =+SUM(L43:L44) -> 2.0671425e+11 | M42: =+IFERROR(K42*100/C42,0) -> 5.0617438 | N42: =+IFERROR(L42*100/C42,0) -> 5.0617438
A43: A-3-9-7-0-01 | B43: Recobros - Reembolsos Régimen Contributivo | C43: =+VLOOKUP(A43,gasto!$A$4:$F$68,3,FALSE) -> 4072663890220 | D43: 0 | E43: 0 | F43: 0 | G43: =+VLOOKUP(A43,gasto!$A$4:$F$68,4,FALSE) -> 2.0644103e+11 | H43: =+VLOOKUP(A43,gasto!$A$4:$F$68,5,FALSE) -> 2.0644103e+11 | I43: =+VLOOKUP(A43,gasto!$A$4:$F$68,6,FALSE) -> 2.0644103e+11 | J43: =+G43+D43 -> 2.0644103e+11 | K43: =+H43+E43 -> 2.0644103e+11 | L43: =+I43+F43 -> 2.0644103e+11 | M43: =+IFERROR(K43*100/C43,0) -> 5.0689434 | N43: =+IFERROR(L43*100/C43,0) -> 5.0689434
A44: A-3-9-7-0-02 | B44: Recobros - Reembolsos Régimen Subsidiado - Tutelas | C44: =+VLOOKUP(A44,gasto!$A$4:$F$68,3,FALSE) -> 11190645546 | D44: 0 | E44: 0 | F44: 0 | G44: =+VLOOKUP(A44,gasto!$A$4:$F$68,4,FALSE) -> 2.7322362e+08 | H44: =+VLOOKUP(A44,gasto!$A$4:$F$68,5,FALSE) -> 2.7322362e+08 | I44: =+VLOOKUP(A44,gasto!$A$4:$F$68,6,FALSE) -> 2.7322362e+08 | J44: =+G44+D44 -> 2.7322362e+08 | K44: =+H44+E44 -> 2.7322362e+08 | L44: =+I44+F44 -> 2.7322362e+08 | M44: =+IFERROR(K44*100/C44,0) -> 2.4415358 | N44: =+IFERROR(L44*100/C44,0) -> 2.4415358
A45: A-3-9-8-0 | B45: Atención en Salud, Transporte Primario, Indemnizaciones y Auxilio Funerario Víctimas | C45: =+SUM(C46:C51) -> 260989164610 | D45: =+SUM(D46:D51) -> 0 | E45: =+SUM(E46:E51) -> 0 | F45: =+SUM(F46:F51) -> 0 | G45: =+SUM(G46:G51) -> 222768589 | H45: =+SUM(H46:H51) -> 222768589 | I45: =+SUM(I46:I51) -> 222768589 | J45: =+SUM(J46:J51) -> 222768589 | ... L45: =+SUM(L46:L51) -> 222768589 | M45: =+IFERROR(K45*100/C45,0) -> 0.085355493 | N45: =+IFERROR(L45*100/C45,0) -> 0.085355493
A46: A-3-9-8-0-01 | B46: Eventos territoristas | C46: =+VLOOKUP(A46,gasto!$A$4:$F$68,3,FALSE) -> 272244074 | D46: 0 | E46: 0 | F46: 0 | G46: =+VLOOKUP(A46,gasto!$A$4:$F$68,4,FALSE) -> 0 | H46: =+VLOOKUP(A46,gasto!$A$4:$F$68,5,FALSE) -> 0 | I46: =+VLOOKUP(A46,gasto!$A$4:$F$68,6,FALSE) -> 0 | J46: =+G46+D46 -> 0 | K46: =+H46+E46 -> 0 | L46: =+I46+F46 -> 0 | M46: =+IFERROR(K46*100/C46,0) -> 0 | N46: =+IFERROR(L46*100/C46,0) -> 0
A47: A-3-9-8-0-02 | B47: Eventos Catastróficos | C47: =+VLOOKUP(A47,gasto!$A$4:$F$68,3,FALSE) -> 2733436752 | D47: 0 | E47: 0 | F47: 0 | G47: =+VLOOKUP(A47,gasto!$A$4:$F$68,4,FALSE) -> 0 | H47: =+VLOOKUP(A47,gasto!$A$4:$F$68,5,FALSE) -> 0 | I47: =+VLOOKUP(A47,gasto!$A$4:$F$68,6,FALSE) -> 0 | J47: =+G47+D47 -> 0 | K47: =+H47+E47 -> 0 | L47: =+I47+F47 -> 0 | M47: =+IFERROR(K47*100/C47,0) -> 0 | N47: =+IFERROR(L47*100/C47,0) -> 0
A48: A-3-9-8-0-03 | B48: Accidentes de Transito | C48: =+VLOOKUP(A48,gasto!$A$4:$F$68,3,FALSE) -> 227724483784 | D48: 0 | E48: 0 | F48: 0 | G48: =+VLOOKUP(A48,gasto!$A$4:$F$68,4,FALSE) -> 0 | H48: =+VLOOKUP(A48,gasto!$A$4:$F$68,5,FALSE) -> 0 | I48: =+VLOOKUP(A48,gasto!$A$4:$F$68,6,FALSE) -> 0 | J48: =+G48+D48 -> 0 | K48: =+H48+E48 -> 0 | L48: =+I48+F48 -> 0 | M48: =+IFERROR(K48*100/C48,0) -> 0 | N48: =+IFERROR(L48*100/C48,0) -> 0
A49: A-3-9-8-0-04 | B49: Apoyo Reclamaciones Reserva especial | C49: =+VLOOKUP(A49,gasto!$A$4:$F$68,3,FALSE) -> 250000000 | D49: 0 | E49: 0 | F49: 0 | G49: =+VLOOKUP(A49,gasto!$A$4:$F$68,4,FALSE) -> 0 | H49: =+VLOOKUP(A49,gasto!$A$4:$F$68,5,FALSE) -> 0 | I49: =+VLOOKUP(A49,gasto!$A$4:$F$68,6,FALSE) -> 0 | J49: =+G49+D49 -> 0 | K49: =+H49+E49 -> 0 | L49: =+I49+F49 -> 0 | M49: =+IFERROR(K49*100/C49,0) -> 0 | N49: =+IFERROR(L49*100/C49,0) -> 0
A50: A-3-9-8-0-05 | B50: Oficina de Gestión Territorial, Emergencias y Desastres-Atención de urgencias nacionales y extranjeros — zonas fronterizas. Art 57 Ley 1815 de 2016 | C50: =+VLOOKUP(A50,gasto!$A$4:$F$68,3,FALSE) -> 30000000000 | D50: 0 | E50: 0 | F50: 0 | G50: =+VLOOKUP(A50,gasto!$A$4:$F$68,4,FALSE) -> 222768589 | H50: =+VLOOKUP(A50,gasto!$A$4:$F$68,5,FALSE) -> 222768589 | I50: =+VLOOKUP(A50,gasto!$A$4:$F$68,6,FALSE) -> 222768589 | J50: =+G50+D50 -> 222768589 | K50: =+H50+E50 -> 222768589 | L50: =+I50+F50 -> 222768589 | M50: =+IFERROR(K50*100/C50,0) -> 0.74256196 | N50: =+IFERROR(L50*100/C50,0) -> 0.74256196
A51: A-3-9-8-0-06 | B51: Apoyo Reclamaciones Victimas Poblaciòn desplazada | C51: =+VLOOKUP(A51,gasto!$A$4:$F$68,3,FALSE) -> 9000000 | D51: 0 | E51: 0 | F51: 0 | G51: =+VLOOKUP(A51,gasto!$A$4:$F$68,4,FALSE) -> 0 | H51: =+VLOOKUP(A51,gasto!$A$4:$F$68,5,FALSE) -> 0 | I51: =+VLOOKUP(A51,gasto!$A$4:$F$68,6,FALSE) -> 0 | J51: =+G51+D51 -> 0 | K51: =+H51+E51 -> 0 | L51: =+I51+F51 -> 0 | M51: =+IFERROR(K51*100/C51,0) -> 0 | N51: =+IFERROR(L51*100/C51,0) -> 0
A52: A-3-9-9-0 | B52: Fortalecimiento Red Nacional de Urgencias, Emergencia Sanitaria y eventos Catastróficos | C52: =+SUM(C53:C55) -> 3988276390 | D52: =+SUM(D53:D55) -> 0 | E52: =+SUM(E53:E55) -> 0 | F52: =+SUM(F53:F55) -> 0 | G52: =+SUM(G53:G55) -> 0 | H52: =+SUM(H53:H55) -> 0 | I52: =+SUM(I53:I55) -> 0 | J52: =+SUM(J53:J55) -> 0 | ... L52: =+SUM(L53:L55) -> 0 | M52: =+IFERROR(K52*100/C52,0) -> 0 | N52: =+IFERROR(L52*100/C52,0) -> 0
A53: A-3-9-9-0-01 | B53: Oficina de Gestión Territorial, Emergencias y Desastres-Fortalecimiento Red Nacional de Urgencias | C53: =+VLOOKUP(A53,gasto!$A$4:$F$68,3,FALSE) -> 3988276390 | D53: 0 | E53: 0 | F53: 0 | G53: =+VLOOKUP(A53,gasto!$A$4:$F$68,4,FALSE) -> 0 | H53: =+VLOOKUP(A53,gasto!$A$4:$F$68,5,FALSE) -> 0 | I53: =+VLOOKUP(A53,gasto!$A$4:$F$68,6,FALSE) -> 0 | J53: =+G53+D53 -> 0 | K53: =+H53+E53 -> 0 | L53: =+I53+F53 -> 0 | M53: =+IFERROR(K53*100/C53,0) -> 0 | N53: =+IFERROR(L53*100/C53,0) -> 0
A54: A-3-9-9-0-02 | B54: Emergencia Sanitaria | C54: =+VLOOKUP(A54,gasto!$A$4:$F$68,3,FALSE) -> 0 | D54: 0 | E54: 0 | F54: 0 | G54: =+VLOOKUP(A54,gasto!$A$4:$F$68,4,FALSE) -> 0 | H54: =+VLOOKUP(A54,gasto!$A$4:$F$68,5,FALSE) -> 0 | I54: =+VLOOKUP(A54,gasto!$A$4:$F$68,6,FALSE) -> 0 | J54: =+G54+D54 -> 0 | K54: =+H54+E54 -> 0 | L54: =+I54+F54 -> 0 | M54: =+IFERROR(K54*100/C54,0) -> 0 | N54: =+IFERROR(L54*100/C54,0) -> 0
A55: A-3-9-9-0-03 | B55: Eventos Catastróficos | C55: =+VLOOKUP(A55,gasto!$A$4:$F$68,3,FALSE) -> 0 | D55: 0 | E55: 0 | F55: 0 | G55: =+VLOOKUP(A55,gasto!$A$4:$F$68,4,FALSE) -> 0 | H55: =+VLOOKUP(A55,gasto!$A$4:$F$68,5,FALSE) -> 0 | I55: =+VLOOKUP(A55,gasto!$A$4:$F$68,6,FALSE) -> 0 | J55: =+G55+D55 -> 0 | K55: =+H55+E55 -> 0 | L55: =+I55+F55 -> 0 | M55: =+IFERROR(K55*100/C55,0) -> 0 | N55: =+IFERROR(L55*100/C55,0) -> 0
A56: A-3-9-10-0 | B56: Otros Programas de Salud Promoción y prevención | C56: =+SUM(C57:C65) -> 104120791000 | D56: =+SUM(D57:D65) -> 0 | E56: =+SUM(E57:E65) -> 0 | F56: =+SUM(F57:F65) -> 0 | G56: =+SUM(G57:G65) -> 13333000000 | H56: =+SUM(H57:H65) -> 0 | I56: =+SUM(I57:I65) -> 0 | J56: =+SUM(J57:J65) -> 13333000000 | ... L56: =+SUM(L57:L65) -> 0 | M56: =+IFERROR(K56*100/C56,0) -> 0 | N56: =+IFERROR(L56*100/C56,0) -> 0
A57: A-3-9-10-0-01 | B57: Dirección de Promoción y Prevención - Programas de Salud de P y P - VACUNAS | C57: =+VLOOKUP(A57,gasto!$A$4:$F$68,3,FALSE) -> 56595754535 | D57: 0 | E57: 0 | F57: 0 | G57: =+VLOOKUP(A57,gasto!$A$4:$F$68,4,FALSE) -> 0 | H57: =+VLOOKUP(A57,gasto!$A$4:$F$68,5,FALSE) -> 0 | I57: =+VLOOKUP(A57,gasto!$A$4:$F$68,6,FALSE) -> 0 | J57: =+G57+D57 -> 0 | K57: =+H57+E57 -> 0 | L57: =+I57+F57 -> 0 | M57: =+IFERROR(K57*100/C57,0) -> 0 | N57: =+IFERROR(L57*100/C57,0) -> 0
A58: A-3-9-10-0-02 | B58: Oficina de Promoción Social - programa de Atención Psicosocial y Salud Integral a Víctimas del Conflicto Armado Programa PAPSIVI | C58: =+VLOOKUP(A58,gasto!$A$4:$F$68,3,FALSE) -> 18000000000 | D58: 0 | E58: 0 | F58: 0 | G58: =+VLOOKUP(A58,gasto!$A$4:$F$68,4,FALSE) -> 13333000000 | H58: =+VLOOKUP(A58,gasto!$A$4:$F$68,5,FALSE) -> 0 | I58: =+VLOOKUP(A58,gasto!$A$4:$F$68,6,FALSE) -> 0 | J58: =+G58+D58 -> 13333000000 | K58: =+H58+E58 -> 0 | L58: =+I58+F58 -> 0 | M58: =+IFERROR(K58*100/C58,0) -> 0 | N58: =+IFERROR(L58*100/C58,0) -> 0
A59: A-3-9-10-0-03 | B59: Programa mujeres víctimas de la violencia | C59: =+VLOOKUP(A59,gasto!$A$4:$F$68,3,FALSE) -> 0 | D59: 0 | E59: 0 | F59: 0 | G59: =+VLOOKUP(A59,gasto!$A$4:$F$68,4,FALSE) -> 0 | H59: =+VLOOKUP(A59,gasto!$A$4:$F$68,5,FALSE) -> 0 | I59: =+VLOOKUP(A59,gasto!$A$4:$F$68,6,FALSE) -> 0 | J59: =+G59+D59 -> 0 | K59: =+H59+E59 -> 0 | L59: =+I59+F59 -> 0 | M59: =+IFERROR(K59*100/C59,0) -> 0 | N59: =+IFERROR(L59*100/C59,0) -> 0
A60: A-3-9-10-0-04 | B60: Otros Programas de Salud diferentes a los anteriores | C60: =+VLOOKUP(A60,gasto!$A$4:$F$68,3,FALSE) -> 0 | D60: 0 | E60: 0 | F60: 0 | G60: =+VLOOKUP(A60,gasto!$A$4:$F$68,4,FALSE) -> 0 | H60: =+VLOOKUP(A60,gasto!$A$4:$F$68,5,FALSE) -> 0 | I60: =+VLOOKUP(A60,gasto!$A$4:$F$68,6,FALSE) -> 0 | J60: =+G60+D60 -> 0 | K60: =+H60+E60 -> 0 | L60: =+I60+F60 -> 0 | M60: =+IFERROR(K60*100/C60,0) -> 0 | N60: =+IFERROR(L60*100/C60,0) -> 0
A61: A-3-9-10-0-05 | B61: Campañas de Prevencion de la Violencia y Promoción de la Convivencia Pacifica a Nivel Nacional o Territorial | C61: =+VLOOKUP(A61,gasto!$A$4:$F$68,3,FALSE) -> 409233681 | D61: 0 | E61: 0 | F61: 0 | G61: =+VLOOKUP(A61,gasto!$A$4:$F$68,4,FALSE) -> 0 | H61: =+VLOOKUP(A61,gasto!$A$4:$F$68,5,FALSE) -> 0 | I61: =+VLOOKUP(A61,gasto!$A$4:$F$68,6,FALSE) -> 0 | J61: =+G61+D61 -> 0 | K61: =+H61+E61 -> 0 | L61: =+I61+F61 -> 0 | M61: =+IFERROR(K61*100/C61,0) -> 0 | N61: =+IFERROR(L61*100/C61,0) -> 0
A62: A-3-9-10-0-06 | B62: Prevención y Sanción de Formas de Violencia y discriminación Contra las Mujeres | C62: =+VLOOKUP(A62,gasto!$A$4:$F$68,3,FALSE) -> 6001557319 | D62: 0 | E62: 0 | F62: 0 | G62: =+VLOOKUP(A62,gasto!$A$4:$F$68,4,FALSE) -> 0 | H62: =+VLOOKUP(A62,gasto!$A$4:$F$68,5,FALSE) -> 0 | I62: =+VLOOKUP(A62,gasto!$A$4:$F$68,6,FALSE) -> 0 | J62: =+G62+D62 -> 0 | K62: =+H62+E62 -> 0 | L62: =+I62+F62 -> 0 | M62: =+IFERROR(K62*100/C62,0) -> 0 | N62: =+IFERROR(L62*100/C62,0) -> 0
A63: A-3-9-10-0-07 | B63: Atención Usuario Protesis PIP Resolución 0258 de 2012 | C63: =+VLOOKUP(A63,gasto!$A$4:$F$68,3,FALSE) -> 160000000 | D63: 0 | E63: 0 | F63: 0 | G63: =+VLOOKUP(A63,gasto!$A$4:$F$68,4,FALSE) -> 0 | H63: =+VLOOKUP(A63,gasto!$A$4:$F$68,5,FALSE) -> 0 | I63: =+VLOOKUP(A63,gasto!$A$4:$F$68,6,FALSE) -> 0 | J63: =+G63+D63 -> 0 | K63: =+H63+E63 -> 0 | L63: =+I63+F63 -> 0 | M63: =+IFERROR(K63*100/C63,0) -> 0 | N63: =+IFERROR(L63*100/C63,0) -> 0
A64: A-3-9-10-0-08 | B64: Déficit Cajas de Compensación Familiar - Balance | C64: =+VLOOKUP(A64,gasto!$A$4:$F$68,3,FALSE) -> 2000000000 | D64: 0 | E64: 0 | F64: 0 | G64: =+VLOOKUP(A64,gasto!$A$4:$F$68,4,FALSE) -> 0 | H64: =+VLOOKUP(A64,gasto!$A$4:$F$68,5,FALSE) -> 0 | I64: =+VLOOKUP(A64,gasto!$A$4:$F$68,6,FALSE) -> 0 | J64: =+G64+D64 -> 0 | K64: =+H64+E64 -> 0 | L64: =+I64+F64 -> 0 | M64: =+IFERROR(K64*100/C64,0) -> 0 | N64: =+IFERROR(L64*100/C64,0) -> 0
A65: A-3-9-10-0-09 | B65: Certificado de Discapacidad, Suministro de Fórmula Terapéutica | C65: =+VLOOKUP(A65,gasto!$A$4:$F$68,3,FALSE) -> 20954245465 | D65: 0 | E65: 0 | F65: 0 | G65: =+VLOOKUP(A65,gasto!$A$4:$F$68,4,FALSE) -> 0 | H65: =+VLOOKUP(A65,gasto!$A$4:$F$68,5,FALSE) -> 0 | I65: =+VLOOKUP(A65,gasto!$A$4:$F$68,6,FALSE) -> 0 | J65: =+G65+D65 -> 0 | K65: =+H65+E65 -> 0 | L65: =+I65+F65 -> 0
A66: A-3-9-11-0 | B66: Recursos con destinación específica | C66: =+SUM(C67:C76) -> 366925255924 | D66: =+SUM(D67:D76) -> 0 | E66: =+SUM(E67:E76) -> 0 | F66: =+SUM(F67:F76) -> 0 | G66: =+SUM(G67:G76) -> 0 | H66: =+SUM(H67:H76) -> 0 | I66: =+SUM(I67:I76) -> 0 | J66: =+SUM(J67:J76) -> 0 | ... L66: =+SUM(L67:L76) -> 0 | M66: =+IFERROR(K66*100/C66,0) -> 0 | N66: =+IFERROR(L66*100/C66,0) -> 0
A67: A-3-9-11-0-01 | B67: Pago a IPS de servicios prestados a la población pobre no asegurada y servicios no incluidos en el Plan de beneficios Pago a IPS de servicios prestados a la población, exceden(Art. 3 Ley 1608 de 2013) | C67: =+VLOOKUP(A67,gasto!$A$4:$F$68,3,FALSE) -> 5801668388 | D67: 0 | E67: 0 | F67: 0 | G67: =+VLOOKUP(A67,gasto!$A$4:$F$68,4,FALSE) -> 0 | H67: =+VLOOKUP(A67,gasto!$A$4:$F$68,5,FALSE) -> 0 | I67: =+VLOOKUP(A67,gasto!$A$4:$F$68,6,FALSE) -> 0 | J67: =+G67+D67 -> 0 | K67: =+H67+E67 -> 0 | L67: =+I67+F67 -> 0 | M67: =+IFERROR(K67*100/C67,0) -> 0 | N67: =+IFERROR(L67*100/C67,0) -> 0
A68: A-3-9-11-0-02 | B68: Reconocimiento de deuda por contratos del Régimen Subsidiado realizados hasta marzo 31 de 2011- Recursos LOTTO en Línea – FONPET | C68: =+VLOOKUP(A68,gasto!$A$4:$F$68,3,FALSE) -> 5000000000 | D68: 0 | E68: 0 | F68: 0 | G68: =+VLOOKUP(A68,gasto!$A$4:$F$68,4,FALSE) -> 0 | H68: =+VLOOKUP(A68,gasto!$A$4:$F$68,5,FALSE) -> 0 | I68: =+VLOOKUP(A68,gasto!$A$4:$F$68,6,FALSE) -> 0 | J68: =+G68+D68 -> 0 | K68: =+H68+E68 -> 0 | L68: =+I68+F68 -> 0 | M68: =+IFERROR(K68*100/C68,0) -> 0 | N68: =+IFERROR(L68*100/C68,0) -> 0
A69: A-3-9-11-0-03 | B69: Reconocimiento de deuda por contratos del Régimen Subsidiado realizados hasta marzo 31 de 2011- Recursos FAEP | C69: =+VLOOKUP(A69,gasto!$A$4:$F$68,3,FALSE) -> 800000000 | D69: 0 | E69: 0 | F69: 0 | G69: =+VLOOKUP(A69,gasto!$A$4:$F$68,4,FALSE) -> 0 | H69: =+VLOOKUP(A69,gasto!$A$4:$F$68,5,FALSE) -> 0 | I69: =+VLOOKUP(A69,gasto!$A$4:$F$68,6,FALSE) -> 0 | J69: =+G69+D69 -> 0 | K69: =+H69+E69 -> 0 | L69: =+I69+F69 -> 0 | M69: =+IFERROR(K69*100/C69,0) -> 0 | N69: =+IFERROR(L69*100/C69,0) -> 0
A70: A-3-9-11-0-04 | B70: Pago de deudas Régimen Subsidiado – Artículo 275 de la Ley 1450 de 2011 - SGP Libre Inversión | C70: =+VLOOKUP(A70,gasto!$A$4:$F$68,3,FALSE) -> 20000000000 | D70: 0 | E70: 0 | F70: 0 | G70: =+VLOOKUP(A70,gasto!$A$4:$F$68,4,FALSE) -> 0 | H70: =+VLOOKUP(A70,gasto!$A$4:$F$68,5,FALSE) -> 0 | I70: =+VLOOKUP(A70,gasto!$A$4:$F$68,6,FALSE) -> 0 | J70: =+G70+D70 -> 0 | K70: =+H70+E70 -> 0 | L70: =+I70+F70 -> 0 | M70: =+IFERROR(K70*100/C70,0) -> 0 | N70: =+IFERROR(L70*100/C70,0) -> 0
A71: A-3-9-11-0-05 | B71: Excedentes de Aportes Patronales / Resolución 2360 de 2016 | C71: =+VLOOKUP(A71,gasto!$A$4:$F$68,3,FALSE) -> 49454127709 | D71: 0 | E71: 0 | F71: 0 | G71: =+VLOOKUP(A71,gasto!$A$4:$F$68,4,FALSE) -> 0 | H71: =+VLOOKUP(A71,gasto!$A$4:$F$68,5,FALSE) -> 0 | I71: =+VLOOKUP(A71,gasto!$A$4:$F$68,6,FALSE) -> 0 | J71: =+G71+D71 -> 0 | K71: =+H71+E71 -> 0 | L71: =+I71+F71 -> 0 | M71: =+IFERROR(K71*100/C71,0) -> 0 | N71: =+IFERROR(L71*100/C71,0) -> 0
A72: A-3-9-11-0-06 | B72: Regalías – Art. 5 Ley 1797 de 2016 | C72: =+VLOOKUP(A72,gasto!$A$4:$F$68,3,FALSE) -> 3000000000 | D72: 0 | E72: 0 | F72: 0 | G72: =+VLOOKUP(A72,gasto!$A$4:$F$68,4,FALSE) -> 0 | H72: =+VLOOKUP(A72,gasto!$A$4:$F$68,5,FALSE) -> 0 | I72: =+VLOOKUP(A72,gasto!$A$4:$F$68,6,FALSE) -> 0 | J72: =+G72+D72 -> 0 | K72: =+H72+E72 -> 0 | L72: =+I72+F72 -> 0 | M72: =+IFERROR(K72*100/C72,0) -> 0 | N72: =+IFERROR(L72*100/C72,0) -> 0
A73: A-3-9-11-0-07 | B73: Otros Recursos con Destinación Especifica | C73: =+VLOOKUP(A73,gasto!$A$4:$F$68,3,FALSE) -> 55000000000 | D73: 0 | E73: 0 | F73: 0 | G73: =+VLOOKUP(A73,gasto!$A$4:$F$68,4,FALSE) -> 0 | H73: =+VLOOKUP(A73,gasto!$A$4:$F$68,5,FALSE) -> 0 | I73: =+VLOOKUP(A73,gasto!$A$4:$F$68,6,FALSE) -> 0 | J73: =+G73+D73 -> 0 | K73: =+H73+E73 -> 0 | L73: =+I73+F73 -> 0 | M73: =+IFERROR(K73*100/C73,0) -> 0 | N73: =+IFERROR(L73*100/C73,0) -> 0
A74: A-3-9-11-0-08 | B74: Recursos CCF / FOSFEC - Ley 1929 de 2018 | C74: =+VLOOKUP(A74,gasto!$A$4:$F$68,3,FALSE) -> 36000000000 | D74: 0 | E74: 0 | F74: 0 | G74: =+VLOOKUP(A74,gasto!$A$4:$F$68,4,FALSE) -> 0 | H74: =+VLOOKUP(A74,gasto!$A$4:$F$68,5,FALSE) -> 0 | I74: =+VLOOKUP(A74,gasto!$A$4:$F$68,6,FALSE) -> 0 | J74: =+G74+D74 -> 0 | K74: =+H74+E74 -> 0 | L74: =+I74+F74 -> 0 | M74: =+IFERROR(K74*100/C74,0) -> 0 | N74: =+IFERROR(L74*100/C74,0) -> 0
A75: A-3-9-11-0-09 | B75: Saneamiento aportes patronales SGP | C75: =+VLOOKUP(A75,gasto!$A$4:$F$68,3,FALSE) -> 76869459827 | D75: 0 | E75: 0 | F75: 0 | G75: =+VLOOKUP(A75,gasto!$A$4:$F$68,4,FALSE) -> 0 | H75: =+VLOOKUP(A75,gasto!$A$4:$F$68,5,FALSE) -> 0 | I75: =+VLOOKUP(A75,gasto!$A$4:$F$68,6,FALSE) -> 0 | J75: =+G75+D75 -> 0 | K75: =+H75+E75 -> 0 | L75: =+I75+F75 -> 0
A76: A-3-9-11-0-10 | B76: Devolución recursos Entidades Territoriales | C76: =+VLOOKUP(A76,gasto!$A$4:$F$68,3,FALSE) -> 115000000000 | D76: 0 | E76: 0 | F76: 0 | G76: =+VLOOKUP(A76,gasto!$A$4:$F$68,4,FALSE) -> 0 | H76: =+VLOOKUP(A76,gasto!$A$4:$F$68,5,FALSE) -> 0 | I76: =+VLOOKUP(A76,gasto!$A$4:$F$68,6,FALSE) -> 0 | J76: =+G76+D76 -> 0 | K76: =+H76+E76 -> 0 | L76: =+I76+F76 -> 0
A77: A-3-9-12-0 | B77: Pago Obligaciones ESE´S con Recursos FONSAET | C77: =+C78 -> 95551523562 | D77: =+D78 -> 0 | E77: =+E78 -> 0 | F77: =+F78 -> 0 | G77: =+G78 -> 0 | H77: =+H78 -> 0 | I77: =+I78 -> 0 | J77: =+J78 -> 0 | ... L77: =+L78 -> 0 | M77: =+IFERROR(K77*100/C77,0) -> 0 | N77: =+IFERROR(L77*100/C77,0) -> 0
A78: A-3-9-12-0-01 | B78: Pago Obligaciones EPS FONSAET | C78: =+VLOOKUP(A78,gasto!$A$4:$F$68,3,FALSE) -> 95551523562 | D78: 0 | E78: 0 | F78: 0 | G78: =+VLOOKUP(A78,gasto!$A$4:$F$68,4,FALSE) -> 0 | H78: =+VLOOKUP(A78,gasto!$A$4:$F$68,5,FALSE) -> 0 | I78: =+VLOOKUP(A78,gasto!$A$4:$F$68,6,FALSE) -> 0 | J78: =+G78+D78 -> 0 | K78: =+H78+E78 -> 0 | L78: =+I78+F78 -> 0 | M78: =+IFERROR(K78*100/C78,0) -> 0 | N78: =+IFERROR(L78*100/C78,0) -> 0
A79: A-3-9-13-0 | B79: Reconocimiento Rendimientos Financieros cuentas de recaudo EPS SSF | C79: =+C80 -> 7615081557 | D79: =+D80 -> 0 | E79: =+E80 -> 0 | F79: =+F80 -> 0 | G79: =+G80 -> 817079635 | H79: =+H80 -> 817079635 | I79: =+I80 -> 817079635 | J79: =+J80 -> 817079635 | ... L79: =+L80 -> 817079635 | M79: =+IFERROR(K79*100/C79,0) -> 10.729756 | N79: =+IFERROR(L79*100/C79,0) -> 10.729756
A80: A-3-9-13-0-01 | B80: Rendimientos Financieros EPS SSF | C80: =+VLOOKUP(A80,gasto!$A$4:$F$68,3,FALSE) -> 7615081557 | D80: 0 | E80: 0 | F80: 0 | G80: =+VLOOKUP(A80,gasto!$A$4:$F$68,4,FALSE) -> 817079635 | H80: =+VLOOKUP(A80,gasto!$A$4:$F$68,5,FALSE) -> 817079635 | I80: =+VLOOKUP(A80,gasto!$A$4:$F$68,6,FALSE) -> 817079635 | J80: =+G80+D80 -> 817079635 | K80: =+H80+E80 -> 817079635 | L80: =+I80+F80 -> 817079635 | M80: =+IFERROR(K80*100/C80,0) -> 10.729756 | N80: =+IFERROR(L80*100/C80,0) -> 10.729756
A81: A-3-9-14-0 | B81: Apoyo Financiero y Fortalecimiento Patrimonial a las Entidades del Sector Salud | C81: =+SUM(C82:C84) -> 100000000000 | D81: =+SUM(D82:D84) -> 0 | E81: =+SUM(E82:E84) -> 0 | F81: =+SUM(F82:F84) -> 0 | G81: =+SUM(G82:G84) -> 0 | H81: =+SUM(H82:H84) -> 0 | I81: =+SUM(I82:I84) -> 0 | J81: =+SUM(J82:J84) -> 0 | ... L81: =+SUM(L82:L84) -> 0 | M81: =+IFERROR(K81*100/C81,0) -> 0 | N81: =+IFERROR(L81*100/C81,0) -> 0
A82: A-3-9-14-0-01 | B82: Operaciones de Compra de Cartera | C82: =+VLOOKUP(A82,gasto!$A$4:$F$100,3,FALSE) -> 60000000000 | D82: 0 | E82: 0 | F82: 0 | G82: =+VLOOKUP(A82,gasto!$A$4:$F$100,4,FALSE) -> 0 | H82: =+VLOOKUP(A82,gasto!$A$4:$F$100,5,FALSE) -> 0 | I82: =+VLOOKUP(A82,gasto!$A$4:$F$100,6,FALSE) -> 0 | J82: =+G82+D82 -> 0 | K82: =+H82+E82 -> 0 | L82: =+I82+F82 -> 0 | M82: =+IFERROR(K82*100/C82,0) -> 0 | N82: =+IFERROR(L82*100/C82,0) -> 0
A83: A-3-9-14-0-02 | B83: Operaciones de Fortalecimiento Patrimonial Tasa Compensada | C83: =+VLOOKUP(A83,gasto!$A$4:$F$100,3,FALSE) -> 40000000000 | D83: 0 | E83: 0 | F83: 0 | G83: =+VLOOKUP(A83,gasto!$A$4:$F$100,4,FALSE) -> 0 | H83: =+VLOOKUP(A83,gasto!$A$4:$F$100,5,FALSE) -> 0 | I83: =+VLOOKUP(A83,gasto!$A$4:$F$100,6,FALSE) -> 0 | J83: =+G83+D83 -> 0 | K83: =+H83+E83 -> 0 | L83: =+I83+F83 -> 0 | M83: =+IFERROR(K83*100/C83,0) -> 0 | N83: =+IFERROR(L83*100/C83,0) -> 0
A84: A-3-9-14-0-03 | B84: Operaciones de Fortalecimiento Patrimonial - Bocas | C84: =+VLOOKUP(A84,gasto!$A$4:$F$100,3,FALSE) -> 0 | D84: 0 | E84: 0 | F84: 0 | G84: =+VLOOKUP(A84,gasto!$A$4:$F$100,4,FALSE) -> 0 | H84: =+VLOOKUP(A84,gasto!$A$4:$F$100,5,FALSE) -> 0 | I84: =+VLOOKUP(A84,gasto!$A$4:$F$100,6,FALSE) -> 0 | J84: =+G84+D84 -> 0 | K84: =+H84+E84 -> 0 | L84: =+I84+F84 -> 0 | M84: =+IFERROR(K84*100/C84,0) -> 0 | N84: =+IFERROR(L84*100/C84,0) -> 0
A85: A-9-9-9-9 | B85: Disponibilidad Final | C85: =+VLOOKUP(A85,gasto!$A$4:$F$100,3,FALSE) -> 254007875000 | D85: 0 | E85: 0 | F85: 0 | G85: =+VLOOKUP(A85,gasto!$A:$K,4,FALSE) -> 0 | H85: =+VLOOKUP(A85,gasto!$A:$K,4,FALSE) -> 0 | I85: =+VLOOKUP(A85,gasto!$A:$K,4,FALSE) -> 0 | J85: =+G85+D85 -> 0 | K85: =+H85+E85 -> 0 | L85: =+I85+F85 -> 0 | M85: =+IFERROR(K85*100/C85,0) -> 0 | N85: =+IFERROR(L85*100/C85,0) -> 0
A87: TOTAL | B87: TOTAL | C87: =+C85+C12 -> 52636824590223 | D87: =+D85+D12 -> 0 | E87: =+E85+E12 -> 0 | F87: =+F85+F12 -> 0 | G87: =+G85+G12 -> 4.1486636e+12 | H87: =+H85+H12 -> 3.9911398e+12 | I87: =+I85+I12 -> 3.9911398e+12 | J87: =+J85+J12 -> 4.1486636e+12 | ... L87: =+L85+L12 -> 3.9911398e+12 | M87: =+IFERROR(K87*100/C87,0) -> 7.5824099 | N87: =+IFERROR(L87*100/C87,0) -> 7.5824099
C88: 52636824590223 | G88: 4.1486636e+12 | H88: 3.9911398e+12 | I88: 3.9911398e+12 | J88: 4.1486636e+12 | K88: 3.9911398e+12 | L88: 3.9911398e+12 | M88: 7.58 | N88: 7.58
C89: =+C88-C87 -> 0 | D89: =+D88-D87 -> 0 | E89: =+E88-E87 -> 0 | F89: =+F88-F87 -> 0 | G89: =+G88-G87 -> 0 | H89: =+H88-H87 -> 0 | I89: =+I88-I87 -> 0 | J89: =+J88-J87 -> 0 | ... N89: =+N88-N87 -> -0.0024099386
C90: =+C88/1000000 -> 52636825 | D90: =+D88/1000000 -> 0 | E90: =+E88/1000000 -> 0 | F90: =+F88/1000000 -> 0 | G90: =+G88/1000000 -> 4148663.6 | H90: =+H88/1000000 -> 3991139.8 | I90: =+I88/1000000 -> 3991139.8 | J90: =+J88/1000000 -> 4148663.6 | ... L90: =+L88/1000000 -> 3991139.8
C91: dif. Por excel | D91: dif. Por excel
B93: =+C80+C26+C31+C34+C39 -> 13575382422734
B94: =+B93/1000000 -> 13575382

Sheet ingresos
A1: RUBRO | B1: inicial | C1: MODIFICACIONES | D1: AFORO DEFINITIVO | E1: INGRESO MES | F1: % | G1: acum
A2: 0-0-0-0 | B2: 422831681000 | C2: 0 | D2: 422831681000 | E2: 422831681000 | F2: 100 | G2: 422831681000 | H2: =+VLOOKUP(A2,'CUADRO 1-EJECUCION DE INGRESOS'!$A$11:$H$97,8,FALSE) -> 422831681000 | I2: =+H2-G2 -> 0
A3: 1-2-1-1 | B3: 17803782346000 | C3: 0 | D3: 17803782346000 | E3: 1241981862167 | F3: 6.98 | G3: 1241981862167 | H3: =+VLOOKUP(A3,'CUADRO 1-EJECUCION DE INGRESOS'!$A$11:$H$97,8,FALSE) -> 1241981862167 | I3: =+H3-G3 -> 0
A4: 1-2-1-1-01 | B4: 13686804885516 | C4: 0 | D4: 13686804885516 | E4: 9.5478383e+11 | F4: 6.98 | G4: 9.5478383e+11 | H4: =+VLOOKUP(A4,'CUADRO 1-EJECUCION DE INGRESOS'!$A$11:$H$97,8,FALSE) -> 9.5478383e+11 | I4: =+H4-G4 -> 0
A5: 1-2-1-1-02 | B5: 4116977460484 | C5: 0 | D5: 4116977460484 | E5: 2.8719804e+11 | F5: 6.98 | G5: 2.8719804e+11 | H5: =+VLOOKUP(A5,'CUADRO 1-EJECUCION DE INGRESOS'!$A$11:$H$97,8,FALSE) -> 2.8719804e+11 | I5: =+H5-G5 -> 0
A6: 1-2-1-2 | B6: 226673765000 | C6: 0 | D6: 226673765000 | E6: 0 | F6: 0 | G6: 0 | H6: =+VLOOKUP(A6,'CUADRO 1-EJECUCION DE INGRESOS'!$A$11:$H$97,8,FALSE) -> 0 | I6: =+H6-G6 -> 0
A7: 1-2-1-3 | B7: 0 | C7: 0 | D7: 0 | E7: 0 | F7: 0 | G7: 0 | H7: =+VLOOKUP(A7,'CUADRO 1-EJECUCION DE INGRESOS'!$A$11:$H$97,8,FALSE) -> 0 | I7: =+H7-G7 -> 0
A8: 1-2-1-4 | B8: 95551523562 | C8: 0 | D8: 95551523562 | E8: 0 | F8: 0 | G8: 0 | H8: =+VLOOKUP(A8,'CUADRO 1-EJECUCION DE INGRESOS'!$A$11:$H$97,8,FALSE) -> 0 | I8: =+H8-G8 -> 0
A9: 1-2-1-5 | B9: 1640527441000 | C9: 0 | D9: 1640527441000 | E9: 2.455599e+11 | F9: 14.97 | G9: 2.455599e+11 | H9: =+VLOOKUP(A9,'CUADRO 1-EJECUCION DE INGRESOS'!$A$11:$H$97,8,FALSE) -> 2.455599e+11 | I9: =+H9-G9 -> 0
A10: 1-2-1-5-01 | B10: 363281118360 | C10: 0 | D10: 363281118360 | E10: 7.770565e+10 | F10: 21.39 | G10: 7.770565e+10 | H10: =+VLOOKUP(A10,'CUADRO 1-EJECUCION DE INGRESOS'!$A$11:$H$97,8,FALSE) -> 7.770565e+10 | I10: =+H10-G10 -> 0
A11: 1-2-1-5-02 | B11: 1277246322640 | C11: 0 | D11: 1277246322640 | E11: 167854247950 | F11: 13.14 | G11: 167854247950 | H11: =+VLOOKUP(A11,'CUADRO 1-EJECUCION DE INGRESOS'!$A$11:$H$97,8,FALSE) -> 167854247950 | I11: =+H11-G11 -> 0
A12: 1-2-1-7 | B12: 6410791000 | C12: 0 | D12: 6410791000 | E12: 15439498040 | F12: 240.84 | G12: 15439498040 | H12: =+VLOOKUP(A12,'CUADRO 1-EJECUCION DE INGRESOS'!$A$11:$H$97,8,FALSE) -> 15439498040 | I12: =+H12-G12 -> 0
A13: 1-2-1-8 | B13: 8851770619 | C13: 0 | D13: 8851770619 | E13: 782571447 | F13: 8.84 | G13: 782571447 | H13: =+VLOOKUP(A13,'CUADRO 1-EJECUCION DE INGRESOS'!$A$11:$H$97,8,FALSE) -> 782571447 | I13: =+H13-G13 -> 0
... A81: 2-9-0-0-02 | B81: 0 | C81: 0 | D81: 0 | E81: 3123909 | F81: 0 | G81: 3123909 | H81: =+VLOOKUP(A81,'CUADRO 1-EJECUCION DE INGRESOS'!$A$11:$H$97,8,FALSE) -> 3123909 | I81: =+H81-G81 -> 0

Sheet gasto
D1: República de Colombia | E1: EJECUCIÓN DE EGRESOS ACUMULADOS | F1: ADRES ADMINISTRADORA DE LOS RECURSOS DEL SGSSS
A2: CÓDIGO RUBRO | B2: CONCEPTO DEL RUBRO | C2: APROPIACIÓN DEFINITIVA | D2: CDP | E2: RP | F2: PAGOS-OGAG | G2: T. CDP | H2: T. RP | I2: T. PAGOS-OGAG | J2: RP | K2: PAGOS
A3: URA
A4: A-3-2-1-0 | B4: Transferencias Entidades de Administración Pública Central | C4: 86345030430 | D4: 0 | E4: 0 | F4: 0 | G4: 0 | H4: 0 | I4: 0 | J4: 0 | K4: 0
A5: A-3-2-1-01 | B5: Contribución IVC Superintendencia Nacional de Salud | C5: 86345030430 | D5: 0 | E5: 0 | F5: 0 | G5: 0 | H5: 0 | I5: 0 | J5: 0 | K5: 0
A6: A-3-2-2-0 | B6: Empresas Públicas Nacionales no financieras -ADRES | C6: 145380000000 | D6: 145380000000 | E6: 4.166544e+09 | F6: 4.166544e+09 | G6: 145380000000 | H6: 4.166544e+09 | I6: 4.166544e+09 | J6: 2.87 | K6: 2.87
A7: A-3-2-2-0-01 | B7: Aportes hasta del 0,5% recursos CSF para el desarrollo objeto ADRES | C7: 145380000000 | D7: 145380000000 | E7: 4.166544e+09 | F7: 4.166544e+09 | G7: 145380000000 | H7: 4.166544e+09 | I7: 4.166544e+09 | J7: 2.87 | K7: 2.87
A8: A-3-6-1-0 | B8: Sentencias y Conciliaciones URA | C8: 20000000000 | D8: 1656232 | E8: 0 | F8: 0 | G8: 1656232 | H8: 0 | I8: 0 | J8: 0 | K8: 0
A9: A-3-6-1-1 | B9: Sentencias URA | C9: 20000000000 | D9: 1656232 | E9: 0 | F9: 0 | G9: 1656232 | H9: 0 | I9: 0 | J9: 0 | K9: 0
A10: A-3-6-1-2 | B10: Conciliaciones URA | C10: 0 | D10: 0 | E10: 0 | F10: 0 | G10: 0 | H10: 0 | I10: 0 | J10: 0 | K10: 0
A11: A-3-6-3-0 | B11: Destinatarios de otras transferencias Corrientes - Compensación Chance | C11: 160000000000 | D11: 0 | E11: 0 | F11: 0 | G11: 0 | H11: 0 | I11: 0 | J11: 0 | K11: 0
A12: A-3-6-3-0-01 | B12: Otras transferencias - Compensación del Chance Decreto 2550/12 | C12: 160000000000 | D12: 0 | E12: 0 | F12: 0 | G12: 0 | H12: 0 | I12: 0 | J12: 0 | K12: 0
A13: A-3-9-1-0 | B13: UPC Régimen Contributivo | C13: 23057892632980 | D13: 1825601270168 | E13: 1825601270168 | F13: 1825601270168 | G13: 1825601270168 | H13: 1825601270168 | I13: 1825601270168 | J13: 7.92 | K13: 7.92
A14: A-3-9-1-0-01 | B14: UPC Régimen Contributivo SSF | C14: 12399109660289 | D14: 910942673794 | E14: 910942673794 | F14: 910942673794 | G14: 910942673794 | H14: 910942673794 | I14: 910942673794 | J14: 7.35 | K14: 7.35
A15: A-3-9-1-0-02 | B15: UPC Régimen Contributivo CSF | C15: 10647939289644 | D15: 914297953268 | E15: 914297953268 | F15: 914297953268 | G15: 914297953268 | H15: 914297953268 | I15: 914297953268 | J15: 8.59 | K15: 8.59
... A73: A-9-9-9-9 | B73: Disponibilidad Final | C73: 254007875000 | D73: 0 | E73: 0 | F73: 0 | G73: 0 | H73: 0 | I73: 0 | J73: 0 | K73: 0

Sheet Hoja1
A3: ADMINISTRADORA DE LOS RECURSOS DEL SISTEMA GENERAL DE SEGURIDAD SOCIAL EN SALUD
A4: PRESUPUESTO DE INGRESOS 2017
A5: UNIDAD DE RECURSOS ADMINISTRADOS - URA
A6: CUADRO No. 1
A8: 1 | B8: 2 | C8: 3 | D8: 4 | E8: 5 | F8: 6 | G8: 7 | H8: 8 | I8: 9 | J8: 10
A9: CÓDIGO RUBRO | B9: CONCEPTO DEL RUBRO | C9: AFORO INICIAL | D9: MODIFICACIÓN PRESUPUESTAL | E9: AFORO DEFINITIVO | F9: Ingresos Acumulados Desde 01/08/2017 hasta 30/11/2017 | G9: Ingresos Desde 01/12/2017 hasta 31/12/2017 | H9: Ingresos Acumulados Desde 01/08/2017 hasta 31/12/2017 | I9: EJECUCIÓN ACUMULADA (%) | J9: PARTICIPACIÓN %
A10: URA
A11: 0-0-0-0 | B11: DISPONIBILIDAD INICIAL | C11: 1049732777065 | D11: 1028793184133 | E11: 2078525961198 | F11: 3.7980893e+11 | G11: 1.698717e+12 | H11: 2.078526e+12 | I11: 100 | J11: 11.173515
A12: 1-2-1-1 | B12: Aportes de la Nación para el Aseguramiento en Salud | C12: 800000000000 | D12: 0 | E12: 800000000000 | F12: 800000000000 | G12: 0 | H12: 800000000000 | I12: 100 | J12: 4.3005534
A13: 1-2-1-1-01 | B13: Aportes de la Nación para el Aseguramiento en Salud Cierre | C13: 800000000000 | D13: 0 | E13: 800000000000 | F13: 800000000000 | G13: 0 | H13: 800000000000 | I13: 100 | J13: 4.3005534
A14: 1-2-1-2 | B14: Compensación Regalías para el Régimen Subsidiado | C14: 0 | D14: 0 | E14: 0 | F14: 0 | G14: 0 | H14: 0 | I14: 0 | J14: 0
A15: 1-2-1-3 | B15: Impuesto sobre la renta para la equidad CREE | C15: 3379423220743 | D15: 0 | E15: 3379423220743 | F15: 2645477901368 | G15: 661369475338 | H15: 3306847376706 | I15: 97.852419 | J15: 17.776592
A16: 1-2-1-4 | B16: SGP FONSAET | C16: 76906712050 | D16: 0 | E16: 76906712050 | F16: 76906712050 | G16: 0 | H16: 76906712050 | I16: 100 | J16: 0.41342677
A17: 1-2-1-5 | B17: PRIMA FONSAT Y CONTRIBUCION SOAT | C17: 630863569234 | D17: 0 | E17: 630863569234 | F17: 4.9668302e+11 | G17: 93551929250 | H17: 5.9023495e+11 | I17: 93.55984 | J17: 3.1729211
A18: 1-2-1-5-01 | B18: % Prima (FONSAT) Decreto Ley 1335 de 2009 | C18: 153176997329 | D18: 0 | E18: 153176997329 | F18: 1.0986192e+11 | G18: 0 | H18: 1.0986192e+11 | I18: 71.722205 | J18: 0.59058382
A19: 1-2-1-5-02 | B19: Contribución Seguro Obligatorio de Accidentes de Tránsito - SOAT- Decreto Ley 1335 de 2009 | C19: 477686571905 | D19: 0 | E19: 477686571905 | F19: 386821096950 | G19: 93551929250 | H19: 480373026200 | I19: 100.56239 | J19: 2.5823373
A20: 1-2-1-7 | B20: Impuesto social a las municiones y explosivos | C20: 31868595127 | D20: 0 | E20: 31868595127 | F20: 31727550335 | G20: 7899641418 | H20: 39627191753 | I20: 124.34559 | J20: 0.21302357
A21: 1-2-1-8 | B21: Impuesto social a las armas | C21: 3612249620 | D21: 0 | E21: 3612249620 | F21: 3452971135 | G21: 969138385 | H21: 4422109520 | I21: 122.41982 | J21: 0.023771897
A22: 1-2-9-0 | B22: Otros aportes e impuestos de la nación | C22: 0 | D22: 0 | E22: 0 | F22: 0 | G22: 0 | H22: 0 | I22: 0 | J22: 0
... A86: 2-9-1-0-06 | B86: Regalías – artículo 5 Ley 1797 de 2016 | C86: 5000000000 | D86: 0 | E86: 5000000000 | F86: 0 | G86: 0 | H86: 0 | I86: 0 | J86: 0
B88: TOTAL | C88: 16692931290975 | D88: 1405041818640 | E88: 18097973109615 | F88: 1.3761589e+13 | G88: 4.8406684e+12 | H88: 1.8602257e+13 | I88: 102.78641 | J88: 100
C90: 16692931290975 | D90: 1405041818640 | E90: 18097973109615 | F90: 1.3761589e+13 | G90: 4.8406684e+12 | H90: 1.8602257e+13 | I90: 102.78641
C91: =+C90-C88 -> 0 | D91: =+D90-D88 -> 0 | E91: =+E90-E88 -> 0 | F91: =+F90-F88 -> 0 | G91: =+G90-G88 -> 0 | H91: =+H90-H88 -> 0 | I91: =+I90-I88 -> 0

Sheet Hoja2
A3: ADMINISTRADORA DE LOS RECURSOS DEL SISTEMA GENERAL DE SEGURIDAD SOCIAL EN SALUD
A4: PRESUPUESTO DE GASTOS 2017
A5: UNIDAD DE RECURSOS ADMINISTRADOS - URA
A6: CUADRO No. 2
A8: 1 | B8: 2 | C8: 3 | D8: 4 | E8: 5 | F8: 6 | G8: 7 | H8: 8 | I8: 9 | J8: 10 | K8: 11 | L8: 12 | M8: 13 | N8: 14
A9: CÓDIGO RUBRO | B9: CONCEPTO DEL RUBRO | C9: APROPIACIÓN DEFINITIVA | D9: EJECUCIÓN PRESUPUESTAL ACUMULADA DESDE 01/08/2017 HASTA 30/11/2017 | G9: EJECUCIÓN PRESUPUESTAL 01/12/2017 HASTA 31/12/2017 | J9: EJECUCIÓN PRESUPUESTAL ACUMULADA DESDE 01/08/2017 HASTA 31/12/2017 | M9: % | O9: SALDO APROPIACIÓN | P9: COMPROMISOS POR PAGAR | Q9: %
D10: T. CDP | E10: T. RP | F10: T. PAGOS-OP | G10: CDP | H10: RP | I10: OP | J10: T. CDP | K10: T. RP | L10: T. PAGOS-OP | M10: RP | N10: OP | Q10: PARTICIPACIÓN
B11: URA
A12: A-9-9-9-9 | B12: Disponibilidad Final | C12: 169607386609 | D12: 0 | E12: 0 | F12: 0 | G12: 0 | H12: 0 | I12: 0 | J12: 0 | K12: 0 | L12: 0 | M12: 0 | N12: 0 | O12: 169607386609 | P12: 0 | Q12: 0
A13: A-3-2-1-0 | B13: Transferencias Entidades de Administración Pública Central | C13: 40479356618 | D13: 22483398888 | E13: 22483398888 | F13: 22483398888 | G13: 5620849724 | H13: 5620849724 | I13: 5620849724 | J13: 28104248612 | K13: 28104248612 | L13: 28104248612 | M13: 69.428595 | N13: 69.428595 | O13: 12375108006 | P13: 0 | Q13: 0.15813624
A14: A-3-2-1-0-01 | B14: Contribución IVC Superintendencia Nacional de Salud | C14: 40479356618 | D14: 22483398888 | E14: 22483398888 | F14: 22483398888 | G14: 5620849724 | H14: 5620849724 | I14: 5620849724 | J14: 28104248612 | K14: 28104248612 | L14: 28104248612 | M14: 69.428595 | N14: 69.428595 | O14: 12375108006 | P14: 0 | Q14: 0.15813624
A15: A-3-2-2-0 | B15: Empresas Públicas Nacionales no financieras | C15: 54432463826 | D15: 54432463826 | E15: 6219861165 | F15: 6219861165 | G15: -1.737463e+10 | H15: 3.0837973e+10 | I15: 9100000000 | J15: 3.7057834e+10 | K15: 3.7057834e+10 | L15: 15319861165 | M15: 68.08039 | N15: 28.144714 | O15: 1.737463e+10 | P15: 2.1737973e+10 | Q15: 0.086201391
A16: A-3-2-2-0-01 | B16: Aportes hasta del 0,5% recursos CSF para el desarrollo objeto ADRES | C16: 54432463826 | D16: 54432463826 | E16: 6219861165 | F16: 6219861165 | G16: -1.737463e+10 | H16: 3.0837973e+10 | I16: 9100000000 | J16: 3.7057834e+10 | K16: 3.7057834e+10 | L16: 15319861165 | M16: 68.08039 | N16: 28.144714 | O16: 1.737463e+10 | P16: 2.1737973e+10 | Q16: 0.086201391
A17: A-3-6-1-0 | B17: Sentencias y Conciliaciones URA | C17: 5059377749 | D17: 1.2391943e+08 | E17: 0 | F17: 0 | G17: 2.2315349e+09 | H17: 2.3554543e+09 | I17: 2.331944e+09 | J17: 2.3554543e+09 | K17: 2.3554543e+09 | L17: 2.331944e+09 | M17: 46.556205 | N17: 46.091518 | O17: 2.7039235e+09 | P17: 23510302 | Q17: 0.013121321
A18: A-3-6-1-1 | B18: Sentencias URA | C18: 5059377749 | D18: 1.2391943e+08 | E18: 0 | F18: 0 | G18: 2.2315349e+09 | H18: 2.3554543e+09 | I18: 2.331944e+09 | J18: 2.3554543e+09 | K18: 2.3554543e+09 | L18: 2.331944e+09 | M18: 46.556205 | N18: 46.091518 | O18: 2.7039235e+09 | P18: 23510302 | Q18: 0.013121321
A19: A-3-6-1-2 | B19: Conciliaciones URA | C19: 0 | D19: 0 | E19: 0 | F19: 0 | G19: 0 | H19: 0 | I19: 0 | J19: 0 | K19: 0 | L19: 0 | M19: 0 | N19: 0 | O19: 0 | P19: 0 | Q19: 0
A20: A-3-6-3-0 | B20: Destinatarios de otras transferencias Corrientes | C20: 30652000000 | D20: 0 | E20: 0 | F20: 0 | G20: 30652000000 | H20: 30652000000 | I20: 30652000000 | J20: 30652000000 | K20: 30652000000 | L20: 30652000000 | M20: 100 | N20: 100 | O20: 0 | P20: 0 | Q20: 0.17247187
A21: A-3-6-3-0-01 | B21: Otras trasnferencias - Compensación del Chance Decreto 2550/12 | C21: 30652000000 | D21: 0 | E21: 0 | F21: 0 | G21: 30652000000 | H21: 30652000000 | I21: 30652000000 | J21: 30652000000 | K21: 30652000000 | L21: 30652000000 | M21: 100 | N21: 100 | O21: 0 | P21: 0 | Q21: 0.17247187
A22: A-3-9-1-0 | B22: UPC Régimen Contributivo | C22: 8076746600070 | D22: 6430211471821 | E22: 6430211471821 | F22: 6424483625438 | G22: 1646200098083 | H22: 1646200098083 | I22: 1651927944466 | J22: 8076411569904 | K22: 8076411569904 | L22: 8076411569904 | M22: 99.995852 | N22: 99.995852 | O22: 335030166 | P22: 0 | Q22: 45.44414
A23: A-3-9-1-0-01 | B23: UPC Régimen Contributivo SSF | C23: 4576838798468 | D23: 3638853998008 | E23: 3638853998008 | F23: 3636391786062 | G23: 937983462711 | H23: 937983462711 | I23: 940445674657 | J23: 4576837460719 | K23: 4576837460719 | L23: 4576837460719 | M23: 99.999971 | N23: 99.999971 | O23: 1337749 | P23: 0 | Q23: 25.752828
... A74: TOTAL | B74: TOTAL | C74: 18097973109615 | D74: 1.3816938e+13 | E74: 1.3767785e+13 | F74: 1.3761589e+13 | G74: 3.9977088e+12 | H74: 4.0468615e+12 | I74: 4.0105851e+12 | J74: 1.7814647e+13 | K74: 1.7814647e+13 | L74: 1.7772174e+13 | M74: 98.434486 | N74: 98.199803 | O74: 2.8332622e+11 | P74: 4.2472859e+10 | Q74: 100
C76: 16692931290975 | D76: 1.3816938e+13 | E76: 1.3816938e+13 | F76: 1.3816938e+13 | G76: 3.9977088e+12 | H76: 4.0468615e+12 | I76: 4.0105851e+12 | J76: 1.3816938e+13 | K76: 1.3816938e+13 | L76: 1.3816938e+13 | M76: 82.771191 | N76: 82.771191
C77: =+C76-C74 -> -1405041818640 | D77: =+D76-D74 -> 0 | E77: =+E76-E74 -> 4.9152731e+10 | F77: =+F76-F74 -> 5.5349216e+10 | G77: =+G76-G74 -> 0 | H77: =+H76-H74 -> 0 | I77: =+I76-I74 -> 0 | J77: =+J76-J74 -> -3.9977088e+12 | ... N77: =+N76-N74 -> -15.428612
