Workbook
Name OLE_LINK1: 'CUADRO 2-EJECUCION DE GASTOS'!#REF!

Sheet CUADRO 1-EJECUCION DE INGRESOS
H1: =+NOW() -> 43818.489 | I1: =+NOW() -> 43818.489
A3: ADMINISTRADORA DE LOS RECURSOS DEL SISTEMA GENERAL DE SEGURIDAD SOCIAL EN SALUD
A4: UNIDAD DE RECURSOS ADMINISTRADOS - URA
A5: CODIGO DE LA EMPRESA 12902 - ADMINISTRACION DE RECURSOS DEL SGSSS
A6: PRESUPUESTO DE INGRESOS DE NOVIEMBRE DE 2019
A7: CUADRO No. 1
A10: CÓDIGO RUBRO | B10: CONCEPTO DEL RUBRO | C10: AFORO INICIAL | D10: MODIFICACIÓN PRESUPUESTAL | E10: AFORO DEFINITIVO | F10: Ingresos Acumulados Desde 01/01/2019 hasta 31/10/2019 | G10: Ingresos Desde 01/11/2019 hasta 30/11/2019 | H10: Ingresos Acumulados Desde 01/01/2019 hasta 30/11/2019 | I10: EJECUCIÓN ACUMULADA (%)
A11: URA
A12: 0-0-0-0 | B12: =+VLOOKUP(A12,Ingresos!$A$2:$B$200,2,FALSE) -> Disponibilidad inicial | C12: 422831681000 | D12: =+VLOOKUP(A12,Ingresos!$A$1:$F$90,3,FALSE) -> 0 | E12: =+VLOOKUP(A12,Ingresos!$A$1:$F$200,4,FALSE) -> 910932869290 | F12: 910932869290 | G12: =+VLOOKUP(A12,Ingresos!$A$1:$E$200,5,FALSE) -> 0 | H12: =+G12+F12 -> 910932869290 | I12: =IFERROR(H12/E12*100,0) -> 100 | J12: =+H12/1000000 -> 910932.87
A13: 1-0-0-0 | B13: INGRESOS CORRIENTES | C13: 52054407755223 | D13: =+D14+D28 -> 0 | E13: =+E14+E28 -> 49290407755223 | F13: 4.2146255e+13 | G13: =+G14+G28 -> 4.7689103e+12 | H13: =+G13+F13 -> 4.6915166e+13 | I13: =IFERROR(H13/E13*100,0) -> 95.181127 | J13: =+H13/1000000 -> 46915166
A14: 1-2-0-0 | B14: Aportes e Impuestos | C14: 19781797637181 | D14: =+D15 -> 0 | E14: =+E15+E27 -> 17017797637181 | F14: 14510629164728 | G14: =+G15+G27 -> 1.3592823e+12 | H14: =+G14+F14 -> 1.5869911e+13 | I14: =IFERROR(H14/E14*100,0) -> 93.25479 | J14: =+H14/1000000 -> 15869911
A15: 1-2-1-0 | B15: Aportes de la Nación | C15: 19781797637181 | D15: =+D16+D19+D20+D21+D22+D25+D26 -> 0 | E15: =+E16+E19+E20+E21+E22+E26+E25+E27 -> 17017797637181 | F15: 14510629164728 | G15: =+G16+G19+G20+G21+G22+G26+G25+G27 -> 1.3592823e+12 | H15: =+G15+F15 -> 1.5869911e+13 | I15: =IFERROR(H15/E15*100,0) -> 93.25479 | J15: =+H15/1000000 -> 15869911
A16: 1-2-1-1 | B16: =+VLOOKUP(A16,Ingresos!$A$2:$B$200,2,FALSE) -> Aportes de la Nación para el Aseguramiento en Salud | C16: 17803782346000 | D16: =+D17+D18 -> 0 | E16: =+E17+E18 -> 15039782346000 | F16: 1.2676174e+13 | G16: =+SUM(G17:G18) -> 1160204084389 | H16: =+G16+F16 -> 1.3836378e+13 | I16: =IFERROR(H16/E16*100,0) -> 91.998527 | J16: =+H16/1000000 -> 13836378
A17: 1-2-1-1-01 | B17: =+VLOOKUP(A17,Ingresos!$A$2:$B$200,2,FALSE) -> Aportes de la Nación para el Aseguramiento en Salud Cierre | C17: 13686804885516 | D17: =+VLOOKUP(A17,Ingresos!$A$1:$F$90,3,FALSE) -> 0 | E17: =+VLOOKUP(A17,Ingresos!$A$1:$F$200,4,FALSE) -> 9743321670830 | F17: 8.456764e+12 | G17: =+VLOOKUP(A17,Ingresos!$A$1:$E$200,5,FALSE) -> 6.2167882e+11 | H17: =+G17+F17 -> 9.0784429e+12 | I17: =IFERROR(H17/E17*100,0) -> 93.176056 | J17: =+H17/1000000 -> 9078442.9
A18: 1-2-1-1-02 | B18: =+VLOOKUP(A18,Ingresos!$A$2:$B$200,2,FALSE) -> Imporenta | C18: 4116977460484 | D18: =+VLOOKUP(A18,Ingresos!$A$1:$F$90,3,FALSE) -> 0 | E18: =+VLOOKUP(A18,Ingresos!$A$1:$F$200,4,FALSE) -> 5296460675170 | F18: 4.2194101e+12 | G18: =+VLOOKUP(A18,Ingresos!$A$1:$E$200,5,FALSE) -> 5.3852527e+11 | H18: =+G18+F18 -> 4.7579354e+12 | I18: =IFERROR(H18/E18*100,0) -> 89.832356 | J18: =+H18/1000000 -> 4757935.4
A19: 1-2-1-2 | B19: =+VLOOKUP(A19,Ingresos!$A$2:$B$200,2,FALSE) -> Compensación Regalías para el Régimen Subsidiado | C19: 226673765000 | D19: =+VLOOKUP(A19,Ingresos!$A$1:$F$90,3,FALSE) -> 0 | E19: =+VLOOKUP(A19,Ingresos!$A$1:$F$200,4,FALSE) -> 226673765000 | F19: 226673765000 | G19: =+VLOOKUP(A19,Ingresos!$A$1:$E$200,5,FALSE) -> 0 | H19: =+G19+F19 -> 226673765000 | I19: =IFERROR(H19/E19*100,0) -> 100 | J19: =+H19/1000000 -> 226673.77
A20: 1-2-1-3 | B20: =+VLOOKUP(A20,Ingresos!$A$2:$B$200,2,FALSE) -> Impuesto sobre la renta para la equidad CREE | C20: 0 | D20: =+VLOOKUP(A20,Ingresos!$A$1:$F$90,3,FALSE) -> 0 | E20: =+VLOOKUP(A20,Ingresos!$A$1:$F$200,4,FALSE) -> 0 | F20: 0 | G20: =+VLOOKUP(A20,Ingresos!$A$1:$E$200,5,FALSE) -> 0 | H20: =+G20+F20 -> 0 | I20: =IFERROR(H20/E20*100,0) -> 0 | J20: =+H20/1000000 -> 0
A21: 1-2-1-4 | B21: =+VLOOKUP(A21,Ingresos!$A$2:$B$200,2,FALSE) -> SGP FONSAET | C21: 95551523562 | D21: =+VLOOKUP(A21,Ingresos!$A$1:$F$90,3,FALSE) -> 0 | E21: =+VLOOKUP(A21,Ingresos!$A$1:$F$200,4,FALSE) -> 95551523562 | F21: 0 | G21: =+VLOOKUP(A21,Ingresos!$A$1:$E$200,5,FALSE) -> 0 | H21: =+G21+F21 -> 0 | I21: =IFERROR(H21/E21*100,0) -> 0 | J21: =+H21/1000000 -> 0
A22: 1-2-1-5 | B22: =+VLOOKUP(A22,Ingresos!$A$2:$B$200,2,FALSE) -> PRIMA FONSAT Y CONTRIBUCION SOAT | C22: 1640527441000 | D22: =+D23+D24 -> 0 | E22: =+E23+E24 -> 1640527441000 | F22: 1.5016448e+12 | G22: =+SUM(G23:G24) -> 1.8790881e+11 | H22: =+G22+F22 -> 1.6895536e+12 | I22: =IFERROR(H22/E22*100,0) -> 102.98844 | J22: =+H22/1000000 -> 1689553.6
A23: 1-2-1-5-01 | B23: =+VLOOKUP(A23,Ingresos!$A$2:$B$200,2,FALSE) -> % Prima (FONSAT) Decreto Ley 1335 de 2009 | C23: 363281118360 | D23: =+VLOOKUP(A23,Ingresos!$A$1:$F$90,3,FALSE) -> 0 | E23: =+VLOOKUP(A23,Ingresos!$A$1:$F$200,4,FALSE) -> 363281118360 | F23: 3.2982961e+11 | G23: =+VLOOKUP(A23,Ingresos!$A$1:$E$200,5,FALSE) -> 6.7235893e+10 | H23: =+G23+F23 -> 3.9706551e+11 | I23: =IFERROR(H23/E23*100,0) -> 109.29979 | J23: =+H23/1000000 -> 397065.51
A24: 1-2-1-5-02 | B24: =+VLOOKUP(A24,Ingresos!$A$2:$B$200,2,FALSE) -> Contribución Seguro Obligatorio de Accidentes de Tránsito - SOAT- Decreto Ley 1335 de 2009 | C24: 1277246322640 | D24: =+VLOOKUP(A24,Ingresos!$A$1:$F$90,3,FALSE) -> 0 | E24: =+VLOOKUP(A24,Ingresos!$A$1:$F$200,4,FALSE) -> 1277246322640 | F24: 1.1718152e+12 | G24: =+VLOOKUP(A24,Ingresos!$A$1:$E$200,5,FALSE) -> 120672915300 | H24: =+G24+F24 -> 1.2924881e+12 | I24: =IFERROR(H24/E24*100,0) -> 101.19333 | J24: =+H24/1000000 -> 1292488.1
A25: 1-2-1-7 | B25: =+VLOOKUP(A25,Ingresos!$A$2:$B$200,2,FALSE) -> Impuesto social a las municiones y explosivos | C25: 6410791000 | D25: =+VLOOKUP(A25,Ingresos!$A$1:$F$90,3,FALSE) -> 0 | E25: =+VLOOKUP(A25,Ingresos!$A$1:$F$200,4,FALSE) -> 6410791000 | F25: 98318924241 | G25: =+VLOOKUP(A25,Ingresos!$A$1:$E$200,5,FALSE) -> 9997809749 | H25: =+G25+F25 -> 108316733990 | I25: =IFERROR(H25/E25*100,0) -> 1689.6001 | J25: =+H25/1000000 -> 108316.73
A26: 1-2-1-8 | B26: =+VLOOKUP(A26,Ingresos!$A$2:$B$200,2,FALSE) -> Impuesto social a las armas | C26: 8851770619 | D26: =+VLOOKUP(A26,Ingresos!$A$1:$F$90,3,FALSE) -> 0 | E26: =+VLOOKUP(A26,Ingresos!$A$1:$F$200,4,FALSE) -> 8851770619 | F26: 7817505342 | G26: =+VLOOKUP(A26,Ingresos!$A$1:$E$200,5,FALSE) -> 1171605398 | H26: =+G26+F26 -> 8989110740 | I26: =IFERROR(H26/E26*100,0) -> 101.55156 | J26: =+H26/1000000 -> 8989.1107
A27: 1-2-9-0 | B27: =+VLOOKUP(A27,Ingresos!$A$2:$B$200,2,FALSE) -> Otros aportes e impuestos de la nación | C27: 0 | D27: =+VLOOKUP(A27,Ingresos!$A$1:$F$90,3,FALSE) -> 0 | E27: =+VLOOKUP(A27,Ingresos!$A$1:$F$200,4,FALSE) -> 0 | F27: 0 | G27: =+VLOOKUP(A27,Ingresos!$A$1:$E$200,5,FALSE) -> 0 | H27: =+G27+F27 -> 0 | I27: =IFERROR(H27/E27*100,0) -> 0 | J27: =+H27/1000000 -> 0
A28: 1-3-0-0 | B28: Otros Ingresos Corrientes | C28: 32272610118042 | D28: =+D29 -> 0 | E28: =+E29+E58 -> 32272610118042 | F28: 2.7635626e+13 | G28: =+G29+G58 -> 3.409628e+12 | H28: =+G28+F28 -> 3.1045254e+13 | I28: =IFERROR(H28/E28*100,0) -> 96.196912 | J28: =+H28/1000000 -> 31045254
A29: 1-3-5-0 | B29: Ingresos Sistema General de Seguridad Social en Salud | C29: 22105255788877 | D29: =+D30+D33+D36+D41+D51+D54+D57 -> 0 | E29: =+E30+E33+E36+E41+E51+E54+E57 -> 22105255788877 | F29: 1.9267898e+13 | G29: =+G30+G33+G36+G41+G51+G54+G57 -> 1.886461e+12 | H29: =+G29+F29 -> 2.1154359e+13 | I29: =IFERROR(H29/E29*100,0) -> 95.698324 | J29: =+H29/1000000 -> 21154359
A30: 1-3-5-1 | B30: =+VLOOKUP(A30,Ingresos!$A$2:$B$200,2,FALSE) -> Cotizaciones al SGSSS | C30: 20346328129563 | D30: =+SUM(D31:D32) -> 0 | E30: =+SUM(E31:E32) -> 20346328129563 | F30: 16888413748856 | G30: =+SUM(G31:G32) -> 1670768305965 | H30: =+G30+F30 -> 18559182054821 | I30: =IFERROR(H30/E30*100,0) -> 91.216371 | J30: =+H30/1000000 -> 18559182
A31: 1-3-5-1-01 | B31: =+VLOOKUP(A31,Ingresos!$A$2:$B$200,2,FALSE) -> Régimen Contributivo CSF | C31: 6807438619821 | D31: =+VLOOKUP(A31,Ingresos!$A$1:$F$90,3,FALSE) -> -107990000000 | E31: =+VLOOKUP(A31,Ingresos!$A$1:$F$200,4,FALSE) -> 6699448619821 | F31: 5700380701536 | G31: =+VLOOKUP(A31,Ingresos!$A$1:$E$200,5,FALSE) -> 527551267486 | H31: =+G31+F31 -> 6227931969022 | I31: =IFERROR(H31/E31*100,0) -> 92.961859 | J31: =+H31/1000000 -> 6227932
A32: 1-3-5-1-02 | B32: =+VLOOKUP(A32,Ingresos!$A$2:$B$200,2,FALSE) -> Régimen Contributivo SSF | C32: 13538889509742 | D32: =+VLOOKUP(A32,Ingresos!$A$1:$F$90,3,FALSE) -> 107990000000 | E32: =+VLOOKUP(A32,Ingresos!$A$1:$F$200,4,FALSE) -> 13646879509742 | F32: 11188033047320 | G32: =+VLOOKUP(A32,Ingresos!$A$1:$E$200,5,FALSE) -> 1143217038479 | H32: =+G32+F32 -> 12331250085799 | I32: =IFERROR(H32/E32*100,0) -> 90.359485 | J32: =+H32/1000000 -> 12331250
A33: 1-3-5-2 | B33: =+VLOOKUP(A33,Ingresos!$A$2:$B$200,2,FALSE) -> Aporte Solidaridad de Regímenes de Excepcion y Especiales | C33: 1000356775894 | D33: =+SUM(D34:D35) -> 0 | E33: =+SUM(E34:E35) -> 1000356775894 | F33: 7.4229323e+11 | G33: =+SUM(G34:G35) -> 7.7705941e+10 | H33: =+G33+F33 -> 8.1999917e+11 | I33: =IFERROR(H33/E33*100,0) -> 81.970672 | J33: =+H33/1000000 -> 819999.17
A34: 1-3-5-2-01 | B34: =+VLOOKUP(A34,Ingresos!$A$2:$B$200,2,FALSE) -> Cotizaciones afiliados REX con ingresos adicionales | C34: 594961177882 | D34: =+VLOOKUP(A34,Ingresos!$A$1:$F$90,3,FALSE) -> 0 | E34: =+VLOOKUP(A34,Ingresos!$A$1:$F$200,4,FALSE) -> 594961177882 | F34: 434906212652 | G34: =+VLOOKUP(A34,Ingresos!$A$1:$E$200,5,FALSE) -> 44120317048 | H34: =+G34+F34 -> 479026529700 | I34: =IFERROR(H34/E34*100,0) -> 80.513914 | J34: =+H34/1000000 -> 479026.53
A35: 1-3-5-2-02 | B35: =+VLOOKUP(A35,Ingresos!$A$2:$B$200,2,FALSE) -> Aporte Solidario entidades REX | C35: 405395598012 | D35: =+VLOOKUP(A35,Ingresos!$A$1:$F$90,3,FALSE) -> 0 | E35: =+VLOOKUP(A35,Ingresos!$A$1:$F$200,4,FALSE) -> 405395598012 | F35: 3.0738702e+11 | G35: =+VLOOKUP(A35,Ingresos!$A$1:$E$200,5,FALSE) -> 3.3585624e+10 | H35: =+G35+F35 -> 3.4097264e+11 | I35: =IFERROR(H35/E35*100,0) -> 84.10862 | J35: =+H35/1000000 -> 340972.64
A36: 1-3-5-3 | B36: =+VLOOKUP(A36,Ingresos!$A$2:$B$200,2,FALSE) -> Aportes Cajas de Compensación Familiar | C36: 499207099674 | D36: =+SUM(D37:D40) -> 0 | E36: =+SUM(E37:E40) -> 499207099674 | F36: 4.469249e+11 | G36: =+SUM(G37:G40) -> 4.1428447e+10 | H36: =+G36+F36 -> 4.8835335e+11 | I36: =IFERROR(H36/E36*100,0) -> 97.825802 | J36: =+H36/1000000 -> 488353.35
A37: 1-3-5-3-01 | B37: =+VLOOKUP(A37,Ingresos!$A$2:$B$200,2,FALSE) -> Aportes CCF Artículo 217 Ley 100 de 1993 CSF | C37: 466578060617 | D37: =+VLOOKUP(A37,Ingresos!$A$1:$F$90,3,FALSE) -> 0 | E37: =+VLOOKUP(A37,Ingresos!$A$1:$F$200,4,FALSE) -> 466578060617 | F37: 4.2049742e+11 | G37: =+VLOOKUP(A37,Ingresos!$A$1:$E$200,5,FALSE) -> 4.0404763e+10 | H37: =+G37+F37 -> 4.6090218e+11 | I37: =IFERROR(H37/E37*100,0) -> 98.783509 | J37: =+H37/1000000 -> 460902.18
A38: 1-3-5-3-02 | B38: =+VLOOKUP(A38,Ingresos!$A$2:$B$200,2,FALSE) -> Aportes CCF Artículo 217 Ley 100 de 1993 SSF | C38: 28877831435 | D38: =+VLOOKUP(A38,Ingresos!$A$1:$F$90,3,FALSE) -> 0 | E38: =+VLOOKUP(A38,Ingresos!$A$1:$F$200,4,FALSE) -> 28877831435 | F38: 2.3598027e+10 | G38: =+VLOOKUP(A38,Ingresos!$A$1:$E$200,5,FALSE) -> 1.0236848e+09 | H38: =+G38+F38 -> 2.4621711e+10 | I38: =IFERROR(H38/E38*100,0) -> 85.261636 | J38: =+H38/1000000 -> 24621.711
A39: 1-3-5-3-03 | B39: =+VLOOKUP(A39,Ingresos!$A$2:$B$200,2,FALSE) -> Aportes CCF Balance | C39: 3751207622 | D39: =+VLOOKUP(A39,Ingresos!$A$1:$F$90,3,FALSE) -> 0 | E39: =+VLOOKUP(A39,Ingresos!$A$1:$F$200,4,FALSE) -> 3751207622 | F39: 2000102769 | G39: =+VLOOKUP(A39,Ingresos!$A$1:$E$200,5,FALSE) -> 0 | H39: =+G39+F39 -> 2000102769 | I39: =IFERROR(H39/E39*100,0) -> 53.318903 | J39: =+H39/1000000 -> 2000.1028
A40: 1-3-5-3-04 | B40: =+VLOOKUP(A40,Ingresos!$A$2:$B$200,2,FALSE) -> Otros Aportes CCF | C40: 0 | D40: =+VLOOKUP(A40,Ingresos!$A$1:$F$90,3,FALSE) -> 0 | E40: =+VLOOKUP(A40,Ingresos!$A$1:$F$200,4,FALSE) -> 0 | F40: 8.2935047e+08 | G40: =+VLOOKUP(A40,Ingresos!$A$1:$E$200,5,FALSE) -> 0 | H40: =+G40+F40 -> 8.2935047e+08 | I40: =IFERROR(H40/E40*100,0) -> 0 | J40: =+H40/1000000 -> 829.35047
A41: 1-3-5-5 | B41: =+VLOOKUP(A41,Ingresos!$A$2:$B$200,2,FALSE) -> Reintegros / Recuperaciones | C41: 0 | D41: =+SUM(D42:D50) -> 0 | E41: =+SUM(E42:E50) -> 0 | F41: 9.9901217e+11 | G41: =+SUM(G42:G50) -> 7.6217125e+10 | H41: =+G41+F41 -> 1.0752293e+12 | I41: =IFERROR(H41/E41*100,0) -> 0 | J41: =+H41/1000000 -> 1075229.3
A42: 1-3-5-5-01 | B42: =+VLOOKUP(A42,Ingresos!$A$2:$B$200,2,FALSE) -> UPC Régimen Contributivo Vigencias anteriores | C42: 0 | D42: =+VLOOKUP(A42,Ingresos!$A$1:$F$90,3,FALSE) -> 0 | E42: =+VLOOKUP(A42,Ingresos!$A$1:$F$200,4,FALSE) -> 0 | F42: 5.470649e+10 | G42: =+VLOOKUP(A42,Ingresos!$A$1:$E$200,5,FALSE) -> 1.4231722e+09 | H42: =+G42+F42 -> 5.6129663e+10 | I42: =IFERROR(H42/E42*100,0) -> 0 | J42: =+H42/1000000 -> 56129.663
A43: 1-3-5-5-02 | B43: =+VLOOKUP(A43,Ingresos!$A$2:$B$200,2,FALSE) -> P&P Vigencias anteriores | C43: 0 | D43: =+VLOOKUP(A43,Ingresos!$A$1:$F$90,3,FALSE) -> 0 | E43: =+VLOOKUP(A43,Ingresos!$A$1:$F$200,4,FALSE) -> 0 | F43: 0 | G43: =+VLOOKUP(A43,Ingresos!$A$1:$E$200,5,FALSE) -> 0 | H43: =+G43+F43 -> 0 | I43: =IFERROR(H43/E43*100,0) -> 0 | J43: =+H43/1000000 -> 0
A44: 1-3-5-5-03 | B44: =+VLOOKUP(A44,Ingresos!$A$2:$B$200,2,FALSE) -> Licencias de Maternidad y Paternidad Vigencias anteriores | C44: 0 | D44: =+VLOOKUP(A44,Ingresos!$A$1:$F$90,3,FALSE) -> 0 | E44: =+VLOOKUP(A44,Ingresos!$A$1:$F$200,4,FALSE) -> 0 | F44: 0 | G44: =+VLOOKUP(A44,Ingresos!$A$1:$E$200,5,FALSE) -> 0 | H44: =+G44+F44 -> 0 | I44: =IFERROR(H44/E44*100,0) -> 0 | J44: =+H44/1000000 -> 0
A45: 1-3-5-5-04 | B45: =+VLOOKUP(A45,Ingresos!$A$2:$B$200,2,FALSE) -> UPC Régimen Subsidiado Vigencias anteriores | C45: 0 | D45: =+VLOOKUP(A45,Ingresos!$A$1:$F$90,3,FALSE) -> 0 | E45: =+VLOOKUP(A45,Ingresos!$A$1:$F$200,4,FALSE) -> 0 | F45: 9.1459026e+11 | G45: =+VLOOKUP(A45,Ingresos!$A$1:$E$200,5,FALSE) -> 7.294082e+10 | H45: =+G45+F45 -> 9.8753107e+11 | I45: =IFERROR(H45/E45*100,0) -> 0 | J45: =+H45/1000000 -> 987531.07
A46: 1-3-5-5-05 | B46: =+VLOOKUP(A46,Ingresos!$A$2:$B$200,2,FALSE) -> Recobros Vigencias anteriores | C46: 0 | D46: =+VLOOKUP(A46,Ingresos!$A$1:$F$90,3,FALSE) -> 0 | E46: =+VLOOKUP(A46,Ingresos!$A$1:$F$200,4,FALSE) -> 0 | F46: 1.1027136e+10 | G46: =+VLOOKUP(A46,Ingresos!$A$1:$E$200,5,FALSE) -> 1.3371801e+09 | H46: =+G46+F46 -> 1.2364316e+10 | I46: =IFERROR(H46/E46*100,0) -> 0 | J46: =+H46/1000000 -> 12364.316
A47: 1-3-5-5-06 | B47: =+VLOOKUP(A47,Ingresos!$A$2:$B$200,2,FALSE) -> Reclamaciones Vigencias anteriores | C47: 0 | D47: =+VLOOKUP(A47,Ingresos!$A$1:$F$90,3,FALSE) -> 0 | E47: =+VLOOKUP(A47,Ingresos!$A$1:$F$200,4,FALSE) -> 0 | F47: 7.194089e+08 | G47: =+VLOOKUP(A47,Ingresos!$A$1:$E$200,5,FALSE) -> 1349081.5 | H47: =+G47+F47 -> 7.2075798e+08 | I47: =IFERROR(H47/E47*100,0) -> 0 | J47: =+H47/1000000 -> 720.75798
A48: 1-3-5-5-07 | B48: =+VLOOKUP(A48,Ingresos!$A$2:$B$200,2,FALSE) -> Procesos de Repetición | C48: 0 | D48: =+VLOOKUP(A48,Ingresos!$A$1:$F$90,3,FALSE) -> 0 | E48: =+VLOOKUP(A48,Ingresos!$A$1:$F$200,4,FALSE) -> 0 | F48: 4.5535463e+08 | G48: =+VLOOKUP(A48,Ingresos!$A$1:$E$200,5,FALSE) -> 74778573 | H48: =+G48+F48 -> 5.301332e+08 | I48: =IFERROR(H48/E48*100,0) -> 0 | J48: =+H48/1000000 -> 530.1332
A49: 1-3-5-5-08 | B49: =+VLOOKUP(A49,Ingresos!$A$2:$B$200,2,FALSE) -> Reintegro por contratos vigencias anteriores | C49: 0 | D49: =+VLOOKUP(A49,Ingresos!$A$1:$F$90,3,FALSE) -> 0 | E49: =+VLOOKUP(A49,Ingresos!$A$1:$F$200,4,FALSE) -> 0 | F49: 1.4462822e+09 | G49: =+VLOOKUP(A49,Ingresos!$A$1:$E$200,5,FALSE) -> 301349444 | H49: =+G49+F49 -> 1.7476316e+09 | I49: =IFERROR(H49/E49*100,0) -> 0 | J49: =+H49/1000000 -> 1747.6316
A50: 1-3-5-5-09 | B50: =+VLOOKUP(A50,Ingresos!$A$2:$B$200,2,FALSE) -> Otros reintegros / recuperaciones | C50: 0 | D50: =+VLOOKUP(A50,Ingresos!$A$1:$F$90,3,FALSE) -> 0 | E50: =+VLOOKUP(A50,Ingresos!$A$1:$F$200,4,FALSE) -> 0 | F50: 1.6067241e+10 | G50: =+VLOOKUP(A50,Ingresos!$A$1:$E$200,5,FALSE) -> 1.3847587e+08 | H50: =+G50+F50 -> 1.6205716e+10 | I50: =IFERROR(H50/E50*100,0) -> 0 | J50: =+H50/1000000 -> 16205.716
A51: 1-3-5-6 | B51: =+VLOOKUP(A51,Ingresos!$A$2:$B$200,2,FALSE) -> Multas | C51: 0 | D51: =+SUM(D52:D53) -> 0 | E51: =+SUM(E52:E53) -> 0 | F51: 70938 | G51: =+SUM(G52:G53) -> 0 | H51: =+G51+F51 -> 70938 | I51: =IFERROR(H51/E51*100,0) -> 0 | J51: =+H51/1000000 -> 0.070938
A52: 1-3-5-6-01 | B52: =+VLOOKUP(A52,Ingresos!$A$2:$B$200,2,FALSE) -> Multas Antitabaco | C52: 0 | D52: =+VLOOKUP(A52,Ingresos!$A$1:$F$90,3,FALSE) -> 0 | E52: =+VLOOKUP(A52,Ingresos!$A$1:$F$200,4,FALSE) -> 0 | F52: 70938 | G52: =+VLOOKUP(A52,Ingresos!$A$1:$E$200,5,FALSE) -> 0 | H52: =+G52+F52 -> 70938 | I52: =IFERROR(H52/E52*100,0) -> 0 | J52: =+H52/1000000 -> 0.070938
A53: 1-3-5-6-02 | B53: =+VLOOKUP(A53,Ingresos!$A$2:$B$200,2,FALSE) -> Otras Multas | C53: 0 | D53: =+VLOOKUP(A53,Ingresos!$A$1:$F$90,3,FALSE) -> 0 | E53: =+VLOOKUP(A53,Ingresos!$A$1:$F$200,4,FALSE) -> 0 | F53: 0 | G53: =+VLOOKUP(A53,Ingresos!$A$1:$E$200,5,FALSE) -> 0 | H53: =+G53+F53 -> 0 | I53: =IFERROR(H53/E53*100,0) -> 0 | J53: =+H53/1000000 -> 0
A54: 1-3-5-7 | B54: =+VLOOKUP(A54,Ingresos!$A$2:$B$200,2,FALSE) -> Otros ingresos Diversos | C54: 259363783746 | D54: =+SUM(D55:D56) -> 0 | E54: =+SUM(E55:E56) -> 0 | F54: 6.5287345e+09 | G54: =+SUM(G55:G56) -> -2734263.6 | H54: =+G54+F54 -> 6.5260002e+09 | I54: =IFERROR(H54/E54*100,0) -> 0 | J54: =+H54/1000000 -> 6526.0002
A55: 1-3-5-7-01 | B55: =+VLOOKUP(A55,Ingresos!$A$2:$B$200,2,FALSE) -> Aportes adicionales en Salud | C55: 259363783746 | D55: =+VLOOKUP(A55,Ingresos!$A$1:$F$90,3,FALSE) -> 0 | E55: =+VLOOKUP(A55,Ingresos!$A$1:$F$200,4,FALSE) -> 0 | F55: 0 | G55: =+VLOOKUP(A55,Ingresos!$A$1:$E$200,5,FALSE) -> 0 | H55: =+G55+F55 -> 0 | I55: =IFERROR(H55/E55*100,0) -> 0 | J55: =+H55/1000000 -> 0
A56: 1-3-5-7-02 | B56: =+VLOOKUP(A56,Ingresos!$A$2:$B$200,2,FALSE) -> Otros ingresos Diversos | C56: 0 | D56: =+VLOOKUP(A56,Ingresos!$A$1:$F$90,3,FALSE) -> 0 | E56: =+VLOOKUP(A56,Ingresos!$A$1:$F$200,4,FALSE) -> 0 | F56: 6.5287345e+09 | G56: =+VLOOKUP(A56,Ingresos!$A$1:$E$200,5,FALSE) -> -2734263.6 | H56: =+G56+F56 -> 6.5260002e+09 | I56: =IFERROR(H56/E56*100,0) -> 0 | J56: =+H56/1000000 -> 6526.0002
A57: 1-3-5-8 | B57: =+VLOOKUP(A57,Ingresos!$A$2:$B$200,2,FALSE) -> Cotizaciones y/o aportes adicionales en salud | C57: 0 | D57: =+VLOOKUP(A57,Ingresos!$A$1:$F$90,3,FALSE) -> 0 | E57: =+VLOOKUP(A57,Ingresos!$A$1:$F$200,4,FALSE) -> 259363783746 | F57: 184725399909 | G57: =+VLOOKUP(A57,Ingresos!$A$1:$E$200,5,FALSE) -> 20343930712 | H57: =+G57+F57 -> 205069330621 | I57: =IFERROR(H57/E57*100,0) -> 79.066294 | J57: =+H57/1000000 -> 205069.33
A58: 1-3-6-0 | B58: Recursos ET Aseguramiento en Salud | C58: 10167354329165 | D58: =+D59+D60+D61+D64+D67 -> 0 | E58: =+E59+E60+E61+E64+E67 -> 10167354329165 | F58: 8.367728e+12 | G58: =+G59+G60+G61+G64+G67 -> 1.523167e+12 | H58: =+G58+F58 -> 9.890895e+12 | I58: =IFERROR(H58/E58*100,0) -> 97.280912 | J58: =+H58/1000000 -> 9890895
A59: 1-3-6-1 | B59: =+VLOOKUP(A59,Ingresos!$A$2:$B$200,2,FALSE) -> Sistema General de Participaciones Régimen Subsidiado | C59: 8428995552661 | D59: =+VLOOKUP(A59,Ingresos!$A$1:$F$90,3,FALSE) -> 0 | E59: =+VLOOKUP(A59,Ingresos!$A$1:$F$200,4,FALSE) -> 8428995552661 | F59: 6431615362055 | G59: =+VLOOKUP(A59,Ingresos!$A$1:$E$200,5,FALSE) -> 1293368092129 | H59: =+G59+F59 -> 7724983454184 | I59: =IFERROR(H59/E59*100,0) -> 91.647734 | J59: =+H59/1000000 -> 7724983.5
A60: 1-3-6-2 | B60: =+VLOOKUP(A60,Ingresos!$A$2:$B$200,2,FALSE) -> Recursos Provenientes de COLJUEGOS para R.S. | C60: 376773007880 | D60: =+VLOOKUP(A60,Ingresos!$A$1:$F$90,3,FALSE) -> 0 | E60: =+VLOOKUP(A60,Ingresos!$A$1:$F$200,4,FALSE) -> 376773007880 | F60: 352418451971 | G60: =+VLOOKUP(A60,Ingresos!$A$1:$E$200,5,FALSE) -> 24053838258 | H60: =+G60+F60 -> 376472290229 | I60: =IFERROR(H60/E60*100,0) -> 99.920186 | J60: =+H60/1000000 -> 376472.29
A61: 1-3-6-7 | B61: =+VLOOKUP(A61,Ingresos!$A$2:$B$200,2,FALSE) -> Recursos Fonpet | C61: 200000000000 | D61: =+SUM(D62:D63) -> 0 | E61: =+SUM(E62:E63) -> 200000000000 | F61: 200000000000 | G61: =+SUM(G62:G63) -> 0 | H61: =+G61+F61 -> 200000000000 | I61: =IFERROR(H61/E61*100,0) -> 100 | J61: =+H61/1000000 -> 200000
A62: 1-3-6-7-01 | B62: =+VLOOKUP(A62,Ingresos!$A$2:$B$200,2,FALSE) -> Recursos LOTTO en Línea-FONPET | C62: 0 | D62: =+VLOOKUP(A62,Ingresos!$A$1:$F$90,3,FALSE) -> 0 | E62: =+VLOOKUP(A62,Ingresos!$A$1:$F$200,4,FALSE) -> 0 | F62: 0 | G62: =+VLOOKUP(A62,Ingresos!$A$1:$E$200,5,FALSE) -> 0 | H62: =+G62+F62 -> 0 | I62: =IFERROR(H62/E62*100,0) -> 0 | J62: =+H62/1000000 -> 0
A63: 1-3-6-7-02 | B63: =+VLOOKUP(A63,Ingresos!$A$2:$B$200,2,FALSE) -> Otros recursos FONPET diferentes a LOTTO en Línea | C63: 200000000000 | D63: =+VLOOKUP(A63,Ingresos!$A$1:$F$90,3,FALSE) -> 0 | E63: =+VLOOKUP(A63,Ingresos!$A$1:$F$200,4,FALSE) -> 200000000000 | F63: 200000000000 | G63: =+VLOOKUP(A63,Ingresos!$A$1:$E$200,5,FALSE) -> 0 | H63: =+G63+F63 -> 200000000000 | I63: =IFERROR(H63/E63*100,0) -> 100 | J63: =+H63/1000000 -> 200000
A64: 1-3-6-8 | B64: =+VLOOKUP(A64,Ingresos!$A$2:$B$200,2,FALSE) -> Otros Recursos de las Entidades Territoriales para Aseguramiento | C64: 1124585768624 | D64: =+SUM(D65:D66) -> 0 | E64: =+SUM(E65:E66) -> 1124585768624 | F64: 1.3488762e+12 | G64: =+SUM(G65:G66) -> 2.0574509e+11 | H64: =+G64+F64 -> 1.5546213e+12 | I64: =IFERROR(H64/E64*100,0) -> 138.23946 | J64: =+H64/1000000 -> 1554621.3
A65: 1-3-6-8-01 | B65: =+VLOOKUP(A65,Ingresos!$A$2:$B$200,2,FALSE) -> Otros recursos Departamentales y Distritales para Aseguramiento | C65: 1042745130904 | D65: =+VLOOKUP(A65,Ingresos!$A$1:$F$90,3,FALSE) -> 0 | E65: =+VLOOKUP(A65,Ingresos!$A$1:$F$200,4,FALSE) -> 1042745130904 | F65: 1.2924585e+12 | G65: =+VLOOKUP(A65,Ingresos!$A$1:$E$200,5,FALSE) -> 200371505880 | H65: =+G65+F65 -> 1.49283e+12 | I65: =IFERROR(H65/E65*100,0) -> 143.16346 | J65: =+H65/1000000 -> 1492830
A66: 1-3-6-8-02 | B66: =+VLOOKUP(A66,Ingresos!$A$2:$B$200,2,FALSE) -> Otros Recursos Municipales para Aseguramiento | C66: 81840637720 | D66: =+VLOOKUP(A66,Ingresos!$A$1:$F$90,3,FALSE) -> 0 | E66: =+VLOOKUP(A66,Ingresos!$A$1:$F$200,4,FALSE) -> 81840637720 | F66: 5.641768e+10 | G66: =+VLOOKUP(A66,Ingresos!$A$1:$E$200,5,FALSE) -> 5.3735799e+09 | H66: =+G66+F66 -> 6.179126e+10 | I66: =IFERROR(H66/E66*100,0) -> 75.501928 | J66: =+H66/1000000 -> 61791.26
A67: 1-3-6-9 | B67: =+VLOOKUP(A67,Ingresos!$A$2:$B$200,2,FALSE) -> Recursos USPEC | C67: 37000000000 | D67: =+VLOOKUP(A67,Ingresos!$A$1:$F$90,3,FALSE) -> 0 | E67: =+VLOOKUP(A67,Ingresos!$A$1:$F$200,4,FALSE) -> 37000000000 | F67: 3.4818e+10 | G67: =+VLOOKUP(A67,Ingresos!$A$1:$E$200,5,FALSE) -> 0 | H67: =+G67+F67 -> 3.4818e+10 | I67: =IFERROR(H67/E67*100,0) -> 94.102703 | J67: =+H67/1000000 -> 34818
A68: 2-0-0-0 | B68: RECURSOS DE CAPITAL | C68: 159585154000 | D68: =+D69+D73+D89+D99 -> 0 | E68: =+E69+E73+E89+E99 -> 3.146239e+12 | F68: 2.1618584e+12 | G68: =+G69+G73+G89+G99 -> 3.0465132e+11 | H68: =+G68+F68 -> 2.4665097e+12 | I68: =IFERROR(H68/E68*100,0) -> 78.395498 | J68: =+H68/1000000 -> 2466509.7
A69: 2-1-0-0 | B69: =+VLOOKUP(A69,Ingresos!$A$2:$B$200,2,FALSE) -> Recuperación de Cartera | C69: 80000000000 | D69: =+SUM(D70:D72) -> 0 | E69: =+SUM(E70:E72) -> 80000000000 | F69: 85817900804 | G69: =+SUM(G70:G72) -> 294821999 | H69: =+G69+F69 -> 86112722803 | I69: =IFERROR(H69/E69*100,0) -> 107.6409 | J69: =+H69/1000000 -> 86112.723
A70: 2-1-0-0-01 | B70: =+VLOOKUP(A70,Ingresos!$A$2:$B$200,2,FALSE) -> Restitución operación Fosyga RS Ley 1608 de 2013 | C70: 0 | D70: =+VLOOKUP(A70,Ingresos!$A$1:$F$90,3,FALSE) -> 0 | E70: =+VLOOKUP(A70,Ingresos!$A$1:$F$200,4,FALSE) -> 0 | F70: 5878109726 | G70: =+VLOOKUP(A70,Ingresos!$A$1:$E$200,5,FALSE) -> 294821999 | H70: =+G70+F70 -> 6172931725 | I70: =IFERROR(H70/E70*100,0) -> 0 | J70: =+H70/1000000 -> 6172.9317
A71: 2-1-0-0-02 | B71: =+VLOOKUP(A71,Ingresos!$A$2:$B$200,2,FALSE) -> Amortización Operaciones de Compra de Cartera | C71: 80000000000 | D71: =+VLOOKUP(A71,Ingresos!$A$1:$F$90,3,FALSE) -> 0 | E71: =+VLOOKUP(A71,Ingresos!$A$1:$F$200,4,FALSE) -> 80000000000 | F71: 79939791078 | G71: =+VLOOKUP(A71,Ingresos!$A$1:$E$200,5,FALSE) -> 0 | H71: =+G71+F71 -> 79939791078 | I71: =IFERROR(H71/E71*100,0) -> 99.924739 | J71: =+H71/1000000 -> 79939.791
A72: 2-1-0-0-03 | B72: =+VLOOKUP(A72,Ingresos!$A$2:$B$200,2,FALSE) -> Recuperación Operaciones de Fortalecimiento Financiero y Patrimonial a entidades del sector salud | C72: 0 | D72: =+VLOOKUP(A72,Ingresos!$A$1:$F$90,3,FALSE) -> 0 | E72: =+VLOOKUP(A72,Ingresos!$A$1:$F$200,4,FALSE) -> 0 | F72: 0 | G72: =+VLOOKUP(A72,Ingresos!$A$1:$E$200,5,FALSE) -> 0 | H72: =+G72+F72 -> 0 | I72: =IFERROR(H72/E72*100,0) -> 0 | J72: =+H72/1000000 -> 0
A73: 2-4-0-0 | B73: =+VLOOKUP(A73,Ingresos!$A$2:$B$200,2,FALSE) -> Rendimientos Financieros e Intereses | C73: 24675676069 | D73: =+SUM(D74:D88) -> 0 | E73: =+SUM(E74:E88) -> 24675676069 | F73: 2.486784e+11 | G73: =+SUM(G74:G88) -> 2.6086677e+10 | H73: =+G73+F73 -> 2.7476508e+11 | I73: =IFERROR(H73/E73*100,0) -> 1113.5058 | J73: =+H73/1000000 -> 274765.08
A74: 2-4-0-0-01 | B74: =+VLOOKUP(A74,Ingresos!$A$2:$B$200,2,FALSE) -> Rendimientos cuentas de recaudo EPS -CSF- | C74: 0 | D74: =+VLOOKUP(A74,Ingresos!$A$1:$F$90,3,FALSE) -> 0 | E74: =+VLOOKUP(A74,Ingresos!$A$1:$F$200,4,FALSE) -> 0 | F74: 3143630127 | G74: =+VLOOKUP(A74,Ingresos!$A$1:$E$200,5,FALSE) -> 33868484 | H74: =+G74+F74 -> 3177498611 | I74: =IFERROR(H74/E74*100,0) -> 0 | J74: =+H74/1000000 -> 3177.4986
A75: 2-4-0-0-02 | B75: =+VLOOKUP(A75,Ingresos!$A$2:$B$200,2,FALSE) -> Rendimientos cuentas de recaudo EPS -SSF- | C75: 7615081557 | D75: =+VLOOKUP(A75,Ingresos!$A$1:$F$90,3,FALSE) -> 1010000000 | E75: =+VLOOKUP(A75,Ingresos!$A$1:$F$200,4,FALSE) -> 8625081557 | F75: 7019264463 | G75: =+VLOOKUP(A75,Ingresos!$A$1:$E$200,5,FALSE) -> 628795606 | H75: =+G75+F75 -> 7648060069 | I75: =IFERROR(H75/E75*100,0) -> 88.672322 | J75: =+H75/1000000 -> 7648.0601
A76: 2-4-0-0-03 | B76: =+VLOOKUP(A76,Ingresos!$A$2:$B$200,2,FALSE) -> Rendimientos cuentas de Ahorros ADRES URA | C76: 7060594512 | D76: =+VLOOKUP(A76,Ingresos!$A$1:$F$90,3,FALSE) -> -1010000000 | E76: =+VLOOKUP(A76,Ingresos!$A$1:$F$200,4,FALSE) -> 6050594512 | F76: 7.4384596e+10 | G76: =+VLOOKUP(A76,Ingresos!$A$1:$E$200,5,FALSE) -> 1.1951362e+10 | H76: =+G76+F76 -> 8.6335959e+10 | I76: =IFERROR(H76/E76*100,0) -> 1426.9004 | J76: =+H76/1000000 -> 86335.959
A77: 2-4-0-0-04 | B77: =+VLOOKUP(A77,Ingresos!$A$2:$B$200,2,FALSE) -> Rendimientos cuentas de Corrientes ADRES URA | C77: 0 | D77: =+VLOOKUP(A77,Ingresos!$A$1:$F$90,3,FALSE) -> 0 | E77: =+VLOOKUP(A77,Ingresos!$A$1:$F$200,4,FALSE) -> 0 | F77: 0 | G77: =+VLOOKUP(A77,Ingresos!$A$1:$E$200,5,FALSE) -> 0 | H77: =+G77+F77 -> 0 | I77: =IFERROR(H77/E77*100,0) -> 0 | J77: =+H77/1000000 -> 0
A78: 2-4-0-0-06 | B78: =+VLOOKUP(A78,Ingresos!$A$2:$B$200,2,FALSE) -> Rendimientos sobre títulos del portafolio de Inversiones | C78: 0 | D78: =+VLOOKUP(A78,Ingresos!$A$1:$F$90,3,FALSE) -> 0 | E78: =+VLOOKUP(A78,Ingresos!$A$1:$F$200,4,FALSE) -> 0 | F78: 0 | G78: =+VLOOKUP(A78,Ingresos!$A$1:$E$200,5,FALSE) -> 0 | H78: =+G78+F78 -> 0 | I78: =IFERROR(H78/E78*100,0) -> 0 | J78: =+H78/1000000 -> 0
A79: 2-4-0-0-07 | B79: =+VLOOKUP(A79,Ingresos!$A$2:$B$200,2,FALSE) -> Rendimientos sobre recursos entregados en administración | C79: 0 | D79: =+VLOOKUP(A79,Ingresos!$A$1:$F$90,3,FALSE) -> 0 | E79: =+VLOOKUP(A79,Ingresos!$A$1:$F$200,4,FALSE) -> 0 | F79: 9.8296437e+09 | G79: =+VLOOKUP(A79,Ingresos!$A$1:$E$200,5,FALSE) -> 4.0574449e+08 | H79: =+G79+F79 -> 1.0235388e+10 | I79: =IFERROR(H79/E79*100,0) -> 0 | J79: =+H79/1000000 -> 10235.388
A80: 2-4-0-0-08 | B80: =+VLOOKUP(A80,Ingresos!$A$2:$B$200,2,FALSE) -> Otros rendimientos financieros | C80: 0 | D80: =+VLOOKUP(A80,Ingresos!$A$1:$F$90,3,FALSE) -> 0 | E80: =+VLOOKUP(A80,Ingresos!$A$1:$F$200,4,FALSE) -> 0 | F80: 3.4526329e+09 | G80: =+VLOOKUP(A80,Ingresos!$A$1:$E$200,5,FALSE) -> 2.0885033e+08 | H80: =+G80+F80 -> 3.6614833e+09 | I80: =IFERROR(H80/E80*100,0) -> 0 | J80: =+H80/1000000 -> 3661.4833
A81: 2-4-0-0-09 | B81: =+VLOOKUP(A81,Ingresos!$A$2:$B$200,2,FALSE) -> Intereses Operaciones Compra de Cartera | C81: 0 | D81: =+VLOOKUP(A81,Ingresos!$A$1:$F$90,3,FALSE) -> 0 | E81: =+VLOOKUP(A81,Ingresos!$A$1:$F$200,4,FALSE) -> 0 | F81: 9.4696157e+08 | G81: =+VLOOKUP(A81,Ingresos!$A$1:$E$200,5,FALSE) -> 0 | H81: =+G81+F81 -> 9.4696157e+08 | I81: =IFERROR(H81/E81*100,0) -> 0 | J81: =+H81/1000000 -> 946.96157
A82: 2-4-0-0-10 | B82: =+VLOOKUP(A82,Ingresos!$A$2:$B$200,2,FALSE) -> Intereses sobre restituciones | C82: 0 | D82: =+VLOOKUP(A82,Ingresos!$A$1:$F$90,3,FALSE) -> 0 | E82: =+VLOOKUP(A82,Ingresos!$A$1:$F$200,4,FALSE) -> 0 | F82: 1.0529609e+09 | G82: =+VLOOKUP(A82,Ingresos!$A$1:$E$200,5,FALSE) -> 1.029973e+09 | H82: =+G82+F82 -> 2.0829339e+09 | I82: =IFERROR(H82/E82*100,0) -> 0 | J82: =+H82/1000000 -> 2082.9339
A83: 2-4-0-0-11 | B83: =+VLOOKUP(A83,Ingresos!$A$2:$B$200,2,FALSE) -> Intereses de mora sobre compra de cartera | C83: 0 | D83: =+VLOOKUP(A83,Ingresos!$A$1:$F$90,3,FALSE) -> 0 | E83: =+VLOOKUP(A83,Ingresos!$A$1:$F$200,4,FALSE) -> 0 | F83: 0 | G83: =+VLOOKUP(A83,Ingresos!$A$1:$E$200,5,FALSE) -> 0 | H83: =+G83+F83 -> 0 | I83: =IFERROR(H83/E83*100,0) -> 0 | J83: =+H83/1000000 -> 0
A84: 2-4-0-0-12 | B84: =+VLOOKUP(A84,Ingresos!$A$2:$B$200,2,FALSE) -> Intereses de mora sobre restituciones | C84: 0 | D84: =+VLOOKUP(A84,Ingresos!$A$1:$F$90,3,FALSE) -> 0 | E84: =+VLOOKUP(A84,Ingresos!$A$1:$F$200,4,FALSE) -> 0 | F84: 7.0696827e+10 | G84: =+VLOOKUP(A84,Ingresos!$A$1:$E$200,5,FALSE) -> 2.9339706e+09 | H84: =+G84+F84 -> 7.3630798e+10 | I84: =IFERROR(H84/E84*100,0) -> 0 | J84: =+H84/1000000 -> 73630.798
A85: 2-4-0-0-13 | B85: =+VLOOKUP(A85,Ingresos!$A$2:$B$200,2,FALSE) -> Intereses de mora cotizaciones R.C. | C85: 10000000000 | D85: =+VLOOKUP(A85,Ingresos!$A$1:$F$90,3,FALSE) -> 0 | E85: =+VLOOKUP(A85,Ingresos!$A$1:$F$200,4,FALSE) -> 10000000000 | F85: 7.7550765e+10 | G85: =+VLOOKUP(A85,Ingresos!$A$1:$E$200,5,FALSE) -> 8873191581 | H85: =+G85+F85 -> 8.6423957e+10 | I85: =IFERROR(H85/E85*100,0) -> 864.23957 | J85: =+H85/1000000 -> 86423.957
... A88: 2-4-0-0-16 | B88: =+VLOOKUP(A88,Ingresos!$A$2:$B$200,2,FALSE) -> Otros Intereses | C88: 0 | D88: =+VLOOKUP(A88,Ingresos!$A$1:$F$90,3,FALSE) -> 0 | E88: =+VLOOKUP(A88,Ingresos!$A$1:$F$200,4,FALSE) -> 0 | F88: 5.8578869e+08 | G88: =+VLOOKUP(A88,Ingresos!$A$1:$E$200,5,FALSE) -> 20619522 | H88: =+G88+F88 -> 6.0640821e+08 | I88: =IFERROR(H88/E88*100,0) -> 0 | J88: =+H88/1000000 -> 606.40821
A89: 2-5-0-0 | B89: =+VLOOKUP(A89,Ingresos!$A$2:$B$200,2,FALSE) -> Recusos con destinación específica | C89: 54909477931 | D89: =+SUM(D90:D98) -> 0 | E89: =+SUM(E90:E98) -> 3.0415633e+12 | F89: 1.8273621e+12 | G89: =+SUM(G90:G98) -> 2.7826982e+11 | H89: =+G89+F89 -> 2.1056319e+12 | I89: =IFERROR(H89/E89*100,0) -> 69.228608 | J89: =+H89/1000000 -> 2105631.9
A90: 2-5-0-0-01 | B90: =+VLOOKUP(A90,Ingresos!$A$2:$B$200,2,FALSE) -> Excedentes -Servicios prestados a la población pobre y los servicios No POS entidades territoriales. (Num, 2 art. 3 Ley 1608 de 2013) | C90: 0 | D90: =+VLOOKUP(A90,Ingresos!$A$1:$F$90,3,FALSE) -> 0 | E90: =+VLOOKUP(A90,Ingresos!$A$1:$F$200,4,FALSE) -> 0 | F90: 0 | G90: =+VLOOKUP(A90,Ingresos!$A$1:$E$200,5,FALSE) -> 0 | H90: =+G90+F90 -> 0 | I90: =IFERROR(H90/E90*100,0) -> 0 | J90: =+H90/1000000 -> 0
A91: 2-5-0-0-02 | B91: =+VLOOKUP(A91,Ingresos!$A$2:$B$200,2,FALSE) -> Recursos SGP Propósito General Libre Inversión | C91: 13909477931 | D91: =+VLOOKUP(A91,Ingresos!$A$1:$F$90,3,FALSE) -> 0 | E91: =+VLOOKUP(A91,Ingresos!$A$1:$F$200,4,FALSE) -> 13909477931 | F91: 4174384004 | G91: =+VLOOKUP(A91,Ingresos!$A$1:$E$200,5,FALSE) -> 441655495 | H91: =+G91+F91 -> 4616039499 | I91: =IFERROR(H91/E91*100,0) -> 33.186289 | J91: =+H91/1000000 -> 4616.0395
A92: 2-5-0-0-03 | B92: =+VLOOKUP(A92,Ingresos!$A$2:$B$200,2,FALSE) -> Excedentes recursos FAEP para el reconocimiento de deuda por contratos del Régimen Subsidiado realizados hasta marzo 31 de 2011. | C92: 0 | D92: =+VLOOKUP(A92,Ingresos!$A$1:$F$90,3,FALSE) -> 0 | E92: =+VLOOKUP(A92,Ingresos!$A$1:$F$200,4,FALSE) -> 0 | F92: 0 | G92: =+VLOOKUP(A92,Ingresos!$A$1:$E$200,5,FALSE) -> 0 | H92: =+G92+F92 -> 0 | I92: =IFERROR(H92/E92*100,0) -> 0 | J92: =+H92/1000000 -> 0
A93: 2-5-0-0-04 | B93: =+VLOOKUP(A93,Ingresos!$A$2:$B$200,2,FALSE) -> Excedentes recursos de LOTTO en línea -FONPET para reconocimiento de deuda por contratos del Régimen Subsidiado realizados hasta marzo 31 de 2011 | C93: 2000000000 | D93: =+VLOOKUP(A93,Ingresos!$A$1:$F$90,3,FALSE) -> 0 | E93: =+VLOOKUP(A93,Ingresos!$A$1:$F$200,4,FALSE) -> 2000000000 | F93: 0 | G93: =+VLOOKUP(A93,Ingresos!$A$1:$E$200,5,FALSE) -> 0 | H93: =+G93+F93 -> 0 | I93: =IFERROR(H93/E93*100,0) -> 0 | J93: =+H93/1000000 -> 0
A94: 2-5-0-0-05 | B94: =+VLOOKUP(A94,Ingresos!$A$2:$B$200,2,FALSE) -> Excedentes de Aportes Patronales / Resolución 2360 de 2016 | C94: 0 | D94: =+VLOOKUP(A94,Ingresos!$A$1:$F$90,3,FALSE) -> 0 | E94: =+VLOOKUP(A94,Ingresos!$A$1:$F$200,4,FALSE) -> 0 | F94: 46202219 | G94: =+VLOOKUP(A94,Ingresos!$A$1:$E$200,5,FALSE) -> -42625787 | H94: =+G94+F94 -> 3576432 | I94: =IFERROR(H94/E94*100,0) -> 0 | J94: =+H94/1000000 -> 3.576432
A95: 2-5-0-0-06 | B95: =+VLOOKUP(A95,Ingresos!$A$2:$B$200,2,FALSE) -> Regalías – artículo 5 Ley 1797 de 2016 | C95: 3000000000 | D95: =+VLOOKUP(A95,Ingresos!$A$1:$F$90,3,FALSE) -> 0 | E95: =+VLOOKUP(A95,Ingresos!$A$1:$F$200,4,FALSE) -> 3000000000 | F95: 0 | G95: =+VLOOKUP(A95,Ingresos!$A$1:$E$200,5,FALSE) -> 0 | H95: =+G95+F95 -> 0 | I95: =IFERROR(H95/E95*100,0) -> 0 | J95: =+H95/1000000 -> 0
A96: 2-5-0-0-07 | B96: =+VLOOKUP(A96,Ingresos!$A$2:$B$200,2,FALSE) -> Recursos CCF / FOSFEC - Ley 1929 de 2018 | C96: 36000000000 | D96: =+VLOOKUP(A96,Ingresos!$A$1:$F$90,3,FALSE) -> 0 | E96: =+VLOOKUP(A96,Ingresos!$A$1:$F$200,4,FALSE) -> 36000000000 | F96: 2.5263724e+10 | G96: =+VLOOKUP(A96,Ingresos!$A$1:$E$200,5,FALSE) -> 1.847633e+09 | H96: =+G96+F96 -> 2.7111357e+10 | I96: =IFERROR(H96/E96*100,0) -> 75.309326 | J96: =+H96/1000000 -> 27111.357
A97: 2-5-0-0-08 | B97: =+VLOOKUP(A97,Ingresos!$A$2:$B$200,2,FALSE) -> Recursos para el reconocimiento de lo establecido en el parágrafo 3 del art.237 de la Ley 1955 de 2019 | C97: 0 | D97: =+VLOOKUP(A97,Ingresos!$A$1:$F$90,3,FALSE) -> 0 | E97: =+VLOOKUP(A97,Ingresos!$A$1:$F$200,4,FALSE) -> 2.2265384e+11 | F97: 1.7519521e+11 | G97: =+VLOOKUP(A97,Ingresos!$A$1:$E$200,5,FALSE) -> 0 | H97: =+G97+F97 -> 1.7519521e+11 | I97: =IFERROR(H97/E97*100,0) -> 78.685015 | J97: =+H97/1000000 -> 175195.21
A98: 2-5-0-0-09 | B98: =+VLOOKUP(A98,Ingresos!$A$2:$B$200,2,FALSE) -> Recursos para la Financiación de Obligaciones del Art.245 de la Ley 1955 de 2019 | C98: 0 | D98: =+VLOOKUP(A98,Ingresos!$A$1:$F$90,3,FALSE) -> 0 | E98: =+VLOOKUP(A98,Ingresos!$A$1:$F$200,4,FALSE) -> 2764000000000 | F98: 1.6226826e+12 | G98: =+VLOOKUP(A98,Ingresos!$A$1:$E$200,5,FALSE) -> 2.7602316e+11 | H98: =+G98+F98 -> 1.8987058e+12 | I98: =IFERROR(H98/E98*100,0) -> 68.69413 | J98: =+H98/1000000 -> 1898705.8
A99: 2-9-0-0 | B99: =+VLOOKUP(A99,Ingresos!$A$2:$B$200,2,FALSE) -> Otros Recursos de Capital | C99: 0 | D99: =+SUM(D100:D101) -> 0 | E99: =+SUM(E100:E101) -> 0 | F99: 0 | G99: =+SUM(G100:G101) -> 0 | H99: =+G99+F99 -> 0 | I99: =IFERROR(H99/E99*100,0) -> 0 | J99: =+H99/1000000 -> 0
A100: 2-9-0-0-01 | B100: =+VLOOKUP(A100,Ingresos!$A$2:$B$200,2,FALSE) -> Liquidación patrimonios autónomos Sector Salud | C100: 0 | D100: =+VLOOKUP(A100,Ingresos!$A$1:$F$90,3,FALSE) -> 0 | E100: =+VLOOKUP(A100,Ingresos!$A$1:$F$200,4,FALSE) -> 0 | F100: 0 | G100: =+VLOOKUP(A100,Ingresos!$A$1:$E$200,5,FALSE) -> 0 | H100: =+G100+F100 -> 0 | I100: =IFERROR(H100/E100*100,0) -> 0 | J100: =+H100/1000000 -> 0
A101: 2-9-0-0-02 | B101: =+VLOOKUP(A101,Ingresos!$A$2:$B$200,2,FALSE) -> Otros Recursos de Capital no contemplados en los anteriores | C101: 0 | D101: =+VLOOKUP(A101,Ingresos!$A$1:$F$90,3,FALSE) -> 0 | E101: =+VLOOKUP(A101,Ingresos!$A$1:$F$200,4,FALSE) -> 0 | F101: 0 | G101: =+VLOOKUP(A101,Ingresos!$A$1:$E$200,5,FALSE) -> 0 | H101: =+G101+F101 -> 0 | I101: =IFERROR(H101/E101*100,0) -> 0 | J101: =+H101/1000000 -> 0
B103: TOTAL | C103: =+C68+C13+C12 -> 52636824590223 | D103: =+D68+D13+D12 -> 0 | E103: =+E68+E13+E12 -> 5.334758e+13 | F103: 4.5219047e+13 | G103: =+G68+G13+G12 -> 5.0735617e+12 | H103: =+H68+H13+H12 -> 5.0292608e+13 | I103: =IFERROR(H103/E103*100,0) -> 94.273459
C104: 52636824590223 | D104: 0 | E104: 53347579621981 | F104: 4.5219047e+13 | G104: 5.0735617e+12 | H104: 5.0292608e+13 | I104: 94.27
C105: =+C104-C103 -> 0 | D105: =+D104-D103 -> 0 | E105: =+E104-E103 -> 0 | F105: =+F104-F103 -> -0.0625 | G105: =+G104-G103 -> 0 | H105: =+H104-H103 -> 0 | I105: =+I104-I103 -> -0.00345862
F106: dif. Por el excel | H106: dif. Por el excel
...

Sheet Ingresos
A1: RUBRO | B1: inicial | C1: MODIFICACIONES | D1: AFORO DEFINITIVO | E1: INGRESO MES | F1: % | G1: según ejec. Sistema acum | H1: formulado
A2: 0-0-0-0 | B2: Disponibilidad inicial | C2: 0 | D2: 910932869290 | E2: 0 | F2: 100 | G2: 910932869290 | H2: =+VLOOKUP(A2,'CUADRO 1-EJECUCION DE INGRESOS'!$A$10:$H$101,8,FALSE) -> 910932869290 | I2: =+H2-G2 -> 0
A3: 1-2-1-1 | B3: Aportes de la Nación para el Aseguramiento en Salud | C3: 0 | D3: 15039782346000 | E3: 1160204084389 | F3: 92 | G3: 1.3836378e+13 | H3: =+VLOOKUP(A3,'CUADRO 1-EJECUCION DE INGRESOS'!$A$10:$H$101,8,FALSE) -> 1.3836378e+13 | I3: =+H3-G3 -> 0.08203125
A4: 1-2-1-1-01 | B4: Aportes de la Nación para el Aseguramiento en Salud Cierre | C4: 0 | D4: 9743321670830 | E4: 6.2167882e+11 | F4: 93.18 | G4: 9.0784429e+12 | H4: =+VLOOKUP(A4,'CUADRO 1-EJECUCION DE INGRESOS'!$A$10:$H$101,8,FALSE) -> 9.0784429e+12 | I4: =+H4-G4 -> 0
A5: 1-2-1-1-02 | B5: Imporenta | C5: 0 | D5: 5296460675170 | E5: 5.3852527e+11 | F5: 89.83 | G5: 4.7579354e+12 | H5: =+VLOOKUP(A5,'CUADRO 1-EJECUCION DE INGRESOS'!$A$10:$H$101,8,FALSE) -> 4.7579354e+12 | I5: =+H5-G5 -> 0
A6: 1-2-1-2 | B6: Compensación Regalías para el Régimen Subsidiado | C6: 0 | D6: 226673765000 | E6: 0 | F6: 100 | G6: 226673765000 | H6: =+VLOOKUP(A6,'CUADRO 1-EJECUCION DE INGRESOS'!$A$10:$H$101,8,FALSE) -> 226673765000 | I6: =+H6-G6 -> 0
A7: 1-2-1-3 | B7: Impuesto sobre la renta para la equidad CREE | C7: 0 | D7: 0 | E7: 0 | F7: 0 | G7: 0 | H7: =+VLOOKUP(A7,'CUADRO 1-EJECUCION DE INGRESOS'!$A$10:$H$101,8,FALSE) -> 0 | I7: =+H7-G7 -> 0
A8: 1-2-1-4 | B8: SGP FONSAET | C8: 0 | D8: 95551523562 | E8: 0 | F8: 0 | G8: 0 | H8: =+VLOOKUP(A8,'CUADRO 1-EJECUCION DE INGRESOS'!$A$10:$H$101,8,FALSE) -> 0 | I8: =+H8-G8 -> 0
A9: 1-2-1-5 | B9: PRIMA FONSAT Y CONTRIBUCION SOAT | C9: 0 | D9: 1640527441000 | E9: 1.8790881e+11 | F9: 102.99 | G9: 1.6895536e+12 | H9: =+VLOOKUP(A9,'CUADRO 1-EJECUCION DE INGRESOS'!$A$10:$H$101,8,FALSE) -> 1.6895536e+12 | I9: =+H9-G9 -> 0
A10: 1-2-1-5-01 | B10: % Prima (FONSAT) Decreto Ley 1335 de 2009 | C10: 0 | D10: 363281118360 | E10: 6.7235893e+10 | F10: 109.3 | G10: 3.9706551e+11 | H10: =+VLOOKUP(A10,'CUADRO 1-EJECUCION DE INGRESOS'!$A$10:$H$101,8,FALSE) -> 3.9706551e+11 | I10: =+H10-G10 -> 0
A11: 1-2-1-5-02 | B11: Contribución Seguro Obligatorio de Accidentes de Tránsito - SOAT- Decreto Ley 1335 de 2009 | C11: 0 | D11: 1277246322640 | E11: 120672915300 | F11: 101.19 | G11: 1.2924881e+12 | H11: =+VLOOKUP(A11,'CUADRO 1-EJECUCION DE INGRESOS'!$A$10:$H$101,8,FALSE) -> 1.2924881e+12 | I11: =+H11-G11 -> 0
A12: 1-2-1-7 | B12: Impuesto social a las municiones y explosivos | C12: 0 | D12: 6410791000 | E12: 9997809749 | F12: 1689.6 | G12: 108316733990 | H12: =+VLOOKUP(A12,'CUADRO 1-EJECUCION DE INGRESOS'!$A$10:$H$101,8,FALSE) -> 108316733990 | I12: =+H12-G12 -> 0
A13: 1-2-1-8 | B13: Impuesto social a las armas | C13: 0 | D13: 8851770619 | E13: 1171605398 | F13: 101.55 | G13: 8989110740 | H13: =+VLOOKUP(A13,'CUADRO 1-EJECUCION DE INGRESOS'!$A$10:$H$101,8,FALSE) -> 8989110740 | I13: =+H13-G13 -> 0
... A84: 2-9-0-0-02 | B84: Otros Recursos de Capital no contemplados en los anteriores | C84: 0 | D84: 0 | E84: 0 | F84: 0 | G84: 0 | H84: =+VLOOKUP(A84,'CUADRO 1-EJECUCION DE INGRESOS'!$A$10:$H$101,8,FALSE) -> 0 | I84: =+H84-G84 -> 0
D85: 5.0735617e+12 | E85: 0 | F85: 94.27

Sheet CUADRO 2-EJECUCION DE GASTOS
M1: =+TODAY() -> 43818 | N1: =+NOW() -> 43818.489
A3: ADMINISTRADORA DE LOS RECURSOS DEL SISTEMA GENERAL DE SEGURIDAD SOCIAL EN SALUD
A4: UNIDAD DE RECURSOS ADMINISTRADOS - URA
A5: CODIGO DE LA EMPRESA 12902 - ADMINISTRACION DE RECURSOS DEL SGSSS
A6: PRESUPUESTO DE GASTOS NOVIEMBRE DE 2019
A7: CUADRO No. 2
A10: CÓDIGO RUBRO | B10: CONCEPTO DEL RUBRO | C10: APROPIACIÓN DEFINITIVA | D10: EJECUCION PRESUPUESTAL ACUMULADA DESDE 01/01/2019 HASTA 31/10/2019 | G10: EJECUCION PRESUPUESTAL DESDE 01/11/2019 HASTA 30/11/2019 | J10: EJECUCION PRESUPUESTAL ACUMULADA DESDE 01/01/2019 HASTA 30/11/2019 | M10: %
D11: T. CDP | E11: T. RP | F11: T. PAGOS-OG | G11: CDP | H11: RP | I11: PAGOS-OG | J11: T. CDP | K11: T. RP | L11: T. PAGOS-OG | M11: RP | N11: OG
B12: URA
A13: A-3-0-0-0 | B13: TRANSFERENCIAS | C13: =+C14+C19+C25 -> 5.3093572e+13 | D13: 4.6380563e+13 | E13: 4.2615021e+13 | F13: 4.2615021e+13 | G13: =+G14+G19+G25 -> 4.8857093e+12 | H13: =+H14+H19+H25 -> 4.1824172e+12 | I13: =+I14+I19+I25 -> 4.1624172e+12 | J13: =+G13+D13 -> 5.1266272e+13 | K13: =+H13+E13 -> 4.6797438e+13 | L13: =+I13+F13 -> 4.6777438e+13 | M13: =+IFERROR(K13*100/C13,0) -> 88.141438 | N13: =+IFERROR(L13*100/C13,0) -> 88.103769 | O13: =+L13/1000000 -> 46777438
A14: A-3-2-0-0 | B14: TRANSFERENCIAS AL SECTOR PUBLICO | C14: =+C15+C17 -> 231725030430 | D14: 228185519661 | E14: 1.0309248e+11 | F14: 1.0309248e+11 | G14: =+G15+G17 -> 0 | H14: =+H15+H17 -> 1.0906417e+10 | I14: =+I15+I17 -> 1.0906417e+10 | J14: =+G14+D14 -> 228185519661 | K14: =+H14+E14 -> 1.139989e+11 | L14: =+I14+F14 -> 1.139989e+11 | M14: =+IFERROR(K14*100/C14,0) -> 49.195764 | N14: =+IFERROR(L14*100/C14,0) -> 49.195764 | O14: =+L14/1000000 -> 113998.9
A15: A-3-2-1-0 | B15: =+VLOOKUP(A15,gasto!$A$4:$B$100,2,FALSE) -> Transferencias Entidades de Administración Pública Central | C15: =+C16 -> 86345030430 | D15: 82805519661 | E15: 6.8840742e+10 | F15: 6.8840742e+10 | G15: =+G16 -> 0 | H15: =+H16 -> 6.8799777e+09 | I15: =+I16 -> 6.8799777e+09 | J15: =+J16 -> 82805519661 | K15: =+K16 -> 7.5720719e+10 | L15: =+L16 -> 7.5720719e+10 | M15: =+IFERROR(K15*100/C15,0) -> 87.695515 | N15: =+IFERROR(L15*100/C15,0) -> 87.695515 | O15: =+L15/1000000 -> 75720.719
A16: A-3-2-1-01 | B16: =+VLOOKUP(A16,gasto!$A$4:$B$100,2,FALSE) -> Contribución IVC Superintendencia Nacional de Salud | C16: =+VLOOKUP(A16,gasto!$A$4:$F$80,3,FALSE) -> 86345030430 | D16: 82805519661 | E16: 6.8840742e+10 | F16: 6.8840742e+10 | G16: =+VLOOKUP(A16,gasto!$A$4:$F$80,4,FALSE) -> 0 | H16: =+VLOOKUP(A16,gasto!$A$4:$F$80,5,FALSE) -> 6.8799777e+09 | I16: =+VLOOKUP(A16,gasto!$A$4:$F$80,6,FALSE) -> 6.8799777e+09 | J16: =+G16+D16 -> 82805519661 | K16: =+H16+E16 -> 7.5720719e+10 | L16: =+I16+F16 -> 7.5720719e+10 | M16: =+IFERROR(K16*100/C16,0) -> 87.695515 | N16: =+IFERROR(L16*100/C16,0) -> 87.695515 | O16: =+L16/1000000 -> 75720.719
A17: A-3-2-2-0 | B17: =+VLOOKUP(A17,gasto!$A$4:$B$100,2,FALSE) -> Empresas Públicas Nacionales no financieras -ADRES | C17: =+C18 -> 145380000000 | D17: 145380000000 | E17: 3.425174e+10 | F17: 3.425174e+10 | G17: =+G18 -> 0 | H17: =+H18 -> 4.0264397e+09 | I17: =+I18 -> 4.0264397e+09 | J17: =+J18 -> 145380000000 | K17: =+K18 -> 3.827818e+10 | L17: =+L18 -> 3.827818e+10 | M17: =+IFERROR(K17*100/C17,0) -> 26.329743 | N17: =+IFERROR(L17*100/C17,0) -> 26.329743 | O17: =+L17/1000000 -> 38278.18
A18: A-3-2-2-0-01 | B18: =+VLOOKUP(A18,gasto!$A$4:$B$100,2,FALSE) -> Aportes hasta del 0,5% recursos CSF para el desarrollo objeto ADRES | C18: =+VLOOKUP(A18,gasto!$A$4:$F$80,3,FALSE) -> 145380000000 | D18: 145380000000 | E18: 3.425174e+10 | F18: 3.425174e+10 | G18: =+VLOOKUP(A18,gasto!$A$4:$F$80,4,FALSE) -> 0 | H18: =+VLOOKUP(A18,gasto!$A$4:$F$80,5,FALSE) -> 4.0264397e+09 | I18: =+VLOOKUP(A18,gasto!$A$4:$F$80,6,FALSE) -> 4.0264397e+09 | J18: =+G18+D18 -> 145380000000 | K18: =+H18+E18 -> 3.827818e+10 | L18: =+I18+F18 -> 3.827818e+10 | M18: =+IFERROR(K18*100/C18,0) -> 26.329743 | N18: =+IFERROR(L18*100/C18,0) -> 26.329743 | O18: =+L18/1000000 -> 38278.18
A19: A-3-6-0-0 | B19: OTRAS TRANSFERENCIAS | C19: =+C20+C23 -> 154000000000 | D19: 2.1803278e+09 | E19: 2.1803278e+09 | F19: 2.1803278e+09 | G19: =+G20+G23 -> 32260652 | H19: =+H20+H23 -> 1298784.6 | I19: =+I20+I23 -> 1298784.6 | J19: =+G19+D19 -> 2.2125885e+09 | K19: =+H19+E19 -> 2.1816266e+09 | L19: =+I19+F19 -> 2.1816266e+09 | M19: =+IFERROR(K19*100/C19,0) -> 1.4166407 | N19: =+IFERROR(L19*100/C19,0) -> 1.4166407 | O19: =+L19/1000000 -> 2181.6266
A20: A-3-6-1-0 | B20: =+VLOOKUP(A20,gasto!$A$4:$B$100,2,FALSE) -> Sentencias y Conciliaciones URA | C20: =+SUM(C21:C22) -> 20000000000 | D20: 2.1803278e+09 | E20: 2.1803278e+09 | F20: 2.1803278e+09 | G20: =+SUM(G21:G22) -> 32260652 | H20: =+SUM(H21:H22) -> 1298784.6 | I20: =+SUM(I21:I22) -> 1298784.6 | J20: =+SUM(J21:J22) -> 2.2125885e+09 | K20: =+SUM(K21:K22) -> 2.1816266e+09 | L20: =+SUM(L21:L22) -> 2.1816266e+09 | M20: =+IFERROR(K20*100/C20,0) -> 10.908133 | N20: =+IFERROR(L20*100/C20,0) -> 10.908133 | O20: =+L20/1000000 -> 2181.6266
A21: A-3-6-1-1 | B21: =+VLOOKUP(A21,gasto!$A$4:$B$100,2,FALSE) -> Sentencias URA | C21: =+VLOOKUP(A21,gasto!$A$4:$F$80,3,FALSE) -> 20000000000 | D21: 2.1803278e+09 | E21: 2.1803278e+09 | F21: 2.1803278e+09 | G21: =+VLOOKUP(A21,gasto!$A$4:$F$80,4,FALSE) -> 32260652 | H21: =+VLOOKUP(A21,gasto!$A$4:$F$80,5,FALSE) -> 1298784.6 | I21: =+VLOOKUP(A21,gasto!$A$4:$F$80,6,FALSE) -> 1298784.6 | J21: =+G21+D21 -> 2.2125885e+09 | K21: =+H21+E21 -> 2.1816266e+09 | L21: =+I21+F21 -> 2.1816266e+09 | M21: =+IFERROR(K21*100/C21,0) -> 10.908133 | N21: =+IFERROR(L21*100/C21,0) -> 10.908133 | O21: =+L21/1000000 -> 2181.6266
A22: A-3-6-1-2 | B22: =+VLOOKUP(A22,gasto!$A$4:$B$100,2,FALSE) -> Conciliaciones URA | C22: =+VLOOKUP(A22,gasto!$A$4:$F$80,3,FALSE) -> 0 | D22: 0 | E22: 0 | F22: 0 | G22: =+VLOOKUP(A22,gasto!$A$4:$F$80,4,FALSE) -> 0 | H22: =+VLOOKUP(A22,gasto!$A$4:$F$80,5,FALSE) -> 0 | I22: =+VLOOKUP(A22,gasto!$A$4:$F$80,6,FALSE) -> 0 | J22: =+G22+D22 -> 0 | K22: =+H22+E22 -> 0 | L22: =+I22+F22 -> 0 | M22: =+IFERROR(K22*100/C22,0) -> 0 | N22: =+IFERROR(L22*100/C22,0) -> 0 | O22: =+L22/1000000 -> 0
A23: A-3-6-3-0 | B23: =+VLOOKUP(A23,gasto!$A$4:$B$100,2,FALSE) -> Destinatarios de otras transferencias Corrientes - Compensación Chance | C23: =+C24 -> 134000000000 | D23: 0 | E23: 0 | F23: 0 | G23: =+G24 -> 0 | H23: =+H24 -> 0 | I23: =+I24 -> 0 | J23: =+J24 -> 0 | K23: =+K24 -> 0 | L23: =+L24 -> 0 | M23: =+IFERROR(K23*100/C23,0) -> 0 | N23: =+IFERROR(L23*100/C23,0) -> 0 | O23: =+L23/1000000 -> 0
A24: A-3-6-3-0-01 | B24: =+VLOOKUP(A24,gasto!$A$4:$B$100,2,FALSE) -> Otras transferencias - Compensación del Chance Decreto 2550/12 | C24: =+VLOOKUP(A24,gasto!$A$4:$F$80,3,FALSE) -> 134000000000 | D24: 0 | E24: 0 | F24: 0 | G24: =+VLOOKUP(A24,gasto!$A$4:$F$80,4,FALSE) -> 0 | H24: =+VLOOKUP(A24,gasto!$A$4:$F$80,5,FALSE) -> 0 | I24: =+VLOOKUP(A24,gasto!$A$4:$F$80,6,FALSE) -> 0 | J24: =+G24+D24 -> 0 | K24: =+H24+E24 -> 0 | L24: =+I24+F24 -> 0 | M24: =+IFERROR(K24*100/C24,0) -> 0 | N24: =+IFERROR(L24*100/C24,0) -> 0 | O24: =+L24/1000000 -> 0
A25: A-3-9-0-0 | B25: ADMINISTRACIÓN DE RECURSOS DEL SGSSS | C25: =+C26+C31+C34+C37+C38+C39+C43+C48+C55+C59+C69+C80+C82+C84+C88+C93 -> 5.2707847e+13 | D25: 4.6050197e+13 | E25: 4.2509583e+13 | F25: 4.2509583e+13 | G25: =+G26+G31+G34+G37+G38+G39+G43+G48+G55+G59+G69+G80+G82+G84+G88+G93 -> 4.885677e+12 | H25: =+H26+H31+H34+H37+H38+H39+H43+H48+H55+H59+H69+H80+H82+H84+H88+H93 -> 4.1715095e+12 | I25: =+I26+I31+I34+I37+I38+I39+I43+I48+I55+I59+I69+I80+I82+I84+I88+I93 -> 4.1515095e+12 | J25: =+J26+J31+J34+J37+J38+J39+J43+J48+J55+J59+J69+J80+J82+J84+J88 -> 5.0935874e+13 | K25: =+K26+K31+K34+K37+K38+K39+K43+K48+K55+K59+K69+K80+K82+K84+K88 -> 4.6681092e+13 | L25: =+L26+L31+L34+L37+L38+L39+L43+L48+L55+L59+L69+L80+L82+L84+L88 -> 4.6661092e+13 | M25: =+IFERROR(K25*100/C25,0) -> 88.565736 | N25: =+IFERROR(L25*100/C25,0) -> 88.527791 | O25: =+L25/1000000 -> 46661092
A26: A-3-9-1-0 | B26: =+VLOOKUP(A26,gasto!$A$4:$B$100,2,FALSE) -> UPC Régimen Contributivo | C26: =+SUM(C27:C30) -> 22863934384378 | D26: 1.9588681e+13 | E26: 18634853148471 | F26: 18634853148471 | G26: =+SUM(G27:G30) -> 3.1690367e+12 | H26: =+SUM(H27:H30) -> 1829621715847 | I26: =+SUM(I27:I30) -> 1829621715847 | J26: =+SUM(J27:J30) -> 22757717488720 | K26: =+SUM(K27:K30) -> 20464474864318 | L26: =+SUM(L27:L30) -> 20464474864318 | M26: =+IFERROR(K26*100/C26,0) -> 89.505483 | N26: =+IFERROR(L26*100/C26,0) -> 89.505483 | O26: =+L26/1000000 -> 20464475
A27: A-3-9-1-0-01 | B27: =+VLOOKUP(A27,gasto!$A$4:$B$100,2,FALSE) -> UPC Régimen Contributivo SSF | C27: =+VLOOKUP(A27,gasto!$A$4:$F$80,3,FALSE) -> 12575109660289 | D27: 1.0578906e+13 | E27: 10308892111405 | F27: 10308892111405 | G27: =+VLOOKUP(A27,gasto!$A$4:$F$80,4,FALSE) -> 1.8899866e+12 | H27: =+VLOOKUP(A27,gasto!$A$4:$F$80,5,FALSE) -> 1054086594082 | I27: =+VLOOKUP(A27,gasto!$A$4:$F$80,6,FALSE) -> 1054086594082 | J27: =+G27+D27 -> 12468892764631 | K27: =+H27+E27 -> 11362978705487 | L27: =+I27+F27 -> 11362978705487 | M27: =+IFERROR(K27*100/C27,0) -> 90.360872 | N27: =+IFERROR(L27*100/C27,0) -> 90.360872 | O27: =+L27/1000000 -> 11362979
A28: A-3-9-1-0-02 | B28: =+VLOOKUP(A28,gasto!$A$4:$B$100,2,FALSE) -> UPC Régimen Contributivo CSF | C28: =+VLOOKUP(A28,gasto!$A$4:$F$80,3,FALSE) -> 10287649289644 | D28: 9008599217429 | E28: 8324785602621 | F28: 8324785602621 | G28: =+VLOOKUP(A28,gasto!$A$4:$F$80,4,FALSE) -> 1279050072215 | H28: =+VLOOKUP(A28,gasto!$A$4:$F$80,5,FALSE) -> 775535121765 | I28: =+VLOOKUP(A28,gasto!$A$4:$F$80,6,FALSE) -> 775535121765 | J28: =+G28+D28 -> 10287649289644 | K28: =+H28+E28 -> 9100320724386 | L28: =+I28+F28 -> 9100320724386 | M28: =+IFERROR(K28*100/C28,0) -> 88.458699 | N28: =+IFERROR(L28*100/C28,0) -> 88.458699 | O28: =+L28/1000000 -> 9100320.7
A29: A-3-9-1-0-03 | B29: =+VLOOKUP(A29,gasto!$A$4:$B$100,2,FALSE) -> Devolución aportes y cotizaciones no conciliadas vigencia anterior | C29: =+VLOOKUP(A29,gasto!$A$4:$F$80,3,FALSE) -> 1175434445 | D29: 1175434445 | E29: 1175434445 | F29: 1175434445 | G29: =+VLOOKUP(A29,gasto!$A$4:$F$80,4,FALSE) -> 0 | H29: =+VLOOKUP(A29,gasto!$A$4:$F$80,5,FALSE) -> 0 | I29: =+VLOOKUP(A29,gasto!$A$4:$F$80,6,FALSE) -> 0 | J29: =+G29+D29 -> 1175434445 | K29: =+H29+E29 -> 1175434445 | L29: =+I29+F29 -> 1175434445 | M29: =+IFERROR(K29*100/C29,0) -> 100 | N29: =+IFERROR(L29*100/C29,0) -> 100 | O29: =+L29/1000000 -> 1175.4344
A30: A-3-9-1-0-04 | B30: =+VLOOKUP(A30,gasto!$A$4:$B$100,2,FALSE) -> Rendimientos Financieros de los Saldos no Compensados de los Aportes Patronales según Art. 12 Decreto 1636 de 2016 | C30: =+VLOOKUP(A30,gasto!$A$4:$F$80,3,FALSE) -> 0 | D30: 0 | E30: 0 | F30: 0 | G30: =+VLOOKUP(A30,gasto!$A$4:$F$80,4,FALSE) -> 0 | H30: =+VLOOKUP(A30,gasto!$A$4:$F$80,5,FALSE) -> 0 | I30: =+VLOOKUP(A30,gasto!$A$4:$F$80,6,FALSE) -> 0 | J30: =+G30+D30 -> 0 | K30: =+H30+E30 -> 0 | L30: =+I30+F30 -> 0 | M30: =+IFERROR(K30*100/C30,0) -> 0 | N30: =+IFERROR(L30*100/C30,0) -> 0 | O30: =+L30/1000000 -> 0
A31: A-3-9-2-0 | B31: =+VLOOKUP(A31,gasto!$A$4:$B$100,2,FALSE) -> Per capita Programas de Promoción y Prevención R.C | C31: =+SUM(C32:C33) -> 547768600953 | D31: 5.2516483e+11 | E31: 423253138281 | F31: 423253138281 | G31: =+SUM(G32:G33) -> 2.2598926e+10 | H31: =+SUM(H32:H33) -> 41146647064 | I31: =+SUM(I32:I33) -> 41146647064 | J31: =+SUM(J32:J33) -> 547763758957 | K31: =+SUM(K32:K33) -> 464399785345 | L31: =+SUM(L32:L33) -> 464399785345 | M31: =+IFERROR(K31*100/C31,0) -> 84.780286 | N31: =+IFERROR(L31*100/C31,0) -> 84.780286 | O31: =+L31/1000000 -> 464399.79
A32: A-3-9-2-0-01 | B32: =+VLOOKUP(A32,gasto!$A$4:$B$100,2,FALSE) -> Per capita Programas de Promoción y Prevención R.C SSF | C32: =+VLOOKUP(A32,gasto!$A$4:$F$80,3,FALSE) -> 411516042986 | D32: 411426168868 | E32: 338609191257 | F32: 338609191257 | G32: =+VLOOKUP(A32,gasto!$A$4:$F$80,4,FALSE) -> 85032122 | H32: =+VLOOKUP(A32,gasto!$A$4:$F$80,5,FALSE) -> 34152449700 | I32: =+VLOOKUP(A32,gasto!$A$4:$F$80,6,FALSE) -> 34152449700 | J32: =+G32+D32 -> 411511200990 | K32: =+H32+E32 -> 372761640957 | L32: =+I32+F32 -> 372761640957 | M32: =+IFERROR(K32*100/C32,0) -> 90.582529 | N32: =+IFERROR(L32*100/C32,0) -> 90.582529 | O32: =+L32/1000000 -> 372761.64
A33: A-3-9-2-0-02 | B33: =+VLOOKUP(A33,gasto!$A$4:$B$100,2,FALSE) -> Per capita Programas de Promoción y Prevención R.C CSF | C33: =+VLOOKUP(A33,gasto!$A$4:$F$80,3,FALSE) -> 136252557967 | D33: 1.1373866e+11 | E33: 84643947024 | F33: 84643947024 | G33: =+VLOOKUP(A33,gasto!$A$4:$F$80,4,FALSE) -> 2.2513894e+10 | H33: =+VLOOKUP(A33,gasto!$A$4:$F$80,5,FALSE) -> 6994197364 | I33: =+VLOOKUP(A33,gasto!$A$4:$F$80,6,FALSE) -> 6994197364 | J33: =+G33+D33 -> 136252557967 | K33: =+H33+E33 -> 91638144388 | L33: =+I33+F33 -> 91638144388 | M33: =+IFERROR(K33*100/C33,0) -> 67.256091 | N33: =+IFERROR(L33*100/C33,0) -> 67.256091 | O33: =+L33/1000000 -> 91638.144
A34: A-3-9-3-0 | B34: =+VLOOKUP(A34,gasto!$A$4:$B$100,2,FALSE) -> Incapacidades | C34: =+SUM(C35:C36) -> 845461941941 | D34: 7.190495e+11 | E34: 681924346779 | F34: 681924346779 | G34: =+SUM(G35:G36) -> 1.2340259e+11 | H34: =+SUM(H35:H36) -> 67250636446 | I34: =+SUM(I35:I36) -> 67250636446 | J34: =+SUM(J35:J36) -> 842452089891 | K34: =+SUM(K35:K36) -> 749174983225 | L34: =+SUM(L35:L36) -> 749174983225 | M34: =+IFERROR(K34*100/C34,0) -> 88.61132 | N34: =+IFERROR(L34*100/C34,0) -> 88.61132 | O34: =+L34/1000000 -> 749174.98
A35: A-3-9-3-0-01 | B35: =+VLOOKUP(A35,gasto!$A$4:$B$100,2,FALSE) -> Incapacidades SSF | C35: =+VLOOKUP(A35,gasto!$A$4:$F$80,3,FALSE) -> 660253806467 | D35: 5.6233398e+11 | E35: 540531744658 | F35: 540531744658 | G35: =+VLOOKUP(A35,gasto!$A$4:$F$80,4,FALSE) -> 9.4909976e+10 | H35: =+VLOOKUP(A35,gasto!$A$4:$F$80,5,FALSE) -> 54977994697 | I35: =+VLOOKUP(A35,gasto!$A$4:$F$80,6,FALSE) -> 54977994697 | J35: =+G35+D35 -> 657243954417 | K35: =+H35+E35 -> 595509739355 | L35: =+I35+F35 -> 595509739355 | M35: =+IFERROR(K35*100/C35,0) -> 90.194064 | N35: =+IFERROR(L35*100/C35,0) -> 90.194064 | O35: =+L35/1000000 -> 595509.74
A36: A-3-9-3-0-02 | B36: =+VLOOKUP(A36,gasto!$A$4:$B$100,2,FALSE) -> Incapacidades CSF | C36: =+VLOOKUP(A36,gasto!$A$4:$F$80,3,FALSE) -> 185208135474 | D36: 156715520546 | E36: 141392602121 | F36: 141392602121 | G36: =+VLOOKUP(A36,gasto!$A$4:$F$80,4,FALSE) -> 28492614928 | H36: =+VLOOKUP(A36,gasto!$A$4:$F$80,5,FALSE) -> 12272641749 | I36: =+VLOOKUP(A36,gasto!$A$4:$F$80,6,FALSE) -> 12272641749 | J36: =+G36+D36 -> 185208135474 | K36: =+H36+E36 -> 153665243870 | L36: =+I36+F36 -> 153665243870 | M36: =+IFERROR(K36*100/C36,0) -> 82.968949 | N36: =+IFERROR(L36*100/C36,0) -> 82.968949 | O36: =+L36/1000000 -> 153665.24
A37: A-3-9-4-0 | B37: =+VLOOKUP(A37,gasto!$A$4:$B$100,2,FALSE) -> Licencias de Maternidad y Paternidad | C37: =+VLOOKUP(A37,gasto!$A$4:$F$80,3,FALSE) -> 838554045453 | D37: 838554045453 | E37: 662280886992 | F37: 662280886992 | G37: =+VLOOKUP(A37,gasto!$A$4:$F$80,4,FALSE) -> 0 | H37: =+VLOOKUP(A37,gasto!$A$4:$F$80,5,FALSE) -> 64400742809 | I37: =+VLOOKUP(A37,gasto!$A$4:$F$80,6,FALSE) -> 64400742809 | J37: =+G37+D37 -> 838554045453 | K37: =+H37+E37 -> 726681629801 | L37: =+I37+F37 -> 726681629801 | M37: =+IFERROR(K37*100/C37,0) -> 86.65889 | N37: =+IFERROR(L37*100/C37,0) -> 86.65889 | O37: =+L37/1000000 -> 726681.63
A38: A-3-9-5-0 | B38: =+VLOOKUP(A38,gasto!$A$4:$B$100,2,FALSE) -> Prestaciones Económicas Regímenes Especial y de Excepción | C38: =+VLOOKUP(A38,gasto!$A$4:$F$80,3,FALSE) -> 5142227236 | D38: 4842227236 | E38: 3518636432 | F38: 3518636432 | G38: =+VLOOKUP(A38,gasto!$A$4:$F$80,4,FALSE) -> 0 | H38: =+VLOOKUP(A38,gasto!$A$4:$F$80,5,FALSE) -> 565599472 | I38: =+VLOOKUP(A38,gasto!$A$4:$F$80,6,FALSE) -> 565599472 | J38: =+G38+D38 -> 4842227236 | K38: =+H38+E38 -> 4084235904 | L38: =+I38+F38 -> 4084235904 | M38: =+IFERROR(K38*100/C38,0) -> 79.425426 | N38: =+IFERROR(L38*100/C38,0) -> 79.425426 | O38: =+L38/1000000 -> 4084.2359
A39: A-3-9-6-0 | B39: =+VLOOKUP(A39,gasto!$A$4:$B$100,2,FALSE) -> UPC Régimen Subsidiado | C39: =+SUM(C40:C42) -> 2.2009869e+13 | D39: 2.0320446e+13 | E39: 1.8283986e+13 | F39: 1.8283986e+13 | G39: =+SUM(G40:G42) -> 1.2658121e+12 | H39: =+SUM(H40:H42) -> 1.830925e+12 | I39: =+SUM(I40:I42) -> 1.830925e+12 | J39: =+SUM(J40:J42) -> 21586257607421 | K39: =+SUM(K40:K42) -> 2.0114911e+13 | L39: =+SUM(L40:L42) -> 2.0114911e+13 | M39: =+IFERROR(K39*100/C39,0) -> 91.390417 | N39: =+IFERROR(L39*100/C39,0) -> 91.390417 | O39: =+L39/1000000 -> 20114911
A40: A-3-9-6-0-01 | B40: =+VLOOKUP(A40,gasto!$A$4:$B$100,2,FALSE) -> UPC´S R.S. Cajas de Compensación Familiar SSF | C40: =+VLOOKUP(A40,gasto!$A$4:$F$80,3,FALSE) -> 28877831435 | D40: 28877831435 | E40: 2.3598027e+10 | F40: 2.3598027e+10 | G40: =+VLOOKUP(A40,gasto!$A$4:$F$80,4,FALSE) -> 0 | H40: =+VLOOKUP(A40,gasto!$A$4:$F$80,5,FALSE) -> 1.0236848e+09 | I40: =+VLOOKUP(A40,gasto!$A$4:$F$80,6,FALSE) -> 1.0236848e+09 | J40: =+G40+D40 -> 28877831435 | K40: =+H40+E40 -> 2.4621711e+10 | L40: =+I40+F40 -> 2.4621711e+10 | M40: =+IFERROR(K40*100/C40,0) -> 85.261636 | N40: =+IFERROR(L40*100/C40,0) -> 85.261636 | O40: =+L40/1000000 -> 24621.711
A41: A-3-9-6-0-02 | B41: =+VLOOKUP(A41,gasto!$A$4:$B$100,2,FALSE) -> UPC´S R.S. CSF | C41: =+VLOOKUP(A41,gasto!$A$4:$F$80,3,FALSE) -> 2.1980992e+13 | D41: 2.0291568e+13 | E41: 1.8260388e+13 | F41: 1.8260388e+13 | G41: =+VLOOKUP(A41,gasto!$A$4:$F$80,4,FALSE) -> 1.2658121e+12 | H41: =+VLOOKUP(A41,gasto!$A$4:$F$80,5,FALSE) -> 1.8299014e+12 | I41: =+VLOOKUP(A41,gasto!$A$4:$F$80,6,FALSE) -> 1.8299014e+12 | J41: =+G41+D41 -> 21557379775986 | K41: =+H41+E41 -> 2.009029e+13 | L41: =+I41+F41 -> 2.009029e+13 | M41: =+IFERROR(K41*100/C41,0) -> 91.398469 | N41: =+IFERROR(L41*100/C41,0) -> 91.398469 | O41: =+L41/1000000 -> 20090290
A42: A-3-9-6-0-03 | B42: =+VLOOKUP(A42,gasto!$A$4:$B$100,2,FALSE) -> UPC´S R.S. USPEC | C42: =+VLOOKUP(A42,gasto!$A$4:$F$80,3,FALSE) -> 0 | D42: 0 | E42: 0 | F42: 0 | G42: =+VLOOKUP(A42,gasto!$A$4:$F$80,4,FALSE) -> 0 | H42: =+VLOOKUP(A42,gasto!$A$4:$F$80,5,FALSE) -> 0 | I42: =+VLOOKUP(A42,gasto!$A$4:$F$80,6,FALSE) -> 0 | J42: =+G42+D42 -> 0 | K42: =+H42+E42 -> 0 | L42: =+I42+F42 -> 0 | M42: =+IFERROR(K42*100/C42,0) -> 0 | N42: =+IFERROR(L42*100/C42,0) -> 0 | O42: =+L42/1000000 -> 0
A43: A-3-9-7-0 | B43: =+VLOOKUP(A43,gasto!$A$4:$B$100,2,FALSE) -> Prestaciones Excepcionales - Recobros | C43: =+SUM(C44:C47) -> 4.7355084e+12 | D43: 3.5350806e+12 | E43: 3.5350806e+12 | F43: 3.5350806e+12 | G43: =+SUM(G44:G47) -> 2.8103751e+11 | H43: =+SUM(H44:H47) -> 2.7613414e+11 | I43: =+SUM(I44:I47) -> 2.7613414e+11 | J43: =+SUM(J44:J47) -> 3.8161181e+12 | K43: =+SUM(K44:K47) -> 3.8112147e+12 | L43: =+SUM(L44:L47) -> 3.8112147e+12 | M43: =+IFERROR(K43*100/C43,0) -> 80.481638 | N43: =+IFERROR(L43*100/C43,0) -> 80.481638 | O43: =+L43/1000000 -> 3811214.7
A44: A-3-9-7-0-01 | B44: =+VLOOKUP(A44,gasto!$A$4:$B$100,2,FALSE) -> Recobros - Reembolsos Régimen Contributivo | C44: =+VLOOKUP(A44,gasto!$A$4:$F$80,3,FALSE) -> 1737663890220 | D44: 1.7294423e+12 | E44: 1.7294423e+12 | F44: 1.7294423e+12 | G44: =+VLOOKUP(A44,gasto!$A$4:$F$80,4,FALSE) -> 1.2391764e+08 | H44: =+VLOOKUP(A44,gasto!$A$4:$F$80,5,FALSE) -> 0 | I44: =+VLOOKUP(A44,gasto!$A$4:$F$80,6,FALSE) -> 0 | J44: =+G44+D44 -> 1.7295662e+12 | K44: =+H44+E44 -> 1.7294423e+12 | L44: =+I44+F44 -> 1.7294423e+12 | M44: =+IFERROR(K44*100/C44,0) -> 99.526859 | N44: =+IFERROR(L44*100/C44,0) -> 99.526859 | O44: =+L44/1000000 -> 1729442.3
A45: A-3-9-7-0-02 | B45: =+VLOOKUP(A45,gasto!$A$4:$B$100,2,FALSE) -> Recobros - Reembolsos Régimen Subsidiado - Tutelas | C45: =+VLOOKUP(A45,gasto!$A$4:$F$80,3,FALSE) -> 11190645546 | D45: 7.8008195e+09 | E45: 7.8008195e+09 | F45: 7.8008195e+09 | G45: =+VLOOKUP(A45,gasto!$A$4:$F$80,4,FALSE) -> 1.1098097e+08 | H45: =+VLOOKUP(A45,gasto!$A$4:$F$80,5,FALSE) -> 1.1098097e+08 | I45: =+VLOOKUP(A45,gasto!$A$4:$F$80,6,FALSE) -> 1.1098097e+08 | J45: =+G45+D45 -> 7.9118005e+09 | K45: =+H45+E45 -> 7.9118005e+09 | L45: =+I45+F45 -> 7.9118005e+09 | M45: =+IFERROR(K45*100/C45,0) -> 70.700126 | N45: =+IFERROR(L45*100/C45,0) -> 70.700126 | O45: =+L45/1000000 -> 7911.8005
A46: A-3-9-7-0-03 | B46: =+VLOOKUP(A46,gasto!$A$4:$B$100,2,FALSE) -> Glosa Transversal, literal c) artículo 73 Ley 1753/2015 – Par. 3 art. 237 Ley 1955/2019 | C46: =+VLOOKUP(A46,gasto!$A$4:$F$80,3,FALSE) -> 2.2265384e+11 | D46: 1.7515487e+11 | E46: 1.7515487e+11 | F46: 1.7515487e+11 | G46: =+VLOOKUP(A46,gasto!$A$4:$F$80,4,FALSE) -> 4.7794549e+09 | H46: =+VLOOKUP(A46,gasto!$A$4:$F$80,5,FALSE) -> 0 | I46: =+VLOOKUP(A46,gasto!$A$4:$F$80,6,FALSE) -> 0 | J46: =+G46+D46 -> 1.7993433e+11 | K46: =+H46+E46 -> 1.7515487e+11 | L46: =+I46+F46 -> 1.7515487e+11 | M46: =+IFERROR(K46*100/C46,0) -> 78.666899 | N46: =+IFERROR(L46*100/C46,0) -> 78.666899 | O46: =+L46/1000000 -> 175154.87
A47: A-3-9-7-0-04 | B47: Financiación de Obligaciones - Art 245 de la Ley 1955 de 2019 | C47: =+VLOOKUP(A47,gasto!$A$4:$F$80,3,FALSE) -> 2764000000000 | D47: 1.6226826e+12 | E47: 1.6226826e+12 | F47: 1.6226826e+12 | G47: =+VLOOKUP(A47,gasto!$A$4:$F$80,4,FALSE) -> 2.7602316e+11 | H47: =+VLOOKUP(A47,gasto!$A$4:$F$80,5,FALSE) -> 2.7602316e+11 | I47: =+VLOOKUP(A47,gasto!$A$4:$F$80,6,FALSE) -> 2.7602316e+11 | J47: =+G47+D47 -> 1.8987058e+12 | K47: =+H47+E47 -> 1.8987058e+12 | L47: =+I47+F47 -> 1.8987058e+12 | M47: =+IFERROR(K47*100/C47,0) -> 68.69413 | N47: =+IFERROR(L47*100/C47,0) -> 68.69413 | O47: =+L47/1000000 -> 1898705.8
A48: A-3-9-8-0 | B48: =+VLOOKUP(A48,gasto!$A$4:$B$100,2,FALSE) -> Atención en Salud, Transporte Primario, Indemnizaciones y Auxilio Funerario Víctimas | C48: =+SUM(C49:C54) -> 1.7291326e+11 | D48: 180222768589 | E48: 1.143673e+11 | F48: 1.143673e+11 | G48: =+SUM(G49:G54) -> -2.9011511e+10 | H48: =+SUM(H49:H54) -> 1.7358657e+10 | I48: =+SUM(I49:I54) -> 1.7358657e+10 | J48: =+SUM(J49:J54) -> 1.5121126e+11 | K48: =+SUM(K49:K54) -> 1.3172596e+11 | L48: =+SUM(L49:L54) -> 1.3172596e+11 | M48: =+IFERROR(K48*100/C48,0) -> 76.180368 | N48: =+IFERROR(L48*100/C48,0) -> 76.180368 | O48: =+L48/1000000 -> 131725.96
A49: A-3-9-8-0-01 | B49: =+VLOOKUP(A49,gasto!$A$4:$B$100,2,FALSE) -> Eventos terroristas | C49: =+VLOOKUP(A49,gasto!$A$4:$F$80,3,FALSE) -> 272244074 | D49: 1.8118396e+08 | E49: 49078022 | F49: 49078022 | G49: =+VLOOKUP(A49,gasto!$A$4:$F$80,4,FALSE) -> 0 | H49: =+VLOOKUP(A49,gasto!$A$4:$F$80,5,FALSE) -> 23950918 | I49: =+VLOOKUP(A49,gasto!$A$4:$F$80,6,FALSE) -> 23950918 | J49: =+G49+D49 -> 1.8118396e+08 | K49: =+H49+E49 -> 73028939 | L49: =+I49+F49 -> 73028939 | M49: =+IFERROR(K49*100/C49,0) -> 26.824804 | N49: =+IFERROR(L49*100/C49,0) -> 26.824804 | O49: =+L49/1000000 -> 73.028939
A50: A-3-9-8-0-02 | B50: =+VLOOKUP(A50,gasto!$A$4:$B$100,2,FALSE) -> Eventos Catastróficos | C50: =+VLOOKUP(A50,gasto!$A$4:$F$80,3,FALSE) -> 2733436752 | D50: 1.3814911e+09 | E50: 3.6218267e+08 | F50: 3.6218267e+08 | G50: =+VLOOKUP(A50,gasto!$A$4:$F$80,4,FALSE) -> 0 | H50: =+VLOOKUP(A50,gasto!$A$4:$F$80,5,FALSE) -> 18008389 | I50: =+VLOOKUP(A50,gasto!$A$4:$F$80,6,FALSE) -> 18008389 | J50: =+G50+D50 -> 1.3814911e+09 | K50: =+H50+E50 -> 3.8019106e+08 | L50: =+I50+F50 -> 3.8019106e+08 | M50: =+IFERROR(K50*100/C50,0) -> 13.908903 | N50: =+IFERROR(L50*100/C50,0) -> 13.908903 | O50: =+L50/1000000 -> 380.19106
A51: A-3-9-8-0-03 | B51: =+VLOOKUP(A51,gasto!$A$4:$B$100,2,FALSE) -> Accidentes de Transito | C51: =+VLOOKUP(A51,gasto!$A$4:$F$80,3,FALSE) -> 8.9425814e+10 | D51: 1.1843732e+11 | E51: 5.3733274e+10 | F51: 5.3733274e+10 | G51: =+VLOOKUP(A51,gasto!$A$4:$F$80,4,FALSE) -> -2.9011511e+10 | H51: =+VLOOKUP(A51,gasto!$A$4:$F$80,5,FALSE) -> 1.7316698e+10 | I51: =+VLOOKUP(A51,gasto!$A$4:$F$80,6,FALSE) -> 1.7316698e+10 | J51: =+G51+D51 -> 8.9425814e+10 | K51: =+H51+E51 -> 7.1049972e+10 | L51: =+I51+F51 -> 7.1049972e+10 | M51: =+IFERROR(K51*100/C51,0) -> 79.4513 | N51: =+IFERROR(L51*100/C51,0) -> 79.4513 | O51: =+L51/1000000 -> 71049.972
A52: A-3-9-8-0-04 | B52: =+VLOOKUP(A52,gasto!$A$4:$B$100,2,FALSE) -> Apoyo Reclamaciones Reserva especial | C52: =+VLOOKUP(A52,gasto!$A$4:$F$80,3,FALSE) -> 250000000 | D52: 0 | E52: 0 | F52: 0 | G52: =+VLOOKUP(A52,gasto!$A$4:$F$80,4,FALSE) -> 0 | H52: =+VLOOKUP(A52,gasto!$A$4:$F$80,5,FALSE) -> 0 | I52: =+VLOOKUP(A52,gasto!$A$4:$F$80,6,FALSE) -> 0 | J52: =+G52+D52 -> 0 | K52: =+H52+E52 -> 0 | L52: =+I52+F52 -> 0 | M52: =+IFERROR(K52*100/C52,0) -> 0 | N52: =+IFERROR(L52*100/C52,0) -> 0 | O52: =+L52/1000000 -> 0
A53: A-3-9-8-0-05 | B53: =+VLOOKUP(A53,gasto!$A$4:$B$100,2,FALSE) -> Oficina de Gestión Territorial, Emergencias y Desastres - Atención de urgencias Nacionales y Extranjeros - Zonas Fronterizas. Art 57 Ley 1815 de 2016 Oficina de Gestión | C53: =+VLOOKUP(A53,gasto!$A$4:$F$80,3,FALSE) -> 80222768589 | D53: 60222768589 | E53: 60222768589 | F53: 60222768589 | G53: =+VLOOKUP(A53,gasto!$A$4:$F$80,4,FALSE) -> 0 | H53: =+VLOOKUP(A53,gasto!$A$4:$F$80,5,FALSE) -> 0 | I53: =+VLOOKUP(A53,gasto!$A$4:$F$80,6,FALSE) -> 0 | J53: =+G53+D53 -> 60222768589 | K53: =+H53+E53 -> 60222768589 | L53: =+I53+F53 -> 60222768589 | M53: =+IFERROR(K53*100/C53,0) -> 75.069422 | N53: =+IFERROR(L53*100/C53,0) -> 75.069422 | O53: =+L53/1000000 -> 60222.769
A54: A-3-9-8-0-06 | B54: =+VLOOKUP(A54,gasto!$A$4:$B$100,2,FALSE) -> Apoyo Reclamaciones Victimas Poblaciòn desplazada | C54: =+VLOOKUP(A54,gasto!$A$4:$F$80,3,FALSE) -> 9000000 | D54: 0 | E54: 0 | F54: 0 | G54: =+VLOOKUP(A54,gasto!$A$4:$F$80,4,FALSE) -> 0 | H54: =+VLOOKUP(A54,gasto!$A$4:$F$80,5,FALSE) -> 0 | I54: =+VLOOKUP(A54,gasto!$A$4:$F$80,6,FALSE) -> 0 | J54: =+G54+D54 -> 0 | K54: =+H54+E54 -> 0 | L54: =+I54+F54 -> 0 | M54: =+IFERROR(K54*100/C54,0) -> 0 | N54: =+IFERROR(L54*100/C54,0) -> 0 | O54: =+L54/1000000 -> 0
A55: A-3-9-9-0 | B55: =+VLOOKUP(A55,gasto!$A$4:$B$100,2,FALSE) -> Fortalecimiento Red Nacional de Urgencias, Emergencia Sanitaria y eventos Catastróficos | C55: =+SUM(C56:C58) -> 3988276390 | D55: 3988276390 | E55: 0 | F55: 0 | G55: =+SUM(G56:G58) -> 0 | H55: =+SUM(H56:H58) -> 0 | I55: =+SUM(I56:I58) -> 0 | J55: =+SUM(J56:J58) -> 3988276390 | K55: =+SUM(K56:K58) -> 0 | L55: =+SUM(L56:L58) -> 0 | M55: =+IFERROR(K55*100/C55,0) -> 0 | N55: =+IFERROR(L55*100/C55,0) -> 0 | O55: =+L55/1000000 -> 0
A56: A-3-9-9-0-01 | B56: =+VLOOKUP(A56,gasto!$A$4:$B$100,2,FALSE) -> Oficina de Gestión Territorial, Emergencias y Desastres - Red Nacional de Urgencias | C56: =+VLOOKUP(A56,gasto!$A$4:$F$80,3,FALSE) -> 3988276390 | D56: 3988276390 | E56: 0 | F56: 0 | G56: =+VLOOKUP(A56,gasto!$A$4:$F$80,4,FALSE) -> 0 | H56: =+VLOOKUP(A56,gasto!$A$4:$F$80,5,FALSE) -> 0 | I56: =+VLOOKUP(A56,gasto!$A$4:$F$80,6,FALSE) -> 0 | J56: =+G56+D56 -> 3988276390 | K56: =+H56+E56 -> 0 | L56: =+I56+F56 -> 0 | M56: =+IFERROR(K56*100/C56,0) -> 0 | N56: =+IFERROR(L56*100/C56,0) -> 0 | O56: =+L56/1000000 -> 0
A57: A-3-9-9-0-02 | B57: =+VLOOKUP(A57,gasto!$A$4:$B$100,2,FALSE) -> Emergencia Sanitaria | C57: =+VLOOKUP(A57,gasto!$A$4:$F$80,3,FALSE) -> 0 | D57: 0 | E57: 0 | F57: 0 | G57: =+VLOOKUP(A57,gasto!$A$4:$F$80,4,FALSE) -> 0 | H57: =+VLOOKUP(A57,gasto!$A$4:$F$80,5,FALSE) -> 0 | I57: =+VLOOKUP(A57,gasto!$A$4:$F$80,6,FALSE) -> 0 | J57: =+G57+D57 -> 0 | K57: =+H57+E57 -> 0 | L57: =+I57+F57 -> 0 | M57: =+IFERROR(K57*100/C57,0) -> 0 | N57: =+IFERROR(L57*100/C57,0) -> 0 | O57: =+L57/1000000 -> 0
A58: A-3-9-9-0-03 | B58: =+VLOOKUP(A58,gasto!$A$4:$B$100,2,FALSE) -> Eventos Catastróficos | C58: =+VLOOKUP(A58,gasto!$A$4:$F$80,3,FALSE) -> 0 | D58: 0 | E58: 0 | F58: 0 | G58: =+VLOOKUP(A58,gasto!$A$4:$F$80,4,FALSE) -> 0 | H58: =+VLOOKUP(A58,gasto!$A$4:$F$80,5,FALSE) -> 0 | I58: =+VLOOKUP(A58,gasto!$A$4:$F$80,6,FALSE) -> 0 | J58: =+G58+D58 -> 0 | K58: =+H58+E58 -> 0 | L58: =+I58+F58 -> 0 | M58: =+IFERROR(K58*100/C58,0) -> 0 | N58: =+IFERROR(L58*100/C58,0) -> 0 | O58: =+L58/1000000 -> 0
A59: A-3-9-10-0 | B59: =+VLOOKUP(A59,gasto!$A$4:$B$100,2,FALSE) -> Otros Programas de Salud Promoción y prevención | C59: =+SUM(C60:C68) -> 19310454771 | D59: 18663300531 | E59: 7104195196 | F59: 7104195196 | G59: =+SUM(G60:G68) -> -3629272297 | H59: =+SUM(H60:H68) -> 3418750379 | I59: =+SUM(I60:I68) -> 3418750379 | J59: =+SUM(J60:J68) -> 15034028234 | K59: =+SUM(K60:K68) -> 10522945575 | L59: =+SUM(L60:L68) -> 10522945575 | M59: =+IFERROR(K59*100/C59,0) -> 54.493515 | N59: =+IFERROR(L59*100/C59,0) -> 54.493515 | O59: =+L59/1000000 -> 10522.946
A60: A-3-9-10-0-01 | B60: =+VLOOKUP(A60,gasto!$A$4:$B$100,2,FALSE) -> Dirección de Promoción y Prevención - Programas de Salud de P y P - VACUNAS | C60: =+VLOOKUP(A60,gasto!$A$4:$F$80,3,FALSE) -> 0 | D60: 0 | E60: 0 | F60: 0 | G60: =+VLOOKUP(A60,gasto!$A$4:$F$80,4,FALSE) -> 0 | H60: =+VLOOKUP(A60,gasto!$A$4:$F$80,5,FALSE) -> 0 | I60: =+VLOOKUP(A60,gasto!$A$4:$F$80,6,FALSE) -> 0 | J60: =+G60+D60 -> 0 | K60: =+H60+E60 -> 0 | L60: =+I60+F60 -> 0 | M60: =+IFERROR(K60*100/C60,0) -> 0 | N60: =+IFERROR(L60*100/C60,0) -> 0 | O60: =+L60/1000000 -> 0
A61: A-3-9-10-0-02 | B61: =+VLOOKUP(A61,gasto!$A$4:$B$100,2,FALSE) -> Oficina de Promoción Social - programa de Atención Psicosocial y Salud Integral a Víctimas del Conflicto Armado Programa PAPSIVI | C61: =+VLOOKUP(A61,gasto!$A$4:$F$80,3,FALSE) -> 14873478755 | D61: 18502751052 | E61: 6943645717 | F61: 6943645717 | G61: =+VLOOKUP(A61,gasto!$A$4:$F$80,4,FALSE) -> -3629272297 | H61: =+VLOOKUP(A61,gasto!$A$4:$F$80,5,FALSE) -> 3418750379 | I61: =+VLOOKUP(A61,gasto!$A$4:$F$80,6,FALSE) -> 3418750379 | J61: =+G61+D61 -> 14873478755 | K61: =+H61+E61 -> 10362396096 | L61: =+I61+F61 -> 10362396096 | M61: =+IFERROR(K61*100/C61,0) -> 69.670292 | N61: =+IFERROR(L61*100/C61,0) -> 69.670292 | O61: =+L61/1000000 -> 10362.396
A62: A-3-9-10-0-03 | B62: =+VLOOKUP(A62,gasto!$A$4:$B$100,2,FALSE) -> Programa mujeres víctimas de la violencia | C62: =+VLOOKUP(A62,gasto!$A$4:$F$80,3,FALSE) -> 0 | D62: 0 | E62: 0 | F62: 0 | G62: =+VLOOKUP(A62,gasto!$A$4:$F$80,4,FALSE) -> 0 | H62: =+VLOOKUP(A62,gasto!$A$4:$F$80,5,FALSE) -> 0 | I62: =+VLOOKUP(A62,gasto!$A$4:$F$80,6,FALSE) -> 0 | J62: =+G62+D62 -> 0 | K62: =+H62+E62 -> 0 | L62: =+I62+F62 -> 0 | M62: =+IFERROR(K62*100/C62,0) -> 0 | N62: =+IFERROR(L62*100/C62,0) -> 0 | O62: =+L62/1000000 -> 0
A63: A-3-9-10-0-04 | B63: =+VLOOKUP(A63,gasto!$A$4:$B$100,2,FALSE) -> Otros Programas de Salud diferentes a los anteriores | C63: =+VLOOKUP(A63,gasto!$A$4:$F$80,3,FALSE) -> 0 | D63: 0 | E63: 0 | F63: 0 | G63: =+VLOOKUP(A63,gasto!$A$4:$F$80,4,FALSE) -> 0 | H63: =+VLOOKUP(A63,gasto!$A$4:$F$80,5,FALSE) -> 0 | I63: =+VLOOKUP(A63,gasto!$A$4:$F$80,6,FALSE) -> 0 | J63: =+G63+D63 -> 0 | K63: =+H63+E63 -> 0 | L63: =+I63+F63 -> 0 | M63: =+IFERROR(K63*100/C63,0) -> 0 | N63: =+IFERROR(L63*100/C63,0) -> 0 | O63: =+L63/1000000 -> 0
A64: A-3-9-10-0-05 | B64: =+VLOOKUP(A64,gasto!$A$4:$B$100,2,FALSE) -> Campañas de Prevencion de la Violencia y Promoción de la Convivencia Pacifica a Nivel Nacional o Territorial | C64: =+VLOOKUP(A64,gasto!$A$4:$F$80,3,FALSE) -> 1538976016 | D64: 0 | E64: 0 | F64: 0 | G64: =+VLOOKUP(A64,gasto!$A$4:$F$80,4,FALSE) -> 0 | H64: =+VLOOKUP(A64,gasto!$A$4:$F$80,5,FALSE) -> 0 | I64: =+VLOOKUP(A64,gasto!$A$4:$F$80,6,FALSE) -> 0 | J64: =+G64+D64 -> 0 | K64: =+H64+E64 -> 0 | L64: =+I64+F64 -> 0 | M64: =+IFERROR(K64*100/C64,0) -> 0 | N64: =+IFERROR(L64*100/C64,0) -> 0 | O64: =+L64/1000000 -> 0
A65: A-3-9-10-0-06 | B65: =+VLOOKUP(A65,gasto!$A$4:$B$100,2,FALSE) -> Prevención y Sanción de Formas de Violencia y discriminación Contra las Mujeres | C65: =+VLOOKUP(A65,gasto!$A$4:$F$80,3,FALSE) -> 0 | D65: 0 | E65: 0 | F65: 0 | G65: =+VLOOKUP(A65,gasto!$A$4:$F$80,4,FALSE) -> 0 | H65: =+VLOOKUP(A65,gasto!$A$4:$F$80,5,FALSE) -> 0 | I65: =+VLOOKUP(A65,gasto!$A$4:$F$80,6,FALSE) -> 0 | J65: =+G65+D65 -> 0 | K65: =+H65+E65 -> 0 | L65: =+I65+F65 -> 0 | M65: =+IFERROR(K65*100/C65,0) -> 0 | N65: =+IFERROR(L65*100/C65,0) -> 0 | O65: =+L65/1000000 -> 0
A66: A-3-9-10-0-07 | B66: =+VLOOKUP(A66,gasto!$A$4:$B$100,2,FALSE) -> Atención Usuario Protesis PIP Resolución 0258 de 2012 | C66: =+VLOOKUP(A66,gasto!$A$4:$F$80,3,FALSE) -> 160000000 | D66: 0 | E66: 0 | F66: 0 | G66: =+VLOOKUP(A66,gasto!$A$4:$F$80,4,FALSE) -> 0 | H66: =+VLOOKUP(A66,gasto!$A$4:$F$80,5,FALSE) -> 0 | I66: =+VLOOKUP(A66,gasto!$A$4:$F$80,6,FALSE) -> 0 | J66: =+G66+D66 -> 0 | K66: =+H66+E66 -> 0 | L66: =+I66+F66 -> 0 | M66: =+IFERROR(K66*100/C66,0) -> 0 | N66: =+IFERROR(L66*100/C66,0) -> 0 | O66: =+L66/1000000 -> 0
A67: A-3-9-10-0-08 | B67: =+VLOOKUP(A67,gasto!$A$4:$B$100,2,FALSE) -> Déficit Cajas de Compensación Familiar - Balance | C67: =+VLOOKUP(A67,gasto!$A$4:$F$80,3,FALSE) -> 2000000000 | D67: 160549479 | E67: 160549479 | F67: 160549479 | G67: =+VLOOKUP(A67,gasto!$A$4:$F$80,4,FALSE) -> 0 | H67: =+VLOOKUP(A67,gasto!$A$4:$F$80,5,FALSE) -> 0 | I67: =+VLOOKUP(A67,gasto!$A$4:$F$80,6,FALSE) -> 0 | J67: =+G67+D67 -> 160549479 | K67: =+H67+E67 -> 160549479 | L67: =+I67+F67 -> 160549479 | M67: =+IFERROR(K67*100/C67,0) -> 8.0274739 | N67: =+IFERROR(L67*100/C67,0) -> 8.0274739 | O67: =+L67/1000000 -> 160.54948
A68: A-3-9-10-0-09 | B68: =+VLOOKUP(A68,gasto!$A$4:$B$100,2,FALSE) -> Certificado de Discapacidad, Suministro de Fórmula Terapéutica | C68: =+VLOOKUP(A68,gasto!$A$4:$F$80,3,FALSE) -> 738000000 | D68: 0 | E68: 0 | F68: 0 | G68: =+VLOOKUP(A68,gasto!$A$4:$F$80,4,FALSE) -> 0 | H68: =+VLOOKUP(A68,gasto!$A$4:$F$80,5,FALSE) -> 0 | I68: =+VLOOKUP(A68,gasto!$A$4:$F$80,6,FALSE) -> 0 | J68: =+G68+D68 -> 0 | K68: =+H68+E68 -> 0 | L68: =+I68+F68 -> 0 | M68: =+IFERROR(K68*100/C68,0) -> 0 | N68: =+IFERROR(L68*100/C68,0) -> 0 | O68: =+L68/1000000 -> 0
A69: A-3-9-11-0 | B69: =+VLOOKUP(A69,gasto!$A$4:$B$100,2,FALSE) -> Recursos con destinación específica | C69: =+SUM(C70:C79) -> 218987631076 | D69: 96969801233 | E69: 1.0880443e+10 | F69: 1.0880443e+10 | G69: =+SUM(G70:G79) -> 0 | H69: =+SUM(H70:H79) -> 1213649 | I69: =+SUM(I70:I79) -> 1213649 | J69: =+SUM(J70:J79) -> 96969801233 | K69: =+SUM(K70:K79) -> 1.0881657e+10 | L69: =+SUM(L70:L79) -> 1.0881657e+10 | M69: =+IFERROR(K69*100/C69,0) -> 4.9690738 | N69: =+IFERROR(L69*100/C69,0) -> 4.9690738 | O69: =+L69/1000000 -> 10881.657
A70: A-3-9-11-0-01 | B70: =+VLOOKUP(A70,gasto!$A$4:$B$100,2,FALSE) -> Pago a IPS de servicios prestados a la población pobre no asegurada y servicios no incluidos en el Plan de beneficios Pago a IPS de servicios prestados a la población, exceden(Art. 3 Ley 1608 de 2013) | C70: =+VLOOKUP(A70,gasto!$A$4:$F$80,3,FALSE) -> 5801668388 | D70: 0 | E70: 0 | F70: 0 | G70: =+VLOOKUP(A70,gasto!$A$4:$F$80,4,FALSE) -> 0 | H70: =+VLOOKUP(A70,gasto!$A$4:$F$80,5,FALSE) -> 0 | I70: =+VLOOKUP(A70,gasto!$A$4:$F$80,6,FALSE) -> 0 | J70: =+G70+D70 -> 0 | K70: =+H70+E70 -> 0 | L70: =+I70+F70 -> 0 | M70: =+IFERROR(K70*100/C70,0) -> 0 | N70: =+IFERROR(L70*100/C70,0) -> 0 | O70: =+L70/1000000 -> 0
A71: A-3-9-11-0-02 | B71: =+VLOOKUP(A71,gasto!$A$4:$B$100,2,FALSE) -> Reconocimiento de deuda por contratos del Régimen Subsidiado realizados hasta marzo 31 de 2011- Recursos LOTTO en Línea – FONPET | C71: =+VLOOKUP(A71,gasto!$A$4:$F$80,3,FALSE) -> 5000000000 | D71: 0 | E71: 0 | F71: 0 | G71: =+VLOOKUP(A71,gasto!$A$4:$F$80,4,FALSE) -> 0 | H71: =+VLOOKUP(A71,gasto!$A$4:$F$80,5,FALSE) -> 0 | I71: =+VLOOKUP(A71,gasto!$A$4:$F$80,6,FALSE) -> 0 | J71: =+G71+D71 -> 0 | K71: =+H71+E71 -> 0 | L71: =+I71+F71 -> 0 | M71: =+IFERROR(K71*100/C71,0) -> 0 | N71: =+IFERROR(L71*100/C71,0) -> 0 | O71: =+L71/1000000 -> 0
A72: A-3-9-11-0-03 | B72: =+VLOOKUP(A72,gasto!$A$4:$B$100,2,FALSE) -> Reconocimiento de deuda por contratos del Régimen Subsidiado realizados hasta marzo 31 de 2011- Recursos FAEP | C72: =+VLOOKUP(A72,gasto!$A$4:$F$80,3,FALSE) -> 800000000 | D72: 0 | E72: 0 | F72: 0 | G72: =+VLOOKUP(A72,gasto!$A$4:$F$80,4,FALSE) -> 0 | H72: =+VLOOKUP(A72,gasto!$A$4:$F$80,5,FALSE) -> 0 | I72: =+VLOOKUP(A72,gasto!$A$4:$F$80,6,FALSE) -> 0 | J72: =+G72+D72 -> 0 | K72: =+H72+E72 -> 0 | L72: =+I72+F72 -> 0 | M72: =+IFERROR(K72*100/C72,0) -> 0 | N72: =+IFERROR(L72*100/C72,0) -> 0 | O72: =+L72/1000000 -> 0
A73: A-3-9-11-0-04 | B73: =+VLOOKUP(A73,gasto!$A$4:$B$100,2,FALSE) -> Pago de deudas Régimen Subsidiado – Artículo 275 de la Ley 1450 de 2011 - SGP Libre Inversión | C73: =+VLOOKUP(A73,gasto!$A$4:$F$80,3,FALSE) -> 20000000000 | D73: 0 | E73: 0 | F73: 0 | G73: =+VLOOKUP(A73,gasto!$A$4:$F$80,4,FALSE) -> 0 | H73: =+VLOOKUP(A73,gasto!$A$4:$F$80,5,FALSE) -> 0 | I73: =+VLOOKUP(A73,gasto!$A$4:$F$80,6,FALSE) -> 0 | J73: =+G73+D73 -> 0 | K73: =+H73+E73 -> 0 | L73: =+I73+F73 -> 0 | M73: =+IFERROR(K73*100/C73,0) -> 0 | N73: =+IFERROR(L73*100/C73,0) -> 0 | O73: =+L73/1000000 -> 0
A74: A-3-9-11-0-05 | B74: =+VLOOKUP(A74,gasto!$A$4:$B$100,2,FALSE) -> Excedentes de Aportes Patronales / Resolución 2360 de 2016 | C74: =+VLOOKUP(A74,gasto!$A$4:$F$80,3,FALSE) -> 49454127709 | D74: 49454127709 | E74: 7.5142741e+09 | F74: 7.5142741e+09 | G74: =+VLOOKUP(A74,gasto!$A$4:$F$80,4,FALSE) -> 0 | H74: =+VLOOKUP(A74,gasto!$A$4:$F$80,5,FALSE) -> 0 | I74: =+VLOOKUP(A74,gasto!$A$4:$F$80,6,FALSE) -> 0 | J74: =+G74+D74 -> 49454127709 | K74: =+H74+E74 -> 7.5142741e+09 | L74: =+I74+F74 -> 7.5142741e+09 | M74: =+IFERROR(K74*100/C74,0) -> 15.194433 | N74: =+IFERROR(L74*100/C74,0) -> 15.194433 | O74: =+L74/1000000 -> 7514.2741
A75: A-3-9-11-0-06 | B75: =+VLOOKUP(A75,gasto!$A$4:$B$100,2,FALSE) -> Regalías – Art. 5 Ley 1797 de 2016 | C75: =+VLOOKUP(A75,gasto!$A$4:$F$80,3,FALSE) -> 3000000000 | D75: 0 | E75: 0 | F75: 0 | G75: =+VLOOKUP(A75,gasto!$A$4:$F$80,4,FALSE) -> 0 | H75: =+VLOOKUP(A75,gasto!$A$4:$F$80,5,FALSE) -> 0 | I75: =+VLOOKUP(A75,gasto!$A$4:$F$80,6,FALSE) -> 0 | J75: =+G75+D75 -> 0 | K75: =+H75+E75 -> 0 | L75: =+I75+F75 -> 0 | M75: =+IFERROR(K75*100/C75,0) -> 0 | N75: =+IFERROR(L75*100/C75,0) -> 0 | O75: =+L75/1000000 -> 0
A76: A-3-9-11-0-07 | B76: =+VLOOKUP(A76,gasto!$A$4:$B$100,2,FALSE) -> Otros Recursos con Destinación Especifica | C76: =+VLOOKUP(A76,gasto!$A$4:$F$80,3,FALSE) -> 21441839921 | D76: 0 | E76: 0 | F76: 0 | G76: =+VLOOKUP(A76,gasto!$A$4:$F$80,4,FALSE) -> 0 | H76: =+VLOOKUP(A76,gasto!$A$4:$F$80,5,FALSE) -> 0 | I76: =+VLOOKUP(A76,gasto!$A$4:$F$80,6,FALSE) -> 0 | J76: =+G76+D76 -> 0 | K76: =+H76+E76 -> 0 | L76: =+I76+F76 -> 0 | M76: =+IFERROR(K76*100/C76,0) -> 0 | N76: =+IFERROR(L76*100/C76,0) -> 0 | O76: =+L76/1000000 -> 0
A77: A-3-9-11-0-08 | B77: =+VLOOKUP(A77,gasto!$A$4:$B$100,2,FALSE) -> Recursos CCF / FOSFEC - Ley 1929 de 2018 | C77: =+VLOOKUP(A77,gasto!$A$4:$F$80,3,FALSE) -> 36000000000 | D77: 0 | E77: 0 | F77: 0 | G77: =+VLOOKUP(A77,gasto!$A$4:$F$80,4,FALSE) -> 0 | H77: =+VLOOKUP(A77,gasto!$A$4:$F$80,5,FALSE) -> 0 | I77: =+VLOOKUP(A77,gasto!$A$4:$F$80,6,FALSE) -> 0 | J77: =+G77+D77 -> 0 | K77: =+H77+E77 -> 0 | L77: =+I77+F77 -> 0 | M77: =+IFERROR(K77*100/C77,0) -> 0 | N77: =+IFERROR(L77*100/C77,0) -> 0 | O77: =+L77/1000000 -> 0
A78: A-3-9-11-0-09 | B78: =+VLOOKUP(A78,gasto!$A$4:$B$100,2,FALSE) -> Saneamiento aportes patronales SGP | C78: =+VLOOKUP(A78,gasto!$A$4:$F$80,3,FALSE) -> 76869459827 | D78: 46895138293 | E78: 3366169361 | F78: 3366169361 | G78: =+VLOOKUP(A78,gasto!$A$4:$F$80,4,FALSE) -> 0 | H78: =+VLOOKUP(A78,gasto!$A$4:$F$80,5,FALSE) -> 1213649 | I78: =+VLOOKUP(A78,gasto!$A$4:$F$80,6,FALSE) -> 1213649 | J78: =+G78+D78 -> 46895138293 | K78: =+H78+E78 -> 3367383010 | L78: =+I78+F78 -> 3367383010 | M78: =+IFERROR(K78*100/C78,0) -> 4.3806513 | N78: =+IFERROR(L78*100/C78,0) -> 4.3806513 | O78: =+L78/1000000 -> 3367.383
A79: A-3-9-11-0-10 | B79: =+VLOOKUP(A79,gasto!$A$4:$B$100,2,FALSE) -> Rendimientos Financieros de los Saldos no Compensados de los Aportes Patronales según Art. 12 Decreto 1636 de 2016 | C79: =+VLOOKUP(A79,gasto!$A$4:$F$80,3,FALSE) -> 620535231 | D79: 620535231 | E79: 0 | F79: 0 | G79: =+VLOOKUP(A79,gasto!$A$4:$F$80,4,FALSE) -> 0 | H79: =+VLOOKUP(A79,gasto!$A$4:$F$80,5,FALSE) -> 0 | I79: =+VLOOKUP(A79,gasto!$A$4:$F$80,6,FALSE) -> 0 | J79: =+G79+D79 -> 620535231 | K79: =+H79+E79 -> 0 | L79: =+I79+F79 -> 0 | M79: =+IFERROR(K79*100/C79,0) -> 0 | N79: =+IFERROR(L79*100/C79,0) -> 0 | O79: =+L79/1000000 -> 0
A80: A-3-9-12-0 | B80: =+VLOOKUP(A80,gasto!$A$4:$B$100,2,FALSE) -> Pago Obligaciones ESE´S con Recursos FONSAET | C80: =+C81 -> 95551523562 | D80: 0 | E80: 0 | F80: 0 | G80: =+G81 -> 5.6425054e+10 | H80: =+H81 -> 0 | I80: =+I81 -> 0 | J80: =+J81 -> 5.6425054e+10 | K80: =+K81 -> 0 | L80: =+L81 -> 0 | M80: =+IFERROR(K80*100/C80,0) -> 0 | N80: =+IFERROR(L80*100/C80,0) -> 0 | O80: =+L80/1000000 -> 0
A81: A-3-9-12-0-01 | B81: =+VLOOKUP(A81,gasto!$A$4:$B$100,2,FALSE) -> Pago Obligaciones EPS FONSAET | C81: =+VLOOKUP(A81,gasto!$A$4:$F$80,3,FALSE) -> 95551523562 | D81: 0 | E81: 0 | F81: 0 | G81: =+VLOOKUP(A81,gasto!$A$4:$F$80,4,FALSE) -> 5.6425054e+10 | H81: =+VLOOKUP(A81,gasto!$A$4:$F$80,5,FALSE) -> 0 | I81: =+VLOOKUP(A81,gasto!$A$4:$F$80,6,FALSE) -> 0 | J81: =+G81+D81 -> 5.6425054e+10 | K81: =+H81+E81 -> 0 | L81: =+I81+F81 -> 0 | M81: =+IFERROR(K81*100/C81,0) -> 0 | N81: =+IFERROR(L81*100/C81,0) -> 0 | O81: =+L81/1000000 -> 0
A82: A-3-9-13-0 | B82: =+VLOOKUP(A82,gasto!$A$4:$B$100,2,FALSE) -> Reconocimiento Rendimientos Financieros cuentas de recaudo EPS SSF | C82: =+C83 -> 8625081557 | D82: 8625081557 | E82: 7019264463 | F82: 7019264463 | G82: =+G83 -> 0 | H82: =+H83 -> 628795606 | I82: =+I83 -> 628795606 | J82: =+J83 -> 8625081557 | K82: =+K83 -> 7648060069 | L82: =+L83 -> 7648060069 | M82: =+IFERROR(K82*100/C82,0) -> 88.672322 | N82: =+IFERROR(L82*100/C82,0) -> 88.672322 | O82: =+L82/1000000 -> 7648.0601
A83: A-3-9-13-0-01 | B83: =+VLOOKUP(A83,gasto!$A$4:$B$100,2,FALSE) -> Rendimientos Financieros EPS SSF | C83: =+VLOOKUP(A83,gasto!A2:K79,3,FALSE) -> 8625081557 | D83: 8625081557 | E83: 7019264463 | F83: 7019264463 | G83: =+VLOOKUP(A83,gasto!$A$4:$F$80,4,FALSE) -> 0 | H83: =+VLOOKUP(A83,gasto!$A$4:$F$80,5,FALSE) -> 628795606 | I83: =+VLOOKUP(A83,gasto!$A$4:$F$80,6,FALSE) -> 628795606 | J83: =+G83+D83 -> 8625081557 | K83: =+H83+E83 -> 7648060069 | L83: =+I83+F83 -> 7648060069 | M83: =+IFERROR(K83*100/C83,0) -> 88.672322 | N83: =+IFERROR(L83*100/C83,0) -> 88.672322 | O83: =+L83/1000000 -> 7648.0601
A84: A-3-9-14-0 | B84: =+VLOOKUP(A84,gasto!$A$4:$B$100,2,FALSE) -> Apoyo Financiero y Fortalecimiento Patrimonial a las Entidades del Sector Salud | C84: =+SUM(C85:C87) -> 40000000000 | D84: 40000000000 | E84: 0 | F84: 0 | G84: =+SUM(G85:G87) -> 0 | H84: =+SUM(H85:H87) -> 40000000000 | I84: =+SUM(I85:I87) -> 20000000000 | J84: =+SUM(J85:J87) -> 40000000000 | K84: =+SUM(K85:K87) -> 40000000000 | L84: =+SUM(L85:L87) -> 20000000000 | M84: =+IFERROR(K84*100/C84,0) -> 100 | N84: =+IFERROR(L84*100/C84,0) -> 50 | O84: =+L84/1000000 -> 20000
A85: A-3-9-14-0-01 | B85: =+VLOOKUP(A85,gasto!$A$4:$B$100,2,FALSE) -> Operaciones de Compra de Cartera | C85: =+VLOOKUP(A85,gasto!$A$4:$F$100,3,FALSE) -> 0 | D85: 0 | E85: 0 | F85: 0 | G85: =+VLOOKUP(A85,gasto!$A$4:$F$100,4,FALSE) -> 0 | H85: =+VLOOKUP(A85,gasto!$A$4:$F$100,5,FALSE) -> 0 | I85: =+VLOOKUP(A85,gasto!$A$4:$F$100,6,FALSE) -> 0 | J85: =+G85+D85 -> 0 | K85: =+H85+E85 -> 0 | L85: =+I85+F85 -> 0 | M85: =+IFERROR(K85*100/C85,0) -> 0 | N85: =+IFERROR(L85*100/C85,0) -> 0 | O85: =+L85/1000000 -> 0
A86: A-3-9-14-0-02 | B86: =+VLOOKUP(A86,gasto!$A$4:$B$100,2,FALSE) -> Operaciones de Fortalecimiento Patrimonial Tasa Compensada | C86: =+VLOOKUP(A86,gasto!$A$4:$F$100,3,FALSE) -> 40000000000 | D86: 40000000000 | E86: 0 | F86: 0 | G86: =+VLOOKUP(A86,gasto!$A$4:$F$100,4,FALSE) -> 0 | H86: =+VLOOKUP(A86,gasto!$A$4:$F$100,5,FALSE) -> 40000000000 | I86: =+VLOOKUP(A86,gasto!$A$4:$F$100,6,FALSE) -> 20000000000 | J86: =+G86+D86 -> 40000000000 | K86: =+H86+E86 -> 40000000000 | L86: =+I86+F86 -> 20000000000 | M86: =+IFERROR(K86*100/C86,0) -> 100 | N86: =+IFERROR(L86*100/C86,0) -> 50 | O86: =+L86/1000000 -> 20000
A87: A-3-9-14-0-03 | B87: =+VLOOKUP(A87,gasto!$A$4:$B$100,2,FALSE) -> Operaciones de Fortalecimiento Patrimonial - Bocas | C87: =+VLOOKUP(A87,gasto!$A$4:$F$100,3,FALSE) -> 0 | D87: 0 | E87: 0 | F87: 0 | G87: =+VLOOKUP(A87,gasto!$A$4:$F$100,4,FALSE) -> 0 | H87: =+VLOOKUP(A87,gasto!$A$4:$F$100,5,FALSE) -> 0 | I87: =+VLOOKUP(A87,gasto!$A$4:$F$100,6,FALSE) -> 0 | J87: =+G87+D87 -> 0 | K87: =+H87+E87 -> 0 | L87: =+I87+F87 -> 0 | M87: =+IFERROR(K87*100/C87,0) -> 0 | N87: =+IFERROR(L87*100/C87,0) -> 0 | O87: =+L87/1000000 -> 0
A88: A-3-9-15-0 | B88: =+VLOOKUP(A88,gasto!$A$4:$B$100,2,FALSE) -> Devoluciones | C88: =+SUM(C89:C92) -> 179398901661 | D88: 1.6991024e+11 | E88: 1.4531443e+11 | F88: 1.4531443e+11 | G88: =+SUM(G89:G92) -> 4898865 | H88: =+SUM(H89:H92) -> 57530224 | I88: =+SUM(I89:I92) -> 57530224 | J88: =+G88+D88 -> 1.6991513e+11 | K88: =+H88+E88 -> 1.4537196e+11 | L88: =+I88+F88 -> 1.4537196e+11 | M88: =+IFERROR(K88*100/C88,0) -> 81.032804 | N88: =+IFERROR(L88*100/C88,0) -> 81.032804 | O88: =+L88/1000000 -> 145371.96
A89: A-3-9-15-0-01 | B89: =+VLOOKUP(A89,gasto!$A$4:$B$100,2,FALSE) -> Devoluciones Aportes y Cotizaciones No Conciliadas Vigencia Anterior | C89: =+VLOOKUP(A89,gasto!$A$4:$F$100,3,FALSE) -> 9047713371 | D89: 9047713371 | E89: 997444711 | F89: 997444711 | G89: =+VLOOKUP(A89,gasto!$A$4:$F$100,4,FALSE) -> 0 | H89: =+VLOOKUP(A89,gasto!$A$4:$F$100,5,FALSE) -> 37314241 | I89: =+VLOOKUP(A89,gasto!$A$4:$F$100,6,FALSE) -> 37314241 | J89: =+G89+D89 -> 9047713371 | K89: =+H89+E89 -> 1034758952 | L89: =+I89+F89 -> 1034758952 | M89: =+IFERROR(K89*100/C89,0) -> 11.43669 | N89: =+IFERROR(L89*100/C89,0) -> 11.43669 | O89: =+L89/1000000 -> 1034.759
A90: A-3-9-15-0-02 | B90: =+VLOOKUP(A90,gasto!$A$4:$B$100,2,FALSE) -> Devoluciones de Aportes de REX | C90: =+VLOOKUP(A90,gasto!$A$4:$F$100,3,FALSE) -> 250000000 | D90: 250000000 | E90: 49226013 | F90: 49226013 | G90: =+VLOOKUP(A90,gasto!$A$4:$F$100,4,FALSE) -> 0 | H90: =+VLOOKUP(A90,gasto!$A$4:$F$100,5,FALSE) -> 9589536 | I90: =+VLOOKUP(A90,gasto!$A$4:$F$100,6,FALSE) -> 9589536 | J90: =+G90+D90 -> 250000000 | K90: =+H90+E90 -> 58815549 | L90: =+I90+F90 -> 58815549 | M90: =+IFERROR(K90*100/C90,0) -> 23.52622 | N90: =+IFERROR(L90*100/C90,0) -> 23.52622 | O90: =+L90/1000000 -> 58.815549
A91: A-3-9-15-0-03 | B91: =+VLOOKUP(A91,gasto!$A$4:$B$100,2,FALSE) -> Devoluciones Recursos Entidades Territoriales | C91: =+VLOOKUP(A91,gasto!$A$4:$F$100,3,FALSE) -> 160101188290 | D91: 160101188290 | E91: 1.4376258e+11 | F91: 1.4376258e+11 | G91: =+VLOOKUP(A91,gasto!$A$4:$F$100,4,FALSE) -> 0 | H91: =+VLOOKUP(A91,gasto!$A$4:$F$100,5,FALSE) -> 0 | I91: =+VLOOKUP(A91,gasto!$A$4:$F$100,6,FALSE) -> 0 | J91: =+G91+D91 -> 160101188290 | K91: =+H91+E91 -> 1.4376258e+11 | L91: =+I91+F91 -> 1.4376258e+11 | M91: =+IFERROR(K91*100/C91,0) -> 89.794822 | N91: =+IFERROR(L91*100/C91,0) -> 89.794822 | O91: =+L91/1000000 -> 143762.58
A92: A-3-9-15-0-04 | B92: =+VLOOKUP(A92,gasto!$A$4:$B$100,2,FALSE) -> Otras Devoluciones | C92: =+VLOOKUP(A92,gasto!$A$4:$F$100,3,FALSE) -> 10000000000 | D92: 5.1133413e+08 | E92: 5.0518255e+08 | F92: 5.0518255e+08 | G92: =+VLOOKUP(A92,gasto!$A$4:$F$100,4,FALSE) -> 4898865 | H92: =+VLOOKUP(A92,gasto!$A$4:$F$100,5,FALSE) -> 10626447 | I92: =+VLOOKUP(A92,gasto!$A$4:$F$100,6,FALSE) -> 10626447 | J92: =+G92+D92 -> 5.1623299e+08 | K92: =+H92+E92 -> 5.1580899e+08 | L92: =+I92+F92 -> 5.1580899e+08 | M92: =+IFERROR(K92*100/C92,0) -> 5.1580899 | N92: =+IFERROR(L92*100/C92,0) -> 5.1580899 | O92: =+L92/1000000 -> 515.80899
A93: A-3-9-16-0 | B93: =+VLOOKUP(A93,gasto!$A$4:$B$100,2,FALSE) -> Reprogramación - Vigencia Anteriores | C93: =+VLOOKUP(A93,gasto!$A$4:$F$100,3,FALSE) -> 122832640438 | D93: 100000000000 | E93: 165011057 | F93: 165011057 | G93: =+SUM(G94) -> 0 | H93: =+SUM(H94) -> 0 | I93: =+SUM(I94) -> 0 | J93: =+G93+D93 -> 100000000000 | K93: =+H93+E93 -> 165011057 | L93: =+I93+F93 -> 165011057 | M93: =+IFERROR(K93*100/C93,0) -> 0.13433812 | N93: =+IFERROR(L93*100/C93,0) -> 0.13433812 | O93: =+L93/1000000 -> 165.01106
A94: A-3-9-16-0-01 | B94: =+VLOOKUP(A94,gasto!$A$4:$B$100,2,FALSE) -> Reprogramaciones - Vigencias Anteriores | C94: =+VLOOKUP(A94,gasto!$A$4:$F$100,3,FALSE) -> 122832640438 | D94: 100000000000 | E94: 165011057 | F94: 165011057 | G94: =+VLOOKUP(A94,gasto!$A$4:$F$100,4,FALSE) -> 0 | H94: =+VLOOKUP(A94,gasto!$A$4:$F$100,5,FALSE) -> 0 | I94: =+VLOOKUP(A94,gasto!$A$4:$F$100,6,FALSE) -> 0 | J94: =+G94+D94 -> 100000000000 | K94: =+H94+E94 -> 165011057 | L94: =+I94+F94 -> 165011057 | M94: =+IFERROR(K94*100/C94,0) -> 0.13433812 | N94: =+IFERROR(L94*100/C94,0) -> 0.13433812 | O94: =+L94/1000000 -> 165.01106
A95: A-9-9-9-9 | B95: =+VLOOKUP(A95,gasto!$A$4:$B$100,2,FALSE) -> Disponibilidad Final | C95: =+VLOOKUP(A95,gasto!$A$4:$F$100,3,FALSE) -> 254007875000 | D95: 0 | E95: 0 | F95: 0 | G95: =+VLOOKUP(A95,gasto!$A:$K,4,FALSE) -> 0 | H95: =+VLOOKUP(A95,gasto!$A:$K,4,FALSE) -> 0 | I95: =+VLOOKUP(A95,gasto!$A:$K,4,FALSE) -> 0 | J95: =+G95+D95 -> 0 | K95: =+H95+E95 -> 0 | L95: =+I95+F95 -> 0 | M95: =+IFERROR(K95*100/C95,0) -> 0 | N95: =+IFERROR(L95*100/C95,0) -> 0 | O95: =+L95/1000000 -> 0
A97: TOTAL | B97: TOTAL | C97: =+C95+C13 -> 5.334758e+13 | D97: 4.6380563e+13 | E97: 4.2615021e+13 | F97: 4.2615021e+13 | G97: =+G95+G13 -> 4.8857093e+12 | H97: =+H95+H13 -> 4.1824172e+12 | I97: =+I95+I13 -> 4.1624172e+12 | J97: =+J95+J13 -> 5.1266272e+13 | K97: =+K95+K13 -> 4.6797438e+13 | L97: =+L95+L13 -> 4.6777438e+13 | M97: =+IFERROR(K97*100/C97,0) -> 87.721764 | N97: =+IFERROR(L97*100/C97,0) -> 87.684274
C98: 53347579621981 | D98: 4.6380563e+13 | E98: 4.2615021e+13 | F98: 4.2615021e+13 | G98: 4.8857093e+12 | H98: 4.1824172e+12 | I98: 4.1624172e+12 | J98: 5.1266272e+13 | K98: 46797437745282 | L98: 46777437745282 | M98: 87.72 | N98: 87.68
C99: =+C98-C97 -> 0 | D99: =+D98-D97 -> 0 | E99: =+E98-E97 -> 0 | F99: =+F98-F97 -> 0 | G99: =+G98-G97 -> 0 | H99: =+H98-H97 -> 0 | I99: =+I98-I97 -> 0 | J99: =+J98-J97 -> 0 | ... N99: =+N98-N97 -> -0.0042737323
C100: =+C98/1000000 -> 53347580 | D100: =+D98/1000000 -> 46380563 | E100: =+E98/1000000 -> 42615021 | F100: =+F98/1000000 -> 42615021 | G100: =+G98/1000000 -> 4885709.3 | H100: =+H98/1000000 -> 4182417.2 | I100: =+I98/1000000 -> 4162417.2 | J100: =+J98/1000000 -> 51266272 | ... L100: =+L98/1000000 -> 46777438
C101: dif. Por excel | D101: dif. Por excel

Sheet gasto
D1: República de Colombia | E1: EJECUCIÓN DE EGRESOS ACUMULADOS | F1: ADRES ADMINISTRADORA DE LOS RECURSOS DEL SGSSS
A2: CÓDIGO RUBRO | B2: CONCEPTO DEL RUBRO | C2: APROPIACIÓN DEFINITIVA | D2: CDP | E2: RP | F2: PAGOS-OGAG | G2: T. CDP | H2: T. RP | I2: T. PAGOS-OGAG | J2: RP | K2: PAGOS
A3: URA
A4: A-3-2-1-0 | B4: Transferencias Entidades de Administración Pública Central | C4: 86345030430 | D4: 0 | E4: 6.8799777e+09 | F4: 6.8799777e+09 | G4: 82805519661 | H4: 7.5720719e+10 | I4: 7.5720719e+10 | J4: 87.7 | K4: 87.7 | M4: =+VLOOKUP(A4,'CUADRO 2-EJECUCION DE GASTOS'!$A$13:$N$95,10,FALSE) -> 82805519661 | N4: =+VLOOKUP(A4,'CUADRO 2-EJECUCION DE GASTOS'!$A$13:$N$95,11,FALSE) -> 7.5720719e+10 | O4: =+VLOOKUP(A4,'CUADRO 2-EJECUCION DE GASTOS'!$A$13:$N$95,12,FALSE) -> 7.5720719e+10 | P4: =+M4-G4 -> 0 | Q4: =+N4-H4 -> 0 | R4: =+O4-I4 -> 0
A5: A-3-2-1-01 | B5: Contribución IVC Superintendencia Nacional de Salud | C5: 86345030430 | D5: 0 | E5: 6.8799777e+09 | F5: 6.8799777e+09 | G5: 82805519661 | H5: 7.5720719e+10 | I5: 7.5720719e+10 | J5: 87.7 | K5: 87.7 | M5: =+VLOOKUP(A5,'CUADRO 2-EJECUCION DE GASTOS'!$A$13:$N$95,10,FALSE) -> 82805519661 | N5: =+VLOOKUP(A5,'CUADRO 2-EJECUCION DE GASTOS'!$A$13:$N$95,11,FALSE) -> 7.5720719e+10 | O5: =+VLOOKUP(A5,'CUADRO 2-EJECUCION DE GASTOS'!$A$13:$N$95,12,FALSE) -> 7.5720719e+10 | P5: =+M5-G5 -> 0 | Q5: =+N5-H5 -> 0 | R5: =+O5-I5 -> 0
A6: A-3-2-2-0 | B6: Empresas Públicas Nacionales no financieras -ADRES | C6: 145380000000 | D6: 0 | E6: 4.0264397e+09 | F6: 4.0264397e+09 | G6: 145380000000 | H6: 3.827818e+10 | I6: 3.827818e+10 | J6: 26.33 | K6: 26.33 | M6: =+VLOOKUP(A6,'CUADRO 2-EJECUCION DE GASTOS'!$A$13:$N$95,10,FALSE) -> 145380000000 | N6: =+VLOOKUP(A6,'CUADRO 2-EJECUCION DE GASTOS'!$A$13:$N$95,11,FALSE) -> 3.827818e+10 | O6: =+VLOOKUP(A6,'CUADRO 2-EJECUCION DE GASTOS'!$A$13:$N$95,12,FALSE) -> 3.827818e+10 | P6: =+M6-G6 -> 0 | Q6: =+N6-H6 -> 0 | R6: =+O6-I6 -> 0
A7: A-3-2-2-0-01 | B7: Aportes hasta del 0,5% recursos CSF para el desarrollo objeto ADRES | C7: 145380000000 | D7: 0 | E7: 4.0264397e+09 | F7: 4.0264397e+09 | G7: 145380000000 | H7: 3.827818e+10 | I7: 3.827818e+10 | J7: 26.33 | K7: 26.33 | M7: =+VLOOKUP(A7,'CUADRO 2-EJECUCION DE GASTOS'!$A$13:$N$95,10,FALSE) -> 145380000000 | N7: =+VLOOKUP(A7,'CUADRO 2-EJECUCION DE GASTOS'!$A$13:$N$95,11,FALSE) -> 3.827818e+10 | O7: =+VLOOKUP(A7,'CUADRO 2-EJECUCION DE GASTOS'!$A$13:$N$95,12,FALSE) -> 3.827818e+10 | P7: =+M7-G7 -> 0 | Q7: =+N7-H7 -> 0 | R7: =+O7-I7 -> 0
A8: A-3-6-1-0 | B8: Sentencias y Conciliaciones URA | C8: 20000000000 | D8: 32260652 | E8: 1298784.6 | F8: 1298784.6 | G8: 2.2125885e+09 | H8: 2.1816266e+09 | I8: 2.1816266e+09 | J8: 10.91 | K8: 10.91 | M8: =+VLOOKUP(A8,'CUADRO 2-EJECUCION DE GASTOS'!$A$13:$N$95,10,FALSE) -> 2.2125885e+09 | N8: =+VLOOKUP(A8,'CUADRO 2-EJECUCION DE GASTOS'!$A$13:$N$95,11,FALSE) -> 2.1816266e+09 | O8: =+VLOOKUP(A8,'CUADRO 2-EJECUCION DE GASTOS'!$A$13:$N$95,12,FALSE) -> 2.1816266e+09 | P8: =+M8-G8 -> 0 | Q8: =+N8-H8 -> 0 | R8: =+O8-I8 -> 0
A9: A-3-6-1-1 | B9: Sentencias URA | C9: 20000000000 | D9: 32260652 | E9: 1298784.6 | F9: 1298784.6 | G9: 2.2125885e+09 | H9: 2.1816266e+09 | I9: 2.1816266e+09 | J9: 10.91 | K9: 10.91 | M9: =+VLOOKUP(A9,'CUADRO 2-EJECUCION DE GASTOS'!$A$13:$N$95,10,FALSE) -> 2.2125885e+09 | N9: =+VLOOKUP(A9,'CUADRO 2-EJECUCION DE GASTOS'!$A$13:$N$95,11,FALSE) -> 2.1816266e+09 | O9: =+VLOOKUP(A9,'CUADRO 2-EJECUCION DE GASTOS'!$A$13:$N$95,12,FALSE) -> 2.1816266e+09 | P9: =+M9-G9 -> 0 | Q9: =+N9-H9 -> 0 | R9: =+O9-I9 -> 0
A10: A-3-6-1-2 | B10: Conciliaciones URA | C10: 0 | D10: 0 | E10: 0 | F10: 0 | G10: 0 | H10: 0 | I10: 0 | J10: 0 | K10: 0 | M10: =+VLOOKUP(A10,'CUADRO 2-EJECUCION DE GASTOS'!$A$13:$N$95,10,FALSE) -> 0 | N10: =+VLOOKUP(A10,'CUADRO 2-EJECUCION DE GASTOS'!$A$13:$N$95,11,FALSE) -> 0 | O10: =+VLOOKUP(A10,'CUADRO 2-EJECUCION DE GASTOS'!$A$13:$N$95,12,FALSE) -> 0 | P10: =+M10-G10 -> 0 | Q10: =+N10-H10 -> 0 | R10: =+O10-I10 -> 0
A11: A-3-6-3-0 | B11: Destinatarios de otras transferencias Corrientes - Compensación Chance | C11: 134000000000 | D11: 0 | E11: 0 | F11: 0 | G11: 0 | H11: 0 | I11: 0 | J11: 0 | K11: 0 | M11: =+VLOOKUP(A11,'CUADRO 2-EJECUCION DE GASTOS'!$A$13:$N$95,10,FALSE) -> 0 | N11: =+VLOOKUP(A11,'CUADRO 2-EJECUCION DE GASTOS'!$A$13:$N$95,11,FALSE) -> 0 | O11: =+VLOOKUP(A11,'CUADRO 2-EJECUCION DE GASTOS'!$A$13:$N$95,12,FALSE) -> 0 | P11: =+M11-G11 -> 0 | Q11: =+N11-H11 -> 0 | R11: =+O11-I11 -> 0
A12: A-3-6-3-0-01 | B12: Otras transferencias - Compensación del Chance Decreto 2550/12 | C12: 134000000000 | D12: 0 | E12: 0 | F12: 0 | G12: 0 | H12: 0 | I12: 0 | J12: 0 | K12: 0 | M12: =+VLOOKUP(A12,'CUADRO 2-EJECUCION DE GASTOS'!$A$13:$N$95,10,FALSE) -> 0 | N12: =+VLOOKUP(A12,'CUADRO 2-EJECUCION DE GASTOS'!$A$13:$N$95,11,FALSE) -> 0 | O12: =+VLOOKUP(A12,'CUADRO 2-EJECUCION DE GASTOS'!$A$13:$N$95,12,FALSE) -> 0 | P12: =+M12-G12 -> 0 | Q12: =+N12-H12 -> 0 | R12: =+O12-I12 -> 0
A13: A-3-9-1-0 | B13: UPC Régimen Contributivo | C13: 22863934384378 | D13: 3.1690367e+12 | E13: 1829621715847 | F13: 1829621715847 | G13: 22757717488720 | H13: 20464474864318 | I13: 20464474864318 | J13: 89.51 | K13: 89.51 | M13: =+VLOOKUP(A13,'CUADRO 2-EJECUCION DE GASTOS'!$A$13:$N$95,10,FALSE) -> 22757717488720 | N13: =+VLOOKUP(A13,'CUADRO 2-EJECUCION DE GASTOS'!$A$13:$N$95,11,FALSE) -> 20464474864318 | O13: =+VLOOKUP(A13,'CUADRO 2-EJECUCION DE GASTOS'!$A$13:$N$95,12,FALSE) -> 20464474864318 | P13: =+M13-G13 -> 0 | Q13: =+N13-H13 -> 0 | R13: =+O13-I13 -> 0
A14: A-3-9-1-0-01 | B14: UPC Régimen Contributivo SSF | C14: 12575109660289 | D14: 1.8899866e+12 | E14: 1054086594082 | F14: 1054086594082 | G14: 12468892764631 | H14: 11362978705487 | I14: 11362978705487 | J14: 90.36 | K14: 90.36 | M14: =+VLOOKUP(A14,'CUADRO 2-EJECUCION DE GASTOS'!$A$13:$N$95,10,FALSE) -> 12468892764631 | N14: =+VLOOKUP(A14,'CUADRO 2-EJECUCION DE GASTOS'!$A$13:$N$95,11,FALSE) -> 11362978705487 | O14: =+VLOOKUP(A14,'CUADRO 2-EJECUCION DE GASTOS'!$A$13:$N$95,12,FALSE) -> 11362978705487 | P14: =+M14-G14 -> 0 | Q14: =+N14-H14 -> 0 | R14: =+O14-I14 -> 0
A15: A-3-9-1-0-02 | B15: UPC Régimen Contributivo CSF | C15: 10287649289644 | D15: 1279050072215 | E15: 775535121765 | F15: 775535121765 | G15: 10287649289644 | H15: 9100320724386 | I15: 9100320724386 | J15: 88.46 | K15: 88.46 | M15: =+VLOOKUP(A15,'CUADRO 2-EJECUCION DE GASTOS'!$A$13:$N$95,10,FALSE) -> 10287649289644 | N15: =+VLOOKUP(A15,'CUADRO 2-EJECUCION DE GASTOS'!$A$13:$N$95,11,FALSE) -> 9100320724386 | O15: =+VLOOKUP(A15,'CUADRO 2-EJECUCION DE GASTOS'!$A$13:$N$95,12,FALSE) -> 9100320724386 | P15: =+M15-G15 -> 0 | Q15: =+N15-H15 -> 0 | R15: =+O15-I15 -> 0
... A82: A-9-9-9-9 | B82: Disponibilidad Final | C82: 254007875000 | D82: 0 | E82: 0 | F82: 0 | G82: 0 | H82: 0 | I82: 0 | J82: 0 | K82: 0 | M82: =+VLOOKUP(A82,'CUADRO 2-EJECUCION DE GASTOS'!$A$13:$N$95,10,FALSE) -> 0 | N82: =+VLOOKUP(A82,'CUADRO 2-EJECUCION DE GASTOS'!$A$13:$N$95,11,FALSE) -> 0 | O82: =+VLOOKUP(A82,'CUADRO 2-EJECUCION DE GASTOS'!$A$13:$N$95,12,FALSE) -> 0 | P82: =+M82-G82 -> 0 | Q82: =+N82-H82 -> 0 | R82: =+O82-I82 -> 0
