Workbook
Name OLE_LINK1: 'CUADRO 2-EJECUCION DE GASTOS'!#REF!

Sheet CUADRO 1-EJECUCION DE INGRESOS
H1: =+NOW() -> 43676.359 | I1: =+NOW() -> 43676.359
A3: ADMINISTRADORA DE LOS RECURSOS DEL SISTEMA GENERAL DE SEGURIDAD SOCIAL EN SALUD
A4: UNIDAD DE RECURSOS ADMINISTRADOS - URA
A5: CODIGO DE LA EMPRESA 12902 - ADMINISTRACION DE RECURSOS DEL SGSSS
A6: PRESUPUESTO DE INGRESOS DE JUNIO DE 2019
A7: CUADRO No. 1
A10: CÓDIGO RUBRO | B10: CONCEPTO DEL RUBRO | C10: AFORO INICIAL | D10: MODIFICACIÓN PRESUPUESTAL | E10: AFORO DEFINITIVO | F10: Ingresos Acumulados Desde 01/01/2019 hasta 31/05/2019 | G10: Ingresos Desde 01/06/2019 hasta 30/06/2019 | H10: Ingresos Acumulados Desde 01/01/2019 hasta 30/06/2019 | I10: EJECUCIÓN ACUMULADA (%)
A11: URA
A12: 0-0-0-0 | B12: =+VLOOKUP(A12,Ingresos!$A$2:$B$82,2,FALSE) -> Disponibilidad inicial | C12: 422831681000 | D12: =+VLOOKUP(A12,Ingresos!$A$1:$F$90,3,FALSE) -> 488101188290 | E12: =+VLOOKUP(A12,Ingresos!$A$1:$F$90,4,FALSE) -> 910932869290 | F12: 422831681000 | G12: =+VLOOKUP(A12,Ingresos!$A$1:$E$100,5,FALSE) -> 488101188290 | H12: =+G12+F12 -> 910932869290 | I12: =IFERROR(H12/E12*100,0) -> 100 | K12: =+H12/1000000 -> 910932.87
A13: 1-0-0-0 | B13: INGRESOS CORRIENTES | C13: 52054407755223 | D13: =+D14+D28 -> 0 | E13: =+E14+E28 -> 52054407755223 | F13: 2.1221951e+13 | G13: =+G14+G28 -> 3.9968027e+12 | H13: =+G13+F13 -> 2.5218754e+13 | I13: =IFERROR(H13/E13*100,0) -> 48.446913 | K13: =+H13/1000000 -> 25218754
A14: 1-2-0-0 | B14: Aportes e Impuestos | C14: 19781797637181 | D14: =+D15 -> 0 | E14: =+E15+E27 -> 19781797637181 | F14: 7.9159637e+12 | G14: =+G15+G27 -> 1293820709385 | H14: =+G14+F14 -> 9.2097844e+12 | I14: =IFERROR(H14/E14*100,0) -> 46.556863 | K14: =+H14/1000000 -> 9209784.4
A15: 1-2-1-0 | B15: Aportes de la Nación | C15: 19781797637181 | D15: =+D16+D19+D20+D21+D22+D25+D26 -> 0 | E15: =+E16+E19+E20+E21+E22+E26+E25+E27 -> 19781797637181 | F15: 7.9159637e+12 | G15: =+G16+G19+G20+G21+G22+G26+G25+G27 -> 1293820709385 | H15: =+G15+F15 -> 9.2097844e+12 | I15: =IFERROR(H15/E15*100,0) -> 46.556863 | K15: =+H15/1000000 -> 9209784.4
A16: 1-2-1-1 | B16: =+VLOOKUP(A16,Ingresos!$A$2:$B$82,2,FALSE) -> Aportes de la Nación para el Aseguramiento en Salud | C16: 17803782346000 | D16: =+D17+D18 -> 0 | E16: =+E17+E18 -> 17803782346000 | F16: 6.8543538e+12 | G16: =+SUM(G17:G18) -> 1166604084389 | H16: =+G16+F16 -> 8.0209578e+12 | I16: =IFERROR(H16/E16*100,0) -> 45.051988 | K16: =+H16/1000000 -> 8020957.8
A17: 1-2-1-1-01 | B17: =+VLOOKUP(A17,Ingresos!$A$2:$B$82,2,FALSE) -> Aportes de la Nación para el Aseguramiento en Salud Cierre | C17: 13686804885516 | D17: =+VLOOKUP(A17,Ingresos!$A$1:$F$90,3,FALSE) -> 0 | E17: =+VLOOKUP(A17,Ingresos!$A$1:$F$90,4,FALSE) -> 12507321670830 | F17: 4.8152469e+12 | G17: =+VLOOKUP(A17,Ingresos!$A$1:$E$100,5,FALSE) -> 8.1955015e+11 | H17: =+G17+F17 -> 5.634797e+12 | I17: =IFERROR(H17/E17*100,0) -> 45.051988 | K17: =+H17/1000000 -> 5634797
A18: 1-2-1-1-02 | B18: =+VLOOKUP(A18,Ingresos!$A$2:$B$82,2,FALSE) -> Imporenta | C18: 4116977460484 | D18: =+VLOOKUP(A18,Ingresos!$A$1:$F$90,3,FALSE) -> 0 | E18: =+VLOOKUP(A18,Ingresos!$A$1:$F$90,4,FALSE) -> 5296460675170 | F18: 2.0391069e+12 | G18: =+VLOOKUP(A18,Ingresos!$A$1:$E$100,5,FALSE) -> 3.4705393e+11 | H18: =+G18+F18 -> 2.3861608e+12 | I18: =IFERROR(H18/E18*100,0) -> 45.051988 | K18: =+H18/1000000 -> 2386160.8
A19: 1-2-1-2 | B19: =+VLOOKUP(A19,Ingresos!$A$2:$B$82,2,FALSE) -> Compensación Regalías para el Régimen Subsidiado | C19: 226673765000 | D19: =+VLOOKUP(A19,Ingresos!$A$1:$F$90,3,FALSE) -> 0 | E19: =+VLOOKUP(A19,Ingresos!$A$1:$F$90,4,FALSE) -> 226673765000 | F19: 226673765000 | G19: =+VLOOKUP(A19,Ingresos!$A$1:$E$100,5,FALSE) -> 0 | H19: =+G19+F19 -> 226673765000 | I19: =IFERROR(H19/E19*100,0) -> 100 | K19: =+H19/1000000 -> 226673.77
A20: 1-2-1-3 | B20: =+VLOOKUP(A20,Ingresos!$A$2:$B$82,2,FALSE) -> Impuesto sobre la renta para la equidad CREE | C20: 0 | D20: =+VLOOKUP(A20,Ingresos!$A$1:$F$90,3,FALSE) -> 0 | E20: =+VLOOKUP(A20,Ingresos!$A$1:$F$90,4,FALSE) -> 0 | F20: 0 | G20: =+VLOOKUP(A20,Ingresos!$A$1:$E$100,5,FALSE) -> 0 | H20: =+G20+F20 -> 0 | I20: =IFERROR(H20/E20*100,0) -> 0 | K20: =+H20/1000000 -> 0
A21: 1-2-1-4 | B21: =+VLOOKUP(A21,Ingresos!$A$2:$B$82,2,FALSE) -> SGP FONSAET | C21: 95551523562 | D21: =+VLOOKUP(A21,Ingresos!$A$1:$F$90,3,FALSE) -> 0 | E21: =+VLOOKUP(A21,Ingresos!$A$1:$F$90,4,FALSE) -> 95551523562 | F21: 0 | G21: =+VLOOKUP(A21,Ingresos!$A$1:$E$100,5,FALSE) -> 0 | H21: =+G21+F21 -> 0 | I21: =IFERROR(H21/E21*100,0) -> 0 | K21: =+H21/1000000 -> 0
A22: 1-2-1-5 | B22: =+VLOOKUP(A22,Ingresos!$A$2:$B$82,2,FALSE) -> PRIMA FONSAT Y CONTRIBUCION SOAT | C22: 1640527441000 | D22: =+D23+D24 -> 0 | E22: =+E23+E24 -> 1640527441000 | F22: 7.8628141e+11 | G22: =+SUM(G23:G24) -> 111862061274 | H22: =+G22+F22 -> 8.9814347e+11 | I22: =IFERROR(H22/E22*100,0) -> 54.747238 | K22: =+H22/1000000 -> 898143.47
A23: 1-2-1-5-01 | B23: =+VLOOKUP(A23,Ingresos!$A$2:$B$82,2,FALSE) -> % Prima (FONSAT) Decreto Ley 1335 de 2009 | C23: 363281118360 | D23: =+VLOOKUP(A23,Ingresos!$A$1:$F$90,3,FALSE) -> 0 | E23: =+VLOOKUP(A23,Ingresos!$A$1:$F$90,4,FALSE) -> 363281118360 | F23: 1.9749469e+11 | G23: =+VLOOKUP(A23,Ingresos!$A$1:$E$100,5,FALSE) -> 0 | H23: =+G23+F23 -> 1.9749469e+11 | I23: =IFERROR(H23/E23*100,0) -> 54.364148 | K23: =+H23/1000000 -> 197494.69
A24: 1-2-1-5-02 | B24: =+VLOOKUP(A24,Ingresos!$A$2:$B$82,2,FALSE) -> Contribución Seguro Obligatorio de Accidentes de Tránsito - SOAT- Decreto Ley 1335 de 2009 | C24: 1277246322640 | D24: =+VLOOKUP(A24,Ingresos!$A$1:$F$90,3,FALSE) -> 0 | E24: =+VLOOKUP(A24,Ingresos!$A$1:$F$90,4,FALSE) -> 1277246322640 | F24: 5.8878672e+11 | G24: =+VLOOKUP(A24,Ingresos!$A$1:$E$100,5,FALSE) -> 111862061274 | H24: =+G24+F24 -> 7.0064878e+11 | I24: =IFERROR(H24/E24*100,0) -> 54.856199 | K24: =+H24/1000000 -> 700648.78
A25: 1-2-1-7 | B25: =+VLOOKUP(A25,Ingresos!$A$2:$B$82,2,FALSE) -> Impuesto social a las municiones y explosivos | C25: 6410791000 | D25: =+VLOOKUP(A25,Ingresos!$A$1:$F$90,3,FALSE) -> 0 | E25: =+VLOOKUP(A25,Ingresos!$A$1:$F$90,4,FALSE) -> 6410791000 | F25: 44811505703 | G25: =+VLOOKUP(A25,Ingresos!$A$1:$E$100,5,FALSE) -> 14354115977 | H25: =+G25+F25 -> 59165621680 | I25: =IFERROR(H25/E25*100,0) -> 922.90673 | K25: =+H25/1000000 -> 59165.622
A26: 1-2-1-8 | B26: =+VLOOKUP(A26,Ingresos!$A$2:$B$82,2,FALSE) -> Impuesto social a las armas | C26: 8851770619 | D26: =+VLOOKUP(A26,Ingresos!$A$1:$F$90,3,FALSE) -> 0 | E26: =+VLOOKUP(A26,Ingresos!$A$1:$F$90,4,FALSE) -> 8851770619 | F26: 3843290647 | G26: =+VLOOKUP(A26,Ingresos!$A$1:$E$100,5,FALSE) -> 1000447745 | H26: =+G26+F26 -> 4843738392 | I26: =IFERROR(H26/E26*100,0) -> 54.720559 | K26: =+H26/1000000 -> 4843.7384
A27: 1-2-9-0 | B27: =+VLOOKUP(A27,Ingresos!$A$2:$B$82,2,FALSE) -> Otros aportes e impuestos de la nación | C27: 0 | D27: =+VLOOKUP(A27,Ingresos!$A$1:$F$90,3,FALSE) -> 0 | E27: =+VLOOKUP(A27,Ingresos!$A$1:$F$90,4,FALSE) -> 0 | F27: 0 | G27: =+VLOOKUP(A27,Ingresos!$A$1:$E$100,5,FALSE) -> 0 | H27: =+G27+F27 -> 0 | I27: =IFERROR(H27/E27*100,0) -> 0 | K27: =+H27/1000000 -> 0
A28: 1-3-0-0 | B28: Otros Ingresos Corrientes | C28: 32272610118042 | D28: =+D29 -> 0 | E28: =+E29+E58 -> 32272610118042 | F28: 1.3305987e+13 | G28: =+G29+G58 -> 2.702982e+12 | H28: =+G28+F28 -> 1.6008969e+13 | I28: =IFERROR(H28/E28*100,0) -> 49.605436 | K28: =+H28/1000000 -> 16008969
A29: 1-3-5-0 | B29: Ingresos Sistema General de Seguridad Social en Salud | C29: 22105255788877 | D29: =+D30+D33+D36+D41+D51+D54+D57 -> 0 | E29: =+E30+E33+E36+E41+E51+E54+E57 -> 22105255788877 | F29: 9.2160333e+12 | G29: =+G30+G33+G36+G41+G51+G54+G57 -> 1.85803e+12 | H29: =+G29+F29 -> 1.1074063e+13 | I29: =IFERROR(H29/E29*100,0) -> 50.09697 | K29: =+H29/1000000 -> 11074063
A30: 1-3-5-1 | B30: =+VLOOKUP(A30,Ingresos!$A$2:$B$82,2,FALSE) -> Cotizaciones al SGSSS | C30: 20346328129563 | D30: =+SUM(D31:D32) -> 0 | E30: =+SUM(E31:E32) -> 20346328129563 | F30: 8270654262719 | G30: =+SUM(G31:G32) -> 1621624101985 | H30: =+G30+F30 -> 9892278364704 | I30: =IFERROR(H30/E30*100,0) -> 48.619477 | K30: =+H30/1000000 -> 9892278.4
A31: 1-3-5-1-01 | B31: =+VLOOKUP(A31,Ingresos!$A$2:$B$82,2,FALSE) -> Régimen Contributivo CSF | C31: 6807438619821 | D31: =+VLOOKUP(A31,Ingresos!$A$1:$F$90,3,FALSE) -> 0 | E31: =+VLOOKUP(A31,Ingresos!$A$1:$F$90,4,FALSE) -> 6807438619821 | F31: 2849919382766 | G31: =+VLOOKUP(A31,Ingresos!$A$1:$E$100,5,FALSE) -> 522355428948 | H31: =+G31+F31 -> 3372274811714 | I31: =IFERROR(H31/E31*100,0) -> 49.538086 | K31: =+H31/1000000 -> 3372274.8
A32: 1-3-5-1-02 | B32: =+VLOOKUP(A32,Ingresos!$A$2:$B$82,2,FALSE) -> Régimen Contributivo SSF | C32: 13538889509742 | D32: =+VLOOKUP(A32,Ingresos!$A$1:$F$90,3,FALSE) -> 0 | E32: =+VLOOKUP(A32,Ingresos!$A$1:$F$90,4,FALSE) -> 13538889509742 | F32: 5420734879953 | G32: =+VLOOKUP(A32,Ingresos!$A$1:$E$100,5,FALSE) -> 1099268673037 | H32: =+G32+F32 -> 6520003552990 | I32: =IFERROR(H32/E32*100,0) -> 48.157595 | K32: =+H32/1000000 -> 6520003.6
A33: 1-3-5-2 | B33: =+VLOOKUP(A33,Ingresos!$A$2:$B$82,2,FALSE) -> Aporte Solidaridad de Regímenes de Excepcion y Especiales | C33: 1000356775894 | D33: =+SUM(D34:D35) -> 0 | E33: =+SUM(E34:E35) -> 1000356775894 | F33: 3.602431e+11 | G33: =+SUM(G34:G35) -> 7.4714521e+10 | H33: =+G33+F33 -> 4.3495762e+11 | I33: =IFERROR(H33/E33*100,0) -> 43.480249 | K33: =+H33/1000000 -> 434957.62
A34: 1-3-5-2-01 | B34: =+VLOOKUP(A34,Ingresos!$A$2:$B$82,2,FALSE) -> Cotizaciones afiliados REX con ingresos adicionales | C34: 594961177882 | D34: =+VLOOKUP(A34,Ingresos!$A$1:$F$90,3,FALSE) -> 0 | E34: =+VLOOKUP(A34,Ingresos!$A$1:$F$90,4,FALSE) -> 594961177882 | F34: 214704214534 | G34: =+VLOOKUP(A34,Ingresos!$A$1:$E$100,5,FALSE) -> 44270775588 | H34: =+G34+F34 -> 258974990122 | I34: =IFERROR(H34/E34*100,0) -> 43.528049 | K34: =+H34/1000000 -> 258974.99
A35: 1-3-5-2-02 | B35: =+VLOOKUP(A35,Ingresos!$A$2:$B$82,2,FALSE) -> Aporte Solidario entidades REX | C35: 405395598012 | D35: =+VLOOKUP(A35,Ingresos!$A$1:$F$90,3,FALSE) -> 0 | E35: =+VLOOKUP(A35,Ingresos!$A$1:$F$90,4,FALSE) -> 405395598012 | F35: 1.4553889e+11 | G35: =+VLOOKUP(A35,Ingresos!$A$1:$E$100,5,FALSE) -> 3.0443746e+10 | H35: =+G35+F35 -> 1.7598263e+11 | I35: =IFERROR(H35/E35*100,0) -> 43.410099 | K35: =+H35/1000000 -> 175982.63
A36: 1-3-5-3 | B36: =+VLOOKUP(A36,Ingresos!$A$2:$B$82,2,FALSE) -> Aportes Cajas de Compensación Familiar | C36: 499207099674 | D36: =+SUM(D37:D40) -> 0 | E36: =+SUM(E37:E40) -> 499207099674 | F36: 2.2280162e+11 | G36: =+SUM(G37:G40) -> 2.072353e+10 | H36: =+G36+F36 -> 243525149523 | I36: =IFERROR(H36/E36*100,0) -> 48.782389 | K36: =+H36/1000000 -> 243525.15
A37: 1-3-5-3-01 | B37: =+VLOOKUP(A37,Ingresos!$A$2:$B$82,2,FALSE) -> Aportes CCF Artículo 217 Ley 100 de 1993 CSF | C37: 466578060617 | D37: =+VLOOKUP(A37,Ingresos!$A$1:$F$90,3,FALSE) -> 0 | E37: =+VLOOKUP(A37,Ingresos!$A$1:$F$90,4,FALSE) -> 466578060617 | F37: 2.0588336e+11 | G37: =+VLOOKUP(A37,Ingresos!$A$1:$E$100,5,FALSE) -> 1.8239265e+10 | H37: =+G37+F37 -> 2.2412263e+11 | I37: =IFERROR(H37/E37*100,0) -> 48.035398 | K37: =+H37/1000000 -> 224122.63
A38: 1-3-5-3-02 | B38: =+VLOOKUP(A38,Ingresos!$A$2:$B$82,2,FALSE) -> Aportes CCF Artículo 217 Ley 100 de 1993 SSF | C38: 28877831435 | D38: =+VLOOKUP(A38,Ingresos!$A$1:$F$90,3,FALSE) -> 0 | E38: =+VLOOKUP(A38,Ingresos!$A$1:$F$90,4,FALSE) -> 28877831435 | F38: 1.4089319e+10 | G38: =+VLOOKUP(A38,Ingresos!$A$1:$E$100,5,FALSE) -> 2484211881 | H38: =+G38+F38 -> 1.657353e+10 | I38: =IFERROR(H38/E38*100,0) -> 57.39188 | K38: =+H38/1000000 -> 16573.53
A39: 1-3-5-3-03 | B39: =+VLOOKUP(A39,Ingresos!$A$2:$B$82,2,FALSE) -> Aportes CCF Balance | C39: 3751207622 | D39: =+VLOOKUP(A39,Ingresos!$A$1:$F$90,3,FALSE) -> 0 | E39: =+VLOOKUP(A39,Ingresos!$A$1:$F$90,4,FALSE) -> 3751207622 | F39: 2000102769 | G39: =+VLOOKUP(A39,Ingresos!$A$1:$E$100,5,FALSE) -> 0 | H39: =+G39+F39 -> 2000102769 | I39: =IFERROR(H39/E39*100,0) -> 53.318903 | K39: =+H39/1000000 -> 2000.1028
A40: 1-3-5-3-04 | B40: =+VLOOKUP(A40,Ingresos!$A$2:$B$82,2,FALSE) -> Otros Aportes CCF | C40: 0 | D40: =+VLOOKUP(A40,Ingresos!$A$1:$F$90,3,FALSE) -> 0 | E40: =+VLOOKUP(A40,Ingresos!$A$1:$F$90,4,FALSE) -> 0 | F40: 828836818 | G40: =+VLOOKUP(A40,Ingresos!$A$1:$E$100,5,FALSE) -> 52881.8 | H40: =+G40+F40 -> 8.288897e+08 | I40: =IFERROR(H40/E40*100,0) -> 0 | K40: =+H40/1000000 -> 828.8897
A41: 1-3-5-5 | B41: =+VLOOKUP(A41,Ingresos!$A$2:$B$82,2,FALSE) -> Reintegros / Recuperaciones | C41: 0 | D41: =+SUM(D42:D50) -> 0 | E41: =+SUM(E42:E50) -> 0 | F41: 2.7199956e+11 | G41: =+SUM(G42:G50) -> 1.231061e+11 | H41: =+G41+F41 -> 3.9510566e+11 | I41: =IFERROR(H41/E41*100,0) -> 0 | K41: =+H41/1000000 -> 395105.66
A42: 1-3-5-5-01 | B42: =+VLOOKUP(A42,Ingresos!$A$2:$B$82,2,FALSE) -> UPC Régimen Contributivo Vigencias anteriores | C42: 0 | D42: =+VLOOKUP(A42,Ingresos!$A$1:$F$90,3,FALSE) -> 0 | E42: =+VLOOKUP(A42,Ingresos!$A$1:$F$90,4,FALSE) -> 0 | F42: 9.0797633e+09 | G42: =+VLOOKUP(A42,Ingresos!$A$1:$E$100,5,FALSE) -> 1571081742 | H42: =+G42+F42 -> 1.0650845e+10 | I42: =IFERROR(H42/E42*100,0) -> 0 | K42: =+H42/1000000 -> 10650.845
A43: 1-3-5-5-02 | B43: =+VLOOKUP(A43,Ingresos!$A$2:$B$82,2,FALSE) -> P&P Vigencias anteriores | C43: 0 | D43: =+VLOOKUP(A43,Ingresos!$A$1:$F$90,3,FALSE) -> 0 | E43: =+VLOOKUP(A43,Ingresos!$A$1:$F$90,4,FALSE) -> 0 | F43: 0 | G43: =+VLOOKUP(A43,Ingresos!$A$1:$E$100,5,FALSE) -> 0 | H43: =+G43+F43 -> 0 | I43: =IFERROR(H43/E43*100,0) -> 0 | K43: =+H43/1000000 -> 0
A44: 1-3-5-5-03 | B44: =+VLOOKUP(A44,Ingresos!$A$2:$B$82,2,FALSE) -> Licencias de Maternidad y Paternidad Vigencias anteriores | C44: 0 | D44: =+VLOOKUP(A44,Ingresos!$A$1:$F$90,3,FALSE) -> 0 | E44: =+VLOOKUP(A44,Ingresos!$A$1:$F$90,4,FALSE) -> 0 | F44: 0 | G44: =+VLOOKUP(A44,Ingresos!$A$1:$E$100,5,FALSE) -> 0 | H44: =+G44+F44 -> 0 | I44: =IFERROR(H44/E44*100,0) -> 0 | K44: =+H44/1000000 -> 0
A45: 1-3-5-5-04 | B45: =+VLOOKUP(A45,Ingresos!$A$2:$B$82,2,FALSE) -> UPC Régimen Subsidiado Vigencias anteriores | C45: 0 | D45: =+VLOOKUP(A45,Ingresos!$A$1:$F$90,3,FALSE) -> 0 | E45: =+VLOOKUP(A45,Ingresos!$A$1:$F$90,4,FALSE) -> 0 | F45: 2.3959484e+11 | G45: =+VLOOKUP(A45,Ingresos!$A$1:$E$100,5,FALSE) -> 1.2024873e+11 | H45: =+G45+F45 -> 3.5984358e+11 | I45: =IFERROR(H45/E45*100,0) -> 0 | K45: =+H45/1000000 -> 359843.58
A46: 1-3-5-5-05 | B46: =+VLOOKUP(A46,Ingresos!$A$2:$B$82,2,FALSE) -> Recobros Vigencias anteriores | C46: 0 | D46: =+VLOOKUP(A46,Ingresos!$A$1:$F$90,3,FALSE) -> 0 | E46: =+VLOOKUP(A46,Ingresos!$A$1:$F$90,4,FALSE) -> 0 | F46: 6.6429794e+09 | G46: =+VLOOKUP(A46,Ingresos!$A$1:$E$100,5,FALSE) -> 7.6301048e+08 | H46: =+G46+F46 -> 7.4059899e+09 | I46: =IFERROR(H46/E46*100,0) -> 0 | K46: =+H46/1000000 -> 7405.9899
A47: 1-3-5-5-06 | B47: =+VLOOKUP(A47,Ingresos!$A$2:$B$82,2,FALSE) -> Reclamaciones Vigencias anteriores | C47: 0 | D47: =+VLOOKUP(A47,Ingresos!$A$1:$F$90,3,FALSE) -> 0 | E47: =+VLOOKUP(A47,Ingresos!$A$1:$F$90,4,FALSE) -> 0 | F47: 1.660667e+08 | G47: =+VLOOKUP(A47,Ingresos!$A$1:$E$100,5,FALSE) -> 407633173 | H47: =+G47+F47 -> 5.7369987e+08 | I47: =IFERROR(H47/E47*100,0) -> 0 | K47: =+H47/1000000 -> 573.69987
A48: 1-3-5-5-07 | B48: =+VLOOKUP(A48,Ingresos!$A$2:$B$82,2,FALSE) -> Procesos de Repetición | C48: 0 | D48: =+VLOOKUP(A48,Ingresos!$A$1:$F$90,3,FALSE) -> 0 | E48: =+VLOOKUP(A48,Ingresos!$A$1:$F$90,4,FALSE) -> 0 | F48: 1.3545453e+08 | G48: =+VLOOKUP(A48,Ingresos!$A$1:$E$100,5,FALSE) -> 13243487 | H48: =+G48+F48 -> 1.4869802e+08 | I48: =IFERROR(H48/E48*100,0) -> 0 | K48: =+H48/1000000 -> 148.69802
A49: 1-3-5-5-08 | B49: =+VLOOKUP(A49,Ingresos!$A$2:$B$82,2,FALSE) -> Reintegro por contratos vigencias anteriores | C49: 0 | D49: =+VLOOKUP(A49,Ingresos!$A$1:$F$90,3,FALSE) -> 0 | E49: =+VLOOKUP(A49,Ingresos!$A$1:$F$90,4,FALSE) -> 0 | F49: 5.7490731e+08 | G49: =+VLOOKUP(A49,Ingresos!$A$1:$E$100,5,FALSE) -> 102404269 | H49: =+G49+F49 -> 6.7731158e+08 | I49: =IFERROR(H49/E49*100,0) -> 0 | K49: =+H49/1000000 -> 677.31158
A50: 1-3-5-5-09 | B50: =+VLOOKUP(A50,Ingresos!$A$2:$B$82,2,FALSE) -> Otros reintegros / recuperaciones | C50: 0 | D50: =+VLOOKUP(A50,Ingresos!$A$1:$F$90,3,FALSE) -> 0 | E50: =+VLOOKUP(A50,Ingresos!$A$1:$F$90,4,FALSE) -> 0 | F50: 1.5805543e+10 | G50: =+VLOOKUP(A50,Ingresos!$A$1:$E$100,5,FALSE) -> 0 | H50: =+G50+F50 -> 1.5805543e+10 | I50: =IFERROR(H50/E50*100,0) -> 0 | K50: =+H50/1000000 -> 15805.543
A51: 1-3-5-6 | B51: =+VLOOKUP(A51,Ingresos!$A$2:$B$82,2,FALSE) -> Multas | C51: 0 | D51: =+SUM(D52:D53) -> 0 | E51: =+SUM(E52:E53) -> 0 | F51: 0 | G51: =+SUM(G52:G53) -> 0 | H51: =+G51+F51 -> 0 | I51: =IFERROR(H51/E51*100,0) -> 0 | K51: =+H51/1000000 -> 0
A52: 1-3-5-6-01 | B52: =+VLOOKUP(A52,Ingresos!$A$2:$B$82,2,FALSE) -> Multas Antitabaco | C52: 0 | D52: =+VLOOKUP(A52,Ingresos!$A$1:$F$90,3,FALSE) -> 0 | E52: =+VLOOKUP(A52,Ingresos!$A$1:$F$90,4,FALSE) -> 0 | F52: 0 | G52: =+VLOOKUP(A52,Ingresos!$A$1:$E$100,5,FALSE) -> 0 | H52: =+G52+F52 -> 0 | I52: =IFERROR(H52/E52*100,0) -> 0 | K52: =+H52/1000000 -> 0
A53: 1-3-5-6-02 | B53: =+VLOOKUP(A53,Ingresos!$A$2:$B$82,2,FALSE) -> Otras Multas | C53: 0 | D53: =+VLOOKUP(A53,Ingresos!$A$1:$F$90,3,FALSE) -> 0 | E53: =+VLOOKUP(A53,Ingresos!$A$1:$F$90,4,FALSE) -> 0 | F53: 0 | G53: =+VLOOKUP(A53,Ingresos!$A$1:$E$100,5,FALSE) -> 0 | H53: =+G53+F53 -> 0 | I53: =IFERROR(H53/E53*100,0) -> 0 | K53: =+H53/1000000 -> 0
A54: 1-3-5-7 | B54: =+VLOOKUP(A54,Ingresos!$A$2:$B$82,2,FALSE) -> Otros ingresos Diversos | C54: 259363783746 | D54: =+SUM(D55:D56) -> 0 | E54: =+SUM(E55:E56) -> 0 | F54: 2.5036001e+09 | G54: =+SUM(G55:G56) -> 8.1979156e+08 | H54: =+G54+F54 -> 3.3233916e+09 | I54: =IFERROR(H54/E54*100,0) -> 0 | K54: =+H54/1000000 -> 3323.3916
A55: 1-3-5-7-01 | B55: =+VLOOKUP(A55,Ingresos!$A$2:$B$82,2,FALSE) -> Aportes adicionales en Salud | C55: 259363783746 | D55: =+VLOOKUP(A55,Ingresos!$A$1:$F$90,3,FALSE) -> 0 | E55: =+VLOOKUP(A55,Ingresos!$A$1:$F$90,4,FALSE) -> 0 | F55: 0 | G55: =+VLOOKUP(A55,Ingresos!$A$1:$E$100,5,FALSE) -> 0 | H55: =+G55+F55 -> 0 | I55: =IFERROR(H55/E55*100,0) -> 0 | K55: =+H55/1000000 -> 0
A56: 1-3-5-7-02 | B56: =+VLOOKUP(A56,Ingresos!$A$2:$B$82,2,FALSE) -> Otros ingresos Diversos | C56: 0 | D56: =+VLOOKUP(A56,Ingresos!$A$1:$F$90,3,FALSE) -> 0 | E56: =+VLOOKUP(A56,Ingresos!$A$1:$F$90,4,FALSE) -> 0 | F56: 2.5036001e+09 | G56: =+VLOOKUP(A56,Ingresos!$A$1:$E$100,5,FALSE) -> 8.1979156e+08 | H56: =+G56+F56 -> 3.3233916e+09 | I56: =IFERROR(H56/E56*100,0) -> 0 | K56: =+H56/1000000 -> 3323.3916
A57: 1-3-5-8 | B57: =+VLOOKUP(A57,Ingresos!$A$2:$B$82,2,FALSE) -> Cotizaciones y/o aportes adicionales en salud | C57: 0 | D57: =+VLOOKUP(A57,Ingresos!$A$1:$F$90,3,FALSE) -> 0 | E57: =+VLOOKUP(A57,Ingresos!$A$1:$F$90,4,FALSE) -> 259363783746 | F57: 87831130000 | G57: =+VLOOKUP(A57,Ingresos!$A$1:$E$100,5,FALSE) -> 17041976045 | H57: =+G57+F57 -> 104873106045 | I57: =IFERROR(H57/E57*100,0) -> 40.434753 | K57: =+H57/1000000 -> 104873.11
A58: 1-3-6-0 | B58: Recursos ET Aseguramiento en Salud | C58: 10167354329165 | D58: =+D59+D60+D61+D64+D67 -> 0 | E58: =+E59+E60+E61+E64+E67 -> 10167354329165 | F58: 4.0899538e+12 | G58: =+G59+G60+G61+G64+G67 -> 8.4495199e+11 | H58: =+G58+F58 -> 4.9349058e+12 | I58: =IFERROR(H58/E58*100,0) -> 48.536774 | K58: =+H58/1000000 -> 4934905.8
A59: 1-3-6-1 | B59: =+VLOOKUP(A59,Ingresos!$A$2:$B$82,2,FALSE) -> Sistema General de Participaciones Régimen Subsidiado | C59: 8428995552661 | D59: =+VLOOKUP(A59,Ingresos!$A$1:$F$90,3,FALSE) -> 0 | E59: =+VLOOKUP(A59,Ingresos!$A$1:$F$90,4,FALSE) -> 8428995552661 | F59: 3188164885310 | G59: =+VLOOKUP(A59,Ingresos!$A$1:$E$100,5,FALSE) -> 648690095349 | H59: =+G59+F59 -> 3836854980659 | I59: =IFERROR(H59/E59*100,0) -> 45.519718 | K59: =+H59/1000000 -> 3836855
A60: 1-3-6-2 | B60: =+VLOOKUP(A60,Ingresos!$A$2:$B$82,2,FALSE) -> Recursos Provenientes de COLJUEGOS para R.S. | C60: 376773007880 | D60: =+VLOOKUP(A60,Ingresos!$A$1:$F$90,3,FALSE) -> 0 | E60: =+VLOOKUP(A60,Ingresos!$A$1:$F$90,4,FALSE) -> 376773007880 | F60: 170579150729 | G60: =+VLOOKUP(A60,Ingresos!$A$1:$E$100,5,FALSE) -> 25251014592 | H60: =+G60+F60 -> 195830165321 | I60: =IFERROR(H60/E60*100,0) -> 51.975636 | K60: =+H60/1000000 -> 195830.17
A61: 1-3-6-7 | B61: =+VLOOKUP(A61,Ingresos!$A$2:$B$82,2,FALSE) -> Recursos Fonpet | C61: 200000000000 | D61: =+SUM(D62:D63) -> 0 | E61: =+SUM(E62:E63) -> 200000000000 | F61: 0 | G61: =+SUM(G62:G63) -> 0 | H61: =+G61+F61 -> 0 | I61: =IFERROR(H61/E61*100,0) -> 0 | K61: =+H61/1000000 -> 0
A62: 1-3-6-7-01 | B62: =+VLOOKUP(A62,Ingresos!$A$2:$B$82,2,FALSE) -> Recursos LOTTO en Línea-FONPET | C62: 0 | D62: =+VLOOKUP(A62,Ingresos!$A$1:$F$90,3,FALSE) -> 0 | E62: =+VLOOKUP(A62,Ingresos!$A$1:$F$90,4,FALSE) -> 0 | F62: 0 | G62: =+VLOOKUP(A62,Ingresos!$A$1:$E$100,5,FALSE) -> 0 | H62: =+G62+F62 -> 0 | I62: =IFERROR(H62/E62*100,0) -> 0 | K62: =+H62/1000000 -> 0
A63: 1-3-6-7-02 | B63: =+VLOOKUP(A63,Ingresos!$A$2:$B$82,2,FALSE) -> Otros recursos FONPET diferentes a LOTTO en Línea | C63: 200000000000 | D63: =+VLOOKUP(A63,Ingresos!$A$1:$F$90,3,FALSE) -> 0 | E63: =+VLOOKUP(A63,Ingresos!$A$1:$F$90,4,FALSE) -> 200000000000 | F63: 0 | G63: =+VLOOKUP(A63,Ingresos!$A$1:$E$100,5,FALSE) -> 0 | H63: =+G63+F63 -> 0 | I63: =IFERROR(H63/E63*100,0) -> 0 | K63: =+H63/1000000 -> 0
A64: 1-3-6-8 | B64: =+VLOOKUP(A64,Ingresos!$A$2:$B$82,2,FALSE) -> Otros Recursos de las Entidades Territoriales para Aseguramiento | C64: 1124585768624 | D64: =+SUM(D65:D66) -> 0 | E64: =+SUM(E65:E66) -> 1124585768624 | F64: 7.1392906e+11 | G64: =+SUM(G65:G66) -> 1.7008121e+11 | H64: =+G64+F64 -> 8.8401027e+11 | I64: =IFERROR(H64/E64*100,0) -> 78.607634 | K64: =+H64/1000000 -> 884010.27
A65: 1-3-6-8-01 | B65: =+VLOOKUP(A65,Ingresos!$A$2:$B$82,2,FALSE) -> Otros recursos Departamentales y Distritales para Aseguramiento | C65: 1042745130904 | D65: =+VLOOKUP(A65,Ingresos!$A$1:$F$90,3,FALSE) -> 0 | E65: =+VLOOKUP(A65,Ingresos!$A$1:$F$90,4,FALSE) -> 1042745130904 | F65: 6.8590127e+11 | G65: =+VLOOKUP(A65,Ingresos!$A$1:$E$100,5,FALSE) -> 1.6422187e+11 | H65: =+G65+F65 -> 8.5012314e+11 | I65: =IFERROR(H65/E65*100,0) -> 81.527414 | K65: =+H65/1000000 -> 850123.14
A66: 1-3-6-8-02 | B66: =+VLOOKUP(A66,Ingresos!$A$2:$B$82,2,FALSE) -> Otros Recursos Municipales para Aseguramiento | C66: 81840637720 | D66: =+VLOOKUP(A66,Ingresos!$A$1:$F$90,3,FALSE) -> 0 | E66: =+VLOOKUP(A66,Ingresos!$A$1:$F$90,4,FALSE) -> 81840637720 | F66: 2.8027785e+10 | G66: =+VLOOKUP(A66,Ingresos!$A$1:$E$100,5,FALSE) -> 5.859341e+09 | H66: =+G66+F66 -> 3.3887126e+10 | I66: =IFERROR(H66/E66*100,0) -> 41.406234 | K66: =+H66/1000000 -> 33887.126
A67: 1-3-6-9 | B67: =+VLOOKUP(A67,Ingresos!$A$2:$B$82,2,FALSE) -> Recursos USPEC | C67: 37000000000 | D67: =+VLOOKUP(A67,Ingresos!$A$1:$F$90,3,FALSE) -> 0 | E67: =+VLOOKUP(A67,Ingresos!$A$1:$F$90,4,FALSE) -> 37000000000 | F67: 1.7280701e+10 | G67: =+VLOOKUP(A67,Ingresos!$A$1:$E$100,5,FALSE) -> 9.2966592e+08 | H67: =+G67+F67 -> 1.8210366e+10 | I67: =IFERROR(H67/E67*100,0) -> 49.217207 | K67: =+H67/1000000 -> 18210.366
A68: 2-0-0-0 | B68: RECURSOS DE CAPITAL | C68: 159585154000 | D68: =+D69+D73+D89+D97 -> 0 | E68: =+E69+E73+E89+E97 -> 159585154000 | F68: 1.9555559e+11 | G68: =+G69+G73+G89+G97 -> 4.2911469e+10 | H68: =+G68+F68 -> 2.3846706e+11 | I68: =IFERROR(H68/E68*100,0) -> 149.42935 | K68: =+H68/1000000 -> 238467.06
A69: 2-1-0-0 | B69: =+VLOOKUP(A69,Ingresos!$A$2:$B$82,2,FALSE) -> Recuperación de Cartera | C69: 80000000000 | D69: =+SUM(D70:D72) -> 0 | E69: =+SUM(E70:E72) -> 80000000000 | F69: 7.1024464e+10 | G69: =+SUM(G70:G72) -> 1.3612786e+10 | H69: =+G69+F69 -> 84637250123 | I69: =IFERROR(H69/E69*100,0) -> 105.79656 | K69: =+H69/1000000 -> 84637.25
A70: 2-1-0-0-01 | B70: =+VLOOKUP(A70,Ingresos!$A$2:$B$82,2,FALSE) -> Restitución operación Fosyga RS Ley 1608 de 2013 | C70: 0 | D70: =+VLOOKUP(A70,Ingresos!$A$1:$F$90,3,FALSE) -> 0 | E70: =+VLOOKUP(A70,Ingresos!$A$1:$F$90,4,FALSE) -> 0 | F70: 4407971624 | G70: =+VLOOKUP(A70,Ingresos!$A$1:$E$100,5,FALSE) -> 289487421 | H70: =+G70+F70 -> 4697459045 | I70: =IFERROR(H70/E70*100,0) -> 0 | K70: =+H70/1000000 -> 4697.459
A71: 2-1-0-0-02 | B71: =+VLOOKUP(A71,Ingresos!$A$2:$B$82,2,FALSE) -> Amortización Operaciones de Compra de Cartera | C71: 80000000000 | D71: =+VLOOKUP(A71,Ingresos!$A$1:$F$90,3,FALSE) -> 0 | E71: =+VLOOKUP(A71,Ingresos!$A$1:$F$90,4,FALSE) -> 80000000000 | F71: 6.6616493e+10 | G71: =+VLOOKUP(A71,Ingresos!$A$1:$E$100,5,FALSE) -> 1.3323299e+10 | H71: =+G71+F71 -> 79939791078 | I71: =IFERROR(H71/E71*100,0) -> 99.924739 | K71: =+H71/1000000 -> 79939.791
A72: 2-1-0-0-03 | B72: =+VLOOKUP(A72,Ingresos!$A$2:$B$82,2,FALSE) -> Recuperación Operaciones de Fortalecimiento Financiero y Patrimonial a entidades del sector salud | C72: 0 | D72: =+VLOOKUP(A72,Ingresos!$A$1:$F$90,3,FALSE) -> 0 | E72: =+VLOOKUP(A72,Ingresos!$A$1:$F$90,4,FALSE) -> 0 | F72: 0 | G72: =+VLOOKUP(A72,Ingresos!$A$1:$E$100,5,FALSE) -> 0 | H72: =+G72+F72 -> 0 | I72: =IFERROR(H72/E72*100,0) -> 0 | K72: =+H72/1000000 -> 0
A73: 2-4-0-0 | B73: =+VLOOKUP(A73,Ingresos!$A$2:$B$82,2,FALSE) -> Rendimientos Financieros e Intereses | C73: 24675676069 | D73: =+SUM(D74:D88) -> 0 | E73: =+SUM(E74:E88) -> 24675676069 | F73: 1.1210351e+11 | G73: =+SUM(G74:G88) -> 2.6485629e+10 | H73: =+G73+F73 -> 1.3858914e+11 | I73: =IFERROR(H73/E73*100,0) -> 561.64274 | K73: =+H73/1000000 -> 138589.14
A74: 2-4-0-0-01 | B74: =+VLOOKUP(A74,Ingresos!$A$2:$B$82,2,FALSE) -> Rendimientos cuentas de recaudo EPS -CSF- | C74: 0 | D74: =+VLOOKUP(A74,Ingresos!$A$1:$F$90,3,FALSE) -> 0 | E74: =+VLOOKUP(A74,Ingresos!$A$1:$F$90,4,FALSE) -> 0 | F74: 739646949 | G74: =+VLOOKUP(A74,Ingresos!$A$1:$E$100,5,FALSE) -> 499005938 | H74: =+G74+F74 -> 1238652887 | I74: =IFERROR(H74/E74*100,0) -> 0 | K74: =+H74/1000000 -> 1238.6529
A75: 2-4-0-0-02 | B75: =+VLOOKUP(A75,Ingresos!$A$2:$B$82,2,FALSE) -> Rendimientos cuentas de recaudo EPS -SSF- | C75: 7615081557 | D75: =+VLOOKUP(A75,Ingresos!$A$1:$F$90,3,FALSE) -> 0 | E75: =+VLOOKUP(A75,Ingresos!$A$1:$F$90,4,FALSE) -> 7615081557 | F75: 1552635328 | G75: =+VLOOKUP(A75,Ingresos!$A$1:$E$100,5,FALSE) -> 1188992875 | H75: =+G75+F75 -> 2741628203 | I75: =IFERROR(H75/E75*100,0) -> 36.002611 | K75: =+H75/1000000 -> 2741.6282
A76: 2-4-0-0-03 | B76: =+VLOOKUP(A76,Ingresos!$A$2:$B$82,2,FALSE) -> Rendimientos cuentas de Ahorros ADRES URA | C76: 7060594512 | D76: =+VLOOKUP(A76,Ingresos!$A$1:$F$90,3,FALSE) -> 0 | E76: =+VLOOKUP(A76,Ingresos!$A$1:$F$90,4,FALSE) -> 7060594512 | F76: 2.9968183e+10 | G76: =+VLOOKUP(A76,Ingresos!$A$1:$E$100,5,FALSE) -> 7.1049199e+09 | H76: =+G76+F76 -> 3.7073103e+10 | I76: =IFERROR(H76/E76*100,0) -> 525.07055 | K76: =+H76/1000000 -> 37073.103
A77: 2-4-0-0-04 | B77: =+VLOOKUP(A77,Ingresos!$A$2:$B$82,2,FALSE) -> Rendimientos cuentas de Corrientes ADRES URA | C77: 0 | D77: =+VLOOKUP(A77,Ingresos!$A$1:$F$90,3,FALSE) -> 0 | E77: =+VLOOKUP(A77,Ingresos!$A$1:$F$90,4,FALSE) -> 0 | F77: 0 | G77: =+VLOOKUP(A77,Ingresos!$A$1:$E$100,5,FALSE) -> 0 | H77: =+G77+F77 -> 0 | I77: =IFERROR(H77/E77*100,0) -> 0 | K77: =+H77/1000000 -> 0
A78: 2-4-0-0-06 | B78: =+VLOOKUP(A78,Ingresos!$A$2:$B$82,2,FALSE) -> Rendimientos sobre títulos del portafolio de Inversiones | C78: 0 | D78: =+VLOOKUP(A78,Ingresos!$A$1:$F$90,3,FALSE) -> 0 | E78: =+VLOOKUP(A78,Ingresos!$A$1:$F$90,4,FALSE) -> 0 | F78: 0 | G78: =+VLOOKUP(A78,Ingresos!$A$1:$E$100,5,FALSE) -> 0 | H78: =+G78+F78 -> 0 | I78: =IFERROR(H78/E78*100,0) -> 0 | K78: =+H78/1000000 -> 0
A79: 2-4-0-0-07 | B79: =+VLOOKUP(A79,Ingresos!$A$2:$B$82,2,FALSE) -> Rendimientos sobre recursos entregados en administración | C79: 0 | D79: =+VLOOKUP(A79,Ingresos!$A$1:$F$90,3,FALSE) -> 0 | E79: =+VLOOKUP(A79,Ingresos!$A$1:$F$90,4,FALSE) -> 0 | F79: 5.3533524e+09 | G79: =+VLOOKUP(A79,Ingresos!$A$1:$E$100,5,FALSE) -> 1168462595 | H79: =+G79+F79 -> 6.521815e+09 | I79: =IFERROR(H79/E79*100,0) -> 0 | K79: =+H79/1000000 -> 6521.815
A80: 2-4-0-0-08 | B80: =+VLOOKUP(A80,Ingresos!$A$2:$B$82,2,FALSE) -> Otros rendimientos financieros | C80: 0 | D80: =+VLOOKUP(A80,Ingresos!$A$1:$F$90,3,FALSE) -> 0 | E80: =+VLOOKUP(A80,Ingresos!$A$1:$F$90,4,FALSE) -> 0 | F80: 2.0925116e+09 | G80: =+VLOOKUP(A80,Ingresos!$A$1:$E$100,5,FALSE) -> 3.5670261e+08 | H80: =+G80+F80 -> 2.4492142e+09 | I80: =IFERROR(H80/E80*100,0) -> 0 | K80: =+H80/1000000 -> 2449.2142
A81: 2-4-0-0-09 | B81: =+VLOOKUP(A81,Ingresos!$A$2:$B$82,2,FALSE) -> Intereses Operaciones Compra de Cartera | C81: 0 | D81: =+VLOOKUP(A81,Ingresos!$A$1:$F$90,3,FALSE) -> 0 | E81: =+VLOOKUP(A81,Ingresos!$A$1:$F$90,4,FALSE) -> 0 | F81: 9.006802e+08 | G81: =+VLOOKUP(A81,Ingresos!$A$1:$E$100,5,FALSE) -> 46281374 | H81: =+G81+F81 -> 9.4696157e+08 | I81: =IFERROR(H81/E81*100,0) -> 0 | K81: =+H81/1000000 -> 946.96157
A82: 2-4-0-0-10 | B82: =+VLOOKUP(A82,Ingresos!$A$2:$B$82,2,FALSE) -> Intereses sobre restituciones | C82: 0 | D82: =+VLOOKUP(A82,Ingresos!$A$1:$F$90,3,FALSE) -> 0 | E82: =+VLOOKUP(A82,Ingresos!$A$1:$F$90,4,FALSE) -> 0 | F82: 4.052803e+08 | G82: =+VLOOKUP(A82,Ingresos!$A$1:$E$100,5,FALSE) -> 3.9285545e+08 | H82: =+G82+F82 -> 7.9813575e+08 | I82: =IFERROR(H82/E82*100,0) -> 0 | K82: =+H82/1000000 -> 798.13575
A83: 2-4-0-0-11 | B83: =+VLOOKUP(A83,Ingresos!$A$2:$B$82,2,FALSE) -> Intereses de mora sobre compra de cartera | C83: 0 | D83: =+VLOOKUP(A83,Ingresos!$A$1:$F$90,3,FALSE) -> 0 | E83: =+VLOOKUP(A83,Ingresos!$A$1:$F$90,4,FALSE) -> 0 | F83: 0 | G83: =+VLOOKUP(A83,Ingresos!$A$1:$E$100,5,FALSE) -> 0 | H83: =+G83+F83 -> 0 | I83: =IFERROR(H83/E83*100,0) -> 0 | K83: =+H83/1000000 -> 0
A84: 2-4-0-0-12 | B84: =+VLOOKUP(A84,Ingresos!$A$2:$B$82,2,FALSE) -> Intereses de mora sobre restituciones | C84: 0 | D84: =+VLOOKUP(A84,Ingresos!$A$1:$F$90,3,FALSE) -> 0 | E84: =+VLOOKUP(A84,Ingresos!$A$1:$F$90,4,FALSE) -> 0 | F84: 5.5168663e+10 | G84: =+VLOOKUP(A84,Ingresos!$A$1:$E$100,5,FALSE) -> 2.6810627e+09 | H84: =+G84+F84 -> 5.7849726e+10 | I84: =IFERROR(H84/E84*100,0) -> 0 | K84: =+H84/1000000 -> 57849.726
A85: 2-4-0-0-13 | B85: =+VLOOKUP(A85,Ingresos!$A$2:$B$82,2,FALSE) -> Intereses de mora cotizaciones R.C. | C85: 10000000000 | D85: =+VLOOKUP(A85,Ingresos!$A$1:$F$90,3,FALSE) -> 0 | E85: =+VLOOKUP(A85,Ingresos!$A$1:$F$90,4,FALSE) -> 10000000000 | F85: 15908300448 | G85: =+VLOOKUP(A85,Ingresos!$A$1:$E$100,5,FALSE) -> 13025708908 | H85: =+G85+F85 -> 28934009356 | I85: =IFERROR(H85/E85*100,0) -> 289.34009 | K85: =+H85/1000000 -> 28934.009
... A88: 2-4-0-0-16 | B88: =+VLOOKUP(A88,Ingresos!$A$2:$B$82,2,FALSE) -> Otros Intereses | C88: 0 | D88: =+VLOOKUP(A88,Ingresos!$A$1:$F$90,3,FALSE) -> 0 | E88: =+VLOOKUP(A88,Ingresos!$A$1:$F$90,4,FALSE) -> 0 | F88: 1545548 | G88: =+VLOOKUP(A88,Ingresos!$A$1:$E$100,5,FALSE) -> 21592613 | H88: =+G88+F88 -> 23138161 | I88: =IFERROR(H88/E88*100,0) -> 0 | K88: =+H88/1000000 -> 23.138161
A89: 2-5-0-0 | B89: =+VLOOKUP(A89,Ingresos!$A$2:$B$82,2,FALSE) -> Recusos con destinación específica | C89: 54909477931 | D89: =+SUM(D90:D96) -> 0 | E89: =+SUM(E90:E96) -> 54909477931 | F89: 1.2417742e+10 | G89: =+SUM(G90:G96) -> 2813054219 | H89: =+G89+F89 -> 1.5230796e+10 | I89: =IFERROR(H89/E89*100,0) -> 27.738009 | K89: =+H89/1000000 -> 15230.796
A90: 2-5-0-0-01 | B90: =+VLOOKUP(A90,Ingresos!$A$2:$B$82,2,FALSE) -> Excedentes -Servicios prestados a la población pobre y los servicios No POS entidades territoriales. (Num, 2 art. 3 Ley 1608 de 2013) | C90: 0 | D90: =+VLOOKUP(A90,Ingresos!$A$1:$F$90,3,FALSE) -> 0 | E90: =+VLOOKUP(A90,Ingresos!$A$1:$F$90,4,FALSE) -> 0 | F90: 0 | G90: =+VLOOKUP(A90,Ingresos!$A$1:$E$100,5,FALSE) -> 0 | H90: =+G90+F90 -> 0 | I90: =IFERROR(H90/E90*100,0) -> 0 | K90: =+H90/1000000 -> 0
A91: 2-5-0-0-02 | B91: =+VLOOKUP(A91,Ingresos!$A$2:$B$82,2,FALSE) -> Recursos SGP Propósito General Libre Inversión | C91: 13909477931 | D91: =+VLOOKUP(A91,Ingresos!$A$1:$F$90,3,FALSE) -> 0 | E91: =+VLOOKUP(A91,Ingresos!$A$1:$F$90,4,FALSE) -> 13909477931 | F91: 2034063044 | G91: =+VLOOKUP(A91,Ingresos!$A$1:$E$100,5,FALSE) -> 428064192 | H91: =+G91+F91 -> 2462127236 | I91: =IFERROR(H91/E91*100,0) -> 17.701076 | K91: =+H91/1000000 -> 2462.1272
A92: 2-5-0-0-03 | B92: =+VLOOKUP(A92,Ingresos!$A$2:$B$82,2,FALSE) -> Excedentes recursos FAEP para el reconocimiento de deuda por contratos del Régimen Subsidiado realizados hasta marzo 31 de 2011. | C92: 0 | D92: =+VLOOKUP(A92,Ingresos!$A$1:$F$90,3,FALSE) -> 0 | E92: =+VLOOKUP(A92,Ingresos!$A$1:$F$90,4,FALSE) -> 0 | F92: 0 | G92: =+VLOOKUP(A92,Ingresos!$A$1:$E$100,5,FALSE) -> 0 | H92: =+G92+F92 -> 0 | I92: =IFERROR(H92/E92*100,0) -> 0 | K92: =+H92/1000000 -> 0
A93: 2-5-0-0-04 | B93: =+VLOOKUP(A93,Ingresos!$A$2:$B$82,2,FALSE) -> Excedentes recursos de LOTTO en línea -FONPET para reconocimiento de deuda por contratos del Régimen Subsidiado realizados hasta marzo 31 de 2011 | C93: 2000000000 | D93: =+VLOOKUP(A93,Ingresos!$A$1:$F$90,3,FALSE) -> 0 | E93: =+VLOOKUP(A93,Ingresos!$A$1:$F$90,4,FALSE) -> 2000000000 | F93: 0 | G93: =+VLOOKUP(A93,Ingresos!$A$1:$E$100,5,FALSE) -> 0 | H93: =+G93+F93 -> 0 | I93: =IFERROR(H93/E93*100,0) -> 0 | K93: =+H93/1000000 -> 0
A94: 2-5-0-0-05 | B94: =+VLOOKUP(A94,Ingresos!$A$2:$B$82,2,FALSE) -> Excedentes de Aportes Patronales / Resolución 2360 de 2016 | C94: 0 | D94: =+VLOOKUP(A94,Ingresos!$A$1:$F$90,3,FALSE) -> 0 | E94: =+VLOOKUP(A94,Ingresos!$A$1:$F$90,4,FALSE) -> 0 | F94: 42930874 | G94: =+VLOOKUP(A94,Ingresos!$A$1:$E$100,5,FALSE) -> 0 | H94: =+G94+F94 -> 42930874 | I94: =IFERROR(H94/E94*100,0) -> 0 | K94: =+H94/1000000 -> 42.930874
A95: 2-5-0-0-06 | B95: =+VLOOKUP(A95,Ingresos!$A$2:$B$82,2,FALSE) -> Regalías – artículo 5 Ley 1797 de 2016 | C95: 3000000000 | D95: =+VLOOKUP(A95,Ingresos!$A$1:$F$90,3,FALSE) -> 0 | E95: =+VLOOKUP(A95,Ingresos!$A$1:$F$90,4,FALSE) -> 3000000000 | F95: 0 | G95: =+VLOOKUP(A95,Ingresos!$A$1:$E$100,5,FALSE) -> 0 | H95: =+G95+F95 -> 0 | I95: =IFERROR(H95/E95*100,0) -> 0 | K95: =+H95/1000000 -> 0
A96: 2-5-0-0-07 | B96: =+VLOOKUP(A96,Ingresos!$A$2:$B$82,2,FALSE) -> Recursos CCF / FOSFEC - Ley 1929 de 2018 | C96: 36000000000 | D96: =+VLOOKUP(A96,Ingresos!$A$1:$F$90,3,FALSE) -> 0 | E96: =+VLOOKUP(A96,Ingresos!$A$1:$F$90,4,FALSE) -> 36000000000 | F96: 1.0340748e+10 | G96: =+VLOOKUP(A96,Ingresos!$A$1:$E$100,5,FALSE) -> 2384990027 | H96: =+G96+F96 -> 1.2725738e+10 | I96: =IFERROR(H96/E96*100,0) -> 35.349272 | K96: =+H96/1000000 -> 12725.738
A97: 2-9-0-0 | B97: =+VLOOKUP(A97,Ingresos!$A$2:$B$82,2,FALSE) -> Otros Recursos de Capital | C97: 0 | D97: =+SUM(D98:D99) -> 0 | E97: =+SUM(E98:E99) -> 0 | F97: 9872709.1 | G97: =+SUM(G98:G99) -> 0 | H97: =+G97+F97 -> 9872709.1 | I97: =IFERROR(H97/E97*100,0) -> 0 | K97: =+H97/1000000 -> 9.8727091
A98: 2-9-0-0-01 | B98: =+VLOOKUP(A98,Ingresos!$A$2:$B$82,2,FALSE) -> Liquidación patrimonios autónomos Sector Salud | C98: 0 | D98: =+VLOOKUP(A98,Ingresos!$A$1:$F$90,3,FALSE) -> 0 | E98: =+VLOOKUP(A98,Ingresos!$A$1:$F$90,4,FALSE) -> 0 | F98: 0 | G98: =+VLOOKUP(A98,Ingresos!$A$1:$E$100,5,FALSE) -> 0 | H98: =+G98+F98 -> 0 | I98: =IFERROR(H98/E98*100,0) -> 0 | K98: =+H98/1000000 -> 0
A99: 2-9-0-0-02 | B99: =+VLOOKUP(A99,Ingresos!$A$2:$B$82,2,FALSE) -> Otros Recursos de Capital no contemplados en los anteriores | C99: 0 | D99: =+VLOOKUP(A99,Ingresos!$A$1:$F$90,3,FALSE) -> 0 | E99: =+VLOOKUP(A99,Ingresos!$A$1:$F$90,4,FALSE) -> 0 | F99: 9872709.1 | G99: =+VLOOKUP(A99,Ingresos!$A$1:$E$100,5,FALSE) -> 0 | H99: =+G99+F99 -> 9872709.1 | I99: =IFERROR(H99/E99*100,0) -> 0 | K99: =+H99/1000000 -> 9.8727091
B101: TOTAL | C101: =+C68+C13+C12 -> 52636824590223 | D101: =+D68+D13+D12 -> 488101188290 | E101: =+E68+E13+E12 -> 53124925778513 | F101: =+F68+F13+F12 -> 2.1840338e+13 | G101: =+G68+G13+G12 -> 4.5278154e+12 | H101: =+H68+H13+H12 -> 2.6368153e+13 | I101: =IFERROR(H101/E101*100,0) -> 49.634241
C102: 52636824590223 | D102: 488101188290 | E102: 53124925778513 | F102: 2.1840338e+13 | G102: 4.5278154e+12 | H102: 2.6368153e+13 | I102: 49.63
C103: =+C102-C101 -> 0 | D103: =+D102-D101 -> 0 | E103: =+E102-E101 -> 0 | F103: =+F102-F101 -> -0.08203125 | G103: =+G102-G101 -> 0 | H103: =+H102-H101 -> -0.08984375 | I103: =+I102-I101 -> -0.0042405293
F104: dif. Por el excel | H104: dif. Por el excel
H106: =+H101/1000000 -> 26368153

Sheet Ingresos
A1: RUBRO | B1: inicial | C1: MODIFICACIONES | D1: AFORO DEFINITIVO | E1: INGRESO MES | F1: % | G1: acum
A2: 0-0-0-0 | B2: Disponibilidad inicial | C2: 488101188290 | D2: 910932869290 | E2: 488101188290 | F2: 100 | G2: 910932869290 | H2: =+VLOOKUP(A2,'CUADRO 1-EJECUCION DE INGRESOS'!$A$12:$I$99,8,FALSE) -> 910932869290 | I2: =+H2-G2 -> 0
A3: 1-2-1-1 | B3: Aportes de la Nación para el Aseguramiento en Salud | C3: 0 | D3: 17803782346000 | E3: 1166604084389 | F3: 45.05 | G3: 8.0209578e+12 | H3: =+VLOOKUP(A3,'CUADRO 1-EJECUCION DE INGRESOS'!$A$12:$I$99,8,FALSE) -> 8.0209578e+12 | I3: =+H3-G3 -> 0
A4: 1-2-1-1-01 | B4: Aportes de la Nación para el Aseguramiento en Salud Cierre | C4: 0 | D4: 12507321670830 | E4: 8.1955015e+11 | F4: 45.05 | G4: 5.634797e+12 | H4: =+VLOOKUP(A4,'CUADRO 1-EJECUCION DE INGRESOS'!$A$12:$I$99,8,FALSE) -> 5.634797e+12 | I4: =+H4-G4 -> 0
A5: 1-2-1-1-02 | B5: Imporenta | C5: 0 | D5: 5296460675170 | E5: 3.4705393e+11 | F5: 45.05 | G5: 2.3861608e+12 | H5: =+VLOOKUP(A5,'CUADRO 1-EJECUCION DE INGRESOS'!$A$12:$I$99,8,FALSE) -> 2.3861608e+12 | I5: =+H5-G5 -> 0
A6: 1-2-1-2 | B6: Compensación Regalías para el Régimen Subsidiado | C6: 0 | D6: 226673765000 | E6: 0 | F6: 100 | G6: 226673765000 | H6: =+VLOOKUP(A6,'CUADRO 1-EJECUCION DE INGRESOS'!$A$12:$I$99,8,FALSE) -> 226673765000 | I6: =+H6-G6 -> 0
A7: 1-2-1-3 | B7: Impuesto sobre la renta para la equidad CREE | C7: 0 | D7: 0 | E7: 0 | F7: 0 | G7: 0 | H7: =+VLOOKUP(A7,'CUADRO 1-EJECUCION DE INGRESOS'!$A$12:$I$99,8,FALSE) -> 0 | I7: =+H7-G7 -> 0
A8: 1-2-1-4 | B8: SGP FONSAET | C8: 0 | D8: 95551523562 | E8: 0 | F8: 0 | G8: 0 | H8: =+VLOOKUP(A8,'CUADRO 1-EJECUCION DE INGRESOS'!$A$12:$I$99,8,FALSE) -> 0 | I8: =+H8-G8 -> 0
A9: 1-2-1-5 | B9: PRIMA FONSAT Y CONTRIBUCION SOAT | C9: 0 | D9: 1640527441000 | E9: 111862061274 | F9: 54.75 | G9: 8.9814347e+11 | H9: =+VLOOKUP(A9,'CUADRO 1-EJECUCION DE INGRESOS'!$A$12:$I$99,8,FALSE) -> 8.9814347e+11 | I9: =+H9-G9 -> 0
A10: 1-2-1-5-01 | B10: % Prima (FONSAT) Decreto Ley 1335 de 2009 | C10: 0 | D10: 363281118360 | E10: 0 | F10: 54.36 | G10: 1.9749469e+11 | H10: =+VLOOKUP(A10,'CUADRO 1-EJECUCION DE INGRESOS'!$A$12:$I$99,8,FALSE) -> 1.9749469e+11 | I10: =+H10-G10 -> 0
A11: 1-2-1-5-02 | B11: Contribución Seguro Obligatorio de Accidentes de Tránsito - SOAT- Decreto Ley 1335 de 2009 | C11: 0 | D11: 1277246322640 | E11: 111862061274 | F11: 54.86 | G11: 7.0064878e+11 | H11: =+VLOOKUP(A11,'CUADRO 1-EJECUCION DE INGRESOS'!$A$12:$I$99,8,FALSE) -> 7.0064878e+11 | I11: =+H11-G11 -> 0
A12: 1-2-1-7 | B12: Impuesto social a las municiones y explosivos | C12: 0 | D12: 6410791000 | E12: 14354115977 | F12: 922.91 | G12: 59165621680 | H12: =+VLOOKUP(A12,'CUADRO 1-EJECUCION DE INGRESOS'!$A$12:$I$99,8,FALSE) -> 59165621680 | I12: =+H12-G12 -> 0
A13: 1-2-1-8 | B13: Impuesto social a las armas | C13: 0 | D13: 8851770619 | E13: 1000447745 | F13: 54.72 | G13: 4843738392 | H13: =+VLOOKUP(A13,'CUADRO 1-EJECUCION DE INGRESOS'!$A$12:$I$99,8,FALSE) -> 4843738392 | I13: =+H13-G13 -> 0
... A82: 2-9-0-0-02 | B82: Otros Recursos de Capital no contemplados en los anteriores | C82: 0 | D82: 0 | E82: 0 | F82: 0 | G82: 9872709.1 | H82: =+VLOOKUP(A82,'CUADRO 1-EJECUCION DE INGRESOS'!$A$12:$I$99,8,FALSE) -> 9872709.1 | I82: =+H82-G82 -> 0

Sheet CUADRO 2-EJECUCION DE GASTOS
M1: =+TODAY() -> 43676 | N1: =+NOW() -> 43676.359
A3: ADMINISTRADORA DE LOS RECURSOS DEL SISTEMA GENERAL DE SEGURIDAD SOCIAL EN SALUD
A4: UNIDAD DE RECURSOS ADMINISTRADOS - URA
A5: CODIGO DE LA EMPRESA 12902 - ADMINISTRACION DE RECURSOS DEL SGSSS
A6: PRESUPUESTO DE GASTOS JUNIO DE 2019
A7: CUADRO No. 2
A10: CÓDIGO RUBRO | B10: CONCEPTO DEL RUBRO | C10: APROPIACIÓN DEFINITIVA | D10: EJECUCION PRESUPUESTAL ACUMULADA DESDE 01/01/2019 HASTA 31/05/2019 | G10: EJECUCION PRESUPUESTAL DESDE 01/06/2019 HASTA 30/06/2019 | J10: EJECUCION PRESUPUESTAL ACUMULADA DESDE 01/01/2019 HASTA 30/06/2019 | M10: %
D11: T. CDP | E11: T. RP | F11: T. PAGOS-OG | G11: CDP | H11: RP | I11: PAGOS-OG | J11: T. CDP | K11: T. RP | L11: T. PAGOS-OG | M11: RP | N11: OG
B12: URA
A13: A-3-0-0-0 | B13: TRANSFERENCIAS | C13: =+C14+C19+C25 -> 52870917903513 | D13: 3.2327818e+13 | E13: 2.0416053e+13 | F13: 2.0416053e+13 | G13: =+G14+G19+G25 -> 1.1969033e+13 | H13: =+H14+H19+H25 -> 4.260865e+12 | I13: =+I14+I19+I25 -> 4.260865e+12 | J13: =+G13+D13 -> 4.4296851e+13 | K13: =+H13+E13 -> 2.4676918e+13 | L13: =+I13+F13 -> 2.4676918e+13 | M13: =+IFERROR(K13*100/C13,0) -> 46.673897 | N13: =+IFERROR(L13*100/C13,0) -> 46.673897
A14: A-3-2-0-0 | B14: TRANSFERENCIAS AL SECTOR PUBLICO | C14: =+C15+C17 -> 231725030430 | D14: 228185519661 | E14: 5.0402254e+10 | F14: 5.0402254e+10 | G14: =+G15+G17 -> 0 | H14: =+H15+H17 -> 1.0967286e+10 | I14: =+I15+I17 -> 1.0967286e+10 | J14: =+G14+D14 -> 228185519661 | K14: =+H14+E14 -> 6.136954e+10 | L14: =+I14+F14 -> 6.136954e+10 | M14: =+IFERROR(K14*100/C14,0) -> 26.483777 | N14: =+IFERROR(L14*100/C14,0) -> 26.483777
A15: A-3-2-1-0 | B15: =+VLOOKUP(A15,gasto!$A$4:$B$78,2,FALSE) -> Transferencias Entidades de Administración Pública Central | C15: =+C16 -> 86345030430 | D15: 82805519661 | E15: 3.4440853e+10 | F15: 3.4440853e+10 | G15: =+G16 -> 0 | H15: =+H16 -> 6.8799777e+09 | I15: =+I16 -> 6.8799777e+09 | J15: =+J16 -> 82805519661 | K15: =+K16 -> 4.1320831e+10 | L15: =+L16 -> 4.1320831e+10 | M15: =+IFERROR(K15*100/C15,0) -> 47.855482 | N15: =+IFERROR(L15*100/C15,0) -> 47.855482
A16: A-3-2-1-01 | B16: =+VLOOKUP(A16,gasto!$A$4:$B$78,2,FALSE) -> Contribución IVC Superintendencia Nacional de Salud | C16: =+VLOOKUP(A16,gasto!$A$4:$F$68,3,FALSE) -> 86345030430 | D16: 82805519661 | E16: 3.4440853e+10 | F16: 3.4440853e+10 | G16: =+VLOOKUP(A16,gasto!$A$4:$F$68,4,FALSE) -> 0 | H16: =+VLOOKUP(A16,gasto!$A$4:$F$68,5,FALSE) -> 6.8799777e+09 | I16: =+VLOOKUP(A16,gasto!$A$4:$F$68,6,FALSE) -> 6.8799777e+09 | J16: =+G16+D16 -> 82805519661 | K16: =+H16+E16 -> 4.1320831e+10 | L16: =+I16+F16 -> 4.1320831e+10 | M16: =+IFERROR(K16*100/C16,0) -> 47.855482 | N16: =+IFERROR(L16*100/C16,0) -> 47.855482
A17: A-3-2-2-0 | B17: =+VLOOKUP(A17,gasto!$A$4:$B$78,2,FALSE) -> Empresas Públicas Nacionales no financieras -ADRES | C17: =+C18 -> 145380000000 | D17: 145380000000 | E17: 1.5961401e+10 | F17: 1.5961401e+10 | G17: =+G18 -> 0 | H17: =+H18 -> 4.0873081e+09 | I17: =+I18 -> 4.0873081e+09 | J17: =+J18 -> 145380000000 | K17: =+K18 -> 20048709556 | L17: =+L18 -> 20048709556 | M17: =+IFERROR(K17*100/C17,0) -> 13.790555 | N17: =+IFERROR(L17*100/C17,0) -> 13.790555
A18: A-3-2-2-0-01 | B18: =+VLOOKUP(A18,gasto!$A$4:$B$78,2,FALSE) -> Aportes hasta del 0,5% recursos CSF para el desarrollo objeto ADRES | C18: =+VLOOKUP(A18,gasto!$A$4:$F$68,3,FALSE) -> 145380000000 | D18: 145380000000 | E18: 1.5961401e+10 | F18: 1.5961401e+10 | G18: =+VLOOKUP(A18,gasto!$A$4:$F$68,4,FALSE) -> 0 | H18: =+VLOOKUP(A18,gasto!$A$4:$F$68,5,FALSE) -> 4.0873081e+09 | I18: =+VLOOKUP(A18,gasto!$A$4:$F$68,6,FALSE) -> 4.0873081e+09 | J18: =+G18+D18 -> 145380000000 | K18: =+H18+E18 -> 20048709556 | L18: =+I18+F18 -> 20048709556 | M18: =+IFERROR(K18*100/C18,0) -> 13.790555 | N18: =+IFERROR(L18*100/C18,0) -> 13.790555
A19: A-3-6-0-0 | B19: OTRAS TRANSFERENCIAS | C19: =+C20+C23 -> 154000000000 | D19: 1.4869192e+09 | E19: 1.3283279e+09 | F19: 1.3283279e+09 | G19: =+G20+G23 -> 2.722844e+08 | H19: =+H20+H23 -> 2.722844e+08 | I19: =+I20+I23 -> 2.722844e+08 | J19: =+G19+D19 -> 1.7592036e+09 | K19: =+H19+E19 -> 1.6006123e+09 | L19: =+I19+F19 -> 1.6006123e+09 | M19: =+IFERROR(K19*100/C19,0) -> 1.0393586 | N19: =+IFERROR(L19*100/C19,0) -> 1.0393586
A20: A-3-6-1-0 | B20: =+VLOOKUP(A20,gasto!$A$4:$B$78,2,FALSE) -> Sentencias y Conciliaciones URA | C20: =+SUM(C21:C22) -> 20000000000 | D20: 1.4869192e+09 | E20: 1.3283279e+09 | F20: 1.3283279e+09 | G20: =+SUM(G21:G22) -> 2.722844e+08 | H20: =+SUM(H21:H22) -> 2.722844e+08 | I20: =+SUM(I21:I22) -> 2.722844e+08 | J20: =+SUM(J21:J22) -> 1.7592036e+09 | K20: =+SUM(K21:K22) -> 1.6006123e+09 | L20: =+SUM(L21:L22) -> 1.6006123e+09 | M20: =+IFERROR(K20*100/C20,0) -> 8.0030615 | N20: =+IFERROR(L20*100/C20,0) -> 8.0030615
A21: A-3-6-1-1 | B21: =+VLOOKUP(A21,gasto!$A$4:$B$78,2,FALSE) -> Sentencias URA | C21: =+VLOOKUP(A21,gasto!$A$4:$F$68,3,FALSE) -> 20000000000 | D21: 1.4869192e+09 | E21: 1.3283279e+09 | F21: 1.3283279e+09 | G21: =+VLOOKUP(A21,gasto!$A$4:$F$68,4,FALSE) -> 2.722844e+08 | H21: =+VLOOKUP(A21,gasto!$A$4:$F$68,5,FALSE) -> 2.722844e+08 | I21: =+VLOOKUP(A21,gasto!$A$4:$F$68,6,FALSE) -> 2.722844e+08 | J21: =+G21+D21 -> 1.7592036e+09 | K21: =+H21+E21 -> 1.6006123e+09 | L21: =+I21+F21 -> 1.6006123e+09 | M21: =+IFERROR(K21*100/C21,0) -> 8.0030615 | N21: =+IFERROR(L21*100/C21,0) -> 8.0030615
A22: A-3-6-1-2 | B22: =+VLOOKUP(A22,gasto!$A$4:$B$78,2,FALSE) -> Conciliaciones URA | C22: =+VLOOKUP(A22,gasto!$A$4:$F$68,3,FALSE) -> 0 | D22: 0 | E22: 0 | F22: 0 | G22: =+VLOOKUP(A22,gasto!$A$4:$F$68,4,FALSE) -> 0 | H22: =+VLOOKUP(A22,gasto!$A$4:$F$68,5,FALSE) -> 0 | I22: =+VLOOKUP(A22,gasto!$A$4:$F$68,6,FALSE) -> 0 | J22: =+G22+D22 -> 0 | K22: =+H22+E22 -> 0 | L22: =+I22+F22 -> 0 | M22: =+IFERROR(K22*100/C22,0) -> 0 | N22: =+IFERROR(L22*100/C22,0) -> 0
A23: A-3-6-3-0 | B23: =+VLOOKUP(A23,gasto!$A$4:$B$78,2,FALSE) -> Destinatarios de otras transferencias Corrientes - Compensación Chance | C23: =+C24 -> 134000000000 | D23: 0 | E23: 0 | F23: 0 | G23: =+G24 -> 0 | H23: =+H24 -> 0 | I23: =+I24 -> 0 | J23: =+J24 -> 0 | K23: =+K24 -> 0 | L23: =+L24 -> 0 | M23: =+IFERROR(K23*100/C23,0) -> 0 | N23: =+IFERROR(L23*100/C23,0) -> 0
A24: A-3-6-3-0-01 | B24: =+VLOOKUP(A24,gasto!$A$4:$B$78,2,FALSE) -> Otras transferencias - Compensación del Chance Decreto 2550/12 | C24: =+VLOOKUP(A24,gasto!$A$4:$F$68,3,FALSE) -> 134000000000 | D24: 0 | E24: 0 | F24: 0 | G24: =+VLOOKUP(A24,gasto!$A$4:$F$68,4,FALSE) -> 0 | H24: =+VLOOKUP(A24,gasto!$A$4:$F$68,5,FALSE) -> 0 | I24: =+VLOOKUP(A24,gasto!$A$4:$F$68,6,FALSE) -> 0 | J24: =+G24+D24 -> 0 | K24: =+H24+E24 -> 0 | L24: =+I24+F24 -> 0 | M24: =+IFERROR(K24*100/C24,0) -> 0 | N24: =+IFERROR(L24*100/C24,0) -> 0
A25: A-3-9-0-0 | B25: ADMINISTRACIÓN DE RECURSOS DEL SGSSS | C25: =+C26+C31+C34+C37+C38+C39+C43+C46+C53+C57+C67+C78+C80+C82+C86 -> 52485192873083 | D25: 3.2098145e+13 | E25: 2.0364322e+13 | F25: 2.0364322e+13 | G25: =+G26+G31+G34+G37+G38+G39+G43+G46+G53+G57+G67+G78+G80+G82+G86 -> 1.1968761e+13 | H25: =+H26+H31+H34+H37+H38+H39+H43+H46+H53+H57+H67+H78+H80+H82+H86 -> 4.2496254e+12 | I25: =+I26+I31+I34+I37+I38+I39+I43+I46+I53+I57+I67+I78+I80+I82+I86 -> 4.2496254e+12 | J25: =+J26+J31+J34+J37+J38+J39+J43+J46+J53+J57+J67+J78+J80+J82+J86 -> 4.4066906e+13 | K25: =+K26+K31+K34+K37+K38+K39+K43+K46+K53+K57+K67+K78+K80+K82+K86 -> 2.4613948e+13 | L25: =+L26+L31+L34+L37+L38+L39+L43+L46+L53+L57+L67+L78+L80+L82+L86 -> 2.4613948e+13 | M25: =+IFERROR(K25*100/C25,0) -> 46.896936 | N25: =+IFERROR(L25*100/C25,0) -> 46.896936
A26: A-3-9-1-0 | B26: =+VLOOKUP(A26,gasto!$A$4:$B$78,2,FALSE) -> UPC Régimen Contributivo | C26: =+SUM(C27:C30) -> 23048224384378 | D26: 1.9520467e+13 | E26: 9172910812472 | F26: 9172910812472 | G26: =+SUM(G27:G30) -> -1124078341 | H26: =+SUM(H27:H30) -> 1797826867199 | I26: =+SUM(I27:I30) -> 1797826867199 | J26: =+SUM(J27:J30) -> 1.9519343e+13 | K26: =+SUM(K27:K30) -> 10970737679671 | L26: =+SUM(L27:L30) -> 10970737679671 | M26: =+IFERROR(K26*100/C26,0) -> 47.599058 | N26: =+IFERROR(L26*100/C26,0) -> 47.599058
A27: A-3-9-1-0-01 | B27: =+VLOOKUP(A27,gasto!$A$4:$B$78,2,FALSE) -> UPC Régimen Contributivo SSF | C27: =+VLOOKUP(A27,gasto!$A$4:$F$68,3,FALSE) -> 12399109660289 | D27: 1.0510693e+13 | E27: 4993045161610 | F27: 4993045161610 | G27: =+VLOOKUP(A27,gasto!$A$4:$F$68,4,FALSE) -> -1124078341 | H27: =+VLOOKUP(A27,gasto!$A$4:$F$68,5,FALSE) -> 1013005546507 | I27: =+VLOOKUP(A27,gasto!$A$4:$F$68,6,FALSE) -> 1013005546507 | J27: =+G27+D27 -> 1.0509568e+13 | K27: =+H27+E27 -> 6006050708117 | L27: =+I27+F27 -> 6006050708117 | M27: =+IFERROR(K27*100/C27,0) -> 48.439371 | N27: =+IFERROR(L27*100/C27,0) -> 48.439371
A28: A-3-9-1-0-02 | B28: =+VLOOKUP(A28,gasto!$A$4:$B$78,2,FALSE) -> UPC Régimen Contributivo CSF | C28: =+VLOOKUP(A28,gasto!$A$4:$F$68,3,FALSE) -> 10647939289644 | D28: 9008599217429 | E28: 4178690216417 | F28: 4178690216417 | G28: =+VLOOKUP(A28,gasto!$A$4:$F$68,4,FALSE) -> 0 | H28: =+VLOOKUP(A28,gasto!$A$4:$F$68,5,FALSE) -> 784821320692 | I28: =+VLOOKUP(A28,gasto!$A$4:$F$68,6,FALSE) -> 784821320692 | J28: =+G28+D28 -> 9008599217429 | K28: =+H28+E28 -> 4963511537109 | L28: =+I28+F28 -> 4963511537109 | M28: =+IFERROR(K28*100/C28,0) -> 46.614762 | N28: =+IFERROR(L28*100/C28,0) -> 46.614762
A29: A-3-9-1-0-03 | B29: =+VLOOKUP(A29,gasto!$A$4:$B$78,2,FALSE) -> Devolución aportes y cotizaciones no conciliadas vigencia anterior | C29: =+VLOOKUP(A29,gasto!$A$4:$F$68,3,FALSE) -> 1175434445 | D29: 1175434445 | E29: 1175434445 | F29: 1175434445 | G29: =+VLOOKUP(A29,gasto!$A$4:$F$68,4,FALSE) -> 0 | H29: =+VLOOKUP(A29,gasto!$A$4:$F$68,5,FALSE) -> 0 | I29: =+VLOOKUP(A29,gasto!$A$4:$F$68,6,FALSE) -> 0 | J29: =+G29+D29 -> 1175434445 | K29: =+H29+E29 -> 1175434445 | L29: =+I29+F29 -> 1175434445 | M29: =+IFERROR(K29*100/C29,0) -> 100 | N29: =+IFERROR(L29*100/C29,0) -> 100
A30: A-3-9-1-0-04 | B30: =+VLOOKUP(A30,gasto!$A$4:$B$78,2,FALSE) -> Rendimientos Financieros de los Saldos no Compensados de los Aportes Patronales según Art. 12 Decreto 1636 de 2016 | C30: =+VLOOKUP(A30,gasto!$A$4:$F$68,3,FALSE) -> 0 | D30: 0 | E30: 0 | F30: 0 | G30: =+VLOOKUP(A30,gasto!$A$4:$F$68,4,FALSE) -> 0 | H30: =+VLOOKUP(A30,gasto!$A$4:$F$68,5,FALSE) -> 0 | I30: =+VLOOKUP(A30,gasto!$A$4:$F$68,6,FALSE) -> 0 | J30: =+G30+D30 -> 0 | K30: =+H30+E30 -> 0 | L30: =+I30+F30 -> 0 | M30: =+IFERROR(K30*100/C30,0) -> 0 | N30: =+IFERROR(L30*100/C30,0) -> 0
A31: A-3-9-2-0 | B31: =+VLOOKUP(A31,gasto!$A$4:$B$78,2,FALSE) -> Per capita Programas de Promoción y Prevención R.C | C31: =+SUM(C32:C33) -> 646778600953 | D31: 5.4189833e+11 | E31: 208386452767 | F31: 208386452767 | G31: =+SUM(G32:G33) -> -33698721 | H31: =+SUM(H32:H33) -> 40512450447 | I31: =+SUM(I32:I33) -> 40512450447 | J31: =+SUM(J32:J33) -> 5.4186464e+11 | K31: =+SUM(K32:K33) -> 248898903214 | L31: =+SUM(L32:L33) -> 248898903214 | M31: =+IFERROR(K31*100/C31,0) -> 38.48286 | N31: =+IFERROR(L31*100/C31,0) -> 38.48286
A32: A-3-9-2-0-01 | B32: =+VLOOKUP(A32,gasto!$A$4:$B$78,2,FALSE) -> Per capita Programas de Promoción y Prevención R.C SSF | C32: =+VLOOKUP(A32,gasto!$A$4:$F$68,3,FALSE) -> 510526042986 | D32: 4.2815967e+11 | E32: 165955167375 | F32: 165955167375 | G32: =+VLOOKUP(A32,gasto!$A$4:$F$68,4,FALSE) -> -33698721 | H32: =+VLOOKUP(A32,gasto!$A$4:$F$68,5,FALSE) -> 33181647751 | I32: =+VLOOKUP(A32,gasto!$A$4:$F$68,6,FALSE) -> 33181647751 | J32: =+G32+D32 -> 4.2812597e+11 | K32: =+H32+E32 -> 199136815126 | L32: =+I32+F32 -> 199136815126 | M32: =+IFERROR(K32*100/C32,0) -> 39.006201 | N32: =+IFERROR(L32*100/C32,0) -> 39.006201
A33: A-3-9-2-0-02 | B33: =+VLOOKUP(A33,gasto!$A$4:$B$78,2,FALSE) -> Per capita Programas de Promoción y Prevención R.C CSF | C33: =+VLOOKUP(A33,gasto!$A$4:$F$68,3,FALSE) -> 136252557967 | D33: 1.1373866e+11 | E33: 42431285392 | F33: 42431285392 | G33: =+VLOOKUP(A33,gasto!$A$4:$F$68,4,FALSE) -> 0 | H33: =+VLOOKUP(A33,gasto!$A$4:$F$68,5,FALSE) -> 7330802696 | I33: =+VLOOKUP(A33,gasto!$A$4:$F$68,6,FALSE) -> 7330802696 | J33: =+G33+D33 -> 1.1373866e+11 | K33: =+H33+E33 -> 49762088088 | L33: =+I33+F33 -> 49762088088 | M33: =+IFERROR(K33*100/C33,0) -> 36.521948 | N33: =+IFERROR(L33*100/C33,0) -> 36.521948
A34: A-3-9-3-0 | B34: =+VLOOKUP(A34,gasto!$A$4:$B$78,2,FALSE) -> Incapacidades | C34: =+SUM(C35:C36) -> 814461941941 | D34: 6.9109461e+11 | E34: 333215276968 | F34: 333215276968 | G34: =+SUM(G35:G36) -> -9930353 | H34: =+SUM(H35:H36) -> 65375823281 | I34: =+SUM(I35:I36) -> 65375823281 | J34: =+SUM(J35:J36) -> 6.9108468e+11 | K34: =+SUM(K35:K36) -> 398591100249 | L34: =+SUM(L35:L36) -> 398591100249 | M34: =+IFERROR(K34*100/C34,0) -> 48.939193 | N34: =+IFERROR(L34*100/C34,0) -> 48.939193
A35: A-3-9-3-0-01 | B35: =+VLOOKUP(A35,gasto!$A$4:$B$78,2,FALSE) -> Incapacidades SSF | C35: =+VLOOKUP(A35,gasto!$A$4:$F$68,3,FALSE) -> 629253806467 | D35: 5.3437909e+11 | E35: 261734550968 | F35: 261734550968 | G35: =+VLOOKUP(A35,gasto!$A$4:$F$68,4,FALSE) -> -9930353 | H35: =+VLOOKUP(A35,gasto!$A$4:$F$68,5,FALSE) -> 53081478779 | I35: =+VLOOKUP(A35,gasto!$A$4:$F$68,6,FALSE) -> 53081478779 | J35: =+G35+D35 -> 5.3436916e+11 | K35: =+H35+E35 -> 314816029747 | L35: =+I35+F35 -> 314816029747 | M35: =+IFERROR(K35*100/C35,0) -> 50.030056 | N35: =+IFERROR(L35*100/C35,0) -> 50.030056
A36: A-3-9-3-0-02 | B36: =+VLOOKUP(A36,gasto!$A$4:$B$78,2,FALSE) -> Incapacidades CSF | C36: =+VLOOKUP(A36,gasto!$A$4:$F$68,3,FALSE) -> 185208135474 | D36: 156715520546 | E36: 71480726000 | F36: 71480726000 | G36: =+VLOOKUP(A36,gasto!$A$4:$F$68,4,FALSE) -> 0 | H36: =+VLOOKUP(A36,gasto!$A$4:$F$68,5,FALSE) -> 12294344502 | I36: =+VLOOKUP(A36,gasto!$A$4:$F$68,6,FALSE) -> 12294344502 | J36: =+G36+D36 -> 156715520546 | K36: =+H36+E36 -> 83775070502 | L36: =+I36+F36 -> 83775070502 | M36: =+IFERROR(K36*100/C36,0) -> 45.232932 | N36: =+IFERROR(L36*100/C36,0) -> 45.232932
A37: A-3-9-4-0 | B37: =+VLOOKUP(A37,gasto!$A$4:$B$78,2,FALSE) -> Licencias de Maternidad y Paternidad | C37: =+VLOOKUP(A37,gasto!$A$4:$F$68,3,FALSE) -> 838554045453 | D37: 838554045453 | E37: 329689815814 | F37: 329689815814 | G37: =+VLOOKUP(A37,gasto!$A$4:$F$68,4,FALSE) -> 0 | H37: =+VLOOKUP(A37,gasto!$A$4:$F$68,5,FALSE) -> 59962441810 | I37: =+VLOOKUP(A37,gasto!$A$4:$F$68,6,FALSE) -> 59962441810 | J37: =+G37+D37 -> 838554045453 | K37: =+H37+E37 -> 389652257624 | L37: =+I37+F37 -> 389652257624 | M37: =+IFERROR(K37*100/C37,0) -> 46.467161 | N37: =+IFERROR(L37*100/C37,0) -> 46.467161
A38: A-3-9-5-0 | B38: =+VLOOKUP(A38,gasto!$A$4:$B$78,2,FALSE) -> Prestaciones Económicas Regímenes Especial y de Excepción | C38: =+VLOOKUP(A38,gasto!$A$4:$F$68,3,FALSE) -> 3852227236 | D38: 3852227236 | E38: 1946536083 | F38: 1946536083 | G38: =+VLOOKUP(A38,gasto!$A$4:$F$68,4,FALSE) -> 0 | H38: =+VLOOKUP(A38,gasto!$A$4:$F$68,5,FALSE) -> 298726073 | I38: =+VLOOKUP(A38,gasto!$A$4:$F$68,6,FALSE) -> 298726073 | J38: =+G38+D38 -> 3852227236 | K38: =+H38+E38 -> 2245262156 | L38: =+I38+F38 -> 2245262156 | M38: =+IFERROR(K38*100/C38,0) -> 58.28478 | N38: =+IFERROR(L38*100/C38,0) -> 58.28478
A39: A-3-9-6-0 | B39: =+VLOOKUP(A39,gasto!$A$4:$B$78,2,FALSE) -> UPC Régimen Subsidiado | C39: =+SUM(C40:C42) -> 21586257607421 | D39: 8.9133482e+12 | E39: 8.9133482e+12 | F39: 8.9133482e+12 | G39: =+SUM(G40:G42) -> 1.1407097e+13 | H39: =+SUM(H40:H42) -> 1.8766695e+12 | I39: =+SUM(I40:I42) -> 1.8766695e+12 | J39: =+SUM(J40:J42) -> 2.0320446e+13 | K39: =+SUM(K40:K42) -> 1.0790018e+13 | L39: =+SUM(L40:L42) -> 1.0790018e+13 | M39: =+IFERROR(K39*100/C39,0) -> 49.985588 | N39: =+IFERROR(L39*100/C39,0) -> 49.985588
A40: A-3-9-6-0-01 | B40: =+VLOOKUP(A40,gasto!$A$4:$B$78,2,FALSE) -> UPC´S R.S. Cajas de Compensación Familiar SSF | C40: =+VLOOKUP(A40,gasto!$A$4:$F$68,3,FALSE) -> 28877831435 | D40: 1.4089319e+10 | E40: 1.4089319e+10 | F40: 1.4089319e+10 | G40: =+VLOOKUP(A40,gasto!$A$4:$F$68,4,FALSE) -> 1.4788513e+10 | H40: =+VLOOKUP(A40,gasto!$A$4:$F$68,5,FALSE) -> 2484211881 | I40: =+VLOOKUP(A40,gasto!$A$4:$F$68,6,FALSE) -> 2484211881 | J40: =+G40+D40 -> 28877831435 | K40: =+H40+E40 -> 1.657353e+10 | L40: =+I40+F40 -> 1.657353e+10 | M40: =+IFERROR(K40*100/C40,0) -> 57.39188 | N40: =+IFERROR(L40*100/C40,0) -> 57.39188
A41: A-3-9-6-0-02 | B41: =+VLOOKUP(A41,gasto!$A$4:$B$78,2,FALSE) -> UPC´S R.S. CSF | C41: =+VLOOKUP(A41,gasto!$A$4:$F$68,3,FALSE) -> 21557379775986 | D41: 8.8992589e+12 | E41: 8.8992589e+12 | F41: 8.8992589e+12 | G41: =+VLOOKUP(A41,gasto!$A$4:$F$68,4,FALSE) -> 1.1392309e+13 | H41: =+VLOOKUP(A41,gasto!$A$4:$F$68,5,FALSE) -> 1.8741853e+12 | I41: =+VLOOKUP(A41,gasto!$A$4:$F$68,6,FALSE) -> 1.8741853e+12 | J41: =+G41+D41 -> 2.0291568e+13 | K41: =+H41+E41 -> 1.0773444e+13 | L41: =+I41+F41 -> 1.0773444e+13 | M41: =+IFERROR(K41*100/C41,0) -> 49.975666 | N41: =+IFERROR(L41*100/C41,0) -> 49.975666
A42: A-3-9-6-0-03 | B42: =+VLOOKUP(A42,gasto!$A$4:$B$78,2,FALSE) -> UPC´S R.S. USPEC | C42: =+VLOOKUP(A42,gasto!$A$4:$F$68,3,FALSE) -> 0 | D42: 0 | E42: 0 | F42: 0 | G42: =+VLOOKUP(A42,gasto!$A$4:$F$68,4,FALSE) -> 0 | H42: =+VLOOKUP(A42,gasto!$A$4:$F$68,5,FALSE) -> 0 | I42: =+VLOOKUP(A42,gasto!$A$4:$F$68,6,FALSE) -> 0 | J42: =+G42+D42 -> 0 | K42: =+H42+E42 -> 0 | L42: =+I42+F42 -> 0 | M42: =+IFERROR(K42*100/C42,0) -> 0 | N42: =+IFERROR(L42*100/C42,0) -> 0
A43: A-3-9-7-0 | B43: =+VLOOKUP(A43,gasto!$A$4:$B$78,2,FALSE) -> Prestaciones Excepcionales - Recobros | C43: =+SUM(C44:C45) -> 4612854535766 | D43: 1.3910627e+12 | E43: 1.3910627e+12 | F43: 1.3910627e+12 | G43: =+SUM(G44:G45) -> 3.4256964e+11 | H43: =+SUM(H44:H45) -> 3.4256964e+11 | I43: =+SUM(I44:I45) -> 3.4256964e+11 | J43: =+SUM(J44:J45) -> 1.7336324e+12 | K43: =+SUM(K44:K45) -> 1.7336324e+12 | L43: =+SUM(L44:L45) -> 1.7336324e+12 | M43: =+IFERROR(K43*100/C43,0) -> 37.582637 | N43: =+IFERROR(L43*100/C43,0) -> 37.582637
A44: A-3-9-7-0-01 | B44: =+VLOOKUP(A44,gasto!$A$4:$B$78,2,FALSE) -> Recobros - Reembolsos Régimen Contributivo | C44: =+VLOOKUP(A44,gasto!$A$4:$F$68,3,FALSE) -> 4601663890220 | D44: 1.3882284e+12 | E44: 1.3882284e+12 | F44: 1.3882284e+12 | G44: =+VLOOKUP(A44,gasto!$A$4:$F$68,4,FALSE) -> 3.4018042e+11 | H44: =+VLOOKUP(A44,gasto!$A$4:$F$68,5,FALSE) -> 3.4018042e+11 | I44: =+VLOOKUP(A44,gasto!$A$4:$F$68,6,FALSE) -> 3.4018042e+11 | J44: =+G44+D44 -> 1.7284088e+12 | K44: =+H44+E44 -> 1.7284088e+12 | L44: =+I44+F44 -> 1.7284088e+12 | M44: =+IFERROR(K44*100/C44,0) -> 37.560519 | N44: =+IFERROR(L44*100/C44,0) -> 37.560519
A45: A-3-9-7-0-02 | B45: =+VLOOKUP(A45,gasto!$A$4:$B$78,2,FALSE) -> Recobros - Reembolsos Régimen Subsidiado - Tutelas | C45: =+VLOOKUP(A45,gasto!$A$4:$F$68,3,FALSE) -> 11190645546 | D45: 2.8343351e+09 | E45: 2.8343351e+09 | F45: 2.8343351e+09 | G45: =+VLOOKUP(A45,gasto!$A$4:$F$68,4,FALSE) -> 2.3892241e+09 | H45: =+VLOOKUP(A45,gasto!$A$4:$F$68,5,FALSE) -> 2.3892241e+09 | I45: =+VLOOKUP(A45,gasto!$A$4:$F$68,6,FALSE) -> 2.3892241e+09 | J45: =+G45+D45 -> 5.2235592e+09 | K45: =+H45+E45 -> 5.2235592e+09 | L45: =+I45+F45 -> 5.2235592e+09 | M45: =+IFERROR(K45*100/C45,0) -> 46.677908 | N45: =+IFERROR(L45*100/C45,0) -> 46.677908
A46: A-3-9-8-0 | B46: =+VLOOKUP(A46,gasto!$A$4:$B$78,2,FALSE) -> Atención en Salud, Transporte Primario, Indemnizaciones y Auxilio Funerario Víctimas | C46: =+SUM(C47:C52) -> 261211933199 | D46: 1.2022277e+11 | E46: 7.6131735e+09 | F46: 7.6131735e+09 | G46: =+SUM(G47:G52) -> 60000000000 | H46: =+SUM(H47:H52) -> 6.5081348e+10 | I46: =+SUM(I47:I52) -> 6.5081348e+10 | J46: =+SUM(J47:J52) -> 180222768589 | K46: =+SUM(K47:K52) -> 7.2694522e+10 | L46: =+SUM(L47:L52) -> 7.2694522e+10 | M46: =+IFERROR(K46*100/C46,0) -> 27.829709 | N46: =+IFERROR(L46*100/C46,0) -> 27.829709
A47: A-3-9-8-0-01 | B47: =+VLOOKUP(A47,gasto!$A$4:$B$78,2,FALSE) -> Eventos terroristas | C47: =+VLOOKUP(A47,gasto!$A$4:$F$68,3,FALSE) -> 272244074 | D47: 1.8118396e+08 | E47: 9162714.3 | F47: 9162714.3 | G47: =+VLOOKUP(A47,gasto!$A$4:$F$68,4,FALSE) -> 0 | H47: =+VLOOKUP(A47,gasto!$A$4:$F$68,5,FALSE) -> 516171.01 | I47: =+VLOOKUP(A47,gasto!$A$4:$F$68,6,FALSE) -> 516171.01 | J47: =+G47+D47 -> 1.8118396e+08 | K47: =+H47+E47 -> 9678885.3 | L47: =+I47+F47 -> 9678885.3 | M47: =+IFERROR(K47*100/C47,0) -> 3.5552235 | N47: =+IFERROR(L47*100/C47,0) -> 3.5552235
A48: A-3-9-8-0-02 | B48: =+VLOOKUP(A48,gasto!$A$4:$B$78,2,FALSE) -> Eventos Catastróficos | C48: =+VLOOKUP(A48,gasto!$A$4:$F$68,3,FALSE) -> 2733436752 | D48: 1.3814911e+09 | E48: 1.3942444e+08 | F48: 1.3942444e+08 | G48: =+VLOOKUP(A48,gasto!$A$4:$F$68,4,FALSE) -> 0 | H48: =+VLOOKUP(A48,gasto!$A$4:$F$68,5,FALSE) -> 1096801.7 | I48: =+VLOOKUP(A48,gasto!$A$4:$F$68,6,FALSE) -> 1096801.7 | J48: =+G48+D48 -> 1.3814911e+09 | K48: =+H48+E48 -> 1.4052124e+08 | L48: =+I48+F48 -> 1.4052124e+08 | M48: =+IFERROR(K48*100/C48,0) -> 5.1408265 | N48: =+IFERROR(L48*100/C48,0) -> 5.1408265
A49: A-3-9-8-0-03 | B49: =+VLOOKUP(A49,gasto!$A$4:$B$78,2,FALSE) -> Accidentes de Transito | C49: =+VLOOKUP(A49,gasto!$A$4:$F$68,3,FALSE) -> 197724483784 | D49: 1.1843732e+11 | E49: 7.2418178e+09 | F49: 7.2418178e+09 | G49: =+VLOOKUP(A49,gasto!$A$4:$F$68,4,FALSE) -> 0 | H49: =+VLOOKUP(A49,gasto!$A$4:$F$68,5,FALSE) -> 5.0797354e+09 | I49: =+VLOOKUP(A49,gasto!$A$4:$F$68,6,FALSE) -> 5.0797354e+09 | J49: =+G49+D49 -> 1.1843732e+11 | K49: =+H49+E49 -> 1.2321553e+10 | L49: =+I49+F49 -> 1.2321553e+10 | M49: =+IFERROR(K49*100/C49,0) -> 6.231678 | N49: =+IFERROR(L49*100/C49,0) -> 6.231678
A50: A-3-9-8-0-04 | B50: =+VLOOKUP(A50,gasto!$A$4:$B$78,2,FALSE) -> Apoyo Reclamaciones Reserva especial | C50: =+VLOOKUP(A50,gasto!$A$4:$F$68,3,FALSE) -> 250000000 | D50: 0 | E50: 0 | F50: 0 | G50: =+VLOOKUP(A50,gasto!$A$4:$F$68,4,FALSE) -> 0 | H50: =+VLOOKUP(A50,gasto!$A$4:$F$68,5,FALSE) -> 0 | I50: =+VLOOKUP(A50,gasto!$A$4:$F$68,6,FALSE) -> 0 | J50: =+G50+D50 -> 0 | K50: =+H50+E50 -> 0 | L50: =+I50+F50 -> 0 | M50: =+IFERROR(K50*100/C50,0) -> 0 | N50: =+IFERROR(L50*100/C50,0) -> 0
A51: A-3-9-8-0-05 | B51: =+VLOOKUP(A51,gasto!$A$4:$B$78,2,FALSE) -> Oficina de Gestión Territorial, Emergencias y Desastres - Atención de urgencias Nacionales y Extranjeros - Zonas Fronterizas. Art 57 Ley 1815 de 2016 Oficina de Gestión | C51: =+VLOOKUP(A51,gasto!$A$4:$F$68,3,FALSE) -> 60222768589 | D51: 222768589 | E51: 222768589 | F51: 222768589 | G51: =+VLOOKUP(A51,gasto!$A$4:$F$68,4,FALSE) -> 60000000000 | H51: =+VLOOKUP(A51,gasto!$A$4:$F$68,5,FALSE) -> 60000000000 | I51: =+VLOOKUP(A51,gasto!$A$4:$F$68,6,FALSE) -> 60000000000 | J51: =+G51+D51 -> 60222768589 | K51: =+H51+E51 -> 60222768589 | L51: =+I51+F51 -> 60222768589 | M51: =+IFERROR(K51*100/C51,0) -> 100 | N51: =+IFERROR(L51*100/C51,0) -> 100
A52: A-3-9-8-0-06 | B52: =+VLOOKUP(A52,gasto!$A$4:$B$78,2,FALSE) -> Apoyo Reclamaciones Victimas Poblaciòn desplazada | C52: =+VLOOKUP(A52,gasto!$A$4:$F$68,3,FALSE) -> 9000000 | D52: 0 | E52: 0 | F52: 0 | G52: =+VLOOKUP(A52,gasto!$A$4:$F$68,4,FALSE) -> 0 | H52: =+VLOOKUP(A52,gasto!$A$4:$F$68,5,FALSE) -> 0 | I52: =+VLOOKUP(A52,gasto!$A$4:$F$68,6,FALSE) -> 0 | J52: =+G52+D52 -> 0 | K52: =+H52+E52 -> 0 | L52: =+I52+F52 -> 0 | M52: =+IFERROR(K52*100/C52,0) -> 0 | N52: =+IFERROR(L52*100/C52,0) -> 0
A53: A-3-9-9-0 | B53: =+VLOOKUP(A53,gasto!$A$4:$B$78,2,FALSE) -> Fortalecimiento Red Nacional de Urgencias, Emergencia Sanitaria y eventos Catastróficos | C53: =+SUM(C54:C56) -> 3988276390 | D53: 0 | E53: 0 | F53: 0 | G53: =+SUM(G54:G56) -> 0 | H53: =+SUM(H54:H56) -> 0 | I53: =+SUM(I54:I56) -> 0 | J53: =+SUM(J54:J56) -> 0 | K53: =+SUM(K54:K56) -> 0 | L53: =+SUM(L54:L56) -> 0 | M53: =+IFERROR(K53*100/C53,0) -> 0 | N53: =+IFERROR(L53*100/C53,0) -> 0
A54: A-3-9-9-0-01 | B54: =+VLOOKUP(A54,gasto!$A$4:$B$78,2,FALSE) -> Oficina de Gestión Territorial, Emergencias y Desastres - Red Nacional de Urgencias | C54: =+VLOOKUP(A54,gasto!$A$4:$F$68,3,FALSE) -> 3988276390 | D54: 0 | E54: 0 | F54: 0 | G54: =+VLOOKUP(A54,gasto!$A$4:$F$68,4,FALSE) -> 0 | H54: =+VLOOKUP(A54,gasto!$A$4:$F$68,5,FALSE) -> 0 | I54: =+VLOOKUP(A54,gasto!$A$4:$F$68,6,FALSE) -> 0 | J54: =+G54+D54 -> 0 | K54: =+H54+E54 -> 0 | L54: =+I54+F54 -> 0 | M54: =+IFERROR(K54*100/C54,0) -> 0 | N54: =+IFERROR(L54*100/C54,0) -> 0
A55: A-3-9-9-0-02 | B55: =+VLOOKUP(A55,gasto!$A$4:$B$78,2,FALSE) -> Emergencia Sanitaria | C55: =+VLOOKUP(A55,gasto!$A$4:$F$68,3,FALSE) -> 0 | D55: 0 | E55: 0 | F55: 0 | G55: =+VLOOKUP(A55,gasto!$A$4:$F$68,4,FALSE) -> 0 | H55: =+VLOOKUP(A55,gasto!$A$4:$F$68,5,FALSE) -> 0 | I55: =+VLOOKUP(A55,gasto!$A$4:$F$68,6,FALSE) -> 0 | J55: =+G55+D55 -> 0 | K55: =+H55+E55 -> 0 | L55: =+I55+F55 -> 0 | M55: =+IFERROR(K55*100/C55,0) -> 0 | N55: =+IFERROR(L55*100/C55,0) -> 0
A56: A-3-9-9-0-03 | B56: =+VLOOKUP(A56,gasto!$A$4:$B$78,2,FALSE) -> Eventos Catastróficos | C56: =+VLOOKUP(A56,gasto!$A$4:$F$68,3,FALSE) -> 0 | D56: 0 | E56: 0 | F56: 0 | G56: =+VLOOKUP(A56,gasto!$A$4:$F$68,4,FALSE) -> 0 | H56: =+VLOOKUP(A56,gasto!$A$4:$F$68,5,FALSE) -> 0 | I56: =+VLOOKUP(A56,gasto!$A$4:$F$68,6,FALSE) -> 0 | J56: =+G56+D56 -> 0 | K56: =+H56+E56 -> 0 | L56: =+I56+F56 -> 0 | M56: =+IFERROR(K56*100/C56,0) -> 0 | N56: =+IFERROR(L56*100/C56,0) -> 0
A57: A-3-9-10-0 | B57: =+VLOOKUP(A57,gasto!$A$4:$B$78,2,FALSE) -> Otros Programas de Salud Promoción y prevención | C57: =+SUM(C58:C66) -> 104623542052 | D57: 13835751052 | E57: 2163097519 | F57: 2163097519 | G57: =+SUM(G58:G66) -> 160549479 | H57: =+SUM(H58:H66) -> 0 | I57: =+SUM(I58:I66) -> 0 | J57: =+SUM(J58:J66) -> 13996300531 | K57: =+SUM(K58:K66) -> 2163097519 | L57: =+SUM(L58:L66) -> 2163097519 | M57: =+IFERROR(K57*100/C57,0) -> 2.0675055 | N57: =+IFERROR(L57*100/C57,0) -> 2.0675055
A58: A-3-9-10-0-01 | B58: =+VLOOKUP(A58,gasto!$A$4:$B$78,2,FALSE) -> Dirección de Promoción y Prevención - Programas de Salud de P y P - VACUNAS | C58: =+VLOOKUP(A58,gasto!$A$4:$F$68,3,FALSE) -> 56595754535 | D58: 0 | E58: 0 | F58: 0 | G58: =+VLOOKUP(A58,gasto!$A$4:$F$68,4,FALSE) -> 0 | H58: =+VLOOKUP(A58,gasto!$A$4:$F$68,5,FALSE) -> 0 | I58: =+VLOOKUP(A58,gasto!$A$4:$F$68,6,FALSE) -> 0 | J58: =+G58+D58 -> 0 | K58: =+H58+E58 -> 0 | L58: =+I58+F58 -> 0 | M58: =+IFERROR(K58*100/C58,0) -> 0 | N58: =+IFERROR(L58*100/C58,0) -> 0
A59: A-3-9-10-0-02 | B59: =+VLOOKUP(A59,gasto!$A$4:$B$78,2,FALSE) -> Oficina de Promoción Social - programa de Atención Psicosocial y Salud Integral a Víctimas del Conflicto Armado Programa PAPSIVI | C59: =+VLOOKUP(A59,gasto!$A$4:$F$68,3,FALSE) -> 18502751052 | D59: 13835751052 | E59: 2163097519 | F59: 2163097519 | G59: =+VLOOKUP(A59,gasto!$A$4:$F$68,4,FALSE) -> 0 | H59: =+VLOOKUP(A59,gasto!$A$4:$F$68,5,FALSE) -> 0 | I59: =+VLOOKUP(A59,gasto!$A$4:$F$68,6,FALSE) -> 0 | J59: =+G59+D59 -> 13835751052 | K59: =+H59+E59 -> 2163097519 | L59: =+I59+F59 -> 2163097519 | M59: =+IFERROR(K59*100/C59,0) -> 11.690681 | N59: =+IFERROR(L59*100/C59,0) -> 11.690681
A60: A-3-9-10-0-03 | B60: =+VLOOKUP(A60,gasto!$A$4:$B$78,2,FALSE) -> Programa mujeres víctimas de la violencia | C60: =+VLOOKUP(A60,gasto!$A$4:$F$68,3,FALSE) -> 0 | D60: 0 | E60: 0 | F60: 0 | G60: =+VLOOKUP(A60,gasto!$A$4:$F$68,4,FALSE) -> 0 | H60: =+VLOOKUP(A60,gasto!$A$4:$F$68,5,FALSE) -> 0 | I60: =+VLOOKUP(A60,gasto!$A$4:$F$68,6,FALSE) -> 0 | J60: =+G60+D60 -> 0 | K60: =+H60+E60 -> 0 | L60: =+I60+F60 -> 0 | M60: =+IFERROR(K60*100/C60,0) -> 0 | N60: =+IFERROR(L60*100/C60,0) -> 0
A61: A-3-9-10-0-04 | B61: =+VLOOKUP(A61,gasto!$A$4:$B$78,2,FALSE) -> Otros Programas de Salud diferentes a los anteriores | C61: =+VLOOKUP(A61,gasto!$A$4:$F$68,3,FALSE) -> 0 | D61: 0 | E61: 0 | F61: 0 | G61: =+VLOOKUP(A61,gasto!$A$4:$F$68,4,FALSE) -> 0 | H61: =+VLOOKUP(A61,gasto!$A$4:$F$68,5,FALSE) -> 0 | I61: =+VLOOKUP(A61,gasto!$A$4:$F$68,6,FALSE) -> 0 | J61: =+G61+D61 -> 0 | K61: =+H61+E61 -> 0 | L61: =+I61+F61 -> 0 | M61: =+IFERROR(K61*100/C61,0) -> 0 | N61: =+IFERROR(L61*100/C61,0) -> 0
A62: A-3-9-10-0-05 | B62: =+VLOOKUP(A62,gasto!$A$4:$B$78,2,FALSE) -> Campañas de Prevencion de la Violencia y Promoción de la Convivencia Pacifica a Nivel Nacional o Territorial | C62: =+VLOOKUP(A62,gasto!$A$4:$F$68,3,FALSE) -> 2136930333 | D62: 0 | E62: 0 | F62: 0 | G62: =+VLOOKUP(A62,gasto!$A$4:$F$68,4,FALSE) -> 0 | H62: =+VLOOKUP(A62,gasto!$A$4:$F$68,5,FALSE) -> 0 | I62: =+VLOOKUP(A62,gasto!$A$4:$F$68,6,FALSE) -> 0 | J62: =+G62+D62 -> 0 | K62: =+H62+E62 -> 0 | L62: =+I62+F62 -> 0 | M62: =+IFERROR(K62*100/C62,0) -> 0 | N62: =+IFERROR(L62*100/C62,0) -> 0
A63: A-3-9-10-0-06 | B63: =+VLOOKUP(A63,gasto!$A$4:$B$78,2,FALSE) -> Prevención y Sanción de Formas de Violencia y discriminación Contra las Mujeres | C63: =+VLOOKUP(A63,gasto!$A$4:$F$68,3,FALSE) -> 4273860667 | D63: 0 | E63: 0 | F63: 0 | G63: =+VLOOKUP(A63,gasto!$A$4:$F$68,4,FALSE) -> 0 | H63: =+VLOOKUP(A63,gasto!$A$4:$F$68,5,FALSE) -> 0 | I63: =+VLOOKUP(A63,gasto!$A$4:$F$68,6,FALSE) -> 0 | J63: =+G63+D63 -> 0 | K63: =+H63+E63 -> 0 | L63: =+I63+F63 -> 0 | M63: =+IFERROR(K63*100/C63,0) -> 0 | N63: =+IFERROR(L63*100/C63,0) -> 0
A64: A-3-9-10-0-07 | B64: =+VLOOKUP(A64,gasto!$A$4:$B$78,2,FALSE) -> Atención Usuario Protesis PIP Resolución 0258 de 2012 | C64: =+VLOOKUP(A64,gasto!$A$4:$F$68,3,FALSE) -> 160000000 | D64: 0 | E64: 0 | F64: 0 | G64: =+VLOOKUP(A64,gasto!$A$4:$F$68,4,FALSE) -> 0 | H64: =+VLOOKUP(A64,gasto!$A$4:$F$68,5,FALSE) -> 0 | I64: =+VLOOKUP(A64,gasto!$A$4:$F$68,6,FALSE) -> 0 | J64: =+G64+D64 -> 0 | K64: =+H64+E64 -> 0 | L64: =+I64+F64 -> 0 | M64: =+IFERROR(K64*100/C64,0) -> 0 | N64: =+IFERROR(L64*100/C64,0) -> 0
A65: A-3-9-10-0-08 | B65: =+VLOOKUP(A65,gasto!$A$4:$B$78,2,FALSE) -> Déficit Cajas de Compensación Familiar - Balance | C65: =+VLOOKUP(A65,gasto!$A$4:$F$68,3,FALSE) -> 2000000000 | D65: 0 | E65: 0 | F65: 0 | G65: =+VLOOKUP(A65,gasto!$A$4:$F$68,4,FALSE) -> 160549479 | H65: =+VLOOKUP(A65,gasto!$A$4:$F$68,5,FALSE) -> 0 | I65: =+VLOOKUP(A65,gasto!$A$4:$F$68,6,FALSE) -> 0 | J65: =+G65+D65 -> 160549479 | K65: =+H65+E65 -> 0 | L65: =+I65+F65 -> 0 | M65: =+IFERROR(K65*100/C65,0) -> 0 | N65: =+IFERROR(L65*100/C65,0) -> 0
A66: A-3-9-10-0-09 | B66: =+VLOOKUP(A66,gasto!$A$4:$B$78,2,FALSE) -> Certificado de Discapacidad, Suministro de Fórmula Terapéutica | C66: =+VLOOKUP(A66,gasto!$A$4:$F$68,3,FALSE) -> 20954245465 | D66: 0 | E66: 0 | F66: 0 | G66: =+VLOOKUP(A66,gasto!$A$4:$F$68,4,FALSE) -> 0 | H66: =+VLOOKUP(A66,gasto!$A$4:$F$68,5,FALSE) -> 0 | I66: =+VLOOKUP(A66,gasto!$A$4:$F$68,6,FALSE) -> 0 | J66: =+G66+D66 -> 0 | K66: =+H66+E66 -> 0 | L66: =+I66+F66 -> 0 | M66: =+IFERROR(K66*100/C66,0) -> 0 | N66: =+IFERROR(L66*100/C66,0) -> 0
A67: A-3-9-11-0 | B67: =+VLOOKUP(A67,gasto!$A$4:$B$78,2,FALSE) -> Recursos con destinación específica | C67: =+SUM(C68:C77) -> 241820271514 | D67: 46895138293 | E67: 1933655991 | F67: 1933655991 | G67: =+SUM(G68:G77) -> 0 | H67: =+SUM(H68:H77) -> 0 | I67: =+SUM(I68:I77) -> 0 | J67: =+SUM(J68:J77) -> 46895138293 | K67: =+SUM(K68:K77) -> 1933655991 | L67: =+SUM(L68:L77) -> 1933655991 | M67: =+IFERROR(K67*100/C67,0) -> 0.79962527 | N67: =+IFERROR(L67*100/C67,0) -> 0.79962527
A68: A-3-9-11-0-01 | B68: =+VLOOKUP(A68,gasto!$A$4:$B$78,2,FALSE) -> Pago a IPS de servicios prestados a la población pobre no asegurada y servicios no incluidos en el Plan de beneficios Pago a IPS de servicios prestados a la población, exceden(Art. 3 Ley 1608 de 2013) | C68: =+VLOOKUP(A68,gasto!$A$4:$F$68,3,FALSE) -> 5801668388 | D68: 0 | E68: 0 | F68: 0 | G68: =+VLOOKUP(A68,gasto!$A$4:$F$68,4,FALSE) -> 0 | H68: =+VLOOKUP(A68,gasto!$A$4:$F$68,5,FALSE) -> 0 | I68: =+VLOOKUP(A68,gasto!$A$4:$F$68,6,FALSE) -> 0 | J68: =+G68+D68 -> 0 | K68: =+H68+E68 -> 0 | L68: =+I68+F68 -> 0 | M68: =+IFERROR(K68*100/C68,0) -> 0 | N68: =+IFERROR(L68*100/C68,0) -> 0
A69: A-3-9-11-0-02 | B69: =+VLOOKUP(A69,gasto!$A$4:$B$78,2,FALSE) -> Reconocimiento de deuda por contratos del Régimen Subsidiado realizados hasta marzo 31 de 2011- Recursos LOTTO en Línea – FONPET | C69: =+VLOOKUP(A69,gasto!$A$4:$F$68,3,FALSE) -> 5000000000 | D69: 0 | E69: 0 | F69: 0 | G69: =+VLOOKUP(A69,gasto!$A$4:$F$68,4,FALSE) -> 0 | H69: =+VLOOKUP(A69,gasto!$A$4:$F$68,5,FALSE) -> 0 | I69: =+VLOOKUP(A69,gasto!$A$4:$F$68,6,FALSE) -> 0 | J69: =+G69+D69 -> 0 | K69: =+H69+E69 -> 0 | L69: =+I69+F69 -> 0 | M69: =+IFERROR(K69*100/C69,0) -> 0 | N69: =+IFERROR(L69*100/C69,0) -> 0
A70: A-3-9-11-0-03 | B70: =+VLOOKUP(A70,gasto!$A$4:$B$78,2,FALSE) -> Reconocimiento de deuda por contratos del Régimen Subsidiado realizados hasta marzo 31 de 2011- Recursos FAEP | C70: =+VLOOKUP(A70,gasto!$A$4:$F$68,3,FALSE) -> 800000000 | D70: 0 | E70: 0 | F70: 0 | G70: =+VLOOKUP(A70,gasto!$A$4:$F$68,4,FALSE) -> 0 | H70: =+VLOOKUP(A70,gasto!$A$4:$F$68,5,FALSE) -> 0 | I70: =+VLOOKUP(A70,gasto!$A$4:$F$68,6,FALSE) -> 0 | J70: =+G70+D70 -> 0 | K70: =+H70+E70 -> 0 | L70: =+I70+F70 -> 0 | M70: =+IFERROR(K70*100/C70,0) -> 0 | N70: =+IFERROR(L70*100/C70,0) -> 0
A71: A-3-9-11-0-04 | B71: =+VLOOKUP(A71,gasto!$A$4:$B$78,2,FALSE) -> Pago de deudas Régimen Subsidiado – Artículo 275 de la Ley 1450 de 2011 - SGP Libre Inversión | C71: =+VLOOKUP(A71,gasto!$A$4:$F$68,3,FALSE) -> 20000000000 | D71: 0 | E71: 0 | F71: 0 | G71: =+VLOOKUP(A71,gasto!$A$4:$F$68,4,FALSE) -> 0 | H71: =+VLOOKUP(A71,gasto!$A$4:$F$68,5,FALSE) -> 0 | I71: =+VLOOKUP(A71,gasto!$A$4:$F$68,6,FALSE) -> 0 | J71: =+G71+D71 -> 0 | K71: =+H71+E71 -> 0 | L71: =+I71+F71 -> 0 | M71: =+IFERROR(K71*100/C71,0) -> 0 | N71: =+IFERROR(L71*100/C71,0) -> 0
A72: A-3-9-11-0-05 | B72: =+VLOOKUP(A72,gasto!$A$4:$B$78,2,FALSE) -> Excedentes de Aportes Patronales / Resolución 2360 de 2016 | C72: =+VLOOKUP(A72,gasto!$A$4:$F$68,3,FALSE) -> 49454127709 | D72: 0 | E72: 0 | F72: 0 | G72: =+VLOOKUP(A72,gasto!$A$4:$F$68,4,FALSE) -> 0 | H72: =+VLOOKUP(A72,gasto!$A$4:$F$68,5,FALSE) -> 0 | I72: =+VLOOKUP(A72,gasto!$A$4:$F$68,6,FALSE) -> 0 | J72: =+G72+D72 -> 0 | K72: =+H72+E72 -> 0 | L72: =+I72+F72 -> 0 | M72: =+IFERROR(K72*100/C72,0) -> 0 | N72: =+IFERROR(L72*100/C72,0) -> 0
A73: A-3-9-11-0-06 | B73: =+VLOOKUP(A73,gasto!$A$4:$B$78,2,FALSE) -> Regalías – Art. 5 Ley 1797 de 2016 | C73: =+VLOOKUP(A73,gasto!$A$4:$F$68,3,FALSE) -> 3000000000 | D73: 0 | E73: 0 | F73: 0 | G73: =+VLOOKUP(A73,gasto!$A$4:$F$68,4,FALSE) -> 0 | H73: =+VLOOKUP(A73,gasto!$A$4:$F$68,5,FALSE) -> 0 | I73: =+VLOOKUP(A73,gasto!$A$4:$F$68,6,FALSE) -> 0 | J73: =+G73+D73 -> 0 | K73: =+H73+E73 -> 0 | L73: =+I73+F73 -> 0 | M73: =+IFERROR(K73*100/C73,0) -> 0 | N73: =+IFERROR(L73*100/C73,0) -> 0
A74: A-3-9-11-0-07 | B74: =+VLOOKUP(A74,gasto!$A$4:$B$78,2,FALSE) -> Otros Recursos con Destinación Especifica | C74: =+VLOOKUP(A74,gasto!$A$4:$F$68,3,FALSE) -> 44274480359 | D74: 0 | E74: 0 | F74: 0 | G74: =+VLOOKUP(A74,gasto!$A$4:$F$68,4,FALSE) -> 0 | H74: =+VLOOKUP(A74,gasto!$A$4:$F$68,5,FALSE) -> 0 | I74: =+VLOOKUP(A74,gasto!$A$4:$F$68,6,FALSE) -> 0 | J74: =+G74+D74 -> 0 | K74: =+H74+E74 -> 0 | L74: =+I74+F74 -> 0 | M74: =+IFERROR(K74*100/C74,0) -> 0 | N74: =+IFERROR(L74*100/C74,0) -> 0
A75: A-3-9-11-0-08 | B75: =+VLOOKUP(A75,gasto!$A$4:$B$78,2,FALSE) -> Recursos CCF / FOSFEC - Ley 1929 de 2018 | C75: =+VLOOKUP(A75,gasto!$A$4:$F$68,3,FALSE) -> 36000000000 | D75: 0 | E75: 0 | F75: 0 | G75: =+VLOOKUP(A75,gasto!$A$4:$F$68,4,FALSE) -> 0 | H75: =+VLOOKUP(A75,gasto!$A$4:$F$68,5,FALSE) -> 0 | I75: =+VLOOKUP(A75,gasto!$A$4:$F$68,6,FALSE) -> 0 | J75: =+G75+D75 -> 0 | K75: =+H75+E75 -> 0 | L75: =+I75+F75 -> 0 | M75: =+IFERROR(K75*100/C75,0) -> 0 | N75: =+IFERROR(L75*100/C75,0) -> 0
A76: A-3-9-11-0-09 | B76: =+VLOOKUP(A76,gasto!$A$4:$B$78,2,FALSE) -> Saneamiento aportes patronales SGP | C76: =+VLOOKUP(A76,gasto!$A$4:$F$68,3,FALSE) -> 76869459827 | D76: 46895138293 | E76: 1933655991 | F76: 1933655991 | G76: =+VLOOKUP(A76,gasto!$A$4:$F$68,4,FALSE) -> 0 | H76: =+VLOOKUP(A76,gasto!$A$4:$F$68,5,FALSE) -> 0 | I76: =+VLOOKUP(A76,gasto!$A$4:$F$68,6,FALSE) -> 0 | J76: =+G76+D76 -> 46895138293 | K76: =+H76+E76 -> 1933655991 | L76: =+I76+F76 -> 1933655991 | M76: =+IFERROR(K76*100/C76,0) -> 2.5155062 | N76: =+IFERROR(L76*100/C76,0) -> 2.5155062
A77: A-3-9-11-0-10 | B77: =+VLOOKUP(A77,gasto!$A$4:$B$78,2,FALSE) -> Rendimientos Financieros de los Saldos no Compensados de los Aportes Patronales según Art. 12 Decreto 1636 de 2016 | C77: =+VLOOKUP(A77,gasto!$A$4:$F$68,3,FALSE) -> 620535231 | D77: 0 | E77: 0 | F77: 0 | G77: =+VLOOKUP(A77,gasto!$A$4:$F$68,4,FALSE) -> 0 | H77: =+VLOOKUP(A77,gasto!$A$4:$F$68,5,FALSE) -> 0 | I77: =+VLOOKUP(A77,gasto!$A$4:$F$68,6,FALSE) -> 0 | J77: =+G77+D77 -> 0 | K77: =+H77+E77 -> 0 | L77: =+I77+F77 -> 0 | M77: =+IFERROR(K77*100/C77,0) -> 0 | N77: =+IFERROR(L77*100/C77,0) -> 0
A78: A-3-9-12-0 | B78: =+VLOOKUP(A78,gasto!$A$4:$B$78,2,FALSE) -> Pago Obligaciones ESE´S con Recursos FONSAET | C78: =+C79 -> 95551523562 | D78: 0 | E78: 0 | F78: 0 | G78: =+G79 -> 0 | H78: =+H79 -> 0 | I78: =+I79 -> 0 | J78: =+J79 -> 0 | K78: =+K79 -> 0 | L78: =+L79 -> 0 | M78: =+IFERROR(K78*100/C78,0) -> 0 | N78: =+IFERROR(L78*100/C78,0) -> 0
A79: A-3-9-12-0-01 | B79: =+VLOOKUP(A79,gasto!$A$4:$B$78,2,FALSE) -> Pago Obligaciones EPS FONSAET | C79: =+VLOOKUP(A79,gasto!$A$4:$F$68,3,FALSE) -> 95551523562 | D79: 0 | E79: 0 | F79: 0 | G79: =+VLOOKUP(A79,gasto!$A$4:$F$68,4,FALSE) -> 0 | H79: =+VLOOKUP(A79,gasto!$A$4:$F$68,5,FALSE) -> 0 | I79: =+VLOOKUP(A79,gasto!$A$4:$F$68,6,FALSE) -> 0 | J79: =+G79+D79 -> 0 | K79: =+H79+E79 -> 0 | L79: =+I79+F79 -> 0 | M79: =+IFERROR(K79*100/C79,0) -> 0 | N79: =+IFERROR(L79*100/C79,0) -> 0
A80: A-3-9-13-0 | B80: =+VLOOKUP(A80,gasto!$A$4:$B$78,2,FALSE) -> Reconocimiento Rendimientos Financieros cuentas de recaudo EPS SSF | C80: =+C81 -> 7615081557 | D80: 7615081557 | E80: 1552635328 | F80: 1552635328 | G80: =+G81 -> 0 | H80: =+H81 -> 1188992875 | I80: =+I81 -> 1188992875 | J80: =+J81 -> 7615081557 | K80: =+K81 -> 2741628203 | L80: =+L81 -> 2741628203 | M80: =+IFERROR(K80*100/C80,0) -> 36.002611 | N80: =+IFERROR(L80*100/C80,0) -> 36.002611
A81: A-3-9-13-0-01 | B81: =+VLOOKUP(A81,gasto!$A$4:$B$78,2,FALSE) -> Rendimientos Financieros EPS SSF | C81: =+VLOOKUP(A81,gasto!$A$4:$F$68,3,FALSE) -> 7615081557 | D81: 7615081557 | E81: 1552635328 | F81: 1552635328 | G81: =+VLOOKUP(A81,gasto!$A$4:$F$68,4,FALSE) -> 0 | H81: =+VLOOKUP(A81,gasto!$A$4:$F$68,5,FALSE) -> 1188992875 | I81: =+VLOOKUP(A81,gasto!$A$4:$F$68,6,FALSE) -> 1188992875 | J81: =+G81+D81 -> 7615081557 | K81: =+H81+E81 -> 2741628203 | L81: =+I81+F81 -> 2741628203 | M81: =+IFERROR(K81*100/C81,0) -> 36.002611 | N81: =+IFERROR(L81*100/C81,0) -> 36.002611
A82: A-3-9-14-0 | B82: =+VLOOKUP(A82,gasto!$A$4:$B$78,2,FALSE) -> Apoyo Financiero y Fortalecimiento Patrimonial a las Entidades del Sector Salud | C82: =+SUM(C83:C85) -> 40000000000 | D82: 0 | E82: 0 | F82: 0 | G82: =+SUM(G83:G85) -> 0 | H82: =+SUM(H83:H85) -> 0 | I82: =+SUM(I83:I85) -> 0 | J82: =+SUM(J83:J85) -> 0 | K82: =+SUM(K83:K85) -> 0 | L82: =+SUM(L83:L85) -> 0 | M82: =+IFERROR(K82*100/C82,0) -> 0 | N82: =+IFERROR(L82*100/C82,0) -> 0
A83: A-3-9-14-0-01 | B83: =+VLOOKUP(A83,gasto!$A$4:$B$78,2,FALSE) -> Operaciones de Compra de Cartera | C83: =+VLOOKUP(A83,gasto!$A$4:$F$100,3,FALSE) -> 0 | D83: 0 | E83: 0 | F83: 0 | G83: =+VLOOKUP(A83,gasto!$A$4:$F$100,4,FALSE) -> 0 | H83: =+VLOOKUP(A83,gasto!$A$4:$F$100,5,FALSE) -> 0 | I83: =+VLOOKUP(A83,gasto!$A$4:$F$100,6,FALSE) -> 0 | J83: =+G83+D83 -> 0 | K83: =+H83+E83 -> 0 | L83: =+I83+F83 -> 0 | M83: =+IFERROR(K83*100/C83,0) -> 0 | N83: =+IFERROR(L83*100/C83,0) -> 0
A84: A-3-9-14-0-02 | B84: =+VLOOKUP(A84,gasto!$A$4:$B$78,2,FALSE) -> Operaciones de Fortalecimiento Patrimonial Tasa Compensada | C84: =+VLOOKUP(A84,gasto!$A$4:$F$100,3,FALSE) -> 40000000000 | D84: 0 | E84: 0 | F84: 0 | G84: =+VLOOKUP(A84,gasto!$A$4:$F$100,4,FALSE) -> 0 | H84: =+VLOOKUP(A84,gasto!$A$4:$F$100,5,FALSE) -> 0 | I84: =+VLOOKUP(A84,gasto!$A$4:$F$100,6,FALSE) -> 0 | J84: =+G84+D84 -> 0 | K84: =+H84+E84 -> 0 | L84: =+I84+F84 -> 0 | M84: =+IFERROR(K84*100/C84,0) -> 0 | N84: =+IFERROR(L84*100/C84,0) -> 0
A85: A-3-9-14-0-03 | B85: =+VLOOKUP(A85,gasto!$A$4:$B$78,2,FALSE) -> Operaciones de Fortalecimiento Patrimonial - Bocas | C85: =+VLOOKUP(A85,gasto!$A$4:$F$100,3,FALSE) -> 0 | D85: 0 | E85: 0 | F85: 0 | G85: =+VLOOKUP(A85,gasto!$A$4:$F$100,4,FALSE) -> 0 | H85: =+VLOOKUP(A85,gasto!$A$4:$F$100,5,FALSE) -> 0 | I85: =+VLOOKUP(A85,gasto!$A$4:$F$100,6,FALSE) -> 0 | J85: =+G85+D85 -> 0 | K85: =+H85+E85 -> 0 | L85: =+I85+F85 -> 0 | M85: =+IFERROR(K85*100/C85,0) -> 0 | N85: =+IFERROR(L85*100/C85,0) -> 0
A86: A-3-9-15-0 | B86: =+VLOOKUP(A86,gasto!$A$4:$B$78,2,FALSE) -> Devoluciones | C86: =+SUM(C87:C90) -> 179398901661 | D86: 9.2992942e+09 | E86: 4.9964834e+08 | F86: 4.9964834e+08 | G86: =+SUM(G87:G90) -> 160101188290 | H86: =+SUM(H87:H90) -> 139653536 | I86: =+SUM(I87:I90) -> 139653536 | J86: =+G86+D86 -> 1.6940048e+11 | K86: =+H86+E86 -> 6.3930188e+08 | L86: =+I86+F86 -> 6.3930188e+08 | M86: =+IFERROR(K86*100/C86,0) -> 0.35635774 | N86: =+IFERROR(L86*100/C86,0) -> 0.35635774
A87: A-3-9-15-0-01 | B87: =+VLOOKUP(A87,gasto!$A$4:$B$78,2,FALSE) -> Devoluciones Aportes y Cotizaciones No Conciliadas Vigencia Anterior | C87: =+VLOOKUP(A87,gasto!$A$4:$F$100,3,FALSE) -> 9047713371 | D87: 9047713371 | E87: 498067540 | F87: 498067540 | G87: =+VLOOKUP(A87,gasto!$A$4:$F$100,4,FALSE) -> 0 | H87: =+VLOOKUP(A87,gasto!$A$4:$F$100,5,FALSE) -> 138475351 | I87: =+VLOOKUP(A87,gasto!$A$4:$F$100,6,FALSE) -> 138475351 | J87: =+G87+D87 -> 9047713371 | K87: =+H87+E87 -> 636542891 | L87: =+I87+F87 -> 636542891 | M87: =+IFERROR(K87*100/C87,0) -> 7.0354007 | N87: =+IFERROR(L87*100/C87,0) -> 7.0354007
A88: A-3-9-15-0-02 | B88: =+VLOOKUP(A88,gasto!$A$4:$B$78,2,FALSE) -> Devoluciones de Aportes de REX | C88: =+VLOOKUP(A88,gasto!$A$4:$F$100,3,FALSE) -> 250000000 | D88: 250000000 | E88: 0 | F88: 0 | G88: =+VLOOKUP(A88,gasto!$A$4:$F$100,4,FALSE) -> 0 | H88: =+VLOOKUP(A88,gasto!$A$4:$F$100,5,FALSE) -> 1178185 | I88: =+VLOOKUP(A88,gasto!$A$4:$F$100,6,FALSE) -> 1178185 | J88: =+G88+D88 -> 250000000 | K88: =+H88+E88 -> 1178185 | L88: =+I88+F88 -> 1178185 | M88: =+IFERROR(K88*100/C88,0) -> 0.471274 | N88: =+IFERROR(L88*100/C88,0) -> 0.471274
A89: A-3-9-15-0-03 | B89: =+VLOOKUP(A89,gasto!$A$4:$B$78,2,FALSE) -> Devoluciones Recursos Entidades Territoriales | C89: =+VLOOKUP(A89,gasto!$A$4:$F$100,3,FALSE) -> 160101188290 | D89: 0 | E89: 0 | F89: 0 | G89: =+VLOOKUP(A89,gasto!$A$4:$F$100,4,FALSE) -> 160101188290 | H89: =+VLOOKUP(A89,gasto!$A$4:$F$100,5,FALSE) -> 0 | I89: =+VLOOKUP(A89,gasto!$A$4:$F$100,6,FALSE) -> 0 | J89: =+G89+D89 -> 160101188290 | K89: =+H89+E89 -> 0 | L89: =+I89+F89 -> 0 | M89: =+IFERROR(K89*100/C89,0) -> 0 | N89: =+IFERROR(L89*100/C89,0) -> 0
A90: A-3-9-15-0-04 | B90: =+VLOOKUP(A90,gasto!$A$4:$B$78,2,FALSE) -> Otras Devoluciones | C90: =+VLOOKUP(A90,gasto!$A$4:$F$100,3,FALSE) -> 10000000000 | D90: 1580799.9 | E90: 1580799.9 | F90: 1580799.9 | G90: =+VLOOKUP(A90,gasto!$A$4:$F$100,4,FALSE) -> 0 | H90: =+VLOOKUP(A90,gasto!$A$4:$F$100,5,FALSE) -> 0 | I90: =+VLOOKUP(A90,gasto!$A$4:$F$100,6,FALSE) -> 0 | J90: =+G90+D90 -> 1580799.9 | K90: =+H90+E90 -> 1580799.9 | L90: =+I90+F90 -> 1580799.9 | M90: =+IFERROR(K90*100/C90,0) -> 0.015807999 | N90: =+IFERROR(L90*100/C90,0) -> 0.015807999
A91: A-9-9-9-9 | B91: =+VLOOKUP(A91,gasto!$A$4:$B$78,2,FALSE) -> Disponibilidad Final | C91: =+VLOOKUP(A91,gasto!$A$4:$F$100,3,FALSE) -> 254007875000 | D91: 0 | E91: 0 | F91: 0 | G91: =+VLOOKUP(A91,gasto!$A:$K,4,FALSE) -> 0 | H91: =+VLOOKUP(A91,gasto!$A:$K,4,FALSE) -> 0 | I91: =+VLOOKUP(A91,gasto!$A:$K,4,FALSE) -> 0 | J91: =+G91+D91 -> 0 | K91: =+H91+E91 -> 0 | L91: =+I91+F91 -> 0 | M91: =+IFERROR(K91*100/C91,0) -> 0 | N91: =+IFERROR(L91*100/C91,0) -> 0
A93: TOTAL | B93: TOTAL | C93: =+C91+C13 -> 53124925778513 | D93: =+D91+D13 -> 3.2327818e+13 | E93: =+E91+E13 -> 2.0416053e+13 | F93: =+F91+F13 -> 2.0416053e+13 | G93: =+G91+G13 -> 1.1969033e+13 | H93: =+H91+H13 -> 4.260865e+12 | I93: =+I91+I13 -> 4.260865e+12 | J93: =+J91+J13 -> 4.4296851e+13 | ... L93: =+L91+L13 -> 2.4676918e+13 | M93: =+IFERROR(K93*100/C93,0) -> 46.450733 | N93: =+IFERROR(L93*100/C93,0) -> 46.450733
C94: 53124925778513 | D94: 3.2327818e+13 | E94: 2.0416053e+13 | F94: 2.0416053e+13 | G94: 1.1969033e+13 | H94: 4.260865e+12 | I94: 4.260865e+12 | J94: 4.4296851e+13 | K94: 2.4676918e+13 | L94: 2.4676918e+13 | M94: 46.45 | N94: 46.45
C95: =+C94-C93 -> 0 | D95: =+D94-D93 -> -0.0625 | E95: =+E94-E93 -> -0.0859375 | F95: =+F94-F93 -> -0.0859375 | G95: =+G94-G93 -> -0.017578125 | H95: =+H94-H93 -> 0 | I95: =+I94-I93 -> 0 | J95: =+J94-J93 -> -0.078125 | ... N95: =+N94-N93 -> -0.00073346274
C96: =+C94/1000000 -> 53124926 | D96: =+D94/1000000 -> 32327818 | E96: =+E94/1000000 -> 20416053 | F96: =+F94/1000000 -> 20416053 | G96: =+G94/1000000 -> 11969033 | H96: =+H94/1000000 -> 4260865 | I96: =+I94/1000000 -> 4260865 | J96: =+J94/1000000 -> 44296851 | ... L96: =+L94/1000000 -> 24676918
C97: dif. Por excel | D97: dif. Por excel

Sheet gasto
D1: República de Colombia | E1: EJECUCIÓN DE EGRESOS ACUMULADOS | F1: ADRES ADMINISTRADORA DE LOS RECURSOS DEL SGSSS
A2: CÓDIGO RUBRO | B2: CONCEPTO DEL RUBRO | C2: APROPIACIÓN DEFINITIVA | D2: CDP | E2: RP | F2: PAGOS-OGAG | G2: T. CDP | H2: T. RP | I2: T. PAGOS-OGAG | J2: RP | K2: PAGOS
A3: URA
A4: A-3-2-1-0 | B4: Transferencias Entidades de Administración Pública Central | C4: 86345030430 | D4: 0 | E4: 6.8799777e+09 | F4: 6.8799777e+09 | G4: 82805519661 | H4: 4.1320831e+10 | I4: 4.1320831e+10 | J4: 47.86 | K4: 47.86
A5: A-3-2-1-01 | B5: Contribución IVC Superintendencia Nacional de Salud | C5: 86345030430 | D5: 0 | E5: 6.8799777e+09 | F5: 6.8799777e+09 | G5: 82805519661 | H5: 4.1320831e+10 | I5: 4.1320831e+10 | J5: 47.86 | K5: 47.86
A6: A-3-2-2-0 | B6: Empresas Públicas Nacionales no financieras -ADRES | C6: 145380000000 | D6: 0 | E6: 4.0873081e+09 | F6: 4.0873081e+09 | G6: 145380000000 | H6: 20048709556 | I6: 20048709556 | J6: 13.79 | K6: 13.79
A7: A-3-2-2-0-01 | B7: Aportes hasta del 0,5% recursos CSF para el desarrollo objeto ADRES | C7: 145380000000 | D7: 0 | E7: 4.0873081e+09 | F7: 4.0873081e+09 | G7: 145380000000 | H7: 20048709556 | I7: 20048709556 | J7: 13.79 | K7: 13.79
A8: A-3-6-1-0 | B8: Sentencias y Conciliaciones URA | C8: 20000000000 | D8: 2.722844e+08 | E8: 2.722844e+08 | F8: 2.722844e+08 | G8: 1.7592036e+09 | H8: 1.6006123e+09 | I8: 1.6006123e+09 | J8: 8 | K8: 8
A9: A-3-6-1-1 | B9: Sentencias URA | C9: 20000000000 | D9: 2.722844e+08 | E9: 2.722844e+08 | F9: 2.722844e+08 | G9: 1.7592036e+09 | H9: 1.6006123e+09 | I9: 1.6006123e+09 | J9: 8 | K9: 8
A10: A-3-6-1-2 | B10: Conciliaciones URA | C10: 0 | D10: 0 | E10: 0 | F10: 0 | G10: 0 | H10: 0 | I10: 0 | J10: 0 | K10: 0
A11: A-3-6-3-0 | B11: Destinatarios de otras transferencias Corrientes - Compensación Chance | C11: 134000000000 | D11: 0 | E11: 0 | F11: 0 | G11: 0 | H11: 0 | I11: 0 | J11: 0 | K11: 0
A12: A-3-6-3-0-01 | B12: Otras transferencias - Compensación del Chance Decreto 2550/12 | C12: 134000000000 | D12: 0 | E12: 0 | F12: 0 | G12: 0 | H12: 0 | I12: 0 | J12: 0 | K12: 0
A13: A-3-9-1-0 | B13: UPC Régimen Contributivo | C13: 23048224384378 | D13: -1124078341 | E13: 1797826867199 | F13: 1797826867199 | G13: 1.9519343e+13 | H13: 10970737679671 | I13: 10970737679671 | J13: 47.6 | K13: 47.6
A14: A-3-9-1-0-01 | B14: UPC Régimen Contributivo SSF | C14: 12399109660289 | D14: -1124078341 | E14: 1013005546507 | F14: 1013005546507 | G14: 1.0509568e+13 | H14: 6006050708117 | I14: 6006050708117 | J14: 48.44 | K14: 48.44
A15: A-3-9-1-0-02 | B15: UPC Régimen Contributivo CSF | C15: 10647939289644 | D15: 0 | E15: 784821320692 | F15: 784821320692 | G15: 9008599217429 | H15: 4963511537109 | I15: 4963511537109 | J15: 46.61 | K15: 46.61
... A72: A-3-9-14-0-03 | B72: Operaciones de Fortalecimiento Patrimonial - Bocas | C72: 0 | D72: 0 | E72: 0 | F72: 0 | G72: 0 | H72: 0 | I72: 0 | J72: 0 | K72: 0
A73: A-3-9-15-0 | B73: Devoluciones | C73: 179398901661 | D73: 160101188290 | E73: 139653536 | F73: 139653536 | G73: 1.6940048e+11 | H73: 6.3930188e+08 | I73: 6.3930188e+08 | J73: 0.36 | K73: 0.36 | L73: 0
A74: A-3-9-15-0-01 | B74: Devoluciones Aportes y Cotizaciones No Conciliadas Vigencia Anterior | C74: 9047713371 | D74: 0 | E74: 138475351 | F74: 138475351 | G74: 9047713371 | H74: 636542891 | I74: 636542891 | J74: 7.04 | K74: 7.04
A75: A-3-9-15-0-02 | B75: Devoluciones de Aportes de REX | C75: 250000000 | D75: 0 | E75: 1178185 | F75: 1178185 | G75: 250000000 | H75: 1178185 | I75: 1178185 | J75: 0.47 | K75: 0.47
A76: A-3-9-15-0-03 | B76: Devoluciones Recursos Entidades Territoriales | C76: 160101188290 | D76: 160101188290 | E76: 0 | F76: 0 | G76: 160101188290 | H76: 0 | I76: 0 | J76: 0 | K76: 0
A77: A-3-9-15-0-04 | B77: Otras Devoluciones | C77: 10000000000 | D77: 0 | E77: 0 | F77: 0 | G77: 1580799.9 | H77: 1580799.9 | I77: 1580799.9 | J77: 0.02 | K77: 0.02
A78: A-9-9-9-9 | B78: Disponibilidad Final | C78: 254007875000 | D78: 0 | E78: 0 | F78: 0 | G78: 0 | H78: 0 | I78: 0 | J78: 0 | K78: 0
F84: =+'CUADRO 2-EJECUCION DE GASTOS'!I95+gasto!F21 -> 65375823281
